Workbook
Name AfricaCountries: CountryList!$A$1:$A$54
Name DegradationRate: expected_production!$J$1

Sheet site_tech_info
A1: Site Name | B1: PV Capacity (W) | C1: PV Inverter Size (kW) | D1: Battery Size (Wh) | E1: Battery Name | F1: Battery Inverter/Hybrid Size | G1: Generator Size | H1: Genset/Grid set point kit | I1: Country | J1: Province | K1: Location | L1: Meter | M1: Contract Type | N1: Business Type | O1: Operational Satus | P1: Sales Type | Q1: Investment Party | R1: Project Number | S1: Commisioned Date | T1: Installer Name | U1: Platform | V1: Offtake Guarantee | W1: Age | X1: Soiling Intensity | Y1: Shading | Z1: Power Limit
A2: 21 Melrose | B2: 14000 | C2: 36 | D2: 35808 | E2: Sunsynk | F2: 3x12kW | G2: None | H2: None | I2: South Africa | J2: Gauteng | K2: 21 Melrose St Melrose | L2: N/A | M2: RTO | N2: Residential | O2: Reduced Demand | Q2: Anuva | R2: P00062 | S2: 44963 | T2: SA Energy | U2: Sunsynk | V2: NO | W2: =IF(ISNUMBER(S2),(TODAY()-S2)/365.25,"") -> 3.7207392 | X2: Low | Y2: Low | Z2: Zero Export
A3: African Global Plastics | B3: 178000 | C3: =2*80 -> 160 | D3: 0 | E3: N/A | F3: N/A | G3: None | H3: None | I3: South Africa | J3: Gauteng | K3: 1st St & 11th road, Kew, Sandton, 2090 | L3: Alester Meter | M3: PPA | N3: Manufacture | O3: Producing | Q3: SSI | R3: P00008 | S3: 45196 | T3: SA Energy | U3: mypower24 | V3: NO | W3: =IF(ISNUMBER(S3),(TODAY()-S3)/365.25,"") -> 3.08282 | X3: Medium | Y3: Low | Z3: Zero Export
A4: Alpine Heath Residential | B4: 36000 | C4: =1*33 -> 33 | D4: 0 | E4: N/A | F4: N/A | G4: None | H4: None | I4: South Africa | J4: KZN | K4: Busingatha, South Africa | L4: Eastron Meter | M4: PPA | N4: Residential | O4: Reduced Demand | Q4: 12B Fund | R4: null | S4: 45658 | T4: SA Energy | U4: isolarCloud | V4: YES | W4: =IF(ISNUMBER(S4),(TODAY()-S4)/365.25,"") -> 1.8179329 | X4: Low | Y4: Low | Z4: Zero Export
A5: Alpine Heath Resort | B5: 217000 | C5: =2*110 -> 220 | D5: 0 | E5: N/A | F5: N/A | G5: N/A | H5: N/A | I5: South Africa | J5: KZN | K5: Busingatha, South Africa | L5: Eastron Meter | M5: PPA | N5: Residential | O5: Producing | Q5: 12B Fund | R5: null | S5: 46140 | T5: SA Energy | U5: IsolarCloud | V5: YES | W5: =IF(ISNUMBER(S5),(TODAY()-S5)/365.25,"") -> 0.49828884 | X5: Low | Y5: Low | Z5: Zero Export
A6: Bendstore Plaza Shops | B6: 110000 | C6: =1*110 -> 110 | D6: 0 | E6: N/A | F6: N/A | G6: N/A | H6: N/A | I6: South Africa | J6: Limpopo | K6: Stand 87, Bendstore Plaza, Giyani Main Rd, Giyani-BA, Giyani, 0832 | L6: null | M6: PPA | N6: Retail | O6: Reduced Demand | Q6: Anuva | R6: P00072 | S6: 44908 | T6: SA Energy | U6: null | V6: NO | W6: =IF(ISNUMBER(S6),(TODAY()-S6)/365.25,"") -> 3.871321 | X6: Low | Y6: Unknown | Z6: Zero Export
A7: Bendstore Spar | B7: 400000 | C7: null | D7: 0 | E7: N/A | F7: N/A | G7: null | H7: null | I7: South Africa | J7: Limpopo | K7: null | L7: null | M7: PPA | N7: Retail | O7: Producing | Q7: Anuva | R7: null | S7: 45272 | T7: SA Energy | U7: null | V7: NO | W7: =IF(ISNUMBER(S7),(TODAY()-S7)/365.25,"") -> 2.8747433 | X7: Low | Y7: Unknown | Z7: Zero Export
A8: Beyerskloof | B8: 78000 | C8: null | D8: 0 | E8: N/A | F8: N/A | G8: null | H8: null | I8: South Africa | J8: Western Cape | K8: Koelenhof Street, R304, Koelenhof, Stellenbosch, 7600 | L8: null | M8: PPA | N8: Manufacture | O8: Reduced Demand | Q8: SSI | R8: null | S8: 45272 | T8: Solar Synergy | U8: null | V8: NO | W8: =IF(ISNUMBER(S8),(TODAY()-S8)/365.25,"") -> 2.8747433 | X8: Low | Y8: Low | Z8: Zero Export
A9: BP Parys | B9: 544000 | C9: 50 | D9: 0 | E9: N/A | F9: N/A | G9: N/A | H9: N/A | I9: South Africa | J9: Free state | K9: 63 Bree St, Parys, 9585 | L9: Eastron Meter | M9: RTO | N9: Retail | O9: Reduced Demand | Q9: SSI | R9: null | S9: 45610 | T9: SA Energy | U9: null | V9: NO | W9: =IF(ISNUMBER(S9),(TODAY()-S9)/365.25,"") -> 1.9493498 | X9: Low | Y9: Unknown | Z9: Zero Export
A10: Buffalo Rock | B10: 15000 | C10: N/A | D10: 57200 | E10: null | F10: 2x12kW | G10: N/A | H10: N/A | I10: South Africa | J10: Mpumalanga | K10: Hazyview Ehlanzeni District Municipality MP | L10: null | M10: RTO | N10: Residential | O10: Reduced Demand | Q10: SSI | R10: P00054 | S10: 45183 | T10: SA Energy | U10: Sunsynk | V10: NO | W10: =IF(ISNUMBER(S10),(TODAY()-S10)/365.25,"") -> 3.118412 | X10: Low | Y10: Unknown | Z10: Zero Export
A11: Checkers De Aar | B11: 154000 | C11: 125 | D11: 0 | E11: N/A | F11: N/A | G11: N/A | H11: NuVo | I11: South Africa | J11: Northern Cape | K11: 21 Alexander St, De Aar, 7000, South Africa | M11: PPA | N11: Retail | O11: Producing | Q11: 12B Fund | R11: P00038 | S11: 45449 | T11: SA Energy | U11: iSolarCloud & NuVo | V11: NO | W11: =IF(ISNUMBER(S11),(TODAY()-S11)/365.25,"") -> 2.3901437 | X11: Low | Y11: Low | Z11: Zero Export
A12: Checkers Lichtenburg | B12: 161000 | C12: 150 | D12: 0 | E12: N/A | F12: N/A | G12: N/A | H12: N/A | I12: South Africa | J12: North West | K12: 33 Nelson Mandela Dr, Lichtenburg, 2740 | L12: Eastron Meter | M12: PPA | N12: Retail | O12: Producing | Q12: SSI | R12: null | S12: 46129 | T12: SA Energy | U12: IsolarCloud | V12: NO | W12: =IF(ISNUMBER(S12),(TODAY()-S12)/365.25,"") -> 0.5284052 | X12: Unknown | Y12: Low | Z12: Zero Export
A13: Checkers Silverlakes Gen | B13: 152000 | C13: 125 | D13: 0 | E13: N/A | F13: N/A | G13: 500 | H13: Nuvo | I13: South Africa | J13: Gauteng | K13: Chamberlain Shopping Cntr (Six Fountains Cnr Solomon Mahlangu Dr, Bendeman Blvd, &, Pretoria, 0081 | L13: Eastron Meter | M13: PPA | N13: Retail | O13: Producing | Q13: 12B Fund | R13: null | S13: 2025/02/29 | T13: SA Energy | U13: isolarCloud | V13: NO | W13: =IF(ISNUMBER(S13),(TODAY()-S13)/365.25,"") | X13: Low | Y13: Low | Z13: Zero Export
A14: Checkers Silverlakes No Gen | B14: 142000 | C14: 125 | D14: 0 | E14: N/A | F14: N/A | G14: N/A | H14: N/A | I14: South Africa | J14: Gauteng | K14: Chamberlain Shopping Cntr (Six Fountains Cnr Solomon Mahlangu Dr, Bendeman Blvd, &, Pretoria, 0081 | L14: Eastron Meter | M14: PPA | N14: Retail | O14: Producing | Q14: 12B Fund | R14: null | S14: 2025/02/29 | T14: SA Energy | U14: isolarCloud | V14: NO | W14: =IF(ISNUMBER(S14),(TODAY()-S14)/365.25,"") | X14: Low | Y14: Low | Z14: Zero Export
A15: Checkrite Inanda | B15: 70000 | C15: =2*33 -> 66 | D15: 0 | E15: N/A | F15: N/A | G15: N/A | H15: N/A | I15: South Africa | J15: Gauteng | K15: 6th Ave, Springs New, Springs, 1560 | L15: null | M15: PPA | N15: Retail | O15: Producing | Q15: 12B Fund | R15: P00056 | S15: 45471 | T15: SA Energy | U15: iSolarCloud | V15: YES | W15: =IF(ISNUMBER(S15),(TODAY()-S15)/365.25,"") -> 2.329911 | X15: Low | Y15: Low | Z15: Zero Export
A16: Club Houghton | B16: 60000 | C16: N/A | D16: 84000 | E16: N/A | F16: 6x12kW Sunsynk Inverters | G16: N/A | H16: null | I16: South Africa | J16: Gauteng | K16: Osborn Rd, Houghton Estate, Johannesburg, 2198, South Africa | L16: N/A | M16: PPA | N16: Residential | O16: Reduced Demand | Q16: Anuva | R16: P00067 | S16: 44665 | T16: SA Energy | U16: Sunsysnk;SolarMd | V16: NO | W16: =IF(ISNUMBER(S16),(TODAY()-S16)/365.25,"") -> 4.5366188 | X16: Low | Y16: Low | Z16: Zero Export
A17: Coldstar International | B17: 41000 | C17: 36 | D17: 0 | E17: N/A | F17: N/A | G17: N/A | H17: N/A | I17: South Africa | J17: KZN | K17: Coldstar International, 3 Rana Rd, Isipingo Rail, Isipingo, 4110 | client miss use data | L17: N/A | M17: PPA | N17: Commercial | O17: Reduced Demand | Q17: Anuva | R17: P00051 | S17: 44643 | T17: SA Energy | U17: iSolarCloud | V17: NO | W17: =IF(ISNUMBER(S17),(TODAY()-S17)/365.25,"") -> 4.5968515 | X17: Low | Y17: Low | Z17: Exporting
A18: Cultura Fresh | B18: 65000 | C18: 110 | D18: 171600 | E18: Atess | F18: ATESS PCS250 | G18: N/A | H18: null | I18: South Africa | J18: Western Cape | K18: null | L18: null | M18: PPA | N18: Agricultural | O18: Reduced Demand | Q18: 12B Fund | R18: null | S18: 45509 | T18: Solar Synergy | U18: null | V18: NO | W18: =IF(ISNUMBER(S18),(TODAY()-S18)/365.25,"") -> 2.2258727 | X18: Low | Y18: Low | Z18: Zero Export
A19: Demco | B19: 235000 | C19: =2*110 -> 220 | D19: 0 | E19: N/A | F19: N/A | G19: N/A | H19: N/A | I19: South Africa | J19: Gauteng | K19: Industries East, 12 -14 Moller Street, Germiston. 1401 | L19: Alester Meter | M19: PPA | N19: Manufacture | O19: Reduced Demand | Q19: 12B Fund | R19: P00035 | S19: 45460 | T19: SA Energy | U19: iSolarCloud | V19: YES | W19: =IF(ISNUMBER(S19),(TODAY()-S19)/365.25,"") -> 2.3600274 | X19: Low | Y19: Low | Z19: Zero Export
A20: Engen Kaalfontein | B20: 114070 | C20: 125 | D20: 0 | E20: N/A | F20: N/A | G20: N/A | H20: N/A | I20: South Africa | J20: Gauteng | K20: 3117 Angelfish St, Kaalfontein, Midrand, 1632 | L20: Eastron Meter | M20: PPA | N20: Retail | O20: Producing | Q20: SSI | R20: null | S20: 46162 | T20: SA Energy | U20: IsolarCloud | V20: YES | W20: =IF(ISNUMBER(S20),(TODAY()-S20)/365.25,"") -> 0.43805613 | X20: High | Y20: Low | Z20: Zero Export
A21: Engen Lotus Gardens | B21: 23010 | D21: 0 | E21: N/A | F21: N/A | G21: N/A | H21: N/A | I21: South Africa | J21: Gauteng | K21: 63WC+CQ4 Pretoria | L21: Eastron Meter | M21: PPA | N21: Retail | O21: Producing | Q21: SSI | R21: null | S21: 45951 | T21: SA Energy | U21: IsolarCloud | V21: YES | W21: =IF(ISNUMBER(S21),(TODAY()-S21)/365.25,"") -> 1.0157426 | X21: Low | Y21: Low | Z21: Zero Export
A22: Giba Gorge Main | B22: 123360 | C22: 160 | D22: 0 | E22: N/A | F22: N/A | G22: N/A | H22: N/A | I22: South Africa | J22: KZN | K22: 5QCJ+XM2 Clifton Canyon, Pinetown Rural | L22: Alester Meter | M22: PPA | N22: Manufacture | O22: Reduced Demand | Q22: SSI | R22: P00069 | S22: 44479 | T22: SA Energy | U22: soliscloud | V22: NO | W22: =IF(ISNUMBER(S22),(TODAY()-S22)/365.25,"") -> 5.045859 | X22: Low | Y22: Low | Z22: Zero Export
A23: Giba Gorge Storage | B23: 106000 | C23: null | D23: 0 | E23: N/A | F23: N/A | G23: N/A | H23: null | I23: South Africa | J23: KZN | K23: 5QCJ+XM2 Clifton Canyon, Pinetown Rural | L23: Alester Meter | M23: PPA | N23: Commercial | O23: Reduced Demand | Q23: SSI | R23: null | S23: 44479 | T23: SA Energy | U23: SolisCloud | V23: NO | W23: =IF(ISNUMBER(S23),(TODAY()-S23)/365.25,"") -> 5.045859 | X23: Low | Y23: Low | Z23: Zero Export
A24: Golden Spot Resort | B24: 30000 | C24: 33 | D24: 0 | E24: N/A | F24: N/A | G24: N/A | H24: N/A | I24: South Africa | J24: Mpumalanga | K24: HR2M+GQ7 Alkmaar (-25.4487127, 30.8344204) | L24: null | M24: PPA | N24: Residential | O24: Reduced Demand | Q24: SSI | R24: P00071 | S24: 45073 | T24: SA Energy | U24: iSolarCloud | V24: YES | W24: =IF(ISNUMBER(S24),(TODAY()-S24)/365.25,"") -> 3.4195756 | X24: Low | Y24: Low | Z24: Zero Export
A25: Golden Spot Shops | B25: 30000 | C25: 33 | D25: 0 | E25: N/A | F25: N/A | G25: N/A | H25: N/A | I25: South Africa | J25: Mpumalanga | K25: HR2M+GQ7 Alkmaar (-25.4487127, 30.8344204) | L25: null | M25: PPA | N25: Retail | O25: Producing | Q25: SSI | R25: P00060 | S25: 45072 | T25: SA Energy | U25: iSolarCloud | V25: YES | W25: =IF(ISNUMBER(S25),(TODAY()-S25)/365.25,"") -> 3.4223135 | X25: Low | Y25: Low | Z25: Zero Export
A26: Grootpan | B26: 170000 | C26: =4*50 -> 200 | D26: 491520 | E26: Deye | F26: Daye | G26: N/A | H26: N/A | I26: South Africa | J26: North West | K26: 2G4H+RXQ Ga-Motlatla | L26: N/A | M26: RTO | N26: Agricultural | O26: Reduced Demand | Q26: SSI | R26: null | S26: 46086 | T26: OTG 4 U | U26: Deye Cloud | V26: NO | W26: =IF(ISNUMBER(S26),(TODAY()-S26)/365.25,"") -> 0.64613279 | X26: Low | Y26: Low | Z26: Zero Export
A27: HB Dunn | B27: 24000 | C27: N/A | D27: 127400 | E27: N/A | F27: 1x50 kW | G27: N/A | H27: N/A | I27: South Africa | J27: Mpumalanga | K27: Kriel Nkangala District Municipality MP | L27: null | M27: RTO | N27: Residential | O27: Reduced Demand | Q27: SSI | R27: P00045 | S27: 45407 | T27: SA Energy | U27: Sunsynk | V27: NO | W27: =IF(ISNUMBER(S27),(TODAY()-S27)/365.25,"") -> 2.5051335 | X27: Low | Y27: Low | Z27: Zero Export
A28: Helderberg Collage | B28: 223000 | C28: null | D28: 0 | E28: N/A | F28: N/A | G28: N/A | H28: null | I28: South Africa | J28: Western Cape | K28: null | L28: null | M28: PPA | N28: Residential | O28: Producing | Q28: SSI | R28: null | S28: 43700 | T28: SA Energy | U28: null | V28: NO | W28: =IF(ISNUMBER(S28),(TODAY()-S28)/365.25,"") -> 7.1786448 | X28: Low | Y28: Low | Z28: Zero Export
A29: Hilston Rotoflo | B29: 240000 | C29: 240 | D29: 0 | E29: N/A | F29: N/A | G29: N/A | H29: N/A | I29: South Africa | J29: Gauteng | K29: 28 Hilston Rd, Kya Sand, Randburg, 2163 | L29: null | M29: PPA | N29: Residential | O29: Producing | Q29: Anuva | R29: P00055 | S29: 45056 | T29: SA Energy | U29: isolarCloud | V29: YES | W29: =IF(ISNUMBER(S29),(TODAY()-S29)/365.25,"") -> 3.4661191 | X29: Low | Y29: Low | Z29: Zero Export
A30: Huis Herfsblaar | B30: 215000 | C30: =2*110 -> 220 | D30: 0 | E30: N/A | F30: N/A | G30: N/A | H30: N/A | I30: South Africa | J30: Gauteng | K30: Edging Pretoria, 1244 Webb Rd, Queenswood, Pretoria, 0186, South Africa | L30: Eastron Meter | M30: PPA | N30: Commercial | O30: Producing | Q30: 12B Fund | R30: P00034 | S30: 45463 | T30: SA Energy | U30: iSolarCloud | V30: YES | W30: =IF(ISNUMBER(S30),(TODAY()-S30)/365.25,"") -> 2.3518138 | X30: Low | Y30: Low | Z30: Zero Export
A31: IPID - Floor 4 | B31: 54740 | C31: null | D31: 0 | E31: N/A | F31: N/A | G31: N/A | H31: N/A | I31: South Africa | J31: Gauteng | K31: 7633+M46 Pretoria | L31: Eastron Meter | M31: PPA | N31: Commercial | O31: Producing | Q31: SSI | R31: null | S31: 45934 | T31: SA Energy | U31: IsolarCloud | V31: YES | W31: =IF(ISNUMBER(S31),(TODAY()-S31)/365.25,"") -> 1.0622861 | X31: Low | Y31: Low | Z31: Zero Export
A32: IPID - Floor 6 | B32: 47600 | C32: null | D32: 0 | E32: N/A | F32: N/A | G32: N/A | H32: N/A | I32: South Africa | J32: Gauteng | K32: 7633+M46 Pretoria | L32: Eastron Meter | M32: PPA | N32: Commercial | O32: Producing | Q32: SSI | R32: null | S32: 45934 | T32: SA Energy | U32: IsolarCloud | V32: YES | W32: =IF(ISNUMBER(S32),(TODAY()-S32)/365.25,"") -> 1.0622861 | X32: Low | Y32: Low | Z32: Zero Export
A33: Kool Village | B33: 79000 | C33: null | D33: 0 | E33: N/A | F33: N/A | G33: N/A | H33: null | I33: South Africa | J33: Northern Cape | K33: Kool Village, 89 Virginia Way, Virginia, 9430 | L33: null | M33: null | N33: Commercial | O33: Producing | Q33: Anuva | R33: null | S33: 2022/16/12 | T33: SA Energy | U33: null | V33: NO | W33: =IF(ISNUMBER(S33),(TODAY()-S33)/365.25,"") | X33: Low | Y33: Low | Z33: Zero Export
A34: Makalali | B34: 120000 | C34: null | D34: 171600 | E34: N/A | F34: 250 | G34: N/A | H34: N/A | I34: South Africa | J34: Limpopo | K34: Makalali game reserve Road D202 Harmony Block 33, Gravelotte | N34: Agriculural | O34: Reduced Demand | Q34: SSI | R34: null | S34: 45050 | T34: SA Energy | W34: =IF(ISNUMBER(S34),(TODAY()-S34)/365.25,"") -> 3.4825462 | X34: Low | Y34: Low | Z34: Zero Export
A35: Mambha Cash & Carry | B35: 184000 | C35: null | D35: 0 | E35: N/A | F35: N/A | G35: N/A | H35: null | I35: South Africa | J35: KZN | K35: null | L35: null | M35: PPA | N35: Retail | O35: Producing | Q35: Anuva | R35: P00015 | S35: 44879 | T35: SA Energy | U35: mypower24 | V35: NO | W35: =IF(ISNUMBER(S35),(TODAY()-S35)/365.25,"") -> 3.9507187 | X35: High | Y35: Low | Z35: Zero Export
A36: Mathe Group Company | B36: 518000 | C36: =4*110 -> 440 | D36: 0 | E36: N/A | F36: N/A | G36: N/A | H36: N/A | I36: South Africa | J36: KZN | K36: 4/160 Buckman Blvd, Cato Ridge, 3699, South Africa | L36: null | M36: PPA | N36: Manufacture | O36: Producing | Q36: Anuva | R36: P00059 | S36: 44692 | T36: SA Energy | U36: iSolarCloud | W36: =IF(ISNUMBER(S36),(TODAY()-S36)/365.25,"") -> 4.4626968 | X36: Low | Y36: Low | Z36: Zero Export
A37: Mdluli | B37: 114000 | C37: null | D37: =228800*2 -> 457600 | E37: N/A | F37: N/A | G37: N/A | H37: null | I37: South Africa | J37: Mpumalanga | K37: Makoko, South Africa,1251 | L37: null | M37: PPA | N37: Residential | O37: Reduced Demand | Q37: 12B Fund | R37: P00083 | S37: 45399 | T37: SA Energy | U37: mypower24&IsolarCloud | V37: YES | W37: =IF(ISNUMBER(S37),(TODAY()-S37)/365.25,"") -> 2.5270363 | X37: Low | Y37: Low | Z37: Zero Export
A38: Medipost | B38: 330000 | C38: null | D38: 0 | E38: N/A | F38: N/A | G38: N/A | H38: N/A | I38: South Africa | J38: Western Cape | K38: 593 Nico Smith St, Gezina, Pretoria, 0084 | L38: Eastron Meter | M38: PPA | N38: Commercial | O38: Producing | Q38: 12B Fund | R38: null | S38: 45713 | T38: SA Energy | U38: null | W38: =IF(ISNUMBER(S38),(TODAY()-S38)/365.25,"") -> 1.6673511 | X38: Low | Y38: Low | Z38: Zero Export
A39: Meredale Heights | B39: 33000 | C39: =1*33 -> 33 | D39: 0 | E39: N/A | F39: N/A | G39: N/A | H39: N/A | I39: South Africa | J39: Gauteng | K39: 40 thomas street | L39: null | M39: PPA | N39: Residential | O39: Producing | Q39: Anuva | R39: P00052 | S39: 45248 | T39: SA Energy | U39: iSolarCloud | V39: YES | W39: =IF(ISNUMBER(S39),(TODAY()-S39)/365.25,"") -> 2.9404517 | X39: Low | Y39: Low | Z39: Zero Export
A40: Monument Park Checkers | B40: 281000 | C40: =2*125 -> 250 | D40: 0 | E40: N/A | F40: N/A | G40: N/A | H40: NuVo | I40: South Africa | J40: Gauteng | K40: 242 Voortrekker Rd, Monument, Krugersdorp, 1739, South Africa | L40: null | M40: PPA | N40: Retail | O40: Producing | Q40: Anuva | R40: P00037 | S40: 45351 | T40: SA Energy | U40: isloarcloud &Nuvo | V40: NO | W40: =IF(ISNUMBER(S40),(TODAY()-S40)/365.25,"") -> 2.6584531 | X40: Low | Y40: Low | Z40: Zero Export
A41: Nkambeni Industrial | B41: 158400 | C41: 125 | D41: 0 | E41: Solar MD | F41: Atess PCS500 | G41: N/A | H41: null | I41: South Africa | J41: Mpumalanga | K41: 139 Numbi Rd Numbi Gate Kruger National Park, Hazyview, 1350 | L41: null | M41: RTO | N41: Residential | O41: Reduced Demand | Q41: SSI | R41: P00040 | S41: 45182 | T41: SA Energy | U41: null | V41: NO | W41: =IF(ISNUMBER(S41),(TODAY()-S41)/365.25,"") -> 3.1211499 | X41: Low | Y41: Low | Z41: Zero Export
A42: Olievenhoutbosch 1 | B42: 300000 | C42: null | D42: 0 | E42: N/A | F42: N/A | G42: N/A | H42: N/A | I42: South Africa | J42: Gauteng | K42: 33WW+C5W Centurion | L42: Eastron Meter | M42: PPA | N42: Retail | O42: Producing | Q42: SSI | R42: null | S42: 45924 | T42: SA Energy | U42: IsolarCloud | V42: YES | W42: =IF(ISNUMBER(S42),(TODAY()-S42)/365.25,"") -> 1.0896646 | X42: High | Y42: Low | Z42: Zero Export
A43: Olievenhoutbosch 2 | B43: 70000 | C43: null | D43: 0 | E43: N/A | F43: N/A | G43: N/A | H43: N/A | I43: South Africa | J43: Gauteng | K43: 33WW+C5W Centurion | L43: Eastron Meter | M43: PPA | N43: Retail | O43: Producing | Q43: SSI | R43: null | S43: 45924 | T43: SA Energy | U43: IsolarCloud | V43: YES | W43: =IF(ISNUMBER(S43),(TODAY()-S43)/365.25,"") -> 1.0896646 | X43: High | Y43: Low | Z43: Zero Export
A44: Opal Students | B44: 35000 | C44: =1*33 -> 33 | D44: 0 | E44: N/A | F44: N/A | G44: N/A | H44: N/A | I44: South Africa | J44: Gauteng | K44: Opal students | L44: null | M44: RTO | N44: Retail | O44: Producing | Q44: Anuva | R44: P00057 | S44: 45174 | T44: SA Energy | U44: iSolarCloud | V44: YES | W44: =IF(ISNUMBER(S44),(TODAY()-S44)/365.25,"") -> 3.1430527 | X44: Low | Y44: Low | Z44: Zero Export
A45: Orthochem Bethlehem | B45: 220000 | C45: null | D45: 0 | E45: N/A | F45: N/A | G45: N/A | H45: null | I45: South Africa | J45: Free state | K45: 6 Sauer Street Bethlehem Free State 9700 | L45: null | M45: PPA | N45: Manufacture | O45: Producing | Q45: SSI | R45: P00063 | S45: 45101 | T45: SA Energy | U45: isolarcloud, & NuVO | V45: NO | W45: =IF(ISNUMBER(S45),(TODAY()-S45)/365.25,"") -> 3.3429158 | X45: Low | Y45: Low | Z45: Zero Export
A46: Plastiplate | B46: 66000 | C46: =2*33 -> 66 | D46: 0 | E46: N/A | F46: N/A | G46: N/A | H46: N/A | I46: South Africa | J46: Gauteng | K46: 6 adderley, Roodepoort, 1724, South Africa | L46: null | M46: PPA | N46: Manufacture | O46: Producing | Q46: Anuva | R46: P00061 | S46: 44688 | T46: SA Energy | U46: iSolarCloud | V46: YES | W46: =IF(ISNUMBER(S46),(TODAY()-S46)/365.25,"") -> 4.4736482 | X46: Low | Y46: Low | Z46: Zero Export
A47: PNB Unlimited | B47: 95000 | C47: null | D47: 0 | E47: N/A | F47: N/A | G47: N/A | H47: null | I47: South Africa | J47: North West | K47: 8X4H+VXW Amaoti | L47: null | M47: PPA | N47: Commercial | O47: Producing | Q47: SSI | R47: null | S47: 44161 | T47: SA Energy | U47: null | V47: NO | W47: =IF(ISNUMBER(S47),(TODAY()-S47)/365.25,"") -> 5.9164956 | X47: Low | Y47: Low | Z47: Zero Export
A48: Q-lity Meat | B48: 35000 | C48: 30 | D48: 0 | E48: N/A | F48: N/A | G48: N/A | H48: NuVo | I48: South Africa | J48: Gauteng | K48: null | L48: null | M48: PPA | N48: Retail | O48: Producing | Q48: SSI | R48: P00007 | S48: 45092 | T48: SA Energy | U48: isloarcloud &Nuvo | V48: NO | W48: =IF(ISNUMBER(S48),(TODAY()-S48)/365.25,"") -> 3.3675565 | X48: Low | Y48: Low | Z48: Zero Export
A49: Quintondale | B49: 40000 | C49: 33 | D49: 0 | E49: N/A | F49: N/A | G49: N/A | H49: N/A | I49: South Africa | J49: Gauteng | K49: 43 Orchards Street, Johannesburg, Johannesburg, Gauteng 2192, South Africa | L49: null | M49: PPA | N49: Residential | O49: Reduced Demand | Q49: SSI | R49: P00065 | S49: 44663 | T49: SA Energy | U49: null | V49: NO | W49: =IF(ISNUMBER(S49),(TODAY()-S49)/365.25,"") -> 4.5420945 | X49: Low | Y49: Low | Z49: Zero Export
A50: Riverside Lodge | B50: 110000 | C50: =2*50 -> 100 | D50: 0 | E50: N/A | F50: N/A | G50: N/A | H50: N/A | I50: South Africa | J50: North West | K50: Hartbeespoort, South Africa | L50: null | M50: PPA | N50: Residential | O50: Producing | Q50: Anuva | R50: P00053 | S50: 45058 | T50: SA Energy | U50: iSolarCloud | V50: YES | W50: =IF(ISNUMBER(S50),(TODAY()-S50)/365.25,"") -> 3.4606434 | X50: Low | Y50: Low | Z50: Zero Export
A51: Roan Foods | B51: 127440 | C51: 100 | D51: 246000 | E51: Deye | F51: Deye | G51: N/A | H51: N/A | I51: Zambia | J51: Lusaka | K51: J8VC+WPJ, Lusaka, Zambia | L51: N/A | M51: RTO | N51: Retail | O51: Producing | Q51: SAWA | R51: null | S51: 46114 | T51: Dorman Energy | U51: Deye Cloud | V51: NO | W51: =IF(ISNUMBER(S51),(TODAY()-S51)/365.25,"") -> 0.56947296 | X51: Unknown | Y51: Low | Z51: Zero Export
A52: Sakhumnotho | B52: 38000 | C52: 30 | D52: 0 | E52: N/A | F52: N/A | G52: N/A | H52: N/A | I52: South Africa | J52: Gauteng | K52: R3W5+96X Johannesburg | L52: null | M52: PPA | N52: Commercial | O52: Decommissioned | Q52: SSI | R52: P00043 | S52: null | T52: SA Energy | U52: null | V52: NO | W52: =IF(ISNUMBER(S52),(TODAY()-S52)/365.25,"") | X52: Low | Y52: Low | Z52: Zero Export
A53: SaveMore Alldays - Store | B53: 180000 | C53: 100 | D53: 0 | E53: N/A | F53: N/A | G53: N/A | H53: N/A | I53: South Africa | J53: Limpopo | K53: R572, Alldays, 0909 | L53: null | M53: PPA | N53: Retail | O53: Reduced Demand | Q53: SSI | R53: P00050 | S53: 45110 | T53: SA Energy | U53: soliscloud | V53: NO | W53: =IF(ISNUMBER(S53),(TODAY()-S53)/365.25,"") -> 3.3182752 | X53: Low | Y53: Low | Z53: Zero Export
A54: Savemore Liquor Alldays | B54: 27300 | C54: 30 | D54: 0 | E54: N/A | F54: N/A | G54: N/A | H54: N/A | I54: South Africa | J54: Limpopo | K54: 84C3+PG2 Alldays | L54: null | M54: PPA | N54: Retail | O54: Reduced Demand | Q54: SSI | R54: null | S54: 45111 | T54: SA Energy | U54: soliscloud | V54: NO | W54: =IF(ISNUMBER(S54),(TODAY()-S54)/365.25,"") -> 3.3155373 | X54: Low | Y54: Low | Z54: Zero Export
A55: Saverite Durban | B55: 95000 | C55: null | D55: 0 | E55: N/A | F55: N/A | G55: N/A | H55: null | I55: South Africa | J55: KZN | K55: null | L55: null | M55: PPA | N55: Retail | O55: Producing | Q55: Anuva | R55: null | S55: 45111 | T55: SA Energy | U55: null | V55: NO | W55: =IF(ISNUMBER(S55),(TODAY()-S55)/365.25,"") -> 3.3155373 | X55: Low | Y55: Low | Z55: Zero Export
A56: Saverite PMB | B56: 96000 | C56: null | D56: 0 | E56: N/A | F56: N/A | G56: N/A | H56: null | I56: South Africa | J56: KZN | K56: 457 Langalibalele St, Pietermaritzburg, 3200 | L56: null | M56: PPA | N56: Retail | O56: Producing | Q56: SSI | R56: null | S56: 44159 | T56: SA Energy | U56: null | V56: NO | W56: =IF(ISNUMBER(S56),(TODAY()-S56)/365.25,"") -> 5.9219713 | X56: Low | Y56: Low | Z56: Zero Export
A57: Secunda Plaza Choppies | B57: 121000 | C57: 110 | D57: 0 | E57: N/A | F57: N/A | G57: N/A | H57: N/A | I57: South Africa | J57: Mpumalanga | K57: 8337 Pichlerplien, Secunda, 2302, South Africa | L57: null | M57: PPA | N57: Retail | O57: Reduced Demand | Q57: SSI | R57: P00076 | S57: 44770 | T57: SA Energy | U57: iSolarCloud | V57: NO | W57: =IF(ISNUMBER(S57),(TODAY()-S57)/365.25,"") -> 4.2491444 | X57: Low | Y57: Low | Z57: Zero Export
A58: Secunda Plaza Shops | B58: 35000 | C58: 33 | D58: 0 | E58: N/A | F58: N/A | G58: N/A | H58: N/A | I58: South Africa | J58: Mpumalanga | K58: 8309 Louwrens Muller St, Secunda, 2302, South Africa | L58: null | M58: PPA | N58: Retail | O58: Reduced Demand | Q58: SSI | R58: P00075 | S58: 44770 | T58: SA Energy | U58: iSolarCloud | V58: NO | W58: =IF(ISNUMBER(S58),(TODAY()-S58)/365.25,"") -> 4.2491444 | X58: Low | Y58: Low | Z58: Zero Export
A59: Shoprite Dube | B59: 153000 | C59: 125 | D59: 0 | E59: N/A | F59: N/A | G59: N/A | H59: N/A | I59: South Africa | J59: Gauteng | K59: Shoprite Maponya Center, 1980 Mahalefele Rd, Dube, Soweto, 1801 | L59: Eastron Meter | M59: PPA | N59: Retail | O59: Producing | Q59: 12B Fund | R59: null | S59: 45666 | T59: SA Energy | U59: isolarCloud | V59: NO | W59: =IF(ISNUMBER(S59),(TODAY()-S59)/365.25,"") -> 1.7960301 | X59: Low | Y59: Low | Z59: Zero Export
A60: Shoprite Ekhaya | B60: 175680 | C60: 150 | D60: 0 | E60: N/A | F60: N/A | G60: N/A | H60: N/A | I60: South Africa | J60: Mpumalanga | K60: Ekhaya Mall, R546, Evander, 2285 | L60: Eastron Meter | M60: PPA | N60: Retail | O60: Producing | Q60: SSI | R60: null | S60: 46068 | T60: SA Energy | U60: IsolarCloud | V60: NO | W60: =IF(ISNUMBER(S60),(TODAY()-S60)/365.25,"") -> 0.6954141 | X60: Unknown | Y60: Low | Z60: Zero Export
A61: Shoprite Hillbrow | B61: 126000 | C61: null | D61: 0 | E61: N/A | F61: N/A | G61: 500kVa | H61: NuVo | I61: South Africa | J61: Gauteng | K61: null | L61: Eastron Meter | M61: PPA | N61: Retail | O61: Producing | Q61: 12B Fund | R61: null | S61: 45590 | T61: SA Energy | U61: null | V61: NO | W61: =IF(ISNUMBER(S61),(TODAY()-S61)/365.25,"") -> 2.0041068 | X61: Low | Y61: High | Z61: Zero Export
A62: Shoprite Ladybrand | B62: 250000 | C62: 110 | D62: 0 | E62: N/A | F62: N/A | G62: N/A | H62: N/A | I62: South Africa | J62: Free state | K62: 248 Voortrekkers Ave, CBD, Ladybrand, 9745, South Africa | L62: Eastron Meter | M62: PPA | N62: Retail | O62: Producing | Q62: 12B Fund | R62: null | S62: 45558 | T62: SA Energy | U62: null | V62: NO | W62: =IF(ISNUMBER(S62),(TODAY()-S62)/365.25,"") -> 2.091718 | X62: Low | Y62: Low | Z62: Zero Export
A63: Shoprite Mayfair | B63: 132680 | C63: 125 | D63: 0 | E63: N/A | F63: N/A | G63: N/A | H63: N/A | I63: South Africa | J63: Gauteng | K63: 1804 Albertina Sisulu Rd, Mayfair, Johannesburg, 2092 | L63: Eastron Meter | M63: PPA | N63: Retail | Q63: SSI | R63: null | S63: 46251 | T63: SA Energy | U63: IsolarCloud | V63: NO | W63: =IF(ISNUMBER(S63),(TODAY()-S63)/365.25,"") -> 0.19438741 | X63: Unknown | Y63: Low | Z63: Zero Export
A64: Shoprite Mini Ganyesa | B64: 240000 | C64: 110 | D64: 0 | E64: N/A | F64: N/A | G64: N/A | H64: NuVo | I64: South Africa | J64: North West | K64: Hartbeespoort, South Africa | L64: Eastron Meter | M64: PPA | N64: Retail | O64: Producing | Q64: 12B Fund | R64: P00078 | S64: 45531 | T64: SA Energy | U64: isloarcloud &Nuvo | V64: NO | W64: =IF(ISNUMBER(S64),(TODAY()-S64)/365.25,"") -> 2.16564 | X64: Low | Y64: Low | Z64: Zero Export
A65: Shoprite Naledi | B65: 125000 | C65: 125 | D65: 0 | E65: N/A | F65: N/A | G65: 500 | H65: NuVo | I65: South Africa | J65: Gauteng | K65: PRVC+MPW Soweto | L65: Eastron Meter | M65: PPA | N65: Retail | O65: Producing | Q65: 12B Fund | R65: null | S65: 45540 | T65: SA Energy | U65: Sunsynk | V65: NO | W65: =IF(ISNUMBER(S65),(TODAY()-S65)/365.25,"") -> 2.1409993 | X65: High | Y65: Low | Z65: Zero Export
A66: Shoprite Newlands | B66: 200000 | C66: null | D66: 0 | E66: N/A | F66: N/A | G66: N/A | H66: N/A | I66: South Africa | J66: KZN | K66: Newlands City Centre, 2 Marble Ray Drive, New Dawn Park, Durban, 4037 | L66: Eastron Meter | M66: PPA | N66: Residential | O66: Producing | Q66: SSI | R66: null | S66: 45992 | T66: SA Energy | U66: null | V66: NO | W66: =IF(ISNUMBER(S66),(TODAY()-S66)/365.25,"") -> 0.90349076 | X66: Low | Y66: Low | Z66: Zero Export
A67: Shoprite SRH Bizana | B67: 148800 | C67: 150 | D67: 0 | E67: N/A | F67: N/A | G67: N/A | H67: N/A | I67: South Africa | J67: Eastern Cape | K67: 4VR3+G6F Mbizana | L67: Eastron Meter | M67: PPA | N67: Retail | O67: Producing | Q67: SSI | R67: null | S67: 46220 | T67: SA Energy | U67: IsolarCloud | V67: NO | W67: =IF(ISNUMBER(S67),(TODAY()-S67)/365.25,"") -> 0.27926078 | X67: Unknown | Y67: Low | Z67: Zero Export
A68: Shoprite Thokoza | B68: 115000 | C68: 125 | D68: 0 | E68: N/A | F68: N/A | G68: N/A | H68: N/A | I68: South Africa | J68: Gauteng | K68: 9102 Khumalo St, Thokoza, 1426 | L68: Eastron Meter | M68: PPA | N68: Retail | O68: Producing | Q68: 12B Fund | R68: null | S68: 45748 | T68: SA Energy | U68: IsolarCloud | V68: NO | W68: =IF(ISNUMBER(S68),(TODAY()-S68)/365.25,"") -> 1.5715264 | X68: High | Y68: Low | Z68: Zero Export
A69: Spring Glade | B69: 116000 | C69: 110 | D69: 0 | E69: N/A | F69: N/A | G69: N/A | H69: N/A | I69: South Africa | J69: Gauteng | K69: VR7R+269 Roodepoort | L69: Alester Meter | M69: PPA | N69: Residential | O69: Reduced Demand | Q69: SSI | R69: null | S69: 44532 | T69: SA Energy | U69: SolisCloud | V69: NO | W69: =IF(ISNUMBER(S69),(TODAY()-S69)/365.25,"") -> 4.9007529 | X69: Low | Y69: Low | Z69: Zero Export
A70: SR Morula TF 1 | B70: 57000 | C70: 50 | D70: 0 | E70: N/A | F70: N/A | G70: N/A | H70: N/A | I70: South Africa | J70: Gauteng | K70: 8408 Mangope Rd, Mabopane Unit M, Mabopane, 0190, South Africa | L70: Eastron Meter | M70: PPA | N70: Retail | O70: Producing | Q70: SSI | R70: P00091 | S70: 45889 | T70: SA Energy | U70: IsolarCloud | V70: YES | W70: =IF(ISNUMBER(S70),(TODAY()-S70)/365.25,"") -> 1.1854894 | X70: High | Y70: Low | Z70: Zero Export
A71: SR Morula TF 1 - Shoprite | B71: 177000 | C71: 125 | D71: 0 | E71: N/A | F71: N/A | G71: N/A | H71: N/A | I71: South Africa | J71: Gauteng | K71: 8409 Mangope Rd, Mabopane Unit M, Mabopane, 0190, South Africa | L71: Eastron Meter | M71: PPA | N71: Retail | O71: Producing | Q71: 12B Fund | R71: P00091 | S71: 45889 | T71: SA Energy | U71: IsolarCloud | V71: NO | W71: =IF(ISNUMBER(S71),(TODAY()-S71)/365.25,"") -> 1.1854894 | X71: High | Y71: Low | Z71: Zero Export
A72: SR Morula TF 2 | B72: 57000 | C72: 50 | D72: 0 | E72: N/A | F72: N/A | G72: N/A | H72: N/A | I72: South Africa | J72: Gauteng | K72: 8410 Mangope Rd, Mabopane Unit M, Mabopane, 0190, South Africa | L72: Eastron Meter | M72: PPA | N72: Retail | O72: Producing | Q72: 12B Fund | R72: P00091 | S72: 45889 | T72: SA Energy | U72: IsolarCloud | V72: YES | W72: =IF(ISNUMBER(S72),(TODAY()-S72)/365.25,"") -> 1.1854894 | X72: High | Y72: Low | Z72: Zero Export
A73: Thakadu Industrial | B73: 61600 | C73: null | D73: 289000 | E73: N/A | F73: N/A | G73: N/A | H73: null | I73: South Africa | J73: North West | K73: D53 Thakadu Gate, Madikwe Game Reserve Molatedi, 2838 | L73: null | M73: PPA | N73: Residential | O73: Reduced Demand | Q73: SSI | R73: null | S73: 45247 | T73: SA Energy | U73: null | V73: NO | W73: =IF(ISNUMBER(S73),(TODAY()-S73)/365.25,"") -> 2.9431896 | X73: Low | Y73: Low | Z73: Zero Export
A74: The Alec | B74: 55000 | C74: 50 | D74: 0 | E74: N/A | F74: N/A | G74: N/A | H74: NuVo | I74: South Africa | J74: Gauteng | K74: 48 Goldreich St, Hillbrow, Johannesburg, 2198, South Africa | L74: null | M74: PPA | N74: Residential | O74: Reduced Demand | Q74: Anuva | R74: null | S74: 45068 | T74: SA Energy | U74: isolarCloud | V74: YES | W74: =IF(ISNUMBER(S74),(TODAY()-S74)/365.25,"") -> 3.4332649 | X74: Low | Y74: Low | Z74: Zero Export
A75: Three Peaks | B75: 40000 | C75: =1*33 -> 33 | D75: 0 | E75: N/A | F75: N/A | G75: N/A | H75: N/A | I75: South Africa | J75: KZN | K75: 22A Underwood Rd, Hatton Estate, Pinetown, 3610 | M75: PPA | N75: Residential | O75: Reduced Demand | Q75: Anuva | R75: P00064 | S75: 44617 | T75: SA Energy | U75: iSolarCloud | V75: NO | W75: =IF(ISNUMBER(S75),(TODAY()-S75)/365.25,"") -> 4.6680356 | X75: Low | Y75: Low | Z75: Exporting
A76: TPF Foods | B76: 34000 | C76: 30 | D76: 0 | E76: N/A | F76: N/A | G76: N/A | H76: null | I76: South Africa | J76: Limpopo | K76: Q2R4+98G Johannesburg | L76: Alester Meter | M76: PPA | N76: Retail | O76: Reduced Demand | Q76: SSI | R76: null | S76: 44351 | T76: SA Energy | U76: null | V76: NO | W76: =IF(ISNUMBER(S76),(TODAY()-S76)/365.25,"") -> 5.3963039 | X76: Low | Y76: Low | Z76: Zero Export
A77: Trouw Nutrition | B77: 103000 | C77: null | D77: 0 | E77: N/A | F77: N/A | G77: N/A | H77: null | I77: South Africa | J77: Gauteng | K77: null | L77: Alester Meter | M77: PPA | N77: Manufacture | O77: Producing | Q77: SSI | R77: null | S77: 44504 | T77: SA Energy | U77: null | V77: NO | W77: =IF(ISNUMBER(S77),(TODAY()-S77)/365.25,"") -> 4.9774127 | X77: Low | Y77: Low | Z77: Zero Export
A78: U Save Botrivier | B78: 33000 | C78: 30 | D78: 0 | E78: N/A | F78: N/A | G78: N/A | H78: N/A | I78: South Africa | J78: Western Cape | K78: 3 8th Ave, Bot River, 7185, South Africa | L78: Eastron Meter | M78: PPA | N78: Retail | O78: Reduced Demand | Q78: SSI | R78: null | S78: 45861 | T78: SA Energy | U78: IsolarCloud | V78: NO | W78: =IF(ISNUMBER(S78),(TODAY()-S78)/365.25,"") -> 1.2621492 | X78: Low | Y78: Low | Z78: Zero Export
A79: Usave Naboomspruit | B79: 29760 | C79: 30 | D79: 0 | E79: N/A | F79: N/A | G79: N/A | H79: N/A | I79: South Africa | J79: Limpopo | K79: 76 Thabo Mbeki St, Mookgophong, 0560 | L79: Eastron Meter | M79: PPA | N79: Retail | Q79: SSI | R79: null | S79: 46185 | T79: SA Energy | U79: IsolarCloud | V79: NO | W79: =IF(ISNUMBER(S79),(TODAY()-S79)/365.25,"") -> 0.37508556 | X79: Unknown | Y79: Low | Z79: Zero Export
A80: Vaal Maseru Klerksdorp | B80: 40000 | D80: 0 | E80: Solar MD | F80: Sunsynk | G80: null | H80: null | I80: South Africa | J80: Free state | K80: Cnr of Mikro and Von Wielligh Streets, Klerksdorp | L80: null | M80: PPA | N80: Commercial | O80: Decommissioned | Q80: SSI | R80: P00044 | S80: null | T80: SA Energy | U80: null | V80: NO | W80: =IF(ISNUMBER(S80),(TODAY()-S80)/365.25,"") | X80: Unknown | Y80: Unknown | Z80: Zero Export
A81: Watt Place Rotoflo | B81: 197000 | C81: =2*110 -> 220 | D81: 0 | E81: N/A | F81: N/A | G81: N/A | H81: NuVo | I81: South Africa | J81: Gauteng | K81: 10 Watt Pl, Kya Sand, Randburg, 2163, South Africa | L81: null | M81: PPA | N81: Manufacture | O81: Producing | Q81: Anuva | R81: P00048 | S81: 45059 | T81: SA Energy | U81: isolarCloud & Nuvo | V81: YES | W81: =IF(ISNUMBER(S81),(TODAY()-S81)/365.25,"") -> 3.4579055 | X81: Low | Y81: Low | Z81: Zero Export
A82: Zwartop Golf Course | B82: 27000 | C82: =1*33 -> 33 | D82: 0 | E82: N/A | F82: N/A | G82: N/A | H82: null | I82: South Africa | J82: Gauteng | K82: ZwartKop Golf and Country club, 108 Golf Avenue Club view Centurion 0157 | L82: null | M82: RTO | N82: Residential | O82: Reduced Demand | Q82: SSI | R82: null | S82: 45188 | T82: SA Energy | U82: null | V82: NO | W82: =IF(ISNUMBER(S82),(TODAY()-S82)/365.25,"") -> 3.1047228 | X82: Low | Y82: Low | Z82: Zero Export
A83: Molapo Crossing Mall | B83: 1113000 | C83: 785 | D83: 480000 | E83: Sigenergy | F83: Sigenergy | G83: N/A | H83: N/A | I83: Botswana | J83: Gaborone | K83: 9V4P+P5J, Gaborone, Botswana | L83: null | M83: PPA | N83: Commercial | Q83: SSI | R83: null | T83: Alensys Solar | W83: =IF(ISNUMBER(S83),(TODAY()-S83)/365.25,"") | X83: Unknown | Y83: Unknown | Z83: Zero Export

Sheet Simulated Production
A1: Site Name | B1: Jan | C1: Feb | D1: Mar | E1: Apr | F1: May | G1: Jun | H1: Jul | I1: Aug | J1: Sep | K1: Oct | L1: Nov | M1: Dec
A2: 21 Melrose | B2: 2634 | C2: 2978 | D2: 2426 | E2: 2082 | F2: 2025 | G2: 1810 | H2: 2016 | I2: 2352 | J2: 2528 | K2: 2675 | L2: 2618 | M2: 2758
A3: African Global Plastics | B3: 26489.3 | C3: 23277.8 | D3: 23704 | E3: 19723.4 | F3: 18790.7 | G3: 16902.6 | H3: 18714.9 | I3: 21796.9 | J3: 24005.1 | K3: 26259.6 | L3: 26494.9 | M3: 27974.1
A4: Alpine Heath Residential | B4: 5335 | C4: 4782 | D4: 5051 | E4: 5133 | F4: 5545 | G4: 5291 | H4: 5201 | I4: 5833 | J4: 5216 | K4: 5258 | L4: 5358 | M4: 5339
A5: Bendstore Plaza Shops | B5: 19132 | C5: 16455 | D5: 18192 | E5: 17513 | F5: 16955 | G5: 15353 | H5: 16159 | I5: 18059 | J5: 18155 | K5: 17437 | L5: 17289 | M5: 19005
A6: Bendstore Spar | B6: 57016.372 | C6: 49003.656 | D6: 54154.745 | E6: 52055.443 | F6: 50303.593 | G6: 45493.302 | H6: 47903.114 | I6: 53629.448 | J6: 54003.213 | K6: 51943.234 | L6: 51542.757 | M6: 56267.013
A7: Beyerskloof | B7: 15319 | C7: 12622 | D7: 12090 | E7: 8698 | F7: 6615 | G7: 5740 | H7: 6183 | I7: 7734 | J7: 9940 | K7: 12572 | L7: 14126 | M7: 15421
A8: BP Parys | B8: 9057 | C8: 8039 | D8: 7862 | E8: 6394 | F8: 6027 | G8: 5319 | H8: 5956 | I8: 7070 | J8: 8021 | K8: 8710 | L8: =9102 -> 9102 | M8: 9142
A9: Buffalo Rock | B9: 2447 | C9: 2204 | D9: 2364 | E9: 1964 | F9: 1813 | G9: 1645 | H9: 1792 | I9: 1960 | J9: 2076 | K9: 2112 | L9: 2039 | M9: 2207
A10: Checkers De Aar | B10: 29655 | C10: 22972 | D10: 22328 | E10: 18096 | F10: 15021 | G10: 13183 | H10: 15099 | I10: 19010 | J10: 21674 | K10: 26757 | L10: 28766 | M10: 31103
A11: Checkers Silverlakes Gen | B11: 23450 | C11: 20245 | D11: 20409 | E11: 16782 | F11: 15700 | G11: 14022 | H11: 15558 | I11: 18491 | J11: 20696 | K11: 22782 | L11: 22890 | M11: 24472
A12: Checkers Silverlakes No Gen | B12: 23450 | C12: 20245 | D12: 20409 | E12: 16782 | F12: 15700 | G12: 14022 | H12: 15558 | I12: 18491 | J12: 20696 | K12: 22782 | L12: 22890 | M12: 24472
A13: Checkrite Inanda | B13: 9627 | C13: 9000 | D13: 8673 | E13: 7260 | F13: 6214 | G13: 5622 | H13: 5969 | I13: 7206 | J13: 7683 | K13: 8926 | L13: 8903 | M13: 9497
A14: Club Houghton | B14: 6408 | C14: 5365 | D14: 5459 | E14: 4611 | F14: 4375 | G14: 3848 | H14: 4305 | I14: 5067 | J14: 5593 | K14: 6237 | L14: 6347 | M14: 6697
A15: Coldstar International | B15: 5761.2 | C15: 5289.7 | D15: 5351.3 | E15: 4476.7 | F15: 4144.2 | G15: 3750.5 | H15: 4019 | I15: 4537.7 | J15: 4477.3 | K15: 4986.7 | L15: 5100.4 | M15: 5950.6
A16: Cultura Fresh | B16: 13109 | C16: 11411 | D16: 11746 | E16: 9262 | F16: 7471 | G16: 6511 | H16: 7170 | I16: 8324 | J16: 9849 | K16: 11513 | L16: 12192 | M16: 12923
A17: Demco | B17: 41895 | C17: 35971 | D17: 36483 | E17: 30848 | F17: 29226 | G17: 26233 | H17: 29069 | I17: 34133 | J17: 37890 | K17: 41280 | L17: 41518 | M17: 43833
A18: Engen Lotus Gardens | B18: 2735 | C18: 2556 | D18: 2535 | E18: 2442 | F18: 2474 | G18: 2756 | H18: 2611 | I18: 2800 | J18: 2707 | K18: 2695 | L18: 2618 | M18: 2708
A19: Giba Gorge Main | B19: 16980 | C19: 15556.6 | D19: 15927.6 | E19: 13677.3 | F19: 12351.6 | G19: 11543.6 | H19: 12195.1 | I19: 13528 | J19: 13644.6 | K19: 15166.4 | L19: 15407.487 | M19: 16842.372
A20: Giba Gorge Storage | B20: 15179.5 | C20: 13524.8 | D20: 13861.9 | E20: 11789.7 | F20: 10618.3 | G20: 9819.1 | H20: 10486.9 | I20: 11678.3 | J20: 11941.8 | K20: 13277 | L20: 13346.218 | M20: 14828.668
... A59: Shoprite Newlands | B59: 34135 | C59: 26981 | D59: 26829 | E59: 20433 | F59: 21068 | G59: 16978 | H59: 19291 | I59: 21448 | J59: 20157 | K59: 25054 | L59: 25471 | M59: 31547
A60: Shoprite Thokoza | B60: 20649 | C60: 17891 | D60: 17668 | E60: =15178 -> 15178 | F60: 14023 | G60: 12327 | H60: 13742 | I60: 16094 | J60: 17988 | K60: 20737 | L60: 20655 | M60: 21136
A61: Spring Glade | B61: 19574.9 | C61: 16723.6 | D61: 17808.6 | E61: 15502.2 | F61: 15075 | G61: 13622.2 | H61: 15167.7 | I61: 17455.2 | J61: 18819 | K61: 19760.2 | L61: 19368.5 | M61: 20469.3
A62: SR Morula TF 1 | B62: 10342 | C62: 8891 | D62: 8671 | E62: 7539 | F62: 6938 | G62: 6138 | H62: 6763 | I62: =7916 -> 7916 | J62: 8738 | K62: 10008 | L62: 9999 | M62: 10268
A63: SR Morula TF 1 - Shoprite | B63: 31888.4 | C63: 27677 | D63: 27300 | E63: 23765 | F63: 21915 | G63: 19368 | H63: 21313 | I63: =24908 -> 24908 | J63: 27534 | K63: 31253 | L63: 31179 | M63: 31893
A64: SR Morula TF 2 | B64: 10668.8 | C64: 9218.6 | D64: 9045 | E64: 7797 | F64: 7144.8 | G64: 6299.2 | H64: 6941.6 | I64: =8155.7 -> 8155.7 | J64: 9060 | K64: 10392 | L64: 10393 | M64: 10647
A65: Thakadu Industrial
A66: The Alec | B66: 8222 | C66: 6998 | D66: 7059 | E66: 5574 | F66: 5282 | G66: 4730 | H66: 5256 | I66: 6045 | J66: 7051 | K66: 8056 | L66: 8145 | M66: 8740
A67: Three Peaks | B67: 5698.8 | C67: 5080.8 | D67: 5209.7 | E67: 4357.5 | F67: 3906.6 | G67: 3553 | H67: 3801.5 | I67: 4316 | J67: 4437 | K67: 5034.3 | L67: 5106.1 | M67: 5754.2
A68: TPF Foods | B68: 5045.9 | C68: 4360.2 | D68: 4711.1 | E68: 4084.1 | F68: 4125.1 | G68: 3778.7 | H68: 4137.8 | I68: 4655.4 | J68: 4964.6 | K68: 5199.2 | L68: 4977 | M68: 5354.9
A69: Trouw Nutrition | B69: 15814.1 | C69: 14182.5 | D69: 15127.6 | E69: 13566.2 | F69: 13865.8 | G69: 12963.1 | H69: 14146.2 | I69: 15603.1 | J69: 15929.8 | K69: 16382.7 | L69: 15892.2 | M69: 16746.5
A70: U Save Botrivier | B70: 8111 | C70: 6915 | D70: 6721 | E70: 5701 | F70: 5135 | G70: 4368 | H70: 4517 | I70: 5248 | J70: 5835 | K70: 7211 | L70: 7571 | M70: 8107
A71: Watt Place Rotoflo | B71: 31142 | C71: 26504 | D71: 26827 | E71: 22270 | F71: 21135 | G71: 18949 | H71: 21000 | I71: 24518 | J71: 27252 | K71: 30285 | L71: 29971 | M71: 32254
A72: Zwartop Golf Course | B72: N/A | C72: N/A | D72: N/A | E72: N/A | F72: N/A | G72: N/A | H72: N/A | I72: N/A | J72: N/A | K72: N/A | L72: N/A | M72: N/A
A73: Shoprite Ekhaya | B73: 31534 | C73: 27088 | D73: 25946 | E73: 22097 | F73: 19717 | G73: 17225 | H73: 19287 | I73: 23158 | J73: 26490 | K73: 30317 | L73: 30935 | M73: 31977
A74: Grootpan | B74: 32305 | C74: 29685 | D74: 31046 | E74: 28456 | F74: 28669 | G74: 26032 | H74: 28480 | I74: 31722 | J74: 32846 | K74: 34908 | L74: 33468 | M74: 32717
A75: Roan Foods | B75: 20178 | C75: 17954 | D75: 19150 | E75: 18060 | F75: 18124 | G75: 15908 | H75: 16827 | I75: 19405 | J75: 19981 | K75: 22401 | L75: 20125 | M75: 20771
A76: Engen Kaalfontein | B76: 19301 | C76: 16753 | D76: 16260 | E76: 13800 | F76: 12669 | G76: 11099 | H76: 12207 | I76: 14565.3 | J76: 16481.3 | K76: 18948 | L76: 19155 | M76: 19406
A77: Checkers Lichtenburg | B77: 29390 | C77: 25795 | D77: 25594 | E77: 22145 | F77: 20838 | G77: 18631 | H77: 20290 | I77: 23679 | J77: 26288 | K77: 29851 | L77: 30171 | M77: 30447
A78: Alpine Heath Resort | B78: 32086 | C78: 28761 | D78: 30379 | E78: 30915 | F78: 33245 | G78: 31827 | H78: 31168 | I78: 35166 | J78: 31389 | K78: 31629 | L78: 32213 | M78: 32115
A79: Usave Naboomspruit | B79: 6637 | C79: 5857 | D79: 5923 | E79: 5363 | F79: 5166 | G79: 4726 | H79: 5161 | I79: 5838 | J79: 6186 | K79: 6701 | L79: 6553 | M79: 6655

Sheet OG
A1: Site Name | B1: Offtake Guarantee | C1: Expected Utilisation% | D1: Age | E1: As-Built kWh | F1: Guaranteed Generation (kWh) | G1: Unavailability kWh | H1: Correct kWh | I1: Actual Generation (kWh) | J1: Shortfall (kWh) | K1: Performance Rate | L1: Notes
A2: Alpine Heath Residential | B2: YES | C2: {=IFERROR(INDEX('Expected Production'!$B$2:$B$79,MATCH(TRIM($A2),INDEX(TRIM('Expected Production'!$A$2:$A$79),0),0)),"Not found")} -> 0.9 | D2: {=_xlfn.IFNA(_xlfn.XLOOKUP(TRIM(A2),TRIM(site_tech_info!$A$2:$A$79),site_tech_info!$W$2:$W$79),"")} -> 1.8179329 | E2: {=IFERROR(SUM(INDEX('Simulated Production'!$B$2:$M$79,MATCH(TRIM($A2),INDEX(TRIM('Simulated Production'!$A$2:$A$79),0),0),0)),"Not found")} -> 63342 | F2: =(Table2[[#This Row],[As-Built kWh]]*Table2[[#This Row],[Expected Utilisation%]])*(1-0.007)^(Table2[[#This Row],[Age]]) -> 56284.423 | G2: =(4681+4732*(9/31)+4546*(10/31)+4620*(3/30)+4991+4762)*(1-0.007)^(Table2[[#This Row],[Age]]) -> 17511.201 | H2: =F2-G2 -> 38773.222 | I2: {=SUMPRODUCT((TRIM(measured[Site Name])=TRIM($A2))*(measured[Date]>=DATE(2025,7,1))*(measured[Date]<=DATE(2026,6,30))*measured[Measured Value (kWh)])} -> 34917.2 | J2: =I2-H2 -> -3856.022 | K2: =(Table2[[#This Row],[Actual Generation (kWh)]]/Table2[[#This Row],[Correct kWh]])*100 -> 90.054935 | L2: The system performed moderately. A few technical issues were experienced , the expected system production was corrected and system restored to normal production.
A3: Checkrite Inanda | B3: YES | C3: {=IFERROR(INDEX('Expected Production'!$B$2:$B$79,MATCH(TRIM($A3),INDEX(TRIM('Expected Production'!$A$2:$A$79),0),0)),"Not found")} -> 0.9 | D3: {=_xlfn.IFNA(_xlfn.XLOOKUP(TRIM(A3),TRIM(site_tech_info!$A$2:$A$79),site_tech_info!$W$2:$W$79),"")} -> 2.329911 | E3: {=IFERROR(SUM(INDEX('Simulated Production'!$B$2:$M$79,MATCH(TRIM($A3),INDEX(TRIM('Simulated Production'!$A$2:$A$79),0),0),0)),"Not found")} -> 94580 | F3: =(Table2[[#This Row],[As-Built kWh]]*Table2[[#This Row],[Expected Utilisation%]])*(1-0.007)^(Table2[[#This Row],[Age]]) -> 83740.17 | G3: =(8100*(1/2)+7806*(1/2))*(1-0.007)^(Table2[[#This Row],[Age]]) -> 7823.8948 | H3: =F3-G3 -> 75916.275 | I3: {=SUMPRODUCT((TRIM(measured[Site Name])=TRIM($A3))*(measured[Date]>=DATE(2025,7,1))*(measured[Date]<=DATE(2026,6,30))*measured[Measured Value (kWh)])} -> 76046.756 | J3: =I3-H3 -> 130.48045 | K3: =(Table2[[#This Row],[Actual Generation (kWh)]]/Table2[[#This Row],[Correct kWh]])*100 -> 100.17187 | L3: The system performed as expected. A few technical issues were experienced during Feb 2026, the expected system production was corrected and system restored to normal production.
A4: Demco | B4: YES | C4: {=IFERROR(INDEX('Expected Production'!$B$2:$B$79,MATCH(TRIM($A4),INDEX(TRIM('Expected Production'!$A$2:$A$79),0),0)),"Not found")} -> 0.8 | D4: {=_xlfn.IFNA(_xlfn.XLOOKUP(TRIM(A4),TRIM(site_tech_info!$A$2:$A$79),site_tech_info!$W$2:$W$79),"")} -> 2.3600274 | E4: {=IFERROR(SUM(INDEX('Simulated Production'!$B$2:$M$79,MATCH(TRIM($A4),INDEX(TRIM('Simulated Production'!$A$2:$A$79),0),0),0)),"Not found")} -> 428379 | F4: =(Table2[[#This Row],[As-Built kWh]]*Table2[[#This Row],[Expected Utilisation%]])*(1-0.007)^(Table2[[#This Row],[Age]]) -> 337068.6 | G4: =(23255*(7/30)+35066*(2/30))*(1-0.007)^(Table2[[#This Row],[Age]]) -> 7636.2489 | H4: =F4-G4 -> 329432.36 | I4: {=SUMPRODUCT((TRIM(measured[Site Name])=TRIM($A4))*(measured[Date]>=DATE(2025,7,1))*(measured[Date]<=DATE(2026,6,30))*measured[Measured Value (kWh)])} -> 166060.42 | J4: =I4-H4 -> -163371.94 | K4: =(Table2[[#This Row],[Actual Generation (kWh)]]/Table2[[#This Row],[Correct kWh]])*100 -> 50.408048 | L4: The system performed as expected. As previously experienced, the site demand is low and the system was not fully utilized.
A5: Golden Spot Resort | B5: YES | C5: {=IFERROR(INDEX('Expected Production'!$B$2:$B$79,MATCH(TRIM($A5),INDEX(TRIM('Expected Production'!$A$2:$A$79),0),0)),"Not found")} -> 0.9 | D5: {=_xlfn.IFNA(_xlfn.XLOOKUP(TRIM(A5),TRIM(site_tech_info!$A$2:$A$79),site_tech_info!$W$2:$W$79),"")} -> 3.4195756 | E5: {=IFERROR(SUM(INDEX('Simulated Production'!$B$2:$M$79,MATCH(TRIM($A5),INDEX(TRIM('Simulated Production'!$A$2:$A$79),0),0),0)),"Not found")} -> 45617 | F5: =(Table2[[#This Row],[As-Built kWh]]*Table2[[#This Row],[Expected Utilisation%]])*(1-0.007)^(Table2[[#This Row],[Age]]) -> 40080.853 | G5: =(4681+3499*(9/31)+2081*(10/31)+4317*(3/30)+4991*(18/31))*(1-0.007)^(Table2[[#This Row],[Age]]) -> 9467.6512 | H5: =F5-G5 -> 30613.202 | I5: {=SUMPRODUCT((TRIM(measured[Site Name])=TRIM($A5))*(measured[Date]>=DATE(2025,7,1))*(measured[Date]<=DATE(2026,6,30))*measured[Measured Value (kWh)])} -> 24341.6 | J5: =I5-H5 -> -6271.6017 | K5: =(Table2[[#This Row],[Actual Generation (kWh)]]/Table2[[#This Row],[Correct kWh]])*100 -> 79.513408
A6: Golden Spot Shops | B6: YES | C6: {=IFERROR(INDEX('Expected Production'!$B$2:$B$79,MATCH(TRIM($A6),INDEX(TRIM('Expected Production'!$A$2:$A$79),0),0)),"Not found")} -> 0.9 | D6: {=_xlfn.IFNA(_xlfn.XLOOKUP(TRIM(A6),TRIM(site_tech_info!$A$2:$A$79),site_tech_info!$W$2:$W$79),"")} -> 3.4223135 | E6: {=IFERROR(SUM(INDEX('Simulated Production'!$B$2:$M$79,MATCH(TRIM($A6),INDEX(TRIM('Simulated Production'!$A$2:$A$79),0),0),0)),"Not found")} -> 40942 | F6: =(Table2[[#This Row],[As-Built kWh]]*Table2[[#This Row],[Expected Utilisation%]])*(1-0.007)^(Table2[[#This Row],[Age]]) -> 35972.526 | G6: =(2974*(24/31)+3147*(2/30))*(1-0.007)^(Table2[[#This Row],[Age]]) -> 2452.5762 | H6: =F6-G6 -> 33519.95 | I6: {=SUMPRODUCT((TRIM(measured[Site Name])=TRIM($A6))*(measured[Date]>=DATE(2025,7,1))*(measured[Date]<=DATE(2026,6,30))*measured[Measured Value (kWh)])} -> 32105.5 | J6: =I6-H6 -> -1414.4498 | K6: =(Table2[[#This Row],[Actual Generation (kWh)]]/Table2[[#This Row],[Correct kWh]])*100 -> 95.780275 | L6: Testing
A7: Hilston Rotoflo | B7: YES | C7: {=IFERROR(INDEX('Expected Production'!$B$2:$B$79,MATCH(TRIM($A7),INDEX(TRIM('Expected Production'!$A$2:$A$79),0),0)),"Not found")} -> 0.85 | D7: {=_xlfn.IFNA(_xlfn.XLOOKUP(TRIM(A7),TRIM(site_tech_info!$A$2:$A$79),site_tech_info!$W$2:$W$79),"")} -> 3.4661191 | E7: {=IFERROR(SUM(INDEX('Simulated Production'!$B$2:$M$79,MATCH(TRIM($A7),INDEX(TRIM('Simulated Production'!$A$2:$A$79),0),0),0)),"Not found")} -> 319608 | F7: =(Table2[[#This Row],[As-Built kWh]]*Table2[[#This Row],[Expected Utilisation%]])*(1-0.007)^(Table2[[#This Row],[Age]]) -> 265132.09 | G7: 0 | H7: =F7-G7 -> 265132.09 | I7: {=SUMPRODUCT((TRIM(measured[Site Name])=TRIM($A7))*(measured[Date]>=DATE(2025,7,1))*(measured[Date]<=DATE(2026,6,30))*measured[Measured Value (kWh)])} -> 254905.02 | J7: =I7-H7 -> -10227.072 | K7: =(Table2[[#This Row],[Actual Generation (kWh)]]/Table2[[#This Row],[Correct kWh]])*100 -> 96.14265 | L7: The system performed as expected. System produced 96% of expected production due to 20 days of closure during December-Jan.
A8: Huis Herfsblaar | B8: YES | C8: {=IFERROR(INDEX('Expected Production'!$B$2:$B$79,MATCH(TRIM($A8),INDEX(TRIM('Expected Production'!$A$2:$A$79),0),0)),"Not found")} -> 0.9 | D8: {=_xlfn.IFNA(_xlfn.XLOOKUP(TRIM(A8),TRIM(site_tech_info!$A$2:$A$79),site_tech_info!$W$2:$W$79),"")} -> 2.3518138 | E8: {=IFERROR(SUM(INDEX('Simulated Production'!$B$2:$M$79,MATCH(TRIM($A8),INDEX(TRIM('Simulated Production'!$A$2:$A$79),0),0),0)),"Not found")} -> 355254 | F8: =(Table2[[#This Row],[As-Built kWh]]*Table2[[#This Row],[Expected Utilisation%]])*(1-0.007)^(Table2[[#This Row],[Age]]) -> 314489.89 | G8: =((22354*(0.5)+26969*(7/31))*(1-0.007)^(Table2[[#This Row],[Age]]))*(1-0.007)^(Table2[[#This Row],[Age]]) -> 16705.582 | H8: =F8-G8 -> 297784.31 | I8: {=SUMPRODUCT((TRIM(measured[Site Name])=TRIM($A8))*(measured[Date]>=DATE(2025,7,1))*(measured[Date]<=DATE(2026,6,30))*measured[Measured Value (kWh)])} -> 271722.18 | J8: =I8-H8 -> -26062.127 | K8: =(Table2[[#This Row],[Actual Generation (kWh)]]/Table2[[#This Row],[Correct kWh]])*100 -> 91.247985 | L8: The system performed as expected. A few technical issues were experienced during July - Aug 2025, the expected system production was corrected and system restored to normal production.
A9: Mdluli | B9: YES | C9: {=IFERROR(INDEX('Expected Production'!$B$2:$B$79,MATCH(TRIM($A9),INDEX(TRIM('Expected Production'!$A$2:$A$79),0),0)),"Not found")} -> 0.8 | D9: {=_xlfn.IFNA(_xlfn.XLOOKUP(TRIM(A9),TRIM(site_tech_info!$A$2:$A$79),site_tech_info!$W$2:$W$79),"")} -> 2.5270363 | E9: {=IFERROR(SUM(INDEX('Simulated Production'!$B$2:$M$79,MATCH(TRIM($A9),INDEX(TRIM('Simulated Production'!$A$2:$A$79),0),0),0)),"Not found")} -> 200775 | F9: =(Table2[[#This Row],[As-Built kWh]]*Table2[[#This Row],[Expected Utilisation%]])*(1-0.007)^(Table2[[#This Row],[Age]]) -> 157793.92 | G9: =('Expected Production'!I33*0.5+'Expected Production'!C33*0.8)*(1-0.007)^(Table2[[#This Row],[Age]]) -> 17807.233 | H9: =F9-G9 -> 139986.69 | I9: {=SUMPRODUCT((TRIM(measured[Site Name])=TRIM($A9))*(measured[Date]>=DATE(2025,7,1))*(measured[Date]<=DATE(2026,6,30))*measured[Measured Value (kWh)])} -> 147166.31 | J9: =I9-H9 -> 7179.6246 | K9: =(Table2[[#This Row],[Actual Generation (kWh)]]/Table2[[#This Row],[Correct kWh]])*100 -> 105.12879 | L9: The system performed as expected. A few technical issues were experienced during July - Aug 2025 and Jan 2026 which limited inverter production during repairs, the expected system production was corrected and system restored to normal production.
A10: Meredale Heights | B10: YES | C10: {=IFERROR(INDEX('Expected Production'!$B$2:$B$79,MATCH(TRIM($A10),INDEX(TRIM('Expected Production'!$A$2:$A$79),0),0)),"Not found")} -> 0.9 | D10: {=_xlfn.IFNA(_xlfn.XLOOKUP(TRIM(A10),TRIM(site_tech_info!$A$2:$A$79),site_tech_info!$W$2:$W$79),"")} -> 2.9404517 | E10: {=IFERROR(SUM(INDEX('Simulated Production'!$B$2:$M$79,MATCH(TRIM($A10),INDEX(TRIM('Simulated Production'!$A$2:$A$79),0),0),0)),"Not found")} -> 73186 | F10: =(Table2[[#This Row],[As-Built kWh]]*Table2[[#This Row],[Expected Utilisation%]])*(1-0.007)^(Table2[[#This Row],[Age]]) -> 64520.828 | G10: 0 | H10: =F10-G10 -> 64520.828 | I10: {=SUMPRODUCT((TRIM(measured[Site Name])=TRIM($A10))*(measured[Date]>=DATE(2025,7,1))*(measured[Date]<=DATE(2026,6,30))*measured[Measured Value (kWh)])} -> 61467.39 | J10: =I10-H10 -> -3053.4382 | K10: =(Table2[[#This Row],[Actual Generation (kWh)]]/Table2[[#This Row],[Correct kWh]])*100 -> 95.267516 | L10: The system performed as expected. As previously experienced, the site demand is low and the system was not fully utilized.
A11: Opal Students | B11: YES | C11: {=IFERROR(INDEX('Expected Production'!$B$2:$B$79,MATCH(TRIM($A11),INDEX(TRIM('Expected Production'!$A$2:$A$79),0),0)),"Not found")} -> 0.9 | D11: {=_xlfn.IFNA(_xlfn.XLOOKUP(TRIM(A11),TRIM(site_tech_info!$A$2:$A$79),site_tech_info!$W$2:$W$79),"")} -> 3.1430527 | E11: {=IFERROR(SUM(INDEX('Simulated Production'!$B$2:$M$79,MATCH(TRIM($A11),INDEX(TRIM('Simulated Production'!$A$2:$A$79),0),0),0)),"Not found")} -> 66026 | F11: =(Table2[[#This Row],[As-Built kWh]]*Table2[[#This Row],[Expected Utilisation%]])*(1-0.007)^(Table2[[#This Row],[Age]]) -> 58125.784 | G11: 0 | H11: =F11-G11 -> 58125.784 | I11: {=SUMPRODUCT((TRIM(measured[Site Name])=TRIM($A11))*(measured[Date]>=DATE(2025,7,1))*(measured[Date]<=DATE(2026,6,30))*measured[Measured Value (kWh)])} -> 46668.7 | J11: =I11-H11 -> -11457.084 | K11: =(Table2[[#This Row],[Actual Generation (kWh)]]/Table2[[#This Row],[Correct kWh]])*100 -> 80.289154 | L11: Testing
A12: Plastiplate | B12: YES | C12: {=IFERROR(INDEX('Expected Production'!$B$2:$B$79,MATCH(TRIM($A12),INDEX(TRIM('Expected Production'!$A$2:$A$79),0),0)),"Not found")} -> 0.75 | D12: {=_xlfn.IFNA(_xlfn.XLOOKUP(TRIM(A12),TRIM(site_tech_info!$A$2:$A$79),site_tech_info!$W$2:$W$79),"")} -> 4.4736482 | E12: {=IFERROR(SUM(INDEX('Simulated Production'!$B$2:$M$79,MATCH(TRIM($A12),INDEX(TRIM('Simulated Production'!$A$2:$A$79),0),0),0)),"Not found")} -> 125072.5 | F12: =(Table2[[#This Row],[As-Built kWh]]*Table2[[#This Row],[Expected Utilisation%]])*(1-0.007)^(Table2[[#This Row],[Age]]) -> 90902.349 | G12: =(5691*0.3*(1-0.007)^(Table2[[#This Row],[Age]]))*(1-0.007)^(Table2[[#This Row],[Age]]) -> 1603.2966 | H12: =F12-G12 -> 89299.052 | I12: {=SUMPRODUCT((TRIM(measured[Site Name])=TRIM($A12))*(measured[Date]>=DATE(2025,7,1))*(measured[Date]<=DATE(2026,6,30))*measured[Measured Value (kWh)])} -> 72438 | J12: =I12-H12 -> -16861.052 | K12: =(Table2[[#This Row],[Actual Generation (kWh)]]/Table2[[#This Row],[Correct kWh]])*100 -> 81.118442 | L12: Testing
A13: Riverside Lodge | B13: YES | C13: {=IFERROR(INDEX('Expected Production'!$B$2:$B$79,MATCH(TRIM($A13),INDEX(TRIM('Expected Production'!$A$2:$A$79),0),0)),"Not found")} -> 0.85 | D13: {=_xlfn.IFNA(_xlfn.XLOOKUP(TRIM(A13),TRIM(site_tech_info!$A$2:$A$79),site_tech_info!$W$2:$W$79),"")} -> 3.4606434 | E13: {=IFERROR(SUM(INDEX('Simulated Production'!$B$2:$M$79,MATCH(TRIM($A13),INDEX(TRIM('Simulated Production'!$A$2:$A$79),0),0),0)),"Not found")} -> 225937 | F13: =(Table2[[#This Row],[As-Built kWh]]*Table2[[#This Row],[Expected Utilisation%]])*(1-0.007)^(Table2[[#This Row],[Age]]) -> 187434.15 | G13: 0 | H13: =F13-G13 -> 187434.15 | I13: {=SUMPRODUCT((TRIM(measured[Site Name])=TRIM($A13))*(measured[Date]>=DATE(2025,7,1))*(measured[Date]<=DATE(2026,6,30))*measured[Measured Value (kWh)])} -> 176720.45 | J13: =I13-H13 -> -10713.7 | K13: =(Table2[[#This Row],[Actual Generation (kWh)]]/Table2[[#This Row],[Correct kWh]])*100 -> 94.284019 | L13: Testing
A14: The Alec | B14: YES | C14: {=IFERROR(INDEX('Expected Production'!$B$2:$B$79,MATCH(TRIM($A14),INDEX(TRIM('Expected Production'!$A$2:$A$79),0),0)),"Not found")} -> 0.925 | D14: {=_xlfn.IFNA(_xlfn.XLOOKUP(TRIM(A14),TRIM(site_tech_info!$A$2:$A$79),site_tech_info!$W$2:$W$79),"")} -> 3.4332649 | E14: {=IFERROR(SUM(INDEX('Simulated Production'!$B$2:$M$79,MATCH(TRIM($A14),INDEX(TRIM('Simulated Production'!$A$2:$A$79),0),0),0)),"Not found")} -> 81158 | F14: =(Table2[[#This Row],[As-Built kWh]]*Table2[[#This Row],[Expected Utilisation%]])*(1-0.007)^(Table2[[#This Row],[Age]]) -> 73282.29 | G14: 0 | H14: =F14-G14 -> 73282.29 | I14: {=SUMPRODUCT((TRIM(measured[Site Name])=TRIM($A14))*(measured[Date]>=DATE(2025,7,1))*(measured[Date]<=DATE(2026,6,30))*measured[Measured Value (kWh)])} -> 56043.3 | J14: =I14-H14 -> -17238.99 | K14: =(Table2[[#This Row],[Actual Generation (kWh)]]/Table2[[#This Row],[Correct kWh]])*100 -> 76.475913 | L14: Testing
A15: Watt Place Rotoflo | B15: YES | C15: {=IFERROR(INDEX('Expected Production'!$B$2:$B$79,MATCH(TRIM($A15),INDEX(TRIM('Expected Production'!$A$2:$A$79),0),0)),"Not found")} -> 0.9 | D15: {=_xlfn.IFNA(_xlfn.XLOOKUP(TRIM(A15),TRIM(site_tech_info!$A$2:$A$79),site_tech_info!$W$2:$W$79),"")} | E15: {=IFERROR(SUM(INDEX('Simulated Production'!$B$2:$M$79,MATCH(TRIM($A15),INDEX(TRIM('Simulated Production'!$A$2:$A$79),0),0),0)),"Not found")} -> 312107 | F15: =(Table2[[#This Row],[As-Built kWh]]*Table2[[#This Row],[Expected Utilisation%]])*(1-0.007)^(Table2[[#This Row],[Age]]) -> #VALUE! | G15: 0 | H15: =F15-G15 -> #VALUE! | I15: {=SUMPRODUCT((TRIM(measured[Site Name])=TRIM($A15))*(measured[Date]>=DATE(2025,7,1))*(measured[Date]<=DATE(2026,6,30))*measured[Measured Value (kWh)])} -> 237169.27 | J15: =I15-H15 -> #VALUE! | K15: =(Table2[[#This Row],[Actual Generation (kWh)]]/Table2[[#This Row],[Correct kWh]])*100 -> #VALUE! | L15: Testing
A16: SR Morula TF 1 | B16: YES | C16: {=IFERROR(INDEX('Expected Production'!$B$2:$B$79,MATCH(TRIM($A16),INDEX(TRIM('Expected Production'!$A$2:$A$79),0),0)),"Not found")} -> 0.9 | D16: {=_xlfn.IFNA(_xlfn.XLOOKUP(TRIM(A16),TRIM(site_tech_info!$A$2:$A$79),site_tech_info!$W$2:$W$79),"")} -> 1.1854894 | E16: {=IFERROR(SUM(INDEX('Simulated Production'!$B$2:$M$79,MATCH(TRIM($A16),INDEX(TRIM('Simulated Production'!$A$2:$A$79),0),0),0)),"Not found")} -> 102211 | F16: =(Table2[[#This Row],[As-Built kWh]]*Table2[[#This Row],[Expected Utilisation%]])*(1-0.007)^(Table2[[#This Row],[Age]]) -> 91227.025 | G16: =(6087*(1-0.007)^(Table2[[#This Row],[Age]]))*(1-0.007)^(Table2[[#This Row],[Age]]) -> 5986.4593 | H16: =F16-G16 -> 85240.566 | I16: {=SUMPRODUCT((TRIM(measured[Site Name])=TRIM($A16))*(measured[Date]>=DATE(2025,7,1))*(measured[Date]<=DATE(2026,6,30))*measured[Measured Value (kWh)])} -> 77775.48 | J16: =I16-H16 -> -7465.0859 | K16: =(Table2[[#This Row],[Actual Generation (kWh)]]/Table2[[#This Row],[Correct kWh]])*100 -> 91.242332 | L16: Testing
A17: SR Morula TF 2 | B17: YES | C17: {=IFERROR(INDEX('Expected Production'!$B$2:$B$79,MATCH(TRIM($A17),INDEX(TRIM('Expected Production'!$A$2:$A$79),0),0)),"Not found")} -> 0.9 | D17: {=_xlfn.IFNA(_xlfn.XLOOKUP(TRIM(A17),TRIM(site_tech_info!$A$2:$A$79),site_tech_info!$W$2:$W$79),"")} -> 1.1854894 | E17: {=IFERROR(SUM(INDEX('Simulated Production'!$B$2:$M$79,MATCH(TRIM($A17),INDEX(TRIM('Simulated Production'!$A$2:$A$79),0),0),0)),"Not found")} -> 105762.7 | F17: =(Table2[[#This Row],[As-Built kWh]]*Table2[[#This Row],[Expected Utilisation%]])*(1-0.007)^(Table2[[#This Row],[Age]]) -> 94397.046 | G17: =(6247*(1-0.007)^(Table2[[#This Row],[Age]]))*(1-0.007)^(Table2[[#This Row],[Age]]) -> 6143.8165 | H17: =F17-G17 -> 88253.23 | I17: {=SUMPRODUCT((TRIM(measured[Site Name])=TRIM($A17))*(measured[Date]>=DATE(2025,7,1))*(measured[Date]<=DATE(2026,6,30))*measured[Measured Value (kWh)])} -> 78264.64 | J17: =I17-H17 -> -9988.5897 | K17: =(Table2[[#This Row],[Actual Generation (kWh)]]/Table2[[#This Row],[Correct kWh]])*100 -> 88.681899 | L17: Testing
A18: Olievenhoutbosch 1 | B18: YES | C18: {=IFERROR(INDEX('Expected Production'!$B$2:$B$79,MATCH(TRIM($A18),INDEX(TRIM('Expected Production'!$A$2:$A$79),0),0)),"Not found")} -> 0.9 | D18: {=_xlfn.IFNA(_xlfn.XLOOKUP(TRIM(A18),TRIM(site_tech_info!$A$2:$A$79),site_tech_info!$W$2:$W$79),"")} -> 1.0896646 | E18: {=IFERROR(SUM(INDEX('Simulated Production'!$B$2:$M$79,MATCH(TRIM($A18),INDEX(TRIM('Simulated Production'!$A$2:$A$79),0),0),0)),"Not found")} -> 524973 | F18: =(Table2[[#This Row],[As-Built kWh]]*Table2[[#This Row],[Expected Utilisation%]])*(1-0.007)^(Table2[[#This Row],[Age]]) -> 468872.95 | G18: =(31229+36815+40778+47657*(5/30))*(1-0.007)^(Table2[[#This Row],[Age]]) -> 115874.47 | H18: =F18-G18 -> 352998.48 | I18: {=SUMPRODUCT((TRIM(measured[Site Name])=TRIM($A18))*(measured[Date]>=DATE(2025,7,1))*(measured[Date]<=DATE(2026,6,30))*measured[Measured Value (kWh)])} -> 300497.96 | J18: =I18-H18 -> -52500.526 | K18: =(Table2[[#This Row],[Actual Generation (kWh)]]/Table2[[#This Row],[Correct kWh]])*100 -> 85.127266 | L18: Testing
A19: Olievenhoutbosch 2 | B19: YES | C19: {=IFERROR(INDEX('Expected Production'!$B$2:$B$79,MATCH(TRIM($A19),INDEX(TRIM('Expected Production'!$A$2:$A$79),0),0)),"Not found")} -> 0.9 | D19: {=_xlfn.IFNA(_xlfn.XLOOKUP(TRIM(A19),TRIM(site_tech_info!$A$2:$A$79),site_tech_info!$W$2:$W$79),"")} -> 1.0896646 | E19: {=IFERROR(SUM(INDEX('Simulated Production'!$B$2:$M$79,MATCH(TRIM($A19),INDEX(TRIM('Simulated Production'!$A$2:$A$79),0),0),0)),"Not found")} -> 138565 | F19: =(Table2[[#This Row],[As-Built kWh]]*Table2[[#This Row],[Expected Utilisation%]])*(1-0.007)^(Table2[[#This Row],[Age]]) -> 123757.57 | G19: =(8307+9721+10756+12191*(5/30))*(1-0.007)^(Table2[[#This Row],[Age]]) -> 30580.855 | H19: =F19-G19 -> 93176.711 | I19: {=SUMPRODUCT((TRIM(measured[Site Name])=TRIM($A19))*(measured[Date]>=DATE(2025,7,1))*(measured[Date]<=DATE(2026,6,30))*measured[Measured Value (kWh)])} -> 81974.633 | J19: =I19-H19 -> -11202.079 | K19: =(Table2[[#This Row],[Actual Generation (kWh)]]/Table2[[#This Row],[Correct kWh]])*100 -> 87.977598 | L19: Testing
A20: IPID - Floor 6 | B20: YES | C20: {=IFERROR(INDEX('Expected Production'!$B$2:$B$79,MATCH(TRIM($A20),INDEX(TRIM('Expected Production'!$A$2:$A$79),0),0)),"Not found")} -> 0.9 | D20: {=_xlfn.IFNA(_xlfn.XLOOKUP(TRIM(A20),TRIM(site_tech_info!$A$2:$A$79),site_tech_info!$W$2:$W$79),"")} -> 1.0622861 | E20: {=IFERROR(SUM(INDEX('Simulated Production'!$B$2:$M$79,MATCH(TRIM($A20),INDEX(TRIM('Simulated Production'!$A$2:$A$79),0),0),0)),"Not found")} -> 89076 | F20: =(Table2[[#This Row],[As-Built kWh]]*Table2[[#This Row],[Expected Utilisation%]])*(1-0.007)^(Table2[[#This Row],[Age]]) -> 79572.398 | G20: =(5785+6585+7019+7479+7553+7553*(3/30))*(1-0.007)^(Table2[[#This Row],[Age]]) -> 34914.786 | H20: =F20-G20 -> 44657.612 | I20: {=SUMPRODUCT((TRIM(measured[Site Name])=TRIM($A20))*(measured[Date]>=DATE(2025,7,1))*(measured[Date]<=DATE(2026,6,30))*measured[Measured Value (kWh)])} -> 33061.7 | J20: =I20-H20 -> -11595.912 | K20: =(Table2[[#This Row],[Actual Generation (kWh)]]/Table2[[#This Row],[Correct kWh]])*100 -> 74.03374 | L20: Testing
A21: IPID - Floor 4 | B21: YES | C21: {=IFERROR(INDEX('Expected Production'!$B$2:$B$79,MATCH(TRIM($A21),INDEX(TRIM('Expected Production'!$A$2:$A$79),0),0)),"Not found")} -> 0.9 | D21: {=_xlfn.IFNA(_xlfn.XLOOKUP(TRIM(A21),TRIM(site_tech_info!$A$2:$A$79),site_tech_info!$W$2:$W$79),"")} -> 1.0622861 | E21: {=IFERROR(SUM(INDEX('Simulated Production'!$B$2:$M$79,MATCH(TRIM($A21),INDEX(TRIM('Simulated Production'!$A$2:$A$79),0),0),0)),"Not found")} -> 89076 | F21: =(Table2[[#This Row],[As-Built kWh]]*Table2[[#This Row],[Expected Utilisation%]])*(1-0.007)^(Table2[[#This Row],[Age]]) -> 79572.398 | G21: =(5785+6585+7019+7479+7553+7553*(3/30))*(1-0.007)^(Table2[[#This Row],[Age]]) -> 34914.786 | H21: =F21-G21 -> 44657.612 | I21: {=SUMPRODUCT((TRIM(measured[Site Name])=TRIM($A21))*(measured[Date]>=DATE(2025,7,1))*(measured[Date]<=DATE(2026,6,30))*measured[Measured Value (kWh)])} -> 47460.3 | J21: =I21-H21 -> 2802.6883 | K21: =(Table2[[#This Row],[Actual Generation (kWh)]]/Table2[[#This Row],[Correct kWh]])*100 -> 106.27595 | L21: Testing
A22: Engen Lotus Gardens | B22: YES | C22: {=IFERROR(INDEX('Expected Production'!$B$2:$B$79,MATCH(TRIM($A22),INDEX(TRIM('Expected Production'!$A$2:$A$79),0),0)),"Not found")} -> 0.9 | D22: {=_xlfn.IFNA(_xlfn.XLOOKUP(TRIM(A22),TRIM(site_tech_info!$A$2:$A$79),site_tech_info!$W$2:$W$79),"")} -> 1.0157426 | E22: {=IFERROR(SUM(INDEX('Simulated Production'!$B$2:$M$79,MATCH(TRIM($A22),INDEX(TRIM('Simulated Production'!$A$2:$A$79),0),0),0)),"Not found")} -> 31637 | F22: =(Table2[[#This Row],[As-Built kWh]]*Table2[[#This Row],[Expected Utilisation%]])*(1-0.007)^(Table2[[#This Row],[Age]]) -> 28270.86 | G22: =(2350+2520+2436+2426+2356+2437)*(1-0.007)^(Table2[[#This Row],[Age]]) -> 14421.73 | H22: =F22-G22 -> 13849.13 | I22: {=SUMPRODUCT((TRIM(measured[Site Name])=TRIM($A22))*(measured[Date]>=DATE(2025,7,1))*(measured[Date]<=DATE(2026,6,30))*measured[Measured Value (kWh)])} -> 17882.44 | J22: =I22-H22 -> 4033.3097 | K22: =(Table2[[#This Row],[Actual Generation (kWh)]]/Table2[[#This Row],[Correct kWh]])*100 -> 129.1232 | L22: Testing
A23: Engen Kaalfontein | B23: YES | C23: {=IFERROR(INDEX('Expected Production'!$B$2:$B$79,MATCH(TRIM($A23),INDEX(TRIM('Expected Production'!$A$2:$A$79),0),0)),"Not found")} -> 0.9 | D23: {=_xlfn.IFNA(_xlfn.XLOOKUP(TRIM(A23),TRIM(site_tech_info!$A$2:$A$79),site_tech_info!$W$2:$W$79),"")} -> 0.43805613 | E23: {=IFERROR(SUM(INDEX('Simulated Production'!$B$2:$M$79,MATCH(TRIM($A23),INDEX(TRIM('Simulated Production'!$A$2:$A$79),0),0),0)),"Not found")} -> 190644.6 | F23: =(Table2[[#This Row],[As-Built kWh]]*Table2[[#This Row],[Expected Utilisation%]])*(1-0.007)^(Table2[[#This Row],[Age]]) -> 171052.97 | G23: 171487.77 | H23: =F23-G23 -> -434.79869 | I23: {=SUMPRODUCT((TRIM(measured[Site Name])=TRIM($A23))*(measured[Date]>=DATE(2025,7,1))*(measured[Date]<=DATE(2026,6,30))*measured[Measured Value (kWh)])} -> 10169 | J23: =I23-H23 -> 10603.799 | K23: =(Table2[[#This Row],[Actual Generation (kWh)]]/Table2[[#This Row],[Correct kWh]])*100 -> -2338.7835 | L23: Testing
A24: Alpine Heath Resort | B24: YES | C24: {=IFERROR(INDEX('Expected Production'!$B$2:$B$79,MATCH(TRIM($A24),INDEX(TRIM('Expected Production'!$A$2:$A$79),0),0)),"Not found")} -> 0.9 | D24: {=_xlfn.IFNA(_xlfn.XLOOKUP(TRIM(A24),TRIM(site_tech_info!$A$2:$A$79),site_tech_info!$W$2:$W$79),"")} -> 0.49828884 | E24: {=IFERROR(SUM(INDEX('Simulated Production'!$B$2:$M$79,MATCH(TRIM($A24),INDEX(TRIM('Simulated Production'!$A$2:$A$79),0),0),0)),"Not found")} -> 380893 | F24: =(Table2[[#This Row],[As-Built kWh]]*Table2[[#This Row],[Expected Utilisation%]])*(1-0.007)^(Table2[[#This Row],[Age]]) -> 341605.89 | G24: =(28051+31649+28250+28466+28992+28904+28877+25885+27341+27824*(28/30))*(1-0.007)^(Table2[[#This Row],[Age]]) -> 281397.37 | H24: =F24-G24 -> 60208.517 | I24: {=SUMPRODUCT((TRIM(measured[Site Name])=TRIM($A24))*(measured[Date]>=DATE(2025,7,1))*(measured[Date]<=DATE(2026,6,30))*measured[Measured Value (kWh)])} -> 53212.2 | J24: =I24-H24 -> -6996.317 | K24: =(Table2[[#This Row],[Actual Generation (kWh)]]/Table2[[#This Row],[Correct kWh]])*100 -> 88.379855 | L24: Testing

Sheet measured
A1: Site Name | B1: Date | C1: Measured Value (kWh)
A2: 21 Melrose | B2: 45292 | C2: 1815
A3: 21 Melrose | B3: 45323 | C3: 2295
A4: 21 Melrose | B4: 45352 | C4: 2474
A5: 21 Melrose | B5: 45383 | C5: 2136
A6: 21 Melrose | B6: 45413 | C6: 2212
A7: 21 Melrose | B7: 45444 | C7: 1863
A8: 21 Melrose | B8: 45474 | C8: 1943
A9: 21 Melrose | B9: 45505 | C9: 1710
A10: 21 Melrose | B10: 45536 | C10: 1579
A11: 21 Melrose | B11: 45566 | C11: 1593
A12: 21 Melrose | B12: 45597 | C12: 1794
A13: 21 Melrose | B13: 45627 | C13: 1794
... A34: 21 Melrose | B34: 46266 | C34: 1161.6
A35: 21 Melrose | B35: 46296
A36: 21 Melrose | B36: 46327
A37: 21 Melrose | B37: 46357
A38: African Global Plastics | B38: 45292 | C38: 23024
A39: African Global Plastics | B39: 45323 | C39: 23235
A40: African Global Plastics | B40: 45352 | C40: 23235
A41: African Global Plastics | B41: 45383 | C41: 19307
A42: African Global Plastics | B42: 45413 | C42: 18418
A43: African Global Plastics | B43: 45444 | C43: 15949
A44: African Global Plastics | B44: 45474 | C44: 17174
A45: African Global Plastics | B45: 45505 | C45: 13588
A46: African Global Plastics | B46: 45536 | C46: 20254
A47: African Global Plastics | B47: 45566 | C47: 27693
A48: African Global Plastics | B48: 45597 | C48: 24041
A49: African Global Plastics | B49: 45627 | C49: 25076
... A70: African Global Plastics | B70: 46266 | C70: 12622.016
A71: African Global Plastics | B71: 46296
A72: African Global Plastics | B72: 46327
A73: African Global Plastics | B73: 46357
A74: Alpine Heath Residential | B74: 45292
A75: Alpine Heath Residential | B75: 45323
A76: Alpine Heath Residential | B76: 45352
A77: Alpine Heath Residential | B77: 45383
A78: Alpine Heath Residential | B78: 45413
A79: Alpine Heath Residential | B79: 45444
A80: Alpine Heath Residential | B80: 45474
A81: Alpine Heath Residential | B81: 45505
A82: Alpine Heath Residential | B82: 45536
... A85: Alpine Heath Residential | B85: 45627
A86: Alpine Heath Residential | B86: 45658 | C86: 2400
A87: Alpine Heath Residential | B87: 45689 | C87: 3000
A88: Alpine Heath Residential | B88: 45717 | C88: 3144
A89: Alpine Heath Residential | B89: 45748 | C89: 2310
A90: Alpine Heath Residential | B90: 45778 | C90: 3866
A91: Alpine Heath Residential | B91: 45809 | C91: 3102
A92: Alpine Heath Residential | B92: 45839
A93: Alpine Heath Residential | B93: 45870 | C93: 4721
A94: Alpine Heath Residential | B94: 45901 | C94: 4200
A95: Alpine Heath Residential | B95: 45931 | C95: 3499
A96: Alpine Heath Residential | B96: 45962 | C96: 4045
A97: Alpine Heath Residential | B97: 45992 | C97: 4277
A98: Alpine Heath Residential | B98: 46023 | C98: 3071
A99: Alpine Heath Residential | B99: 46054 | C99: 3013
A100: Alpine Heath Residential | B100: 46082 | C100: 2340.8
A101: Alpine Heath Residential | B101: 46113 | C101: 1505.4
A102: Alpine Heath Residential | B102: 46143 | C102: 1467
A103: Alpine Heath Residential | B103: 46174 | C103: 2778
A104: Alpine Heath Residential | B104: 46204 | C104: 2644
... A106: Alpine Heath Residential | B106: 46266 | C106: 2338
A107: Alpine Heath Residential | B107: 46296
A108: Alpine Heath Residential | B108: 46327
A109: Alpine Heath Residential | B109: 46357
A110: BP Parys | B110: 45292
A111: BP Parys | B111: 45323
A112: BP Parys | B112: 45352
A113: BP Parys | B113: 45383
A114: BP Parys | B114: 45413
A115: BP Parys | B115: 45444
A116: BP Parys | B116: 45474
A117: BP Parys | B117: 45505
A118: BP Parys | B118: 45536
... A121: BP Parys | B121: 45627
A122: BP Parys | B122: 45658 | C122: 5900
A123: BP Parys | B123: 45689 | C123: 4277
A124: BP Parys | B124: 45717 | C124: 4770
A125: BP Parys | B125: 45748 | C125: 3375
A126: BP Parys | B126: 45778 | C126: 3507
A127: BP Parys | B127: 45809 | C127: 2400
A128: BP Parys | B128: 45839 | C128: 2169
A129: BP Parys | B129: 45870 | C129: 968.6
A130: BP Parys | B130: 45901 | C130: 2001.5
A131: BP Parys | B131: 45931 | C131: 3111
A132: BP Parys | B132: 45962 | C132: 1605
A133: BP Parys | B133: 45992
A134: BP Parys | B134: 46023
A135: BP Parys | B135: 46054 | C135: 6068
A136: BP Parys | B136: 46082 | C136: 4800
A137: BP Parys | B137: 46113 | C137: 4318
A138: BP Parys | B138: 46143 | C138: 3727.7
A139: BP Parys | B139: 46174 | C139: 3149
A140: Alpine Heath Resort | B140: 46204 | C140: 27942
A141: BP Parys | B141: 46235 | C141: 3313
A142: BP Parys | B142: 46266 | C142: 4204.16
A143: BP Parys | B143: 46296
A144: BP Parys | B144: 46327
A145: BP Parys | B145: 46357
...

Sheet Expected Production
A1: Site Name | B1: Expected Utilisation% | C1: Jan | D1: Feb | E1: Mar | F1: Apr | G1: May | H1: Jun | I1: Jul | J1: Aug | K1: Sep | L1: Oct | M1: Nov | N1: Dec
A2: 21 Melrose | B2: 0.9 | C2: =Table4[[#This Row],[Jan]]*$B2 -> 2370.6 | D2: =Table4[[#This Row],[Feb]]*$B2 -> 2680.2 | E2: =Table4[[#This Row],[Mar]]*$B2 -> 2183.4 | F2: =Table4[[#This Row],[Apr]]*$B2 -> 1873.8 | G2: =Table4[[#This Row],[May]]*$B2 -> 1822.5 | H2: =Table4[[#This Row],[Jun]]*$B2 -> 1629 | I2: =Table4[[#This Row],[Jul]]*$B2 -> 1814.4 | J2: =Table4[[#This Row],[Aug]]*$B2 -> 2116.8 | K2: =Table4[[#This Row],[Sep]]*$B2 -> 2275.2 | L2: =Table4[[#This Row],[Oct]]*$B2 -> 2407.5 | M2: =Table4[[#This Row],[Nov]]*$B2 -> 2356.2 | N2: =Table4[[#This Row],[Dec]]*$B2 -> 2482.2 | Q2: 2027
A3: African Global Plastics | B3: 0.85 | C3: =Table4[[#This Row],[Jan]]*$B3 -> 22515.905 | D3: =Table4[[#This Row],[Feb]]*$B3 -> 19786.13 | E3: =Table4[[#This Row],[Mar]]*$B3 -> 20148.4 | F3: =Table4[[#This Row],[Apr]]*$B3 -> 16764.89 | G3: =Table4[[#This Row],[May]]*$B3 -> 15972.095 | H3: =Table4[[#This Row],[Jun]]*$B3 -> 14367.21 | I3: =Table4[[#This Row],[Jul]]*$B3 -> 15907.665 | J3: =Table4[[#This Row],[Aug]]*$B3 -> 18527.365 | K3: =Table4[[#This Row],[Sep]]*$B3 -> 20404.335 | L3: =Table4[[#This Row],[Oct]]*$B3 -> 22320.66 | M3: =Table4[[#This Row],[Nov]]*$B3 -> 22520.665 | N3: =Table4[[#This Row],[Dec]]*$B3 -> 23777.985
A4: Alpine Heath Residential | B4: 0.9 | C4: =Table4[[#This Row],[Jan]]*$B4 -> 4801.5 | D4: =Table4[[#This Row],[Feb]]*$B4 -> 4303.8 | E4: =Table4[[#This Row],[Mar]]*$B4 -> 4545.9 | F4: =Table4[[#This Row],[Apr]]*$B4 -> 4619.7 | G4: =Table4[[#This Row],[May]]*$B4 -> 4990.5 | H4: =Table4[[#This Row],[Jun]]*$B4 -> 4761.9 | I4: =Table4[[#This Row],[Jul]]*$B4 -> 4680.9 | J4: =Table4[[#This Row],[Aug]]*$B4 -> 5249.7 | K4: =Table4[[#This Row],[Sep]]*$B4 -> 4694.4 | L4: =Table4[[#This Row],[Oct]]*$B4 -> 4732.2 | M4: =Table4[[#This Row],[Nov]]*$B4 -> 4822.2 | N4: =Table4[[#This Row],[Dec]]*$B4 -> 4805.1
A5: Bendstore Plaza Shops | B5: 0.85 | C5: =Table4[[#This Row],[Jan]]*$B5 -> 16262.2 | D5: =Table4[[#This Row],[Feb]]*$B5 -> 13986.75 | E5: =Table4[[#This Row],[Mar]]*$B5 -> 15463.2 | F5: =Table4[[#This Row],[Apr]]*$B5 -> 14886.05 | G5: =Table4[[#This Row],[May]]*$B5 -> 14411.75 | H5: =Table4[[#This Row],[Jun]]*$B5 -> 13050.05 | I5: =Table4[[#This Row],[Jul]]*$B5 -> 13735.15 | J5: =Table4[[#This Row],[Aug]]*$B5 -> 15350.15 | K5: =Table4[[#This Row],[Sep]]*$B5 -> 15431.75 | L5: =Table4[[#This Row],[Oct]]*$B5 -> 14821.45 | M5: =Table4[[#This Row],[Nov]]*$B5 -> 14695.65 | N5: =Table4[[#This Row],[Dec]]*$B5 -> 16154.25
A6: Bendstore Spar | B6: 0.9 | C6: =Table4[[#This Row],[Jan]]*$B6 -> 51314.735 | D6: =Table4[[#This Row],[Feb]]*$B6 -> 44103.291 | E6: =Table4[[#This Row],[Mar]]*$B6 -> 48739.27 | F6: =Table4[[#This Row],[Apr]]*$B6 -> 46849.899 | G6: =Table4[[#This Row],[May]]*$B6 -> 45273.233 | H6: =Table4[[#This Row],[Jun]]*$B6 -> 40943.972 | I6: =Table4[[#This Row],[Jul]]*$B6 -> 43112.803 | J6: =Table4[[#This Row],[Aug]]*$B6 -> 48266.503 | K6: =Table4[[#This Row],[Sep]]*$B6 -> 48602.891 | L6: =Table4[[#This Row],[Oct]]*$B6 -> 46748.911 | M6: =Table4[[#This Row],[Nov]]*$B6 -> 46388.482 | N6: =Table4[[#This Row],[Dec]]*$B6 -> 50640.311
A7: Beyerskloof | B7: 0.9 | C7: =Table4[[#This Row],[Jan]]*$B7 -> 13787.1 | D7: =Table4[[#This Row],[Feb]]*$B7 -> 11359.8 | E7: =Table4[[#This Row],[Mar]]*$B7 -> 10881 | F7: =Table4[[#This Row],[Apr]]*$B7 -> 7828.2 | G7: =Table4[[#This Row],[May]]*$B7 -> 5953.5 | H7: =Table4[[#This Row],[Jun]]*$B7 -> 5166 | I7: =Table4[[#This Row],[Jul]]*$B7 -> 5564.7 | J7: =Table4[[#This Row],[Aug]]*$B7 -> 6960.6 | K7: =Table4[[#This Row],[Sep]]*$B7 -> 8946 | L7: =Table4[[#This Row],[Oct]]*$B7 -> 11314.8 | M7: =Table4[[#This Row],[Nov]]*$B7 -> 12713.4 | N7: =Table4[[#This Row],[Dec]]*$B7 -> 13878.9
A8: BP Parys | B8: 0.9 | C8: =Table4[[#This Row],[Jan]]*$B8 -> 8151.3 | D8: =Table4[[#This Row],[Feb]]*$B8 -> 7235.1 | E8: =Table4[[#This Row],[Mar]]*$B8 -> 7075.8 | F8: =Table4[[#This Row],[Apr]]*$B8 -> 5754.6 | G8: =Table4[[#This Row],[May]]*$B8 -> 5424.3 | H8: =Table4[[#This Row],[Jun]]*$B8 -> 4787.1 | I8: =Table4[[#This Row],[Jul]]*$B8 -> 5360.4 | J8: =Table4[[#This Row],[Aug]]*$B8 -> 6363 | K8: =Table4[[#This Row],[Sep]]*$B8 -> 7218.9 | L8: =Table4[[#This Row],[Oct]]*$B8 -> 7839 | M8: =Table4[[#This Row],[Nov]]*$B8 -> 8191.8 | N8: =Table4[[#This Row],[Dec]]*$B8 -> 8227.8
A9: Buffalo Rock | B9: 0.9 | C9: =Table4[[#This Row],[Jan]]*$B9 -> 2202.3 | D9: =Table4[[#This Row],[Feb]]*$B9 -> 1983.6 | E9: =Table4[[#This Row],[Mar]]*$B9 -> 2127.6 | F9: =Table4[[#This Row],[Apr]]*$B9 -> 1767.6 | G9: =Table4[[#This Row],[May]]*$B9 -> 1631.7 | H9: =Table4[[#This Row],[Jun]]*$B9 -> 1480.5 | I9: =Table4[[#This Row],[Jul]]*$B9 -> 1612.8 | J9: =Table4[[#This Row],[Aug]]*$B9 -> 1764 | K9: =Table4[[#This Row],[Sep]]*$B9 -> 1868.4 | L9: =Table4[[#This Row],[Oct]]*$B9 -> 1900.8 | M9: =Table4[[#This Row],[Nov]]*$B9 -> 1835.1 | N9: =Table4[[#This Row],[Dec]]*$B9 -> 1986.3
A10: Checkers De Aar | B10: 0.9 | C10: =Table4[[#This Row],[Jan]]*$B10 -> 26689.5 | D10: =Table4[[#This Row],[Feb]]*$B10 -> 20674.8 | E10: =Table4[[#This Row],[Mar]]*$B10 -> 20095.2 | F10: =Table4[[#This Row],[Apr]]*$B10 -> 16286.4 | G10: =Table4[[#This Row],[May]]*$B10 -> 13518.9 | H10: =Table4[[#This Row],[Jun]]*$B10 -> 11864.7 | I10: =Table4[[#This Row],[Jul]]*$B10 -> 13589.1 | J10: =Table4[[#This Row],[Aug]]*$B10 -> 17109 | K10: =Table4[[#This Row],[Sep]]*$B10 -> 19506.6 | L10: =Table4[[#This Row],[Oct]]*$B10 -> 24081.3 | M10: =Table4[[#This Row],[Nov]]*$B10 -> 25889.4 | N10: =Table4[[#This Row],[Dec]]*$B10 -> 27992.7
A11: Checkers Silverlakes Gen | B11: 0.9 | C11: =Table4[[#This Row],[Jan]]*$B11 -> 21105 | D11: =Table4[[#This Row],[Feb]]*$B11 -> 18220.5 | E11: =Table4[[#This Row],[Mar]]*$B11 -> 18368.1 | F11: =Table4[[#This Row],[Apr]]*$B11 -> 15103.8 | G11: =Table4[[#This Row],[May]]*$B11 -> 14130 | H11: =Table4[[#This Row],[Jun]]*$B11 -> 12619.8 | I11: =Table4[[#This Row],[Jul]]*$B11 -> 14002.2 | J11: =Table4[[#This Row],[Aug]]*$B11 -> 16641.9 | K11: =Table4[[#This Row],[Sep]]*$B11 -> 18626.4 | L11: =Table4[[#This Row],[Oct]]*$B11 -> 20503.8 | M11: =Table4[[#This Row],[Nov]]*$B11 -> 20601 | N11: =Table4[[#This Row],[Dec]]*$B11 -> 22024.8
A12: Checkers Silverlakes No Gen | B12: 0.9 | C12: =Table4[[#This Row],[Jan]]*$B12 -> 21105 | D12: =Table4[[#This Row],[Feb]]*$B12 -> 18220.5 | E12: =Table4[[#This Row],[Mar]]*$B12 -> 18368.1 | F12: =Table4[[#This Row],[Apr]]*$B12 -> 15103.8 | G12: =Table4[[#This Row],[May]]*$B12 -> 14130 | H12: =Table4[[#This Row],[Jun]]*$B12 -> 12619.8 | I12: =Table4[[#This Row],[Jul]]*$B12 -> 14002.2 | J12: =Table4[[#This Row],[Aug]]*$B12 -> 16641.9 | K12: =Table4[[#This Row],[Sep]]*$B12 -> 18626.4 | L12: =Table4[[#This Row],[Oct]]*$B12 -> 20503.8 | M12: =Table4[[#This Row],[Nov]]*$B12 -> 20601 | N12: =Table4[[#This Row],[Dec]]*$B12 -> 22024.8
A13: Checkrite Inanda | B13: 0.9 | C13: =Table4[[#This Row],[Jan]]*$B13 -> 8664.3 | D13: =Table4[[#This Row],[Feb]]*$B13 -> 8100 | E13: =Table4[[#This Row],[Mar]]*$B13 -> 7805.7 | F13: =Table4[[#This Row],[Apr]]*$B13 -> 6534 | G13: =Table4[[#This Row],[May]]*$B13 -> 5592.6 | H13: =Table4[[#This Row],[Jun]]*$B13 -> 5059.8 | I13: =Table4[[#This Row],[Jul]]*$B13 -> 5372.1 | J13: =Table4[[#This Row],[Aug]]*$B13 -> 6485.4 | K13: =Table4[[#This Row],[Sep]]*$B13 -> 6914.7 | L13: =Table4[[#This Row],[Oct]]*$B13 -> 8033.4 | M13: =Table4[[#This Row],[Nov]]*$B13 -> 8012.7 | N13: =Table4[[#This Row],[Dec]]*$B13 -> 8547.3
A14: Club Houghton | B14: 0.9 | C14: =Table4[[#This Row],[Jan]]*$B14 -> 5767.2 | D14: =Table4[[#This Row],[Feb]]*$B14 -> 4828.5 | E14: =Table4[[#This Row],[Mar]]*$B14 -> 4913.1 | F14: =Table4[[#This Row],[Apr]]*$B14 -> 4149.9 | G14: =Table4[[#This Row],[May]]*$B14 -> 3937.5 | H14: =Table4[[#This Row],[Jun]]*$B14 -> 3463.2 | I14: =Table4[[#This Row],[Jul]]*$B14 -> 3874.5 | J14: =Table4[[#This Row],[Aug]]*$B14 -> 4560.3 | K14: =Table4[[#This Row],[Sep]]*$B14 -> 5033.7 | L14: =Table4[[#This Row],[Oct]]*$B14 -> 5613.3 | M14: =Table4[[#This Row],[Nov]]*$B14 -> 5712.3 | N14: =Table4[[#This Row],[Dec]]*$B14 -> 6027.3
... A64: SR Morula TF 2 | B64: 0.9 | C64: =Table4[[#This Row],[Jan]]*$B64 -> 9601.92 | D64: =Table4[[#This Row],[Feb]]*$B64 -> 8296.74 | E64: =Table4[[#This Row],[Mar]]*$B64 -> 8140.5 | F64: =Table4[[#This Row],[Apr]]*$B64 -> 7017.3 | G64: =Table4[[#This Row],[May]]*$B64 -> 6430.32 | H64: =Table4[[#This Row],[Jun]]*$B64 -> 5669.28 | I64: =Table4[[#This Row],[Jul]]*$B64 -> 6247.44 | J64: =Table4[[#This Row],[Aug]]*$B64 -> 7340.13 | K64: =Table4[[#This Row],[Sep]]*$B64 -> 8154 | L64: =Table4[[#This Row],[Oct]]*$B64 -> 9352.8 | M64: =Table4[[#This Row],[Nov]]*$B64 -> 9353.7 | N64: =Table4[[#This Row],[Dec]]*$B64 -> 9582.3
A65: Thakadu Industrial | C65: =Table4[[#This Row],[Jan]]*$B65 -> 0 | D65: =Table4[[#This Row],[Feb]]*$B65 -> 0 | E65: =Table4[[#This Row],[Mar]]*$B65 -> 0 | F65: =Table4[[#This Row],[Apr]]*$B65 -> 0 | G65: =Table4[[#This Row],[May]]*$B65 -> 0 | H65: =Table4[[#This Row],[Jun]]*$B65 -> 0 | I65: =Table4[[#This Row],[Jul]]*$B65 -> 0 | J65: =Table4[[#This Row],[Aug]]*$B65 -> 0 | K65: =Table4[[#This Row],[Sep]]*$B65 -> 0 | L65: =Table4[[#This Row],[Oct]]*$B65 -> 0 | M65: =Table4[[#This Row],[Nov]]*$B65 -> 0 | N65: =Table4[[#This Row],[Dec]]*$B65 -> 0
A66: The Alec | B66: 0.925 | C66: =Table4[[#This Row],[Jan]]*$B66 -> 7605.35 | D66: =Table4[[#This Row],[Feb]]*$B66 -> 6473.15 | E66: =Table4[[#This Row],[Mar]]*$B66 -> 6529.575 | F66: =Table4[[#This Row],[Apr]]*$B66 -> 5155.95 | G66: =Table4[[#This Row],[May]]*$B66 -> 4885.85 | H66: =Table4[[#This Row],[Jun]]*$B66 -> 4375.25 | I66: =Table4[[#This Row],[Jul]]*$B66 -> 4861.8 | J66: =Table4[[#This Row],[Aug]]*$B66 -> 5591.625 | K66: =Table4[[#This Row],[Sep]]*$B66 -> 6522.175 | L66: =Table4[[#This Row],[Oct]]*$B66 -> 7451.8 | M66: =Table4[[#This Row],[Nov]]*$B66 -> 7534.125 | N66: =Table4[[#This Row],[Dec]]*$B66 -> 8084.5
A67: Three Peaks | B67: 0.75 | C67: =Table4[[#This Row],[Jan]]*$B67 -> 4274.1 | D67: =Table4[[#This Row],[Feb]]*$B67 -> 3810.6 | E67: =Table4[[#This Row],[Mar]]*$B67 -> 3907.275 | F67: =Table4[[#This Row],[Apr]]*$B67 -> 3268.125 | G67: =Table4[[#This Row],[May]]*$B67 -> 2929.95 | H67: =Table4[[#This Row],[Jun]]*$B67 -> 2664.75 | I67: =Table4[[#This Row],[Jul]]*$B67 -> 2851.125 | J67: =Table4[[#This Row],[Aug]]*$B67 -> 3237 | K67: =Table4[[#This Row],[Sep]]*$B67 -> 3327.75 | L67: =Table4[[#This Row],[Oct]]*$B67 -> 3775.725 | M67: =Table4[[#This Row],[Nov]]*$B67 -> 3829.575 | N67: =Table4[[#This Row],[Dec]]*$B67 -> 4315.65
A68: TPF Foods | B68: 0.75 | C68: =Table4[[#This Row],[Jan]]*$B68 -> 3784.425 | D68: =Table4[[#This Row],[Feb]]*$B68 -> 3270.15 | E68: =Table4[[#This Row],[Mar]]*$B68 -> 3533.325 | F68: =Table4[[#This Row],[Apr]]*$B68 -> 3063.075 | G68: =Table4[[#This Row],[May]]*$B68 -> 3093.825 | H68: =Table4[[#This Row],[Jun]]*$B68 -> 2834.025 | I68: =Table4[[#This Row],[Jul]]*$B68 -> 3103.35 | J68: =Table4[[#This Row],[Aug]]*$B68 -> 3491.55 | K68: =Table4[[#This Row],[Sep]]*$B68 -> 3723.45 | L68: =Table4[[#This Row],[Oct]]*$B68 -> 3899.4 | M68: =Table4[[#This Row],[Nov]]*$B68 -> 3732.75 | N68: =Table4[[#This Row],[Dec]]*$B68 -> 4016.175
A69: Trouw Nutrition | B69: 0.85 | C69: =Table4[[#This Row],[Jan]]*$B69 -> 13441.985 | D69: =Table4[[#This Row],[Feb]]*$B69 -> 12055.125 | E69: =Table4[[#This Row],[Mar]]*$B69 -> 12858.46 | F69: =Table4[[#This Row],[Apr]]*$B69 -> 11531.27 | G69: =Table4[[#This Row],[May]]*$B69 -> 11785.93 | H69: =Table4[[#This Row],[Jun]]*$B69 -> 11018.635 | I69: =Table4[[#This Row],[Jul]]*$B69 -> 12024.27 | J69: =Table4[[#This Row],[Aug]]*$B69 -> 13262.635 | K69: =Table4[[#This Row],[Sep]]*$B69 -> 13540.33 | L69: =Table4[[#This Row],[Oct]]*$B69 -> 13925.295 | M69: =Table4[[#This Row],[Nov]]*$B69 -> 13508.37 | N69: =Table4[[#This Row],[Dec]]*$B69 -> 14234.525
A70: U Save Botrivier | B70: 0.9 | C70: =Table4[[#This Row],[Jan]]*$B70 -> 7299.9 | D70: =Table4[[#This Row],[Feb]]*$B70 -> 6223.5 | E70: =Table4[[#This Row],[Mar]]*$B70 -> 6048.9 | F70: =Table4[[#This Row],[Apr]]*$B70 -> 5130.9 | G70: =Table4[[#This Row],[May]]*$B70 -> 4621.5 | H70: =Table4[[#This Row],[Jun]]*$B70 -> 3931.2 | I70: =Table4[[#This Row],[Jul]]*$B70 -> 4065.3 | J70: =Table4[[#This Row],[Aug]]*$B70 -> 4723.2 | K70: =Table4[[#This Row],[Sep]]*$B70 -> 5251.5 | L70: =Table4[[#This Row],[Oct]]*$B70 -> 6489.9 | M70: =Table4[[#This Row],[Nov]]*$B70 -> 6813.9 | N70: =Table4[[#This Row],[Dec]]*$B70 -> 7296.3
A71: Watt Place Rotoflo | B71: 0.9 | C71: =Table4[[#This Row],[Jan]]*$B71 -> 28027.8 | D71: =Table4[[#This Row],[Feb]]*$B71 -> 23853.6 | E71: =Table4[[#This Row],[Mar]]*$B71 -> 24144.3 | F71: =Table4[[#This Row],[Apr]]*$B71 -> 20043 | G71: =Table4[[#This Row],[May]]*$B71 -> 19021.5 | H71: =Table4[[#This Row],[Jun]]*$B71 -> 17054.1 | I71: =Table4[[#This Row],[Jul]]*$B71 -> 18900 | J71: =Table4[[#This Row],[Aug]]*$B71 -> 22066.2 | K71: =Table4[[#This Row],[Sep]]*$B71 -> 24526.8 | L71: =Table4[[#This Row],[Oct]]*$B71 -> 27256.5 | M71: =Table4[[#This Row],[Nov]]*$B71 -> 26973.9 | N71: =Table4[[#This Row],[Dec]]*$B71 -> 29028.6
A72: Zwartop Golf Course | B72: 0.9 | C72: =Table4[[#This Row],[Jan]]*$B72 -> #VALUE! | D72: =Table4[[#This Row],[Feb]]*$B72 -> #VALUE! | E72: =Table4[[#This Row],[Mar]]*$B72 -> #VALUE! | F72: =Table4[[#This Row],[Apr]]*$B72 -> #VALUE! | G72: =Table4[[#This Row],[May]]*$B72 -> #VALUE! | H72: =Table4[[#This Row],[Jun]]*$B72 -> #VALUE! | I72: =Table4[[#This Row],[Jul]]*$B72 -> #VALUE! | J72: =Table4[[#This Row],[Aug]]*$B72 -> #VALUE! | K72: =Table4[[#This Row],[Sep]]*$B72 -> #VALUE! | L72: =Table4[[#This Row],[Oct]]*$B72 -> #VALUE! | M72: =Table4[[#This Row],[Nov]]*$B72 -> #VALUE! | N72: =Table4[[#This Row],[Dec]]*$B72 -> #VALUE!
A73: Shoprite Ekhaya | B73: 0.9 | C73: =Table4[[#This Row],[Jan]]*$B73 -> 28380.6 | D73: =Table4[[#This Row],[Feb]]*$B73 -> 24379.2 | E73: =Table4[[#This Row],[Mar]]*$B73 -> 23351.4 | F73: =Table4[[#This Row],[Apr]]*$B73 -> 19887.3 | G73: =Table4[[#This Row],[May]]*$B73 -> 17745.3 | H73: =Table4[[#This Row],[Jun]]*$B73 -> 15502.5 | I73: =Table4[[#This Row],[Jul]]*$B73 -> 17358.3 | J73: =Table4[[#This Row],[Aug]]*$B73 -> 20842.2 | K73: =Table4[[#This Row],[Sep]]*$B73 -> 23841 | L73: =Table4[[#This Row],[Oct]]*$B73 -> 27285.3 | M73: =Table4[[#This Row],[Nov]]*$B73 -> 27841.5 | N73: =Table4[[#This Row],[Dec]]*$B73 -> 28779.3
A74: Grootpan | B74: 0.9 | C74: =Table4[[#This Row],[Jan]]*$B74 -> 29074.5 | D74: =Table4[[#This Row],[Feb]]*$B74 -> 26716.5 | E74: =Table4[[#This Row],[Mar]]*$B74 -> 27941.4 | F74: =Table4[[#This Row],[Apr]]*$B74 -> 25610.4 | G74: =Table4[[#This Row],[May]]*$B74 -> 25802.1 | H74: =Table4[[#This Row],[Jun]]*$B74 -> 23428.8 | I74: =Table4[[#This Row],[Jul]]*$B74 -> 25632 | J74: =Table4[[#This Row],[Aug]]*$B74 -> 28549.8 | K74: =Table4[[#This Row],[Sep]]*$B74 -> 29561.4 | L74: =Table4[[#This Row],[Oct]]*$B74 -> 31417.2 | M74: =Table4[[#This Row],[Nov]]*$B74 -> 30121.2 | N74: =Table4[[#This Row],[Dec]]*$B74 -> 29445.3
A75: Roan Foods | B75: 1 | C75: =Table4[[#This Row],[Jan]]*$B75 -> 20178 | D75: =Table4[[#This Row],[Feb]]*$B75 -> 17954 | E75: =Table4[[#This Row],[Mar]]*$B75 -> 19150 | F75: =Table4[[#This Row],[Apr]]*$B75 -> 18060 | G75: =Table4[[#This Row],[May]]*$B75 -> 18124 | H75: =Table4[[#This Row],[Jun]]*$B75 -> 15908 | I75: =Table4[[#This Row],[Jul]]*$B75 -> 16827 | J75: =Table4[[#This Row],[Aug]]*$B75 -> 19405 | K75: =Table4[[#This Row],[Sep]]*$B75 -> 19981 | L75: =Table4[[#This Row],[Oct]]*$B75 -> 22401 | M75: =Table4[[#This Row],[Nov]]*$B75 -> 20125 | N75: =Table4[[#This Row],[Dec]]*$B75 -> 20771
A76: Engen Kaalfontein | B76: 0.9 | C76: =Table4[[#This Row],[Jan]]*$B76 -> 17370.9 | D76: =Table4[[#This Row],[Feb]]*$B76 -> 15077.7 | E76: =Table4[[#This Row],[Mar]]*$B76 -> 14634 | F76: =Table4[[#This Row],[Apr]]*$B76 -> 12420 | G76: =Table4[[#This Row],[May]]*$B76 -> 11402.1 | H76: =Table4[[#This Row],[Jun]]*$B76 -> 9989.1 | I76: =Table4[[#This Row],[Jul]]*$B76 -> 10986.3 | J76: =Table4[[#This Row],[Aug]]*$B76 -> 13108.77 | K76: =Table4[[#This Row],[Sep]]*$B76 -> 14833.17 | L76: =Table4[[#This Row],[Oct]]*$B76 -> 17053.2 | M76: =Table4[[#This Row],[Nov]]*$B76 -> 17239.5 | N76: =Table4[[#This Row],[Dec]]*$B76 -> 17465.4
A77: Checkers Lichtenburg | B77: 0.9 | C77: =Table4[[#This Row],[Jan]]*$B77 -> 26451 | D77: =Table4[[#This Row],[Feb]]*$B77 -> 23215.5 | E77: =Table4[[#This Row],[Mar]]*$B77 -> 23034.6 | F77: =Table4[[#This Row],[Apr]]*$B77 -> 19930.5 | G77: =Table4[[#This Row],[May]]*$B77 -> 18754.2 | H77: =Table4[[#This Row],[Jun]]*$B77 -> 16767.9 | I77: =Table4[[#This Row],[Jul]]*$B77 -> 18261 | J77: =Table4[[#This Row],[Aug]]*$B77 -> 21311.1 | K77: =Table4[[#This Row],[Sep]]*$B77 -> 23659.2 | L77: =Table4[[#This Row],[Oct]]*$B77 -> 26865.9 | M77: =Table4[[#This Row],[Nov]]*$B77 -> 27153.9 | N77: =Table4[[#This Row],[Dec]]*$B77 -> 27402.3
... A79: Usave Naboomspruit | B79: 0.9 | C79: =Table4[[#This Row],[Jan]]*$B79 -> 5973.3 | D79: =Table4[[#This Row],[Feb]]*$B79 -> 5271.3 | E79: =Table4[[#This Row],[Mar]]*$B79 -> 5330.7 | F79: =Table4[[#This Row],[Apr]]*$B79 -> 4826.7 | G79: =Table4[[#This Row],[May]]*$B79 -> 4649.4 | H79: =Table4[[#This Row],[Jun]]*$B79 -> 4253.4 | I79: =Table4[[#This Row],[Jul]]*$B79 -> 4644.9 | J79: =Table4[[#This Row],[Aug]]*$B79 -> 5254.2 | K79: =Table4[[#This Row],[Sep]]*$B79 -> 5567.4 | L79: =Table4[[#This Row],[Oct]]*$B79 -> 6030.9 | M79: =Table4[[#This Row],[Nov]]*$B79 -> 5897.7 | N79: =Table4[[#This Row],[Dec]]*$B79 -> 5989.5
F84: =19931/30 -> 664.36667

Sheet expected_production
A1: Site Name | B1: Date | C1: Base Expected (kWh) | D1: Commissioned Date | E1: Age (yrs) | F1: Degradation Factor | G1: Expected Production (kWh) | I1: Annual degradation rate | J1: 0.007
A2: 21 Melrose | B2: 45292 | C2: 2370.6 | D2: =_xlfn.XLOOKUP(expected_production[[#This Row],[Site Name]],Table1[[Site Name ]],Table1[Commisioned Date],"") -> 44963 | E2: =IF(ISNUMBER(expected_production[[#This Row],[Commissioned Date]]),MAX(0,(expected_production[[#This Row],[Date]]-expected_production[[#This Row],[Commissioned Date]])/365.25),"") -> 0.90075291 | F2: =IF(expected_production[[#This Row],[Age (yrs)]]="",1,(1-DegradationRate)^expected_production[[#This Row],[Age (yrs)]]) -> 0.99369253 | G2: =IF(expected_production[[#This Row],[Base Expected (kWh)]]="","",expected_production[[#This Row],[Base Expected (kWh)]]*expected_production[[#This Row],[Degradation Factor]]) -> 2355.6475
A3: 21 Melrose | B3: 45323 | C3: 2680.2 | D3: =_xlfn.XLOOKUP(expected_production[[#This Row],[Site Name]],Table1[[Site Name ]],Table1[Commisioned Date],"") -> 44963 | E3: =IF(ISNUMBER(expected_production[[#This Row],[Commissioned Date]]),MAX(0,(expected_production[[#This Row],[Date]]-expected_production[[#This Row],[Commissioned Date]])/365.25),"") -> 0.98562628 | F3: =IF(expected_production[[#This Row],[Age (yrs)]]="",1,(1-DegradationRate)^expected_production[[#This Row],[Age (yrs)]]) -> 0.99310027 | G3: =IF(expected_production[[#This Row],[Base Expected (kWh)]]="","",expected_production[[#This Row],[Base Expected (kWh)]]*expected_production[[#This Row],[Degradation Factor]]) -> 2661.7073
A4: 21 Melrose | B4: 45352 | C4: 2183.4 | D4: =_xlfn.XLOOKUP(expected_production[[#This Row],[Site Name]],Table1[[Site Name ]],Table1[Commisioned Date],"") -> 44963 | E4: =IF(ISNUMBER(expected_production[[#This Row],[Commissioned Date]]),MAX(0,(expected_production[[#This Row],[Date]]-expected_production[[#This Row],[Commissioned Date]])/365.25),"") -> 1.065024 | F4: =IF(expected_production[[#This Row],[Age (yrs)]]="",1,(1-DegradationRate)^expected_production[[#This Row],[Age (yrs)]]) -> 0.99254653 | G4: =IF(expected_production[[#This Row],[Base Expected (kWh)]]="","",expected_production[[#This Row],[Base Expected (kWh)]]*expected_production[[#This Row],[Degradation Factor]]) -> 2167.1261
A5: 21 Melrose | B5: 45383 | C5: 1873.8 | D5: =_xlfn.XLOOKUP(expected_production[[#This Row],[Site Name]],Table1[[Site Name ]],Table1[Commisioned Date],"") -> 44963 | E5: =IF(ISNUMBER(expected_production[[#This Row],[Commissioned Date]]),MAX(0,(expected_production[[#This Row],[Date]]-expected_production[[#This Row],[Commissioned Date]])/365.25),"") -> 1.1498973 | F5: =IF(expected_production[[#This Row],[Age (yrs)]]="",1,(1-DegradationRate)^expected_production[[#This Row],[Age (yrs)]]) -> 0.99195495 | G5: =IF(expected_production[[#This Row],[Base Expected (kWh)]]="","",expected_production[[#This Row],[Base Expected (kWh)]]*expected_production[[#This Row],[Degradation Factor]]) -> 1858.7252
A6: 21 Melrose | B6: 45413 | C6: 1822.5 | D6: =_xlfn.XLOOKUP(expected_production[[#This Row],[Site Name]],Table1[[Site Name ]],Table1[Commisioned Date],"") -> 44963 | E6: =IF(ISNUMBER(expected_production[[#This Row],[Commissioned Date]]),MAX(0,(expected_production[[#This Row],[Date]]-expected_production[[#This Row],[Commissioned Date]])/365.25),"") -> 1.2320329 | F6: =IF(expected_production[[#This Row],[Age (yrs)]]="",1,(1-DegradationRate)^expected_production[[#This Row],[Age (yrs)]]) -> 0.99138279 | G6: =IF(expected_production[[#This Row],[Base Expected (kWh)]]="","",expected_production[[#This Row],[Base Expected (kWh)]]*expected_production[[#This Row],[Degradation Factor]]) -> 1806.7951
A7: 21 Melrose | B7: 45444 | C7: 1629 | D7: =_xlfn.XLOOKUP(expected_production[[#This Row],[Site Name]],Table1[[Site Name ]],Table1[Commisioned Date],"") -> 44963 | E7: =IF(ISNUMBER(expected_production[[#This Row],[Commissioned Date]]),MAX(0,(expected_production[[#This Row],[Date]]-expected_production[[#This Row],[Commissioned Date]])/365.25),"") -> 1.3169062 | F7: =IF(expected_production[[#This Row],[Age (yrs)]]="",1,(1-DegradationRate)^expected_production[[#This Row],[Age (yrs)]]) -> 0.9907919 | G7: =IF(expected_production[[#This Row],[Base Expected (kWh)]]="","",expected_production[[#This Row],[Base Expected (kWh)]]*expected_production[[#This Row],[Degradation Factor]]) -> 1614
A8: 21 Melrose | B8: 45474 | C8: 1814.4 | D8: =_xlfn.XLOOKUP(expected_production[[#This Row],[Site Name]],Table1[[Site Name ]],Table1[Commisioned Date],"") -> 44963 | E8: =IF(ISNUMBER(expected_production[[#This Row],[Commissioned Date]]),MAX(0,(expected_production[[#This Row],[Date]]-expected_production[[#This Row],[Commissioned Date]])/365.25),"") -> 1.3990418 | F8: =IF(expected_production[[#This Row],[Age (yrs)]]="",1,(1-DegradationRate)^expected_production[[#This Row],[Age (yrs)]]) -> 0.9902204 | G8: =IF(expected_production[[#This Row],[Base Expected (kWh)]]="","",expected_production[[#This Row],[Base Expected (kWh)]]*expected_production[[#This Row],[Degradation Factor]]) -> 1796.6559
A9: 21 Melrose | B9: 45505 | C9: 2116.8 | D9: =_xlfn.XLOOKUP(expected_production[[#This Row],[Site Name]],Table1[[Site Name ]],Table1[Commisioned Date],"") -> 44963 | E9: =IF(ISNUMBER(expected_production[[#This Row],[Commissioned Date]]),MAX(0,(expected_production[[#This Row],[Date]]-expected_production[[#This Row],[Commissioned Date]])/365.25),"") -> 1.4839151 | F9: =IF(expected_production[[#This Row],[Age (yrs)]]="",1,(1-DegradationRate)^expected_production[[#This Row],[Age (yrs)]]) -> 0.98963021 | G9: =IF(expected_production[[#This Row],[Base Expected (kWh)]]="","",expected_production[[#This Row],[Base Expected (kWh)]]*expected_production[[#This Row],[Degradation Factor]]) -> 2094.8492
A10: 21 Melrose | B10: 45536 | C10: 2275.2 | D10: =_xlfn.XLOOKUP(expected_production[[#This Row],[Site Name]],Table1[[Site Name ]],Table1[Commisioned Date],"") -> 44963 | E10: =IF(ISNUMBER(expected_production[[#This Row],[Commissioned Date]]),MAX(0,(expected_production[[#This Row],[Date]]-expected_production[[#This Row],[Commissioned Date]])/365.25),"") -> 1.5687885 | F10: =IF(expected_production[[#This Row],[Age (yrs)]]="",1,(1-DegradationRate)^expected_production[[#This Row],[Age (yrs)]]) -> 0.98904036 | G10: =IF(expected_production[[#This Row],[Base Expected (kWh)]]="","",expected_production[[#This Row],[Base Expected (kWh)]]*expected_production[[#This Row],[Degradation Factor]]) -> 2250.2646
A11: 21 Melrose | B11: 45566 | C11: 2407.5 | D11: =_xlfn.XLOOKUP(expected_production[[#This Row],[Site Name]],Table1[[Site Name ]],Table1[Commisioned Date],"") -> 44963 | E11: =IF(ISNUMBER(expected_production[[#This Row],[Commissioned Date]]),MAX(0,(expected_production[[#This Row],[Date]]-expected_production[[#This Row],[Commissioned Date]])/365.25),"") -> 1.650924 | F11: =IF(expected_production[[#This Row],[Age (yrs)]]="",1,(1-DegradationRate)^expected_production[[#This Row],[Age (yrs)]]) -> 0.98846988 | G11: =IF(expected_production[[#This Row],[Base Expected (kWh)]]="","",expected_production[[#This Row],[Base Expected (kWh)]]*expected_production[[#This Row],[Degradation Factor]]) -> 2379.7412
A12: 21 Melrose | B12: 45597 | C12: 2356.2 | D12: =_xlfn.XLOOKUP(expected_production[[#This Row],[Site Name]],Table1[[Site Name ]],Table1[Commisioned Date],"") -> 44963 | E12: =IF(ISNUMBER(expected_production[[#This Row],[Commissioned Date]]),MAX(0,(expected_production[[#This Row],[Date]]-expected_production[[#This Row],[Commissioned Date]])/365.25),"") -> 1.7357974 | F12: =IF(expected_production[[#This Row],[Age (yrs)]]="",1,(1-DegradationRate)^expected_production[[#This Row],[Age (yrs)]]) -> 0.98788073 | G12: =IF(expected_production[[#This Row],[Base Expected (kWh)]]="","",expected_production[[#This Row],[Base Expected (kWh)]]*expected_production[[#This Row],[Degradation Factor]]) -> 2327.6446
A13: 21 Melrose | B13: 45627 | C13: 2482.2 | D13: =_xlfn.XLOOKUP(expected_production[[#This Row],[Site Name]],Table1[[Site Name ]],Table1[Commisioned Date],"") -> 44963 | E13: =IF(ISNUMBER(expected_production[[#This Row],[Commissioned Date]]),MAX(0,(expected_production[[#This Row],[Date]]-expected_production[[#This Row],[Commissioned Date]])/365.25),"") -> 1.8179329 | F13: =IF(expected_production[[#This Row],[Age (yrs)]]="",1,(1-DegradationRate)^expected_production[[#This Row],[Age (yrs)]]) -> 0.98731092 | G13: =IF(expected_production[[#This Row],[Base Expected (kWh)]]="","",expected_production[[#This Row],[Base Expected (kWh)]]*expected_production[[#This Row],[Degradation Factor]]) -> 2450.7032
... A1046: Kool Village | B1046: 46357 | C1046: 12998.7 | D1046: =_xlfn.XLOOKUP(expected_production[[#This Row],[Site Name]],Table1[[Site Name ]],Table1[Commisioned Date],"") -> 2022/16/12 | E1046: =IF(ISNUMBER(expected_production[[#This Row],[Commissioned Date]]),MAX(0,(expected_production[[#This Row],[Date]]-expected_production[[#This Row],[Commissioned Date]])/365.25),"") | F1046: =IF(expected_production[[#This Row],[Age (yrs)]]="",1,(1-DegradationRate)^expected_production[[#This Row],[Age (yrs)]]) -> 1 | G1046: =IF(expected_production[[#This Row],[Base Expected (kWh)]]="","",expected_production[[#This Row],[Base Expected (kWh)]]*expected_production[[#This Row],[Degradation Factor]]) -> 12998.7
A1047: Makalali | B1047: 45292 | C1047: {=IFERROR(INDEX('Expected Production'!$C$2:$N$79,MATCH($A1047,'Expected Production'!$A$2:$A$79,0),MONTH($B1047)),"")} -> 16602.939 | D1047: =_xlfn.XLOOKUP(expected_production[[#This Row],[Site Name]],Table1[[Site Name ]],Table1[Commisioned Date],"") -> 45050 | E1047: =IF(ISNUMBER(expected_production[[#This Row],[Commissioned Date]]),MAX(0,(expected_production[[#This Row],[Date]]-expected_production[[#This Row],[Commissioned Date]])/365.25),"") -> 0.66255989 | F1047: =IF(expected_production[[#This Row],[Age (yrs)]]="",1,(1-DegradationRate)^expected_production[[#This Row],[Age (yrs)]]) -> 0.99535659 | G1047: =IF(expected_production[[#This Row],[Base Expected (kWh)]]="","",expected_production[[#This Row],[Base Expected (kWh)]]*expected_production[[#This Row],[Degradation Factor]]) -> 16525.845
A1048: Makalali | B1048: 45323 | C1048: {=IFERROR(INDEX('Expected Production'!$C$2:$N$79,MATCH($A1048,'Expected Production'!$A$2:$A$79,0),MONTH($B1048)),"")} -> 14966.051 | D1048: =_xlfn.XLOOKUP(expected_production[[#This Row],[Site Name]],Table1[[Site Name ]],Table1[Commisioned Date],"") -> 45050 | E1048: =IF(ISNUMBER(expected_production[[#This Row],[Commissioned Date]]),MAX(0,(expected_production[[#This Row],[Date]]-expected_production[[#This Row],[Commissioned Date]])/365.25),"") -> 0.74743326 | F1048: =IF(expected_production[[#This Row],[Age (yrs)]]="",1,(1-DegradationRate)^expected_production[[#This Row],[Age (yrs)]]) -> 0.99476333 | G1048: =IF(expected_production[[#This Row],[Base Expected (kWh)]]="","",expected_production[[#This Row],[Base Expected (kWh)]]*expected_production[[#This Row],[Degradation Factor]]) -> 14887.679
A1049: Makalali | B1049: 45352 | C1049: {=IFERROR(INDEX('Expected Production'!$C$2:$N$79,MATCH($A1049,'Expected Production'!$A$2:$A$79,0),MONTH($B1049)),"")} -> 16335.486 | D1049: =_xlfn.XLOOKUP(expected_production[[#This Row],[Site Name]],Table1[[Site Name ]],Table1[Commisioned Date],"") -> 45050 | E1049: =IF(ISNUMBER(expected_production[[#This Row],[Commissioned Date]]),MAX(0,(expected_production[[#This Row],[Date]]-expected_production[[#This Row],[Commissioned Date]])/365.25),"") -> 0.82683094 | F1049: =IF(expected_production[[#This Row],[Age (yrs)]]="",1,(1-DegradationRate)^expected_production[[#This Row],[Age (yrs)]]) -> 0.99420867 | G1049: =IF(expected_production[[#This Row],[Base Expected (kWh)]]="","",expected_production[[#This Row],[Base Expected (kWh)]]*expected_production[[#This Row],[Degradation Factor]]) -> 16240.881
A1050: Makalali | B1050: 45383 | C1050: {=IFERROR(INDEX('Expected Production'!$C$2:$N$79,MATCH($A1050,'Expected Production'!$A$2:$A$79,0),MONTH($B1050)),"")} -> 15100.351 | D1050: =_xlfn.XLOOKUP(expected_production[[#This Row],[Site Name]],Table1[[Site Name ]],Table1[Commisioned Date],"") -> 45050 | E1050: =IF(ISNUMBER(expected_production[[#This Row],[Commissioned Date]]),MAX(0,(expected_production[[#This Row],[Date]]-expected_production[[#This Row],[Commissioned Date]])/365.25),"") -> 0.91170431 | F1050: =IF(expected_production[[#This Row],[Age (yrs)]]="",1,(1-DegradationRate)^expected_production[[#This Row],[Age (yrs)]]) -> 0.99361609 | G1050: =IF(expected_production[[#This Row],[Base Expected (kWh)]]="","",expected_production[[#This Row],[Base Expected (kWh)]]*expected_production[[#This Row],[Degradation Factor]]) -> 15003.952
A1051: Makalali | B1051: 45413 | C1051: {=IFERROR(INDEX('Expected Production'!$C$2:$N$79,MATCH($A1051,'Expected Production'!$A$2:$A$79,0),MONTH($B1051)),"")} -> 15271.045 | D1051: =_xlfn.XLOOKUP(expected_production[[#This Row],[Site Name]],Table1[[Site Name ]],Table1[Commisioned Date],"") -> 45050 | E1051: =IF(ISNUMBER(expected_production[[#This Row],[Commissioned Date]]),MAX(0,(expected_production[[#This Row],[Date]]-expected_production[[#This Row],[Commissioned Date]])/365.25),"") -> 0.99383984 | F1051: =IF(expected_production[[#This Row],[Age (yrs)]]="",1,(1-DegradationRate)^expected_production[[#This Row],[Age (yrs)]]) -> 0.99304297 | G1051: =IF(expected_production[[#This Row],[Base Expected (kWh)]]="","",expected_production[[#This Row],[Base Expected (kWh)]]*expected_production[[#This Row],[Degradation Factor]]) -> 15164.804
A1052: Makalali | B1052: 45444 | C1052: {=IFERROR(INDEX('Expected Production'!$C$2:$N$79,MATCH($A1052,'Expected Production'!$A$2:$A$79,0),MONTH($B1052)),"")} -> 14168.007 | D1052: =_xlfn.XLOOKUP(expected_production[[#This Row],[Site Name]],Table1[[Site Name ]],Table1[Commisioned Date],"") -> 45050 | E1052: =IF(ISNUMBER(expected_production[[#This Row],[Commissioned Date]]),MAX(0,(expected_production[[#This Row],[Date]]-expected_production[[#This Row],[Commissioned Date]])/365.25),"") -> 1.0787132 | F1052: =IF(expected_production[[#This Row],[Age (yrs)]]="",1,(1-DegradationRate)^expected_production[[#This Row],[Age (yrs)]]) -> 0.99245109 | G1052: =IF(expected_production[[#This Row],[Base Expected (kWh)]]="","",expected_production[[#This Row],[Base Expected (kWh)]]*expected_production[[#This Row],[Degradation Factor]]) -> 14061.054
A1053: Makalali | B1053: 45474 | C1053: {=IFERROR(INDEX('Expected Production'!$C$2:$N$79,MATCH($A1053,'Expected Production'!$A$2:$A$79,0),MONTH($B1053)),"")} -> 15171.29 | D1053: =_xlfn.XLOOKUP(expected_production[[#This Row],[Site Name]],Table1[[Site Name ]],Table1[Commisioned Date],"") -> 45050 | E1053: =IF(ISNUMBER(expected_production[[#This Row],[Commissioned Date]]),MAX(0,(expected_production[[#This Row],[Date]]-expected_production[[#This Row],[Commissioned Date]])/365.25),"") -> 1.1608487 | F1053: =IF(expected_production[[#This Row],[Age (yrs)]]="",1,(1-DegradationRate)^expected_production[[#This Row],[Age (yrs)]]) -> 0.99187864 | G1053: =IF(expected_production[[#This Row],[Base Expected (kWh)]]="","",expected_production[[#This Row],[Base Expected (kWh)]]*expected_production[[#This Row],[Degradation Factor]]) -> 15048.078
A1054: Makalali | B1054: 45505 | C1054: {=IFERROR(INDEX('Expected Production'!$C$2:$N$79,MATCH($A1054,'Expected Production'!$A$2:$A$79,0),MONTH($B1054)),"")} -> 16365.447 | D1054: =_xlfn.XLOOKUP(expected_production[[#This Row],[Site Name]],Table1[[Site Name ]],Table1[Commisioned Date],"") -> 45050 | E1054: =IF(ISNUMBER(expected_production[[#This Row],[Commissioned Date]]),MAX(0,(expected_production[[#This Row],[Date]]-expected_production[[#This Row],[Commissioned Date]])/365.25),"") -> 1.2457221 | F1054: =IF(expected_production[[#This Row],[Age (yrs)]]="",1,(1-DegradationRate)^expected_production[[#This Row],[Age (yrs)]]) -> 0.99128746 | G1054: =IF(expected_production[[#This Row],[Base Expected (kWh)]]="","",expected_production[[#This Row],[Base Expected (kWh)]]*expected_production[[#This Row],[Degradation Factor]]) -> 16222.863
A1055: Makalali | B1055: 45536 | C1055: {=IFERROR(INDEX('Expected Production'!$C$2:$N$79,MATCH($A1055,'Expected Production'!$A$2:$A$79,0),MONTH($B1055)),"")} -> 16283.933 | D1055: =_xlfn.XLOOKUP(expected_production[[#This Row],[Site Name]],Table1[[Site Name ]],Table1[Commisioned Date],"") -> 45050 | E1055: =IF(ISNUMBER(expected_production[[#This Row],[Commissioned Date]]),MAX(0,(expected_production[[#This Row],[Date]]-expected_production[[#This Row],[Commissioned Date]])/365.25),"") -> 1.3305955 | F1055: =IF(expected_production[[#This Row],[Age (yrs)]]="",1,(1-DegradationRate)^expected_production[[#This Row],[Age (yrs)]]) -> 0.99069663 | G1055: =IF(expected_production[[#This Row],[Base Expected (kWh)]]="","",expected_production[[#This Row],[Base Expected (kWh)]]*expected_production[[#This Row],[Degradation Factor]]) -> 16132.438
A1056: Makalali | B1056: 45566 | C1056: {=IFERROR(INDEX('Expected Production'!$C$2:$N$79,MATCH($A1056,'Expected Production'!$A$2:$A$79,0),MONTH($B1056)),"")} -> 15891.08 | D1056: =_xlfn.XLOOKUP(expected_production[[#This Row],[Site Name]],Table1[[Site Name ]],Table1[Commisioned Date],"") -> 45050 | E1056: =IF(ISNUMBER(expected_production[[#This Row],[Commissioned Date]]),MAX(0,(expected_production[[#This Row],[Date]]-expected_production[[#This Row],[Commissioned Date]])/365.25),"") -> 1.412731 | F1056: =IF(expected_production[[#This Row],[Age (yrs)]]="",1,(1-DegradationRate)^expected_production[[#This Row],[Age (yrs)]]) -> 0.99012519 | G1056: =IF(expected_production[[#This Row],[Base Expected (kWh)]]="","",expected_production[[#This Row],[Base Expected (kWh)]]*expected_production[[#This Row],[Degradation Factor]]) -> 15734.159
A1057: Makalali | B1057: 45597 | C1057: {=IFERROR(INDEX('Expected Production'!$C$2:$N$79,MATCH($A1057,'Expected Production'!$A$2:$A$79,0),MONTH($B1057)),"")} -> 15343.218 | D1057: =_xlfn.XLOOKUP(expected_production[[#This Row],[Site Name]],Table1[[Site Name ]],Table1[Commisioned Date],"") -> 45050 | E1057: =IF(ISNUMBER(expected_production[[#This Row],[Commissioned Date]]),MAX(0,(expected_production[[#This Row],[Date]]-expected_production[[#This Row],[Commissioned Date]])/365.25),"") -> 1.4976044 | F1057: =IF(expected_production[[#This Row],[Age (yrs)]]="",1,(1-DegradationRate)^expected_production[[#This Row],[Age (yrs)]]) -> 0.98953505 | G1057: =IF(expected_production[[#This Row],[Base Expected (kWh)]]="","",expected_production[[#This Row],[Base Expected (kWh)]]*expected_production[[#This Row],[Degradation Factor]]) -> 15182.652
A1058: Makalali | B1058: 45627 | C1058: {=IFERROR(INDEX('Expected Production'!$C$2:$N$79,MATCH($A1058,'Expected Production'!$A$2:$A$79,0),MONTH($B1058)),"")} -> 16261.638 | D1058: =_xlfn.XLOOKUP(expected_production[[#This Row],[Site Name]],Table1[[Site Name ]],Table1[Commisioned Date],"") -> 45050 | E1058: =IF(ISNUMBER(expected_production[[#This Row],[Commissioned Date]]),MAX(0,(expected_production[[#This Row],[Date]]-expected_production[[#This Row],[Commissioned Date]])/365.25),"") -> 1.5797399 | F1058: =IF(expected_production[[#This Row],[Age (yrs)]]="",1,(1-DegradationRate)^expected_production[[#This Row],[Age (yrs)]]) -> 0.98896428 | G1058: =IF(expected_production[[#This Row],[Base Expected (kWh)]]="","",expected_production[[#This Row],[Base Expected (kWh)]]*expected_production[[#This Row],[Degradation Factor]]) -> 16082.179
... A1082: Makalali | B1082: 46357 | C1082: {=IFERROR(INDEX('Expected Production'!$C$2:$N$79,MATCH($A1082,'Expected Production'!$A$2:$A$79,0),MONTH($B1082)),"")} -> 16261.638 | D1082: =_xlfn.XLOOKUP(expected_production[[#This Row],[Site Name]],Table1[[Site Name ]],Table1[Commisioned Date],"") -> 45050 | E1082: =IF(ISNUMBER(expected_production[[#This Row],[Commissioned Date]]),MAX(0,(expected_production[[#This Row],[Date]]-expected_production[[#This Row],[Commissioned Date]])/365.25),"") -> 3.578371 | F1082: =IF(expected_production[[#This Row],[Age (yrs)]]="",1,(1-DegradationRate)^expected_production[[#This Row],[Age (yrs)]]) -> 0.97517662 | G1082: =IF(expected_production[[#This Row],[Base Expected (kWh)]]="","",expected_production[[#This Row],[Base Expected (kWh)]]*expected_production[[#This Row],[Degradation Factor]]) -> 15857.969
A1083: Mambha Cash & Carry | B1083: 45292 | C1083: 22241.7 | D1083: =_xlfn.XLOOKUP(expected_production[[#This Row],[Site Name]],Table1[[Site Name ]],Table1[Commisioned Date],"") -> 44879 | E1083: =IF(ISNUMBER(expected_production[[#This Row],[Commissioned Date]]),MAX(0,(expected_production[[#This Row],[Date]]-expected_production[[#This Row],[Commissioned Date]])/365.25),"") -> 1.1307324 | F1083: =IF(expected_production[[#This Row],[Age (yrs)]]="",1,(1-DegradationRate)^expected_production[[#This Row],[Age (yrs)]]) -> 0.9920885 | G1083: =IF(expected_production[[#This Row],[Base Expected (kWh)]]="","",expected_production[[#This Row],[Base Expected (kWh)]]*expected_production[[#This Row],[Degradation Factor]]) -> 22065.735
A1084: Mambha Cash & Carry | B1084: 45323 | C1084: 19450.8 | D1084: =_xlfn.XLOOKUP(expected_production[[#This Row],[Site Name]],Table1[[Site Name ]],Table1[Commisioned Date],"") -> 44879 | E1084: =IF(ISNUMBER(expected_production[[#This Row],[Commissioned Date]]),MAX(0,(expected_production[[#This Row],[Date]]-expected_production[[#This Row],[Commissioned Date]])/365.25),"") -> 1.2156057 | F1084: =IF(expected_production[[#This Row],[Age (yrs)]]="",1,(1-DegradationRate)^expected_production[[#This Row],[Age (yrs)]]) -> 0.99149719 | G1084: =IF(expected_production[[#This Row],[Base Expected (kWh)]]="","",expected_production[[#This Row],[Base Expected (kWh)]]*expected_production[[#This Row],[Degradation Factor]]) -> 19285.414
A1085: Mambha Cash & Carry | B1085: 45352 | C1085: 19575 | D1085: =_xlfn.XLOOKUP(expected_production[[#This Row],[Site Name]],Table1[[Site Name ]],Table1[Commisioned Date],"") -> 44879 | E1085: =IF(ISNUMBER(expected_production[[#This Row],[Commissioned Date]]),MAX(0,(expected_production[[#This Row],[Date]]-expected_production[[#This Row],[Commissioned Date]])/365.25),"") -> 1.2950034 | F1085: =IF(expected_production[[#This Row],[Age (yrs)]]="",1,(1-DegradationRate)^expected_production[[#This Row],[Age (yrs)]]) -> 0.99094435 | G1085: =IF(expected_production[[#This Row],[Base Expected (kWh)]]="","",expected_production[[#This Row],[Base Expected (kWh)]]*expected_production[[#This Row],[Degradation Factor]]) -> 19397.736
A1086: Mambha Cash & Carry | B1086: 45383 | C1086: 15792.3 | D1086: =_xlfn.XLOOKUP(expected_production[[#This Row],[Site Name]],Table1[[Site Name ]],Table1[Commisioned Date],"") -> 44879 | E1086: =IF(ISNUMBER(expected_production[[#This Row],[Commissioned Date]]),MAX(0,(expected_production[[#This Row],[Date]]-expected_production[[#This Row],[Commissioned Date]])/365.25),"") -> 1.3798768 | F1086: =IF(expected_production[[#This Row],[Age (yrs)]]="",1,(1-DegradationRate)^expected_production[[#This Row],[Age (yrs)]]) -> 0.99035372 | G1086: =IF(expected_production[[#This Row],[Base Expected (kWh)]]="","",expected_production[[#This Row],[Base Expected (kWh)]]*expected_production[[#This Row],[Degradation Factor]]) -> 15639.963
A1087: Mambha Cash & Carry | B1087: 45413 | C1087: 13477.5 | D1087: =_xlfn.XLOOKUP(expected_production[[#This Row],[Site Name]],Table1[[Site Name ]],Table1[Commisioned Date],"") -> 44879 | E1087: =IF(ISNUMBER(expected_production[[#This Row],[Commissioned Date]]),MAX(0,(expected_production[[#This Row],[Date]]-expected_production[[#This Row],[Commissioned Date]])/365.25),"") -> 1.4620123 | F1087: =IF(expected_production[[#This Row],[Age (yrs)]]="",1,(1-DegradationRate)^expected_production[[#This Row],[Age (yrs)]]) -> 0.98978248 | G1087: =IF(expected_production[[#This Row],[Base Expected (kWh)]]="","",expected_production[[#This Row],[Base Expected (kWh)]]*expected_production[[#This Row],[Degradation Factor]]) -> 13339.793
A1088: Mambha Cash & Carry | B1088: 45444 | C1088: 12124.8 | D1088: =_xlfn.XLOOKUP(expected_production[[#This Row],[Site Name]],Table1[[Site Name ]],Table1[Commisioned Date],"") -> 44879 | E1088: =IF(ISNUMBER(expected_production[[#This Row],[Commissioned Date]]),MAX(0,(expected_production[[#This Row],[Date]]-expected_production[[#This Row],[Commissioned Date]])/365.25),"") -> 1.5468857 | F1088: =IF(expected_production[[#This Row],[Age (yrs)]]="",1,(1-DegradationRate)^expected_production[[#This Row],[Age (yrs)]]) -> 0.98919255 | G1088: =IF(expected_production[[#This Row],[Base Expected (kWh)]]="","",expected_production[[#This Row],[Base Expected (kWh)]]*expected_production[[#This Row],[Degradation Factor]]) -> 11993.762
A1089: Mambha Cash & Carry | B1089: 45474 | C1089: 13099.5 | D1089: =_xlfn.XLOOKUP(expected_production[[#This Row],[Site Name]],Table1[[Site Name ]],Table1[Commisioned Date],"") -> 44879 | E1089: =IF(ISNUMBER(expected_production[[#This Row],[Commissioned Date]]),MAX(0,(expected_production[[#This Row],[Date]]-expected_production[[#This Row],[Commissioned Date]])/365.25),"") -> 1.6290212 | F1089: =IF(expected_production[[#This Row],[Age (yrs)]]="",1,(1-DegradationRate)^expected_production[[#This Row],[Age (yrs)]]) -> 0.98862198 | G1089: =IF(expected_production[[#This Row],[Base Expected (kWh)]]="","",expected_production[[#This Row],[Base Expected (kWh)]]*expected_production[[#This Row],[Degradation Factor]]) -> 12950.454
A1090: Mambha Cash & Carry | B1090: 45505 | C1090: 15450.3 | D1090: =_xlfn.XLOOKUP(expected_production[[#This Row],[Site Name]],Table1[[Site Name ]],Table1[Commisioned Date],"") -> 44879 | E1090: =IF(ISNUMBER(expected_production[[#This Row],[Commissioned Date]]),MAX(0,(expected_production[[#This Row],[Date]]-expected_production[[#This Row],[Commissioned Date]])/365.25),"") -> 1.7138946 | F1090: =IF(expected_production[[#This Row],[Age (yrs)]]="",1,(1-DegradationRate)^expected_production[[#This Row],[Age (yrs)]]) -> 0.98803273 | G1090: =IF(expected_production[[#This Row],[Base Expected (kWh)]]="","",expected_production[[#This Row],[Base Expected (kWh)]]*expected_production[[#This Row],[Degradation Factor]]) -> 15265.402
A1091: Mambha Cash & Carry | B1091: 45536 | C1091: 16583.4 | D1091: =_xlfn.XLOOKUP(expected_production[[#This Row],[Site Name]],Table1[[Site Name ]],Table1[Commisioned Date],"") -> 44879 | E1091: =IF(ISNUMBER(expected_production[[#This Row],[Commissioned Date]]),MAX(0,(expected_production[[#This Row],[Date]]-expected_production[[#This Row],[Commissioned Date]])/365.25),"") -> 1.798768 | F1091: =IF(expected_production[[#This Row],[Age (yrs)]]="",1,(1-DegradationRate)^expected_production[[#This Row],[Age (yrs)]]) -> 0.98744384 | G1091: =IF(expected_production[[#This Row],[Base Expected (kWh)]]="","",expected_production[[#This Row],[Base Expected (kWh)]]*expected_production[[#This Row],[Degradation Factor]]) -> 16375.176
A1092: Mambha Cash & Carry | B1092: 45566 | C1092: 19432.8 | D1092: =_xlfn.XLOOKUP(expected_production[[#This Row],[Site Name]],Table1[[Site Name ]],Table1[Commisioned Date],"") -> 44879 | E1092: =IF(ISNUMBER(expected_production[[#This Row],[Commissioned Date]]),MAX(0,(expected_production[[#This Row],[Date]]-expected_production[[#This Row],[Commissioned Date]])/365.25),"") -> 1.8809035 | F1092: =IF(expected_production[[#This Row],[Age (yrs)]]="",1,(1-DegradationRate)^expected_production[[#This Row],[Age (yrs)]]) -> 0.98687428 | G1092: =IF(expected_production[[#This Row],[Base Expected (kWh)]]="","",expected_production[[#This Row],[Base Expected (kWh)]]*expected_production[[#This Row],[Degradation Factor]]) -> 19177.731
A1093: Mambha Cash & Carry | B1093: 45597 | C1093: 20010.6 | D1093: =_xlfn.XLOOKUP(expected_production[[#This Row],[Site Name]],Table1[[Site Name ]],Table1[Commisioned Date],"") -> 44879 | E1093: =IF(ISNUMBER(expected_production[[#This Row],[Commissioned Date]]),MAX(0,(expected_production[[#This Row],[Date]]-expected_production[[#This Row],[Commissioned Date]])/365.25),"") -> 1.9657769 | F1093: =IF(expected_production[[#This Row],[Age (yrs)]]="",1,(1-DegradationRate)^expected_production[[#This Row],[Age (yrs)]]) -> 0.98628608 | G1093: =IF(expected_production[[#This Row],[Base Expected (kWh)]]="","",expected_production[[#This Row],[Base Expected (kWh)]]*expected_production[[#This Row],[Degradation Factor]]) -> 19736.176
A1094: Mambha Cash & Carry | B1094: 45627 | C1094: 22485.6 | D1094: =_xlfn.XLOOKUP(expected_production[[#This Row],[Site Name]],Table1[[Site Name ]],Table1[Commisioned Date],"") -> 44879 | E1094: =IF(ISNUMBER(expected_production[[#This Row],[Commissioned Date]]),MAX(0,(expected_production[[#This Row],[Date]]-expected_production[[#This Row],[Commissioned Date]])/365.25),"") -> 2.0479124 | F1094: =IF(expected_production[[#This Row],[Age (yrs)]]="",1,(1-DegradationRate)^expected_production[[#This Row],[Age (yrs)]]) -> 0.98571719 | G1094: =IF(expected_production[[#This Row],[Base Expected (kWh)]]="","",expected_production[[#This Row],[Base Expected (kWh)]]*expected_production[[#This Row],[Degradation Factor]]) -> 22164.442
... A2630: Watt Place Rotoflo | B2630: 46357 | C2630: 29028.6 | D2630: =_xlfn.XLOOKUP(expected_production[[#This Row],[Site Name]],Table1[[Site Name ]],Table1[Commisioned Date],"") -> 45059 | E2630: =IF(ISNUMBER(expected_production[[#This Row],[Commissioned Date]]),MAX(0,(expected_production[[#This Row],[Date]]-expected_production[[#This Row],[Commissioned Date]])/365.25),"") -> 3.5537303 | F2630: =IF(expected_production[[#This Row],[Age (yrs)]]="",1,(1-DegradationRate)^expected_production[[#This Row],[Age (yrs)]]) -> 0.97534543 | G2630: =IF(expected_production[[#This Row],[Base Expected (kWh)]]="","",expected_production[[#This Row],[Base Expected (kWh)]]*expected_production[[#This Row],[Degradation Factor]]) -> 28312.912
A2631: Zwartop Golf Course | B2631: 45292 | D2631: =_xlfn.XLOOKUP(expected_production[[#This Row],[Site Name]],Table1[[Site Name ]],Table1[Commisioned Date],"") -> 45188 | E2631: =IF(ISNUMBER(expected_production[[#This Row],[Commissioned Date]]),MAX(0,(expected_production[[#This Row],[Date]]-expected_production[[#This Row],[Commissioned Date]])/365.25),"") -> 0.28473648 | F2631: =IF(expected_production[[#This Row],[Age (yrs)]]="",1,(1-DegradationRate)^expected_production[[#This Row],[Age (yrs)]]) -> 0.99800183 | G2631: =IF(expected_production[[#This Row],[Base Expected (kWh)]]="","",expected_production[[#This Row],[Base Expected (kWh)]]*expected_production[[#This Row],[Degradation Factor]])
A2632: Zwartop Golf Course | B2632: 45323 | D2632: =_xlfn.XLOOKUP(expected_production[[#This Row],[Site Name]],Table1[[Site Name ]],Table1[Commisioned Date],"") -> 45188 | E2632: =IF(ISNUMBER(expected_production[[#This Row],[Commissioned Date]]),MAX(0,(expected_production[[#This Row],[Date]]-expected_production[[#This Row],[Commissioned Date]])/365.25),"") -> 0.36960986 | F2632: =IF(expected_production[[#This Row],[Age (yrs)]]="",1,(1-DegradationRate)^expected_production[[#This Row],[Age (yrs)]]) -> 0.997407 | G2632: =IF(expected_production[[#This Row],[Base Expected (kWh)]]="","",expected_production[[#This Row],[Base Expected (kWh)]]*expected_production[[#This Row],[Degradation Factor]])
A2633: Zwartop Golf Course | B2633: 45352 | D2633: =_xlfn.XLOOKUP(expected_production[[#This Row],[Site Name]],Table1[[Site Name ]],Table1[Commisioned Date],"") -> 45188 | E2633: =IF(ISNUMBER(expected_production[[#This Row],[Commissioned Date]]),MAX(0,(expected_production[[#This Row],[Date]]-expected_production[[#This Row],[Commissioned Date]])/365.25),"") -> 0.44900753 | F2633: =IF(expected_production[[#This Row],[Age (yrs)]]="",1,(1-DegradationRate)^expected_production[[#This Row],[Age (yrs)]]) -> 0.99685086 | G2633: =IF(expected_production[[#This Row],[Base Expected (kWh)]]="","",expected_production[[#This Row],[Base Expected (kWh)]]*expected_production[[#This Row],[Degradation Factor]])
A2634: Zwartop Golf Course | B2634: 45383 | D2634: =_xlfn.XLOOKUP(expected_production[[#This Row],[Site Name]],Table1[[Site Name ]],Table1[Commisioned Date],"") -> 45188 | E2634: =IF(ISNUMBER(expected_production[[#This Row],[Commissioned Date]]),MAX(0,(expected_production[[#This Row],[Date]]-expected_production[[#This Row],[Commissioned Date]])/365.25),"") -> 0.5338809 | F2634: =IF(expected_production[[#This Row],[Age (yrs)]]="",1,(1-DegradationRate)^expected_production[[#This Row],[Age (yrs)]]) -> 0.99625672 | G2634: =IF(expected_production[[#This Row],[Base Expected (kWh)]]="","",expected_production[[#This Row],[Base Expected (kWh)]]*expected_production[[#This Row],[Degradation Factor]])
A2635: Zwartop Golf Course | B2635: 45413 | D2635: =_xlfn.XLOOKUP(expected_production[[#This Row],[Site Name]],Table1[[Site Name ]],Table1[Commisioned Date],"") -> 45188 | E2635: =IF(ISNUMBER(expected_production[[#This Row],[Commissioned Date]]),MAX(0,(expected_production[[#This Row],[Date]]-expected_production[[#This Row],[Commissioned Date]])/365.25),"") -> 0.61601643 | F2635: =IF(expected_production[[#This Row],[Age (yrs)]]="",1,(1-DegradationRate)^expected_production[[#This Row],[Age (yrs)]]) -> 0.99568207 | G2635: =IF(expected_production[[#This Row],[Base Expected (kWh)]]="","",expected_production[[#This Row],[Base Expected (kWh)]]*expected_production[[#This Row],[Degradation Factor]])
A2636: Zwartop Golf Course | B2636: 45444 | D2636: =_xlfn.XLOOKUP(expected_production[[#This Row],[Site Name]],Table1[[Site Name ]],Table1[Commisioned Date],"") -> 45188 | E2636: =IF(ISNUMBER(expected_production[[#This Row],[Commissioned Date]]),MAX(0,(expected_production[[#This Row],[Date]]-expected_production[[#This Row],[Commissioned Date]])/365.25),"") -> 0.7008898 | F2636: =IF(expected_production[[#This Row],[Age (yrs)]]="",1,(1-DegradationRate)^expected_production[[#This Row],[Age (yrs)]]) -> 0.99508862 | G2636: =IF(expected_production[[#This Row],[Base Expected (kWh)]]="","",expected_production[[#This Row],[Base Expected (kWh)]]*expected_production[[#This Row],[Degradation Factor]])
A2637: Zwartop Golf Course | B2637: 45474 | D2637: =_xlfn.XLOOKUP(expected_production[[#This Row],[Site Name]],Table1[[Site Name ]],Table1[Commisioned Date],"") -> 45188 | E2637: =IF(ISNUMBER(expected_production[[#This Row],[Commissioned Date]]),MAX(0,(expected_production[[#This Row],[Date]]-expected_production[[#This Row],[Commissioned Date]])/365.25),"") -> 0.78302533 | F2637: =IF(expected_production[[#This Row],[Age (yrs)]]="",1,(1-DegradationRate)^expected_production[[#This Row],[Age (yrs)]]) -> 0.99451465 | G2637: =IF(expected_production[[#This Row],[Base Expected (kWh)]]="","",expected_production[[#This Row],[Base Expected (kWh)]]*expected_production[[#This Row],[Degradation Factor]])
A2638: Zwartop Golf Course | B2638: 45505 | D2638: =_xlfn.XLOOKUP(expected_production[[#This Row],[Site Name]],Table1[[Site Name ]],Table1[Commisioned Date],"") -> 45188 | E2638: =IF(ISNUMBER(expected_production[[#This Row],[Commissioned Date]]),MAX(0,(expected_production[[#This Row],[Date]]-expected_production[[#This Row],[Commissioned Date]])/365.25),"") -> 0.8678987 | F2638: =IF(expected_production[[#This Row],[Age (yrs)]]="",1,(1-DegradationRate)^expected_production[[#This Row],[Age (yrs)]]) -> 0.99392189 | G2638: =IF(expected_production[[#This Row],[Base Expected (kWh)]]="","",expected_production[[#This Row],[Base Expected (kWh)]]*expected_production[[#This Row],[Degradation Factor]])
A2639: Zwartop Golf Course | B2639: 45536 | D2639: =_xlfn.XLOOKUP(expected_production[[#This Row],[Site Name]],Table1[[Site Name ]],Table1[Commisioned Date],"") -> 45188 | E2639: =IF(ISNUMBER(expected_production[[#This Row],[Commissioned Date]]),MAX(0,(expected_production[[#This Row],[Date]]-expected_production[[#This Row],[Commissioned Date]])/365.25),"") -> 0.95277207 | F2639: =IF(expected_production[[#This Row],[Age (yrs)]]="",1,(1-DegradationRate)^expected_production[[#This Row],[Age (yrs)]]) -> 0.99332949 | G2639: =IF(expected_production[[#This Row],[Base Expected (kWh)]]="","",expected_production[[#This Row],[Base Expected (kWh)]]*expected_production[[#This Row],[Degradation Factor]])
A2640: Zwartop Golf Course | B2640: 45566 | D2640: =_xlfn.XLOOKUP(expected_production[[#This Row],[Site Name]],Table1[[Site Name ]],Table1[Commisioned Date],"") -> 45188 | E2640: =IF(ISNUMBER(expected_production[[#This Row],[Commissioned Date]]),MAX(0,(expected_production[[#This Row],[Date]]-expected_production[[#This Row],[Commissioned Date]])/365.25),"") -> 1.0349076 | F2640: =IF(expected_production[[#This Row],[Age (yrs)]]="",1,(1-DegradationRate)^expected_production[[#This Row],[Age (yrs)]]) -> 0.99275653 | G2640: =IF(expected_production[[#This Row],[Base Expected (kWh)]]="","",expected_production[[#This Row],[Base Expected (kWh)]]*expected_production[[#This Row],[Degradation Factor]])
A2641: Zwartop Golf Course | B2641: 45597 | D2641: =_xlfn.XLOOKUP(expected_production[[#This Row],[Site Name]],Table1[[Site Name ]],Table1[Commisioned Date],"") -> 45188 | E2641: =IF(ISNUMBER(expected_production[[#This Row],[Commissioned Date]]),MAX(0,(expected_production[[#This Row],[Date]]-expected_production[[#This Row],[Commissioned Date]])/365.25),"") -> 1.119781 | F2641: =IF(expected_production[[#This Row],[Age (yrs)]]="",1,(1-DegradationRate)^expected_production[[#This Row],[Age (yrs)]]) -> 0.99216483 | G2641: =IF(expected_production[[#This Row],[Base Expected (kWh)]]="","",expected_production[[#This Row],[Base Expected (kWh)]]*expected_production[[#This Row],[Degradation Factor]])
A2642: Zwartop Golf Course | B2642: 45627 | D2642: =_xlfn.XLOOKUP(expected_production[[#This Row],[Site Name]],Table1[[Site Name ]],Table1[Commisioned Date],"") -> 45188 | E2642: =IF(ISNUMBER(expected_production[[#This Row],[Commissioned Date]]),MAX(0,(expected_production[[#This Row],[Date]]-expected_production[[#This Row],[Commissioned Date]])/365.25),"") -> 1.2019165 | F2642: =IF(expected_production[[#This Row],[Age (yrs)]]="",1,(1-DegradationRate)^expected_production[[#This Row],[Age (yrs)]]) -> 0.99159254 | G2642: =IF(expected_production[[#This Row],[Base Expected (kWh)]]="","",expected_production[[#This Row],[Base Expected (kWh)]]*expected_production[[#This Row],[Degradation Factor]])
... A2666: Zwartop Golf Course | B2666: 46357 | D2666: =_xlfn.XLOOKUP(expected_production[[#This Row],[Site Name]],Table1[[Site Name ]],Table1[Commisioned Date],"") -> 45188 | E2666: =IF(ISNUMBER(expected_production[[#This Row],[Commissioned Date]]),MAX(0,(expected_production[[#This Row],[Date]]-expected_production[[#This Row],[Commissioned Date]])/365.25),"") -> 3.2005476 | F2666: =IF(expected_production[[#This Row],[Age (yrs)]]="",1,(1-DegradationRate)^expected_production[[#This Row],[Age (yrs)]]) -> 0.97776824 | G2666: =IF(expected_production[[#This Row],[Base Expected (kWh)]]="","",expected_production[[#This Row],[Base Expected (kWh)]]*expected_production[[#This Row],[Degradation Factor]])
A2667: Engen Kaalfontein | B2667: 45292 | C2667: {=IFERROR(INDEX('Expected Production'!$C$2:$N$199,MATCH(A2667,'Expected Production'!$A$2:$A$199,0),MONTH(B2667)),"")} -> 17370.9 | D2667: =_xlfn.XLOOKUP(expected_production[[#This Row],[Site Name]],Table1[[Site Name ]],Table1[Commisioned Date],"") -> 46162 | E2667: =IF(ISNUMBER(expected_production[[#This Row],[Commissioned Date]]),MAX(0,(expected_production[[#This Row],[Date]]-expected_production[[#This Row],[Commissioned Date]])/365.25),"") -> 0 | F2667: =IF(expected_production[[#This Row],[Age (yrs)]]="",1,(1-DegradationRate)^expected_production[[#This Row],[Age (yrs)]]) -> 1 | G2667: =IF(expected_production[[#This Row],[Base Expected (kWh)]]="","",expected_production[[#This Row],[Base Expected (kWh)]]*expected_production[[#This Row],[Degradation Factor]]) -> 17370.9
A2668: Engen Kaalfontein | B2668: 45323 | C2668: {=IFERROR(INDEX('Expected Production'!$C$2:$N$199,MATCH(A2668,'Expected Production'!$A$2:$A$199,0),MONTH(B2668)),"")} -> 15077.7 | D2668: =_xlfn.XLOOKUP(expected_production[[#This Row],[Site Name]],Table1[[Site Name ]],Table1[Commisioned Date],"") -> 46162 | E2668: =IF(ISNUMBER(expected_production[[#This Row],[Commissioned Date]]),MAX(0,(expected_production[[#This Row],[Date]]-expected_production[[#This Row],[Commissioned Date]])/365.25),"") -> 0 | F2668: =IF(expected_production[[#This Row],[Age (yrs)]]="",1,(1-DegradationRate)^expected_production[[#This Row],[Age (yrs)]]) -> 1 | G2668: =IF(expected_production[[#This Row],[Base Expected (kWh)]]="","",expected_production[[#This Row],[Base Expected (kWh)]]*expected_production[[#This Row],[Degradation Factor]]) -> 15077.7
A2669: Engen Kaalfontein | B2669: 45352 | C2669: {=IFERROR(INDEX('Expected Production'!$C$2:$N$199,MATCH(A2669,'Expected Production'!$A$2:$A$199,0),MONTH(B2669)),"")} -> 14634 | D2669: =_xlfn.XLOOKUP(expected_production[[#This Row],[Site Name]],Table1[[Site Name ]],Table1[Commisioned Date],"") -> 46162 | E2669: =IF(ISNUMBER(expected_production[[#This Row],[Commissioned Date]]),MAX(0,(expected_production[[#This Row],[Date]]-expected_production[[#This Row],[Commissioned Date]])/365.25),"") -> 0 | F2669: =IF(expected_production[[#This Row],[Age (yrs)]]="",1,(1-DegradationRate)^expected_production[[#This Row],[Age (yrs)]]) -> 1 | G2669: =IF(expected_production[[#This Row],[Base Expected (kWh)]]="","",expected_production[[#This Row],[Base Expected (kWh)]]*expected_production[[#This Row],[Degradation Factor]]) -> 14634
A2670: Engen Kaalfontein | B2670: 45383 | C2670: {=IFERROR(INDEX('Expected Production'!$C$2:$N$199,MATCH(A2670,'Expected Production'!$A$2:$A$199,0),MONTH(B2670)),"")} -> 12420 | D2670: =_xlfn.XLOOKUP(expected_production[[#This Row],[Site Name]],Table1[[Site Name ]],Table1[Commisioned Date],"") -> 46162 | E2670: =IF(ISNUMBER(expected_production[[#This Row],[Commissioned Date]]),MAX(0,(expected_production[[#This Row],[Date]]-expected_production[[#This Row],[Commissioned Date]])/365.25),"") -> 0 | F2670: =IF(expected_production[[#This Row],[Age (yrs)]]="",1,(1-DegradationRate)^expected_production[[#This Row],[Age (yrs)]]) -> 1 | G2670: =IF(expected_production[[#This Row],[Base Expected (kWh)]]="","",expected_production[[#This Row],[Base Expected (kWh)]]*expected_production[[#This Row],[Degradation Factor]]) -> 12420
A2671: Engen Kaalfontein | B2671: 45413 | C2671: {=IFERROR(INDEX('Expected Production'!$C$2:$N$199,MATCH(A2671,'Expected Production'!$A$2:$A$199,0),MONTH(B2671)),"")} -> 11402.1 | D2671: =_xlfn.XLOOKUP(expected_production[[#This Row],[Site Name]],Table1[[Site Name ]],Table1[Commisioned Date],"") -> 46162 | E2671: =IF(ISNUMBER(expected_production[[#This Row],[Commissioned Date]]),MAX(0,(expected_production[[#This Row],[Date]]-expected_production[[#This Row],[Commissioned Date]])/365.25),"") -> 0 | F2671: =IF(expected_production[[#This Row],[Age (yrs)]]="",1,(1-DegradationRate)^expected_production[[#This Row],[Age (yrs)]]) -> 1 | G2671: =IF(expected_production[[#This Row],[Base Expected (kWh)]]="","",expected_production[[#This Row],[Base Expected (kWh)]]*expected_production[[#This Row],[Degradation Factor]]) -> 11402.1
A2672: Engen Kaalfontein | B2672: 45444 | C2672: {=IFERROR(INDEX('Expected Production'!$C$2:$N$199,MATCH(A2672,'Expected Production'!$A$2:$A$199,0),MONTH(B2672)),"")} -> 9989.1 | D2672: =_xlfn.XLOOKUP(expected_production[[#This Row],[Site Name]],Table1[[Site Name ]],Table1[Commisioned Date],"") -> 46162 | E2672: =IF(ISNUMBER(expected_production[[#This Row],[Commissioned Date]]),MAX(0,(expected_production[[#This Row],[Date]]-expected_production[[#This Row],[Commissioned Date]])/365.25),"") -> 0 | F2672: =IF(expected_production[[#This Row],[Age (yrs)]]="",1,(1-DegradationRate)^expected_production[[#This Row],[Age (yrs)]]) -> 1 | G2672: =IF(expected_production[[#This Row],[Base Expected (kWh)]]="","",expected_production[[#This Row],[Base Expected (kWh)]]*expected_production[[#This Row],[Degradation Factor]]) -> 9989.1
A2673: Engen Kaalfontein | B2673: 45474 | C2673: {=IFERROR(INDEX('Expected Production'!$C$2:$N$199,MATCH(A2673,'Expected Production'!$A$2:$A$199,0),MONTH(B2673)),"")} -> 10986.3 | D2673: =_xlfn.XLOOKUP(expected_production[[#This Row],[Site Name]],Table1[[Site Name ]],Table1[Commisioned Date],"") -> 46162 | E2673: =IF(ISNUMBER(expected_production[[#This Row],[Commissioned Date]]),MAX(0,(expected_production[[#This Row],[Date]]-expected_production[[#This Row],[Commissioned Date]])/365.25),"") -> 0 | F2673: =IF(expected_production[[#This Row],[Age (yrs)]]="",1,(1-DegradationRate)^expected_production[[#This Row],[Age (yrs)]]) -> 1 | G2673: =IF(expected_production[[#This Row],[Base Expected (kWh)]]="","",expected_production[[#This Row],[Base Expected (kWh)]]*expected_production[[#This Row],[Degradation Factor]]) -> 10986.3
A2674: Engen Kaalfontein | B2674: 45505 | C2674: {=IFERROR(INDEX('Expected Production'!$C$2:$N$199,MATCH(A2674,'Expected Production'!$A$2:$A$199,0),MONTH(B2674)),"")} -> 13108.77 | D2674: =_xlfn.XLOOKUP(expected_production[[#This Row],[Site Name]],Table1[[Site Name ]],Table1[Commisioned Date],"") -> 46162 | E2674: =IF(ISNUMBER(expected_production[[#This Row],[Commissioned Date]]),MAX(0,(expected_production[[#This Row],[Date]]-expected_production[[#This Row],[Commissioned Date]])/365.25),"") -> 0 | F2674: =IF(expected_production[[#This Row],[Age (yrs)]]="",1,(1-DegradationRate)^expected_production[[#This Row],[Age (yrs)]]) -> 1 | G2674: =IF(expected_production[[#This Row],[Base Expected (kWh)]]="","",expected_production[[#This Row],[Base Expected (kWh)]]*expected_production[[#This Row],[Degradation Factor]]) -> 13108.77
A2675: Engen Kaalfontein | B2675: 45536 | C2675: {=IFERROR(INDEX('Expected Production'!$C$2:$N$199,MATCH(A2675,'Expected Production'!$A$2:$A$199,0),MONTH(B2675)),"")} -> 14833.17 | D2675: =_xlfn.XLOOKUP(expected_production[[#This Row],[Site Name]],Table1[[Site Name ]],Table1[Commisioned Date],"") -> 46162 | E2675: =IF(ISNUMBER(expected_production[[#This Row],[Commissioned Date]]),MAX(0,(expected_production[[#This Row],[Date]]-expected_production[[#This Row],[Commissioned Date]])/365.25),"") -> 0 | F2675: =IF(expected_production[[#This Row],[Age (yrs)]]="",1,(1-DegradationRate)^expected_production[[#This Row],[Age (yrs)]]) -> 1 | G2675: =IF(expected_production[[#This Row],[Base Expected (kWh)]]="","",expected_production[[#This Row],[Base Expected (kWh)]]*expected_production[[#This Row],[Degradation Factor]]) -> 14833.17
A2676: Engen Kaalfontein | B2676: 45566 | C2676: {=IFERROR(INDEX('Expected Production'!$C$2:$N$199,MATCH(A2676,'Expected Production'!$A$2:$A$199,0),MONTH(B2676)),"")} -> 17053.2 | D2676: =_xlfn.XLOOKUP(expected_production[[#This Row],[Site Name]],Table1[[Site Name ]],Table1[Commisioned Date],"") -> 46162 | E2676: =IF(ISNUMBER(expected_production[[#This Row],[Commissioned Date]]),MAX(0,(expected_production[[#This Row],[Date]]-expected_production[[#This Row],[Commissioned Date]])/365.25),"") -> 0 | F2676: =IF(expected_production[[#This Row],[Age (yrs)]]="",1,(1-DegradationRate)^expected_production[[#This Row],[Age (yrs)]]) -> 1 | G2676: =IF(expected_production[[#This Row],[Base Expected (kWh)]]="","",expected_production[[#This Row],[Base Expected (kWh)]]*expected_production[[#This Row],[Degradation Factor]]) -> 17053.2
A2677: Engen Kaalfontein | B2677: 45597 | C2677: {=IFERROR(INDEX('Expected Production'!$C$2:$N$199,MATCH(A2677,'Expected Production'!$A$2:$A$199,0),MONTH(B2677)),"")} -> 17239.5 | D2677: =_xlfn.XLOOKUP(expected_production[[#This Row],[Site Name]],Table1[[Site Name ]],Table1[Commisioned Date],"") -> 46162 | E2677: =IF(ISNUMBER(expected_production[[#This Row],[Commissioned Date]]),MAX(0,(expected_production[[#This Row],[Date]]-expected_production[[#This Row],[Commissioned Date]])/365.25),"") -> 0 | F2677: =IF(expected_production[[#This Row],[Age (yrs)]]="",1,(1-DegradationRate)^expected_production[[#This Row],[Age (yrs)]]) -> 1 | G2677: =IF(expected_production[[#This Row],[Base Expected (kWh)]]="","",expected_production[[#This Row],[Base Expected (kWh)]]*expected_production[[#This Row],[Degradation Factor]]) -> 17239.5
A2678: Engen Kaalfontein | B2678: 45627 | C2678: {=IFERROR(INDEX('Expected Production'!$C$2:$N$199,MATCH(A2678,'Expected Production'!$A$2:$A$199,0),MONTH(B2678)),"")} -> 17465.4 | D2678: =_xlfn.XLOOKUP(expected_production[[#This Row],[Site Name]],Table1[[Site Name ]],Table1[Commisioned Date],"") -> 46162 | E2678: =IF(ISNUMBER(expected_production[[#This Row],[Commissioned Date]]),MAX(0,(expected_production[[#This Row],[Date]]-expected_production[[#This Row],[Commissioned Date]])/365.25),"") -> 0 | F2678: =IF(expected_production[[#This Row],[Age (yrs)]]="",1,(1-DegradationRate)^expected_production[[#This Row],[Age (yrs)]]) -> 1 | G2678: =IF(expected_production[[#This Row],[Base Expected (kWh)]]="","",expected_production[[#This Row],[Base Expected (kWh)]]*expected_production[[#This Row],[Degradation Factor]]) -> 17465.4
... A2780: Usave Naboomspruit | B2780: 46357 | C2780: {=IFERROR(INDEX('Expected Production'!$C$2:$N$199,MATCH(A2780,'Expected Production'!$A$2:$A$199,0),MONTH(B2780)),"")} -> 5989.5 | D2780: =_xlfn.XLOOKUP(expected_production[[#This Row],[Site Name]],Table1[[Site Name ]],Table1[Commisioned Date],"") -> 46185 | E2780: =IF(ISNUMBER(expected_production[[#This Row],[Commissioned Date]]),MAX(0,(expected_production[[#This Row],[Date]]-expected_production[[#This Row],[Commissioned Date]])/365.25),"") -> 0.47091034 | F2780: =IF(expected_production[[#This Row],[Age (yrs)]]="",1,(1-DegradationRate)^expected_production[[#This Row],[Age (yrs)]]) -> 0.9966975 | G2780: =IF(expected_production[[#This Row],[Base Expected (kWh)]]="","",expected_production[[#This Row],[Base Expected (kWh)]]*expected_production[[#This Row],[Degradation Factor]]) -> 5969.7197

Sheet performance
A1: Site Name | B1: Date | C1: Measured (kWh) | D1: Expected (kWh) | E1: Performance | F1: PF Band | G1: Discussion
A2: 21 Melrose | B2: 45292 | C2: {=IFERROR(IF(SUMPRODUCT((measured[Site Name]=A2)*(measured[Date]=B2)*ISNUMBER(measured[Measured Value (kWh)]))=0,"",SUMIFS(measured[Measured Value (kWh)],measured[Site Name],A2,measured[Date],B2)),"")} -> 1815 | D2: {=IFERROR(IF(SUMPRODUCT((expected_production[Site Name]=A2)*(expected_production[Date]=B2)*ISNUMBER(expected_production[Expected Production (kWh)]))=0,"",SUMIFS(expected_production[Expected Production (kWh)],expected_production[Site Name],A2,expected_production[Date],B2)),"")} -> 2355.6475 | E2: =IF(OR(C2="",D2="",D2=0),"",C2/D2) -> 0.77048879 | F2: =IF(E2="","",IF(E2>=0.9,"Expected",IF(E2>=0.7,"Moderate","Poor"))) -> Moderate
A3: 21 Melrose | B3: 45323 | C3: {=IFERROR(IF(SUMPRODUCT((measured[Site Name]=A3)*(measured[Date]=B3)*ISNUMBER(measured[Measured Value (kWh)]))=0,"",SUMIFS(measured[Measured Value (kWh)],measured[Site Name],A3,measured[Date],B3)),"")} -> 2295 | D3: {=IFERROR(IF(SUMPRODUCT((expected_production[Site Name]=A3)*(expected_production[Date]=B3)*ISNUMBER(expected_production[Expected Production (kWh)]))=0,"",SUMIFS(expected_production[Expected Production (kWh)],expected_production[Site Name],A3,expected_production[Date],B3)),"")} -> 2661.7073 | E3: =IF(OR(C3="",D3="",D3=0),"",C3/D3) -> 0.86222853 | F3: =IF(E3="","",IF(E3>=0.9,"Expected",IF(E3>=0.7,"Moderate","Poor"))) -> Moderate
A4: 21 Melrose | B4: 45352 | C4: {=IFERROR(IF(SUMPRODUCT((measured[Site Name]=A4)*(measured[Date]=B4)*ISNUMBER(measured[Measured Value (kWh)]))=0,"",SUMIFS(measured[Measured Value (kWh)],measured[Site Name],A4,measured[Date],B4)),"")} -> 2474 | D4: {=IFERROR(IF(SUMPRODUCT((expected_production[Site Name]=A4)*(expected_production[Date]=B4)*ISNUMBER(expected_production[Expected Production (kWh)]))=0,"",SUMIFS(expected_production[Expected Production (kWh)],expected_production[Site Name],A4,expected_production[Date],B4)),"")} -> 2167.1261 | E4: =IF(OR(C4="",D4="",D4=0),"",C4/D4) -> 1.1416041 | F4: =IF(E4="","",IF(E4>=0.9,"Expected",IF(E4>=0.7,"Moderate","Poor"))) -> Expected
A5: 21 Melrose | B5: 45383 | C5: {=IFERROR(IF(SUMPRODUCT((measured[Site Name]=A5)*(measured[Date]=B5)*ISNUMBER(measured[Measured Value (kWh)]))=0,"",SUMIFS(measured[Measured Value (kWh)],measured[Site Name],A5,measured[Date],B5)),"")} -> 2136 | D5: {=IFERROR(IF(SUMPRODUCT((expected_production[Site Name]=A5)*(expected_production[Date]=B5)*ISNUMBER(expected_production[Expected Production (kWh)]))=0,"",SUMIFS(expected_production[Expected Production (kWh)],expected_production[Site Name],A5,expected_production[Date],B5)),"")} -> 1858.7252 | E5: =IF(OR(C5="",D5="",D5=0),"",C5/D5) -> 1.1491747 | F5: =IF(E5="","",IF(E5>=0.9,"Expected",IF(E5>=0.7,"Moderate","Poor"))) -> Expected
A6: 21 Melrose | B6: 45413 | C6: {=IFERROR(IF(SUMPRODUCT((measured[Site Name]=A6)*(measured[Date]=B6)*ISNUMBER(measured[Measured Value (kWh)]))=0,"",SUMIFS(measured[Measured Value (kWh)],measured[Site Name],A6,measured[Date],B6)),"")} -> 2212 | D6: {=IFERROR(IF(SUMPRODUCT((expected_production[Site Name]=A6)*(expected_production[Date]=B6)*ISNUMBER(expected_production[Expected Production (kWh)]))=0,"",SUMIFS(expected_production[Expected Production (kWh)],expected_production[Site Name],A6,expected_production[Date],B6)),"")} -> 1806.7951 | E6: =IF(OR(C6="",D6="",D6=0),"",C6/D6) -> 1.2242672 | F6: =IF(E6="","",IF(E6>=0.9,"Expected",IF(E6>=0.7,"Moderate","Poor"))) -> Expected
A7: 21 Melrose | B7: 45444 | C7: {=IFERROR(IF(SUMPRODUCT((measured[Site Name]=A7)*(measured[Date]=B7)*ISNUMBER(measured[Measured Value (kWh)]))=0,"",SUMIFS(measured[Measured Value (kWh)],measured[Site Name],A7,measured[Date],B7)),"")} -> 1863 | D7: {=IFERROR(IF(SUMPRODUCT((expected_production[Site Name]=A7)*(expected_production[Date]=B7)*ISNUMBER(expected_production[Expected Production (kWh)]))=0,"",SUMIFS(expected_production[Expected Production (kWh)],expected_production[Site Name],A7,expected_production[Date],B7)),"")} -> 1614 | E7: =IF(OR(C7="",D7="",D7=0),"",C7/D7) -> 1.1542751 | F7: =IF(E7="","",IF(E7>=0.9,"Expected",IF(E7>=0.7,"Moderate","Poor"))) -> Expected
A8: 21 Melrose | B8: 45474 | C8: {=IFERROR(IF(SUMPRODUCT((measured[Site Name]=A8)*(measured[Date]=B8)*ISNUMBER(measured[Measured Value (kWh)]))=0,"",SUMIFS(measured[Measured Value (kWh)],measured[Site Name],A8,measured[Date],B8)),"")} -> 1943 | D8: {=IFERROR(IF(SUMPRODUCT((expected_production[Site Name]=A8)*(expected_production[Date]=B8)*ISNUMBER(expected_production[Expected Production (kWh)]))=0,"",SUMIFS(expected_production[Expected Production (kWh)],expected_production[Site Name],A8,expected_production[Date],B8)),"")} -> 1796.6559 | E8: =IF(OR(C8="",D8="",D8=0),"",C8/D8) -> 1.0814536 | F8: =IF(E8="","",IF(E8>=0.9,"Expected",IF(E8>=0.7,"Moderate","Poor"))) -> Expected
A9: 21 Melrose | B9: 45505 | C9: {=IFERROR(IF(SUMPRODUCT((measured[Site Name]=A9)*(measured[Date]=B9)*ISNUMBER(measured[Measured Value (kWh)]))=0,"",SUMIFS(measured[Measured Value (kWh)],measured[Site Name],A9,measured[Date],B9)),"")} -> 1710 | D9: {=IFERROR(IF(SUMPRODUCT((expected_production[Site Name]=A9)*(expected_production[Date]=B9)*ISNUMBER(expected_production[Expected Production (kWh)]))=0,"",SUMIFS(expected_production[Expected Production (kWh)],expected_production[Site Name],A9,expected_production[Date],B9)),"")} -> 2094.8492 | E9: =IF(OR(C9="",D9="",D9=0),"",C9/D9) -> 0.81628786 | F9: =IF(E9="","",IF(E9>=0.9,"Expected",IF(E9>=0.7,"Moderate","Poor"))) -> Moderate
A10: 21 Melrose | B10: 45536 | C10: {=IFERROR(IF(SUMPRODUCT((measured[Site Name]=A10)*(measured[Date]=B10)*ISNUMBER(measured[Measured Value (kWh)]))=0,"",SUMIFS(measured[Measured Value (kWh)],measured[Site Name],A10,measured[Date],B10)),"")} -> 1579 | D10: {=IFERROR(IF(SUMPRODUCT((expected_production[Site Name]=A10)*(expected_production[Date]=B10)*ISNUMBER(expected_production[Expected Production (kWh)]))=0,"",SUMIFS(expected_production[Expected Production (kWh)],expected_production[Site Name],A10,expected_production[Date],B10)),"")} -> 2250.2646 | E10: =IF(OR(C10="",D10="",D10=0),"",C10/D10) -> 0.70169525 | F10: =IF(E10="","",IF(E10>=0.9,"Expected",IF(E10>=0.7,"Moderate","Poor"))) -> Moderate
A11: 21 Melrose | B11: 45566 | C11: {=IFERROR(IF(SUMPRODUCT((measured[Site Name]=A11)*(measured[Date]=B11)*ISNUMBER(measured[Measured Value (kWh)]))=0,"",SUMIFS(measured[Measured Value (kWh)],measured[Site Name],A11,measured[Date],B11)),"")} -> 1593 | D11: {=IFERROR(IF(SUMPRODUCT((expected_production[Site Name]=A11)*(expected_production[Date]=B11)*ISNUMBER(expected_production[Expected Production (kWh)]))=0,"",SUMIFS(expected_production[Expected Production (kWh)],expected_production[Site Name],A11,expected_production[Date],B11)),"")} -> 2379.7412 | E11: =IF(OR(C11="",D11="",D11=0),"",C11/D11) -> 0.66940051 | F11: =IF(E11="","",IF(E11>=0.9,"Expected",IF(E11>=0.7,"Moderate","Poor"))) -> Poor
A12: 21 Melrose | B12: 45597 | C12: {=IFERROR(IF(SUMPRODUCT((measured[Site Name]=A12)*(measured[Date]=B12)*ISNUMBER(measured[Measured Value (kWh)]))=0,"",SUMIFS(measured[Measured Value (kWh)],measured[Site Name],A12,measured[Date],B12)),"")} -> 1794 | D12: {=IFERROR(IF(SUMPRODUCT((expected_production[Site Name]=A12)*(expected_production[Date]=B12)*ISNUMBER(expected_production[Expected Production (kWh)]))=0,"",SUMIFS(expected_production[Expected Production (kWh)],expected_production[Site Name],A12,expected_production[Date],B12)),"")} -> 2327.6446 | E12: =IF(OR(C12="",D12="",D12=0),"",C12/D12) -> 0.77073623 | F12: =IF(E12="","",IF(E12>=0.9,"Expected",IF(E12>=0.7,"Moderate","Poor"))) -> Moderate
A13: 21 Melrose | B13: 45627 | C13: {=IFERROR(IF(SUMPRODUCT((measured[Site Name]=A13)*(measured[Date]=B13)*ISNUMBER(measured[Measured Value (kWh)]))=0,"",SUMIFS(measured[Measured Value (kWh)],measured[Site Name],A13,measured[Date],B13)),"")} -> 1794 | D13: {=IFERROR(IF(SUMPRODUCT((expected_production[Site Name]=A13)*(expected_production[Date]=B13)*ISNUMBER(expected_production[Expected Production (kWh)]))=0,"",SUMIFS(expected_production[Expected Production (kWh)],expected_production[Site Name],A13,expected_production[Date],B13)),"")} -> 2450.7032 | E13: =IF(OR(C13="",D13="",D13=0),"",C13/D13) -> 0.7320348 | F13: =IF(E13="","",IF(E13>=0.9,"Expected",IF(E13>=0.7,"Moderate","Poor"))) -> Moderate
... A31: 21 Melrose | B31: 46174 | C31: {=IFERROR(IF(SUMPRODUCT((measured[Site Name]=A31)*(measured[Date]=B31)*ISNUMBER(measured[Measured Value (kWh)]))=0,"",SUMIFS(measured[Measured Value (kWh)],measured[Site Name],A31,measured[Date],B31)),"")} -> 1287 | D31: {=IFERROR(IF(SUMPRODUCT((expected_production[Site Name]=A31)*(expected_production[Date]=B31)*ISNUMBER(expected_production[Expected Production (kWh)]))=0,"",SUMIFS(expected_production[Expected Production (kWh)],expected_production[Site Name],A31,expected_production[Date],B31)),"")} -> 1591.4984 | E31: =IF(OR(C31="",D31="",D31=0),"",C31/D31) -> 0.80867188 | F31: =IF(E31="","",IF(E31>=0.9,"Expected",IF(E31>=0.7,"Moderate","Poor"))) -> Moderate
A32: 21 Melrose | B32: 46204 | C32: {=IFERROR(IF(SUMPRODUCT((measured[Site Name]=A32)*(measured[Date]=B32)*ISNUMBER(measured[Measured Value (kWh)]))=0,"",SUMIFS(measured[Measured Value (kWh)],measured[Site Name],A32,measured[Date],B32)),"")} -> 1638 | D32: {=IFERROR(IF(SUMPRODUCT((expected_production[Site Name]=A32)*(expected_production[Date]=B32)*ISNUMBER(expected_production[Expected Production (kWh)]))=0,"",SUMIFS(expected_production[Expected Production (kWh)],expected_production[Site Name],A32,expected_production[Date],B32)),"")} -> 1771.6078 | E32: =IF(OR(C32="",D32="",D32=0),"",C32/D32) -> 0.92458388 | F32: =IF(E32="","",IF(E32>=0.9,"Expected",IF(E32>=0.7,"Moderate","Poor"))) -> Expected | G32: NO
A33: 21 Melrose | B33: 46235 | C33: {=IFERROR(IF(SUMPRODUCT((measured[Site Name]=A33)*(measured[Date]=B33)*ISNUMBER(measured[Measured Value (kWh)]))=0,"",SUMIFS(measured[Measured Value (kWh)],measured[Site Name],A33,measured[Date],B33)),"")} -> 1374 | D33: {=IFERROR(IF(SUMPRODUCT((expected_production[Site Name]=A33)*(expected_production[Date]=B33)*ISNUMBER(expected_production[Expected Production (kWh)]))=0,"",SUMIFS(expected_production[Expected Production (kWh)],expected_production[Site Name],A33,expected_production[Date],B33)),"")} -> 2065.6438 | E33: =IF(OR(C33="",D33="",D33=0),"",C33/D33) -> 0.66516791 | F33: =IF(E33="","",IF(E33>=0.9,"Expected",IF(E33>=0.7,"Moderate","Poor"))) -> Poor | G33: NO
A34: 21 Melrose | B34: 46266 | C34: {=IFERROR(IF(SUMPRODUCT((measured[Site Name]=A34)*(measured[Date]=B34)*ISNUMBER(measured[Measured Value (kWh)]))=0,"",SUMIFS(measured[Measured Value (kWh)],measured[Site Name],A34,measured[Date],B34)),"")} -> 1161.6 | D34: {=IFERROR(IF(SUMPRODUCT((expected_production[Site Name]=A34)*(expected_production[Date]=B34)*ISNUMBER(expected_production[Expected Production (kWh)]))=0,"",SUMIFS(expected_production[Expected Production (kWh)],expected_production[Site Name],A34,expected_production[Date],B34)),"")} -> 2218.8925 | E34: =IF(OR(C34="",D34="",D34=0),"",C34/D34) -> 0.5235044 | F34: =IF(E34="","",IF(E34>=0.9,"Expected",IF(E34>=0.7,"Moderate","Poor"))) -> Poor | G34: NO
A35: 21 Melrose | B35: 46296 | C35: {=IFERROR(IF(SUMPRODUCT((measured[Site Name]=A35)*(measured[Date]=B35)*ISNUMBER(measured[Measured Value (kWh)]))=0,"",SUMIFS(measured[Measured Value (kWh)],measured[Site Name],A35,measured[Date],B35)),"")} | D35: {=IFERROR(IF(SUMPRODUCT((expected_production[Site Name]=A35)*(expected_production[Date]=B35)*ISNUMBER(expected_production[Expected Production (kWh)]))=0,"",SUMIFS(expected_production[Expected Production (kWh)],expected_production[Site Name],A35,expected_production[Date],B35)),"")} -> 2346.564 | E35: =IF(OR(C35="",D35="",D35=0),"",C35/D35) | F35: =IF(E35="","",IF(E35>=0.9,"Expected",IF(E35>=0.7,"Moderate","Poor")))
A36: 21 Melrose | B36: 46327 | C36: {=IFERROR(IF(SUMPRODUCT((measured[Site Name]=A36)*(measured[Date]=B36)*ISNUMBER(measured[Measured Value (kWh)]))=0,"",SUMIFS(measured[Measured Value (kWh)],measured[Site Name],A36,measured[Date],B36)),"")} | D36: {=IFERROR(IF(SUMPRODUCT((expected_production[Site Name]=A36)*(expected_production[Date]=B36)*ISNUMBER(expected_production[Expected Production (kWh)]))=0,"",SUMIFS(expected_production[Expected Production (kWh)],expected_production[Site Name],A36,expected_production[Date],B36)),"")} -> 2295.1937 | E36: =IF(OR(C36="",D36="",D36=0),"",C36/D36) | F36: =IF(E36="","",IF(E36>=0.9,"Expected",IF(E36>=0.7,"Moderate","Poor")))
A37: 21 Melrose | B37: 46357 | C37: {=IFERROR(IF(SUMPRODUCT((measured[Site Name]=A37)*(measured[Date]=B37)*ISNUMBER(measured[Measured Value (kWh)]))=0,"",SUMIFS(measured[Measured Value (kWh)],measured[Site Name],A37,measured[Date],B37)),"")} | D37: {=IFERROR(IF(SUMPRODUCT((expected_production[Site Name]=A37)*(expected_production[Date]=B37)*ISNUMBER(expected_production[Expected Production (kWh)]))=0,"",SUMIFS(expected_production[Expected Production (kWh)],expected_production[Site Name],A37,expected_production[Date],B37)),"")} -> 2416.5366 | E37: =IF(OR(C37="",D37="",D37=0),"",C37/D37) | F37: =IF(E37="","",IF(E37>=0.9,"Expected",IF(E37>=0.7,"Moderate","Poor")))
A38: African Global Plastics | B38: 45292 | C38: {=IFERROR(IF(SUMPRODUCT((measured[Site Name]=A38)*(measured[Date]=B38)*ISNUMBER(measured[Measured Value (kWh)]))=0,"",SUMIFS(measured[Measured Value (kWh)],measured[Site Name],A38,measured[Date],B38)),"")} -> 23024 | D38: {=IFERROR(IF(SUMPRODUCT((expected_production[Site Name]=A38)*(expected_production[Date]=B38)*ISNUMBER(expected_production[Expected Production (kWh)]))=0,"",SUMIFS(expected_production[Expected Production (kWh)],expected_production[Site Name],A38,expected_production[Date],B38)),"")} -> 22474.372 | E38: =IF(OR(C38="",D38="",D38=0),"",C38/D38) -> 1.0244558 | F38: =IF(E38="","",IF(E38>=0.9,"Expected",IF(E38>=0.7,"Moderate","Poor"))) -> Expected
A39: African Global Plastics | B39: 45323 | C39: {=IFERROR(IF(SUMPRODUCT((measured[Site Name]=A39)*(measured[Date]=B39)*ISNUMBER(measured[Measured Value (kWh)]))=0,"",SUMIFS(measured[Measured Value (kWh)],measured[Site Name],A39,measured[Date],B39)),"")} -> 23235 | D39: {=IFERROR(IF(SUMPRODUCT((expected_production[Site Name]=A39)*(expected_production[Date]=B39)*ISNUMBER(expected_production[Expected Production (kWh)]))=0,"",SUMIFS(expected_production[Expected Production (kWh)],expected_production[Site Name],A39,expected_production[Date],B39)),"")} -> 19737.861 | E39: =IF(OR(C39="",D39="",D39=0),"",C39/D39) -> 1.1771792 | F39: =IF(E39="","",IF(E39>=0.9,"Expected",IF(E39>=0.7,"Moderate","Poor"))) -> Expected
A40: African Global Plastics | B40: 45352 | C40: {=IFERROR(IF(SUMPRODUCT((measured[Site Name]=A40)*(measured[Date]=B40)*ISNUMBER(measured[Measured Value (kWh)]))=0,"",SUMIFS(measured[Measured Value (kWh)],measured[Site Name],A40,measured[Date],B40)),"")} -> 23235 | D40: {=IFERROR(IF(SUMPRODUCT((expected_production[Site Name]=A40)*(expected_production[Date]=B40)*ISNUMBER(expected_production[Expected Production (kWh)]))=0,"",SUMIFS(expected_production[Expected Production (kWh)],expected_production[Site Name],A40,expected_production[Date],B40)),"")} -> 20088.04 | E40: =IF(OR(C40="",D40="",D40=0),"",C40/D40) -> 1.1566584 | F40: =IF(E40="","",IF(E40>=0.9,"Expected",IF(E40>=0.7,"Moderate","Poor"))) -> Expected
A41: African Global Plastics | B41: 45383 | C41: {=IFERROR(IF(SUMPRODUCT((measured[Site Name]=A41)*(measured[Date]=B41)*ISNUMBER(measured[Measured Value (kWh)]))=0,"",SUMIFS(measured[Measured Value (kWh)],measured[Site Name],A41,measured[Date],B41)),"")} -> 19307 | D41: {=IFERROR(IF(SUMPRODUCT((expected_production[Site Name]=A41)*(expected_production[Date]=B41)*ISNUMBER(expected_production[Expected Production (kWh)]))=0,"",SUMIFS(expected_production[Expected Production (kWh)],expected_production[Site Name],A41,expected_production[Date],B41)),"")} -> 16704.704 | E41: =IF(OR(C41="",D41="",D41=0),"",C41/D41) -> 1.1557822 | F41: =IF(E41="","",IF(E41>=0.9,"Expected",IF(E41>=0.7,"Moderate","Poor"))) -> Expected
A42: African Global Plastics | B42: 45413 | C42: {=IFERROR(IF(SUMPRODUCT((measured[Site Name]=A42)*(measured[Date]=B42)*ISNUMBER(measured[Measured Value (kWh)]))=0,"",SUMIFS(measured[Measured Value (kWh)],measured[Site Name],A42,measured[Date],B42)),"")} -> 18418 | D42: {=IFERROR(IF(SUMPRODUCT((expected_production[Site Name]=A42)*(expected_production[Date]=B42)*ISNUMBER(expected_production[Expected Production (kWh)]))=0,"",SUMIFS(expected_production[Expected Production (kWh)],expected_production[Site Name],A42,expected_production[Date],B42)),"")} -> 15905.576 | E42: =IF(OR(C42="",D42="",D42=0),"",C42/D42) -> 1.1579587 | F42: =IF(E42="","",IF(E42>=0.9,"Expected",IF(E42>=0.7,"Moderate","Poor"))) -> Expected
A43: African Global Plastics | B43: 45444 | C43: {=IFERROR(IF(SUMPRODUCT((measured[Site Name]=A43)*(measured[Date]=B43)*ISNUMBER(measured[Measured Value (kWh)]))=0,"",SUMIFS(measured[Measured Value (kWh)],measured[Site Name],A43,measured[Date],B43)),"")} -> 15949 | D43: {=IFERROR(IF(SUMPRODUCT((expected_production[Site Name]=A43)*(expected_production[Date]=B43)*ISNUMBER(expected_production[Expected Production (kWh)]))=0,"",SUMIFS(expected_production[Expected Production (kWh)],expected_production[Site Name],A43,expected_production[Date],B43)),"")} -> 14298.847 | E43: =IF(OR(C43="",D43="",D43=0),"",C43/D43) -> 1.1154046 | F43: =IF(E43="","",IF(E43>=0.9,"Expected",IF(E43>=0.7,"Moderate","Poor"))) -> Expected
A44: African Global Plastics | B44: 45474 | C44: {=IFERROR(IF(SUMPRODUCT((measured[Site Name]=A44)*(measured[Date]=B44)*ISNUMBER(measured[Measured Value (kWh)]))=0,"",SUMIFS(measured[Measured Value (kWh)],measured[Site Name],A44,measured[Date],B44)),"")} -> 17174 | D44: {=IFERROR(IF(SUMPRODUCT((expected_production[Site Name]=A44)*(expected_production[Date]=B44)*ISNUMBER(expected_production[Expected Production (kWh)]))=0,"",SUMIFS(expected_production[Expected Production (kWh)],expected_production[Site Name],A44,expected_production[Date],B44)),"")} -> 15822.84 | E44: =IF(OR(C44="",D44="",D44=0),"",C44/D44) -> 1.085393 | F44: =IF(E44="","",IF(E44>=0.9,"Expected",IF(E44>=0.7,"Moderate","Poor"))) -> Expected
A45: African Global Plastics | B45: 45505 | C45: {=IFERROR(IF(SUMPRODUCT((measured[Site Name]=A45)*(measured[Date]=B45)*ISNUMBER(measured[Measured Value (kWh)]))=0,"",SUMIFS(measured[Measured Value (kWh)],measured[Site Name],A45,measured[Date],B45)),"")} -> 13588 | D45: {=IFERROR(IF(SUMPRODUCT((expected_production[Site Name]=A45)*(expected_production[Date]=B45)*ISNUMBER(expected_production[Expected Production (kWh)]))=0,"",SUMIFS(expected_production[Expected Production (kWh)],expected_production[Site Name],A45,expected_production[Date],B45)),"")} -> 18417.587 | E45: =IF(OR(C45="",D45="",D45=0),"",C45/D45) -> 0.73777308 | F45: =IF(E45="","",IF(E45>=0.9,"Expected",IF(E45>=0.7,"Moderate","Poor"))) -> Moderate
A46: African Global Plastics | B46: 45536 | C46: {=IFERROR(IF(SUMPRODUCT((measured[Site Name]=A46)*(measured[Date]=B46)*ISNUMBER(measured[Measured Value (kWh)]))=0,"",SUMIFS(measured[Measured Value (kWh)],measured[Site Name],A46,measured[Date],B46)),"")} -> 20254 | D46: {=IFERROR(IF(SUMPRODUCT((expected_production[Site Name]=A46)*(expected_production[Date]=B46)*ISNUMBER(expected_production[Expected Production (kWh)]))=0,"",SUMIFS(expected_production[Expected Production (kWh)],expected_production[Site Name],A46,expected_production[Date],B46)),"")} -> 20271.346 | E46: =IF(OR(C46="",D46="",D46=0),"",C46/D46) -> 0.99914429 | F46: =IF(E46="","",IF(E46>=0.9,"Expected",IF(E46>=0.7,"Moderate","Poor"))) -> Expected
... A67: African Global Plastics | B67: 46174 | C67: {=IFERROR(IF(SUMPRODUCT((measured[Site Name]=A67)*(measured[Date]=B67)*ISNUMBER(measured[Measured Value (kWh)]))=0,"",SUMIFS(measured[Measured Value (kWh)],measured[Site Name],A67,measured[Date],B67)),"")} -> 10184.42 | D67: {=IFERROR(IF(SUMPRODUCT((expected_production[Site Name]=A67)*(expected_production[Date]=B67)*ISNUMBER(expected_production[Expected Production (kWh)]))=0,"",SUMIFS(expected_production[Expected Production (kWh)],expected_production[Site Name],A67,expected_production[Date],B67)),"")} -> 14099.499 | E67: =IF(OR(C67="",D67="",D67=0),"",C67/D67) -> 0.72232494 | F67: =IF(E67="","",IF(E67>=0.9,"Expected",IF(E67>=0.7,"Moderate","Poor"))) -> Moderate
A68: African Global Plastics | B68: 46204 | C68: {=IFERROR(IF(SUMPRODUCT((measured[Site Name]=A68)*(measured[Date]=B68)*ISNUMBER(measured[Measured Value (kWh)]))=0,"",SUMIFS(measured[Measured Value (kWh)],measured[Site Name],A68,measured[Date],B68)),"")} -> 13136.53 | D68: {=IFERROR(IF(SUMPRODUCT((expected_production[Site Name]=A68)*(expected_production[Date]=B68)*ISNUMBER(expected_production[Expected Production (kWh)]))=0,"",SUMIFS(expected_production[Expected Production (kWh)],expected_production[Site Name],A68,expected_production[Date],B68)),"")} -> 15602.246 | E68: =IF(OR(C68="",D68="",D68=0),"",C68/D68) -> 0.84196407 | F68: =IF(E68="","",IF(E68>=0.9,"Expected",IF(E68>=0.7,"Moderate","Poor"))) -> Moderate | G68: NO
A69: African Global Plastics | B69: 46235 | C69: {=IFERROR(IF(SUMPRODUCT((measured[Site Name]=A69)*(measured[Date]=B69)*ISNUMBER(measured[Measured Value (kWh)]))=0,"",SUMIFS(measured[Measured Value (kWh)],measured[Site Name],A69,measured[Date],B69)),"")} -> 13435.047 | D69: {=IFERROR(IF(SUMPRODUCT((expected_production[Site Name]=A69)*(expected_production[Date]=B69)*ISNUMBER(expected_production[Expected Production (kWh)]))=0,"",SUMIFS(expected_production[Expected Production (kWh)],expected_production[Site Name],A69,expected_production[Date],B69)),"")} -> 18160.818 | E69: =IF(OR(C69="",D69="",D69=0),"",C69/D69) -> 0.73978204 | F69: =IF(E69="","",IF(E69>=0.9,"Expected",IF(E69>=0.7,"Moderate","Poor"))) -> Moderate | G69: NO
A70: African Global Plastics | B70: 46266 | C70: {=IFERROR(IF(SUMPRODUCT((measured[Site Name]=A70)*(measured[Date]=B70)*ISNUMBER(measured[Measured Value (kWh)]))=0,"",SUMIFS(measured[Measured Value (kWh)],measured[Site Name],A70,measured[Date],B70)),"")} -> 12622.016 | D70: {=IFERROR(IF(SUMPRODUCT((expected_production[Site Name]=A70)*(expected_production[Date]=B70)*ISNUMBER(expected_production[Expected Production (kWh)]))=0,"",SUMIFS(expected_production[Expected Production (kWh)],expected_production[Site Name],A70,expected_production[Date],B70)),"")} -> 19988.733 | E70: =IF(OR(C70="",D70="",D70=0),"",C70/D70) -> 0.63145655 | F70: =IF(E70="","",IF(E70>=0.9,"Expected",IF(E70>=0.7,"Moderate","Poor"))) -> Poor | G70: NO
A71: African Global Plastics | B71: 46296 | C71: {=IFERROR(IF(SUMPRODUCT((measured[Site Name]=A71)*(measured[Date]=B71)*ISNUMBER(measured[Measured Value (kWh)]))=0,"",SUMIFS(measured[Measured Value (kWh)],measured[Site Name],A71,measured[Date],B71)),"")} | D71: {=IFERROR(IF(SUMPRODUCT((expected_production[Site Name]=A71)*(expected_production[Date]=B71)*ISNUMBER(expected_production[Expected Production (kWh)]))=0,"",SUMIFS(expected_production[Expected Production (kWh)],expected_production[Site Name],A71,expected_production[Date],B71)),"")} -> 21853.413 | E71: =IF(OR(C71="",D71="",D71=0),"",C71/D71) | F71: =IF(E71="","",IF(E71>=0.9,"Expected",IF(E71>=0.7,"Moderate","Poor")))
A72: African Global Plastics | B72: 46327 | C72: {=IFERROR(IF(SUMPRODUCT((measured[Site Name]=A72)*(measured[Date]=B72)*ISNUMBER(measured[Measured Value (kWh)]))=0,"",SUMIFS(measured[Measured Value (kWh)],measured[Site Name],A72,measured[Date],B72)),"")} | D72: {=IFERROR(IF(SUMPRODUCT((expected_production[Site Name]=A72)*(expected_production[Date]=B72)*ISNUMBER(expected_production[Expected Production (kWh)]))=0,"",SUMIFS(expected_production[Expected Production (kWh)],expected_production[Site Name],A72,expected_production[Date],B72)),"")} -> 22036.09 | E72: =IF(OR(C72="",D72="",D72=0),"",C72/D72) | F72: =IF(E72="","",IF(E72>=0.9,"Expected",IF(E72>=0.7,"Moderate","Poor")))
A73: African Global Plastics | B73: 46357 | C73: {=IFERROR(IF(SUMPRODUCT((measured[Site Name]=A73)*(measured[Date]=B73)*ISNUMBER(measured[Measured Value (kWh)]))=0,"",SUMIFS(measured[Measured Value (kWh)],measured[Site Name],A73,measured[Date],B73)),"")} | D73: {=IFERROR(IF(SUMPRODUCT((expected_production[Site Name]=A73)*(expected_production[Date]=B73)*ISNUMBER(expected_production[Expected Production (kWh)]))=0,"",SUMIFS(expected_production[Expected Production (kWh)],expected_production[Site Name],A73,expected_production[Date],B73)),"")} -> 23252.936 | E73: =IF(OR(C73="",D73="",D73=0),"",C73/D73) | F73: =IF(E73="","",IF(E73>=0.9,"Expected",IF(E73>=0.7,"Moderate","Poor")))
A74: Alpine Heath Residential | B74: 45292 | C74: {=IFERROR(IF(SUMPRODUCT((measured[Site Name]=A74)*(measured[Date]=B74)*ISNUMBER(measured[Measured Value (kWh)]))=0,"",SUMIFS(measured[Measured Value (kWh)],measured[Site Name],A74,measured[Date],B74)),"")} | D74: {=IFERROR(IF(SUMPRODUCT((expected_production[Site Name]=A74)*(expected_production[Date]=B74)*ISNUMBER(expected_production[Expected Production (kWh)]))=0,"",SUMIFS(expected_production[Expected Production (kWh)],expected_production[Site Name],A74,expected_production[Date],B74)),"")} -> 4801.5 | E74: =IF(OR(C74="",D74="",D74=0),"",C74/D74) | F74: =IF(E74="","",IF(E74>=0.9,"Expected",IF(E74>=0.7,"Moderate","Poor")))
A75: Alpine Heath Residential | B75: 45323 | C75: {=IFERROR(IF(SUMPRODUCT((measured[Site Name]=A75)*(measured[Date]=B75)*ISNUMBER(measured[Measured Value (kWh)]))=0,"",SUMIFS(measured[Measured Value (kWh)],measured[Site Name],A75,measured[Date],B75)),"")} | D75: {=IFERROR(IF(SUMPRODUCT((expected_production[Site Name]=A75)*(expected_production[Date]=B75)*ISNUMBER(expected_production[Expected Production (kWh)]))=0,"",SUMIFS(expected_production[Expected Production (kWh)],expected_production[Site Name],A75,expected_production[Date],B75)),"")} -> 4303.8 | E75: =IF(OR(C75="",D75="",D75=0),"",C75/D75) | F75: =IF(E75="","",IF(E75>=0.9,"Expected",IF(E75>=0.7,"Moderate","Poor")))
A76: Alpine Heath Residential | B76: 45352 | C76: {=IFERROR(IF(SUMPRODUCT((measured[Site Name]=A76)*(measured[Date]=B76)*ISNUMBER(measured[Measured Value (kWh)]))=0,"",SUMIFS(measured[Measured Value (kWh)],measured[Site Name],A76,measured[Date],B76)),"")} | D76: {=IFERROR(IF(SUMPRODUCT((expected_production[Site Name]=A76)*(expected_production[Date]=B76)*ISNUMBER(expected_production[Expected Production (kWh)]))=0,"",SUMIFS(expected_production[Expected Production (kWh)],expected_production[Site Name],A76,expected_production[Date],B76)),"")} -> 4545.9 | E76: =IF(OR(C76="",D76="",D76=0),"",C76/D76) | F76: =IF(E76="","",IF(E76>=0.9,"Expected",IF(E76>=0.7,"Moderate","Poor")))
A77: Alpine Heath Residential | B77: 45383 | C77: {=IFERROR(IF(SUMPRODUCT((measured[Site Name]=A77)*(measured[Date]=B77)*ISNUMBER(measured[Measured Value (kWh)]))=0,"",SUMIFS(measured[Measured Value (kWh)],measured[Site Name],A77,measured[Date],B77)),"")} | D77: {=IFERROR(IF(SUMPRODUCT((expected_production[Site Name]=A77)*(expected_production[Date]=B77)*ISNUMBER(expected_production[Expected Production (kWh)]))=0,"",SUMIFS(expected_production[Expected Production (kWh)],expected_production[Site Name],A77,expected_production[Date],B77)),"")} -> 4619.7 | E77: =IF(OR(C77="",D77="",D77=0),"",C77/D77) | F77: =IF(E77="","",IF(E77>=0.9,"Expected",IF(E77>=0.7,"Moderate","Poor")))
A78: Alpine Heath Residential | B78: 45413 | C78: {=IFERROR(IF(SUMPRODUCT((measured[Site Name]=A78)*(measured[Date]=B78)*ISNUMBER(measured[Measured Value (kWh)]))=0,"",SUMIFS(measured[Measured Value (kWh)],measured[Site Name],A78,measured[Date],B78)),"")} | D78: {=IFERROR(IF(SUMPRODUCT((expected_production[Site Name]=A78)*(expected_production[Date]=B78)*ISNUMBER(expected_production[Expected Production (kWh)]))=0,"",SUMIFS(expected_production[Expected Production (kWh)],expected_production[Site Name],A78,expected_production[Date],B78)),"")} -> 4990.5 | E78: =IF(OR(C78="",D78="",D78=0),"",C78/D78) | F78: =IF(E78="","",IF(E78>=0.9,"Expected",IF(E78>=0.7,"Moderate","Poor")))
A79: Alpine Heath Residential | B79: 45444 | C79: {=IFERROR(IF(SUMPRODUCT((measured[Site Name]=A79)*(measured[Date]=B79)*ISNUMBER(measured[Measured Value (kWh)]))=0,"",SUMIFS(measured[Measured Value (kWh)],measured[Site Name],A79,measured[Date],B79)),"")} | D79: {=IFERROR(IF(SUMPRODUCT((expected_production[Site Name]=A79)*(expected_production[Date]=B79)*ISNUMBER(expected_production[Expected Production (kWh)]))=0,"",SUMIFS(expected_production[Expected Production (kWh)],expected_production[Site Name],A79,expected_production[Date],B79)),"")} -> 4761.9 | E79: =IF(OR(C79="",D79="",D79=0),"",C79/D79) | F79: =IF(E79="","",IF(E79>=0.9,"Expected",IF(E79>=0.7,"Moderate","Poor")))
A80: Alpine Heath Residential | B80: 45474 | C80: {=IFERROR(IF(SUMPRODUCT((measured[Site Name]=A80)*(measured[Date]=B80)*ISNUMBER(measured[Measured Value (kWh)]))=0,"",SUMIFS(measured[Measured Value (kWh)],measured[Site Name],A80,measured[Date],B80)),"")} | D80: {=IFERROR(IF(SUMPRODUCT((expected_production[Site Name]=A80)*(expected_production[Date]=B80)*ISNUMBER(expected_production[Expected Production (kWh)]))=0,"",SUMIFS(expected_production[Expected Production (kWh)],expected_production[Site Name],A80,expected_production[Date],B80)),"")} -> 4680.9 | E80: =IF(OR(C80="",D80="",D80=0),"",C80/D80) | F80: =IF(E80="","",IF(E80>=0.9,"Expected",IF(E80>=0.7,"Moderate","Poor")))
A81: Alpine Heath Residential | B81: 45505 | C81: {=IFERROR(IF(SUMPRODUCT((measured[Site Name]=A81)*(measured[Date]=B81)*ISNUMBER(measured[Measured Value (kWh)]))=0,"",SUMIFS(measured[Measured Value (kWh)],measured[Site Name],A81,measured[Date],B81)),"")} | D81: {=IFERROR(IF(SUMPRODUCT((expected_production[Site Name]=A81)*(expected_production[Date]=B81)*ISNUMBER(expected_production[Expected Production (kWh)]))=0,"",SUMIFS(expected_production[Expected Production (kWh)],expected_production[Site Name],A81,expected_production[Date],B81)),"")} -> 5249.7 | E81: =IF(OR(C81="",D81="",D81=0),"",C81/D81) | F81: =IF(E81="","",IF(E81>=0.9,"Expected",IF(E81>=0.7,"Moderate","Poor")))
A82: Alpine Heath Residential | B82: 45536 | C82: {=IFERROR(IF(SUMPRODUCT((measured[Site Name]=A82)*(measured[Date]=B82)*ISNUMBER(measured[Measured Value (kWh)]))=0,"",SUMIFS(measured[Measured Value (kWh)],measured[Site Name],A82,measured[Date],B82)),"")} | D82: {=IFERROR(IF(SUMPRODUCT((expected_production[Site Name]=A82)*(expected_production[Date]=B82)*ISNUMBER(expected_production[Expected Production (kWh)]))=0,"",SUMIFS(expected_production[Expected Production (kWh)],expected_production[Site Name],A82,expected_production[Date],B82)),"")} -> 4694.4 | E82: =IF(OR(C82="",D82="",D82=0),"",C82/D82) | F82: =IF(E82="","",IF(E82>=0.9,"Expected",IF(E82>=0.7,"Moderate","Poor")))
... A103: Alpine Heath Residential | B103: 46174 | C103: {=IFERROR(IF(SUMPRODUCT((measured[Site Name]=A103)*(measured[Date]=B103)*ISNUMBER(measured[Measured Value (kWh)]))=0,"",SUMIFS(measured[Measured Value (kWh)],measured[Site Name],A103,measured[Date],B103)),"")} -> 2778 | D103: {=IFERROR(IF(SUMPRODUCT((expected_production[Site Name]=A103)*(expected_production[Date]=B103)*ISNUMBER(expected_production[Expected Production (kWh)]))=0,"",SUMIFS(expected_production[Expected Production (kWh)],expected_production[Site Name],A103,expected_production[Date],B103)),"")} -> 4714.8771 | E103: =IF(OR(C103="",D103="",D103=0),"",C103/D103) -> 0.58919881 | F103: =IF(E103="","",IF(E103>=0.9,"Expected",IF(E103>=0.7,"Moderate","Poor"))) -> Poor
A104: Alpine Heath Residential | B104: 46204 | C104: {=IFERROR(IF(SUMPRODUCT((measured[Site Name]=A104)*(measured[Date]=B104)*ISNUMBER(measured[Measured Value (kWh)]))=0,"",SUMIFS(measured[Measured Value (kWh)],measured[Site Name],A104,measured[Date],B104)),"")} -> 2644 | D104: {=IFERROR(IF(SUMPRODUCT((expected_production[Site Name]=A104)*(expected_production[Date]=B104)*ISNUMBER(expected_production[Expected Production (kWh)]))=0,"",SUMIFS(expected_production[Expected Production (kWh)],expected_production[Site Name],A104,expected_production[Date],B104)),"")} -> 4632.0037 | E104: =IF(OR(C104="",D104="",D104=0),"",C104/D104) -> 0.57081129 | F104: =IF(E104="","",IF(E104>=0.9,"Expected",IF(E104>=0.7,"Moderate","Poor"))) -> Poor | G104: NO
A105: Alpine Heath Residential | B105: 46235 | C105: {=IFERROR(IF(SUMPRODUCT((measured[Site Name]=A105)*(measured[Date]=B105)*ISNUMBER(measured[Measured Value (kWh)]))=0,"",SUMIFS(measured[Measured Value (kWh)],measured[Site Name],A105,measured[Date],B105)),"")} -> 2758 | D105: {=IFERROR(IF(SUMPRODUCT((expected_production[Site Name]=A105)*(expected_production[Date]=B105)*ISNUMBER(expected_production[Expected Production (kWh)]))=0,"",SUMIFS(expected_production[Expected Production (kWh)],expected_production[Site Name],A105,expected_production[Date],B105)),"")} -> 5191.7658 | E105: =IF(OR(C105="",D105="",D105=0),"",C105/D105) -> 0.53122581 | F105: =IF(E105="","",IF(E105>=0.9,"Expected",IF(E105>=0.7,"Moderate","Poor"))) -> Poor | G105: NO
A106: Alpine Heath Residential | B106: 46266 | C106: {=IFERROR(IF(SUMPRODUCT((measured[Site Name]=A106)*(measured[Date]=B106)*ISNUMBER(measured[Measured Value (kWh)]))=0,"",SUMIFS(measured[Measured Value (kWh)],measured[Site Name],A106,measured[Date],B106)),"")} -> 2338 | D106: {=IFERROR(IF(SUMPRODUCT((expected_production[Site Name]=A106)*(expected_production[Date]=B106)*ISNUMBER(expected_production[Expected Production (kWh)]))=0,"",SUMIFS(expected_production[Expected Production (kWh)],expected_production[Site Name],A106,expected_production[Date],B106)),"")} -> 4639.8268 | E106: =IF(OR(C106="",D106="",D106=0),"",C106/D106) -> 0.50389812 | F106: =IF(E106="","",IF(E106>=0.9,"Expected",IF(E106>=0.7,"Moderate","Poor"))) -> Poor | G106: NO
A107: Alpine Heath Residential | B107: 46296 | C107: {=IFERROR(IF(SUMPRODUCT((measured[Site Name]=A107)*(measured[Date]=B107)*ISNUMBER(measured[Measured Value (kWh)]))=0,"",SUMIFS(measured[Measured Value (kWh)],measured[Site Name],A107,measured[Date],B107)),"")} | D107: {=IFERROR(IF(SUMPRODUCT((expected_production[Site Name]=A107)*(expected_production[Date]=B107)*ISNUMBER(expected_production[Expected Production (kWh)]))=0,"",SUMIFS(expected_production[Expected Production (kWh)],expected_production[Site Name],A107,expected_production[Date],B107)),"")} -> 4674.4896 | E107: =IF(OR(C107="",D107="",D107=0),"",C107/D107) | F107: =IF(E107="","",IF(E107>=0.9,"Expected",IF(E107>=0.7,"Moderate","Poor")))
A108: Alpine Heath Residential | B108: 46327 | C108: {=IFERROR(IF(SUMPRODUCT((measured[Site Name]=A108)*(measured[Date]=B108)*ISNUMBER(measured[Measured Value (kWh)]))=0,"",SUMIFS(measured[Measured Value (kWh)],measured[Site Name],A108,measured[Date],B108)),"")} | D108: {=IFERROR(IF(SUMPRODUCT((expected_production[Site Name]=A108)*(expected_production[Date]=B108)*ISNUMBER(expected_production[Expected Production (kWh)]))=0,"",SUMIFS(expected_production[Expected Production (kWh)],expected_production[Site Name],A108,expected_production[Date],B108)),"")} -> 4760.5529 | E108: =IF(OR(C108="",D108="",D108=0),"",C108/D108) | F108: =IF(E108="","",IF(E108>=0.9,"Expected",IF(E108>=0.7,"Moderate","Poor")))
A109: Alpine Heath Residential | B109: 46357 | C109: {=IFERROR(IF(SUMPRODUCT((measured[Site Name]=A109)*(measured[Date]=B109)*ISNUMBER(measured[Measured Value (kWh)]))=0,"",SUMIFS(measured[Measured Value (kWh)],measured[Site Name],A109,measured[Date],B109)),"")} | D109: {=IFERROR(IF(SUMPRODUCT((expected_production[Site Name]=A109)*(expected_production[Date]=B109)*ISNUMBER(expected_production[Expected Production (kWh)]))=0,"",SUMIFS(expected_production[Expected Production (kWh)],expected_production[Site Name],A109,expected_production[Date],B109)),"")} -> 4740.9353 | E109: =IF(OR(C109="",D109="",D109=0),"",C109/D109) | F109: =IF(E109="","",IF(E109>=0.9,"Expected",IF(E109>=0.7,"Moderate","Poor")))
A110: BP Parys | B110: 45292 | C110: {=IFERROR(IF(SUMPRODUCT((measured[Site Name]=A110)*(measured[Date]=B110)*ISNUMBER(measured[Measured Value (kWh)]))=0,"",SUMIFS(measured[Measured Value (kWh)],measured[Site Name],A110,measured[Date],B110)),"")} | D110: {=IFERROR(IF(SUMPRODUCT((expected_production[Site Name]=A110)*(expected_production[Date]=B110)*ISNUMBER(expected_production[Expected Production (kWh)]))=0,"",SUMIFS(expected_production[Expected Production (kWh)],expected_production[Site Name],A110,expected_production[Date],B110)),"")} -> 8151.3 | E110: =IF(OR(C110="",D110="",D110=0),"",C110/D110) | F110: =IF(E110="","",IF(E110>=0.9,"Expected",IF(E110>=0.7,"Moderate","Poor")))
A111: BP Parys | B111: 45323 | C111: {=IFERROR(IF(SUMPRODUCT((measured[Site Name]=A111)*(measured[Date]=B111)*ISNUMBER(measured[Measured Value (kWh)]))=0,"",SUMIFS(measured[Measured Value (kWh)],measured[Site Name],A111,measured[Date],B111)),"")} | D111: {=IFERROR(IF(SUMPRODUCT((expected_production[Site Name]=A111)*(expected_production[Date]=B111)*ISNUMBER(expected_production[Expected Production (kWh)]))=0,"",SUMIFS(expected_production[Expected Production (kWh)],expected_production[Site Name],A111,expected_production[Date],B111)),"")} -> 7235.1 | E111: =IF(OR(C111="",D111="",D111=0),"",C111/D111) | F111: =IF(E111="","",IF(E111>=0.9,"Expected",IF(E111>=0.7,"Moderate","Poor")))
A112: BP Parys | B112: 45352 | C112: {=IFERROR(IF(SUMPRODUCT((measured[Site Name]=A112)*(measured[Date]=B112)*ISNUMBER(measured[Measured Value (kWh)]))=0,"",SUMIFS(measured[Measured Value (kWh)],measured[Site Name],A112,measured[Date],B112)),"")} | D112: {=IFERROR(IF(SUMPRODUCT((expected_production[Site Name]=A112)*(expected_production[Date]=B112)*ISNUMBER(expected_production[Expected Production (kWh)]))=0,"",SUMIFS(expected_production[Expected Production (kWh)],expected_production[Site Name],A112,expected_production[Date],B112)),"")} -> 7075.8 | E112: =IF(OR(C112="",D112="",D112=0),"",C112/D112) | F112: =IF(E112="","",IF(E112>=0.9,"Expected",IF(E112>=0.7,"Moderate","Poor")))
A113: BP Parys | B113: 45383 | C113: {=IFERROR(IF(SUMPRODUCT((measured[Site Name]=A113)*(measured[Date]=B113)*ISNUMBER(measured[Measured Value (kWh)]))=0,"",SUMIFS(measured[Measured Value (kWh)],measured[Site Name],A113,measured[Date],B113)),"")} | D113: {=IFERROR(IF(SUMPRODUCT((expected_production[Site Name]=A113)*(expected_production[Date]=B113)*ISNUMBER(expected_production[Expected Production (kWh)]))=0,"",SUMIFS(expected_production[Expected Production (kWh)],expected_production[Site Name],A113,expected_production[Date],B113)),"")} -> 5754.6 | E113: =IF(OR(C113="",D113="",D113=0),"",C113/D113) | F113: =IF(E113="","",IF(E113>=0.9,"Expected",IF(E113>=0.7,"Moderate","Poor")))
A114: BP Parys | B114: 45413 | C114: {=IFERROR(IF(SUMPRODUCT((measured[Site Name]=A114)*(measured[Date]=B114)*ISNUMBER(measured[Measured Value (kWh)]))=0,"",SUMIFS(measured[Measured Value (kWh)],measured[Site Name],A114,measured[Date],B114)),"")} | D114: {=IFERROR(IF(SUMPRODUCT((expected_production[Site Name]=A114)*(expected_production[Date]=B114)*ISNUMBER(expected_production[Expected Production (kWh)]))=0,"",SUMIFS(expected_production[Expected Production (kWh)],expected_production[Site Name],A114,expected_production[Date],B114)),"")} -> 5424.3 | E114: =IF(OR(C114="",D114="",D114=0),"",C114/D114) | F114: =IF(E114="","",IF(E114>=0.9,"Expected",IF(E114>=0.7,"Moderate","Poor")))
A115: BP Parys | B115: 45444 | C115: {=IFERROR(IF(SUMPRODUCT((measured[Site Name]=A115)*(measured[Date]=B115)*ISNUMBER(measured[Measured Value (kWh)]))=0,"",SUMIFS(measured[Measured Value (kWh)],measured[Site Name],A115,measured[Date],B115)),"")} | D115: {=IFERROR(IF(SUMPRODUCT((expected_production[Site Name]=A115)*(expected_production[Date]=B115)*ISNUMBER(expected_production[Expected Production (kWh)]))=0,"",SUMIFS(expected_production[Expected Production (kWh)],expected_production[Site Name],A115,expected_production[Date],B115)),"")} -> 4787.1 | E115: =IF(OR(C115="",D115="",D115=0),"",C115/D115) | F115: =IF(E115="","",IF(E115>=0.9,"Expected",IF(E115>=0.7,"Moderate","Poor")))
A116: BP Parys | B116: 45474 | C116: {=IFERROR(IF(SUMPRODUCT((measured[Site Name]=A116)*(measured[Date]=B116)*ISNUMBER(measured[Measured Value (kWh)]))=0,"",SUMIFS(measured[Measured Value (kWh)],measured[Site Name],A116,measured[Date],B116)),"")} | D116: {=IFERROR(IF(SUMPRODUCT((expected_production[Site Name]=A116)*(expected_production[Date]=B116)*ISNUMBER(expected_production[Expected Production (kWh)]))=0,"",SUMIFS(expected_production[Expected Production (kWh)],expected_production[Site Name],A116,expected_production[Date],B116)),"")} -> 5360.4 | E116: =IF(OR(C116="",D116="",D116=0),"",C116/D116) | F116: =IF(E116="","",IF(E116>=0.9,"Expected",IF(E116>=0.7,"Moderate","Poor")))
A117: BP Parys | B117: 45505 | C117: {=IFERROR(IF(SUMPRODUCT((measured[Site Name]=A117)*(measured[Date]=B117)*ISNUMBER(measured[Measured Value (kWh)]))=0,"",SUMIFS(measured[Measured Value (kWh)],measured[Site Name],A117,measured[Date],B117)),"")} | D117: {=IFERROR(IF(SUMPRODUCT((expected_production[Site Name]=A117)*(expected_production[Date]=B117)*ISNUMBER(expected_production[Expected Production (kWh)]))=0,"",SUMIFS(expected_production[Expected Production (kWh)],expected_production[Site Name],A117,expected_production[Date],B117)),"")} -> 6363 | E117: =IF(OR(C117="",D117="",D117=0),"",C117/D117) | F117: =IF(E117="","",IF(E117>=0.9,"Expected",IF(E117>=0.7,"Moderate","Poor")))
A118: BP Parys | B118: 45536 | C118: {=IFERROR(IF(SUMPRODUCT((measured[Site Name]=A118)*(measured[Date]=B118)*ISNUMBER(measured[Measured Value (kWh)]))=0,"",SUMIFS(measured[Measured Value (kWh)],measured[Site Name],A118,measured[Date],B118)),"")} | D118: {=IFERROR(IF(SUMPRODUCT((expected_production[Site Name]=A118)*(expected_production[Date]=B118)*ISNUMBER(expected_production[Expected Production (kWh)]))=0,"",SUMIFS(expected_production[Expected Production (kWh)],expected_production[Site Name],A118,expected_production[Date],B118)),"")} -> 7218.9 | E118: =IF(OR(C118="",D118="",D118=0),"",C118/D118) | F118: =IF(E118="","",IF(E118>=0.9,"Expected",IF(E118>=0.7,"Moderate","Poor")))
... A139: BP Parys | B139: 46174 | C139: {=IFERROR(IF(SUMPRODUCT((measured[Site Name]=A139)*(measured[Date]=B139)*ISNUMBER(measured[Measured Value (kWh)]))=0,"",SUMIFS(measured[Measured Value (kWh)],measured[Site Name],A139,measured[Date],B139)),"")} -> 3149 | D139: {=IFERROR(IF(SUMPRODUCT((expected_production[Site Name]=A139)*(expected_production[Date]=B139)*ISNUMBER(expected_production[Expected Production (kWh)]))=0,"",SUMIFS(expected_production[Expected Production (kWh)],expected_production[Site Name],A139,expected_production[Date],B139)),"")} -> 4735.4547 | E139: =IF(OR(C139="",D139="",D139=0),"",C139/D139) -> 0.66498366 | F139: =IF(E139="","",IF(E139>=0.9,"Expected",IF(E139>=0.7,"Moderate","Poor"))) -> Poor
A140: Alpine Heath Resort | B140: 46204 | C140: {=IFERROR(IF(SUMPRODUCT((measured[Site Name]=A140)*(measured[Date]=B140)*ISNUMBER(measured[Measured Value (kWh)]))=0,"",SUMIFS(measured[Measured Value (kWh)],measured[Site Name],A140,measured[Date],B140)),"")} -> 27942 | D140: {=IFERROR(IF(SUMPRODUCT((expected_production[Site Name]=A140)*(expected_production[Date]=B140)*ISNUMBER(expected_production[Expected Production (kWh)]))=0,"",SUMIFS(expected_production[Expected Production (kWh)],expected_production[Site Name],A140,expected_production[Date],B140)),"")} -> 28016.694 | E140: =IF(OR(C140="",D140="",D140=0),"",C140/D140) -> 0.99733395 | F140: =IF(E140="","",IF(E140>=0.9,"Expected",IF(E140>=0.7,"Moderate","Poor"))) -> Expected | G140: NO
A141: BP Parys | B141: 46235 | C141: {=IFERROR(IF(SUMPRODUCT((measured[Site Name]=A141)*(measured[Date]=B141)*ISNUMBER(measured[Measured Value (kWh)]))=0,"",SUMIFS(measured[Measured Value (kWh)],measured[Site Name],A141,measured[Date],B141)),"")} -> 3313 | D141: {=IFERROR(IF(SUMPRODUCT((expected_production[Site Name]=A141)*(expected_production[Date]=B141)*ISNUMBER(expected_production[Expected Production (kWh)]))=0,"",SUMIFS(expected_production[Expected Production (kWh)],expected_production[Site Name],A141,expected_production[Date],B141)),"")} -> 6286.9732 | E141: =IF(OR(C141="",D141="",D141=0),"",C141/D141) -> 0.52696264 | F141: =IF(E141="","",IF(E141>=0.9,"Expected",IF(E141>=0.7,"Moderate","Poor"))) -> Poor | G141: YES
A142: BP Parys | B142: 46266 | C142: {=IFERROR(IF(SUMPRODUCT((measured[Site Name]=A142)*(measured[Date]=B142)*ISNUMBER(measured[Measured Value (kWh)]))=0,"",SUMIFS(measured[Measured Value (kWh)],measured[Site Name],A142,measured[Date],B142)),"")} -> 4204.16 | D142: {=IFERROR(IF(SUMPRODUCT((expected_production[Site Name]=A142)*(expected_production[Date]=B142)*ISNUMBER(expected_production[Expected Production (kWh)]))=0,"",SUMIFS(expected_production[Expected Production (kWh)],expected_production[Site Name],A142,expected_production[Date],B142)),"")} -> 7128.3954 | E142: =IF(OR(C142="",D142="",D142=0),"",C142/D142) -> 0.58977648 | F142: =IF(E142="","",IF(E142>=0.9,"Expected",IF(E142>=0.7,"Moderate","Poor"))) -> Poor | G142: NO
A143: BP Parys | B143: 46296 | C143: {=IFERROR(IF(SUMPRODUCT((measured[Site Name]=A143)*(measured[Date]=B143)*ISNUMBER(measured[Measured Value (kWh)]))=0,"",SUMIFS(measured[Measured Value (kWh)],measured[Site Name],A143,measured[Date],B143)),"")} | D143: {=IFERROR(IF(SUMPRODUCT((expected_production[Site Name]=A143)*(expected_production[Date]=B143)*ISNUMBER(expected_production[Expected Production (kWh)]))=0,"",SUMIFS(expected_production[Expected Production (kWh)],expected_production[Site Name],A143,expected_production[Date],B143)),"")} -> 7736.2563 | E143: =IF(OR(C143="",D143="",D143=0),"",C143/D143) | F143: =IF(E143="","",IF(E143>=0.9,"Expected",IF(E143>=0.7,"Moderate","Poor")))
A144: BP Parys | B144: 46327 | C144: {=IFERROR(IF(SUMPRODUCT((measured[Site Name]=A144)*(measured[Date]=B144)*ISNUMBER(measured[Measured Value (kWh)]))=0,"",SUMIFS(measured[Measured Value (kWh)],measured[Site Name],A144,measured[Date],B144)),"")} | D144: {=IFERROR(IF(SUMPRODUCT((expected_production[Site Name]=A144)*(expected_production[Date]=B144)*ISNUMBER(expected_production[Expected Production (kWh)]))=0,"",SUMIFS(expected_production[Expected Production (kWh)],expected_production[Site Name],A144,expected_production[Date],B144)),"")} -> 8079.6137 | E144: =IF(OR(C144="",D144="",D144=0),"",C144/D144) | F144: =IF(E144="","",IF(E144>=0.9,"Expected",IF(E144>=0.7,"Moderate","Poor")))
A145: BP Parys | B145: 46357 | C145: {=IFERROR(IF(SUMPRODUCT((measured[Site Name]=A145)*(measured[Date]=B145)*ISNUMBER(measured[Measured Value (kWh)]))=0,"",SUMIFS(measured[Measured Value (kWh)],measured[Site Name],A145,measured[Date],B145)),"")} | D145: {=IFERROR(IF(SUMPRODUCT((expected_production[Site Name]=A145)*(expected_production[Date]=B145)*ISNUMBER(expected_production[Expected Production (kWh)]))=0,"",SUMIFS(expected_production[Expected Production (kWh)],expected_production[Site Name],A145,expected_production[Date],B145)),"")} -> 8110.4398 | E145: =IF(OR(C145="",D145="",D145=0),"",C145/D145) | F145: =IF(E145="","",IF(E145>=0.9,"Expected",IF(E145>=0.7,"Moderate","Poor")))
A146: Bendstore Plaza Shops | B146: 45292 | C146: {=IFERROR(IF(SUMPRODUCT((measured[Site Name]=A146)*(measured[Date]=B146)*ISNUMBER(measured[Measured Value (kWh)]))=0,"",SUMIFS(measured[Measured Value (kWh)],measured[Site Name],A146,measured[Date],B146)),"")} -> 7453 | D146: {=IFERROR(IF(SUMPRODUCT((expected_production[Site Name]=A146)*(expected_production[Date]=B146)*ISNUMBER(expected_production[Expected Production (kWh)]))=0,"",SUMIFS(expected_production[Expected Production (kWh)],expected_production[Site Name],A146,expected_production[Date],B146)),"")} -> 16142.542 | E146: =IF(OR(C146="",D146="",D146=0),"",C146/D146) -> 0.46169927 | F146: =IF(E146="","",IF(E146>=0.9,"Expected",IF(E146>=0.7,"Moderate","Poor"))) -> Poor
A147: Bendstore Plaza Shops | B147: 45323 | C147: {=IFERROR(IF(SUMPRODUCT((measured[Site Name]=A147)*(measured[Date]=B147)*ISNUMBER(measured[Measured Value (kWh)]))=0,"",SUMIFS(measured[Measured Value (kWh)],measured[Site Name],A147,measured[Date],B147)),"")} -> 10174 | D147: {=IFERROR(IF(SUMPRODUCT((expected_production[Site Name]=A147)*(expected_production[Date]=B147)*ISNUMBER(expected_production[Expected Production (kWh)]))=0,"",SUMIFS(expected_production[Expected Production (kWh)],expected_production[Site Name],A147,expected_production[Date],B147)),"")} -> 13875.56 | E147: =IF(OR(C147="",D147="",D147=0),"",C147/D147) -> 0.73323166 | F147: =IF(E147="","",IF(E147>=0.9,"Expected",IF(E147>=0.7,"Moderate","Poor"))) -> Moderate
A148: Bendstore Plaza Shops | B148: 45352 | C148: {=IFERROR(IF(SUMPRODUCT((measured[Site Name]=A148)*(measured[Date]=B148)*ISNUMBER(measured[Measured Value (kWh)]))=0,"",SUMIFS(measured[Measured Value (kWh)],measured[Site Name],A148,measured[Date],B148)),"")} -> 12197 | D148: {=IFERROR(IF(SUMPRODUCT((expected_production[Site Name]=A148)*(expected_production[Date]=B148)*ISNUMBER(expected_production[Expected Production (kWh)]))=0,"",SUMIFS(expected_production[Expected Production (kWh)],expected_production[Site Name],A148,expected_production[Date],B148)),"")} -> 15331.719 | E148: =IF(OR(C148="",D148="",D148=0),"",C148/D148) -> 0.79554026 | F148: =IF(E148="","",IF(E148>=0.9,"Expected",IF(E148>=0.7,"Moderate","Poor"))) -> Moderate
A149: Bendstore Plaza Shops | B149: 45383 | C149: {=IFERROR(IF(SUMPRODUCT((measured[Site Name]=A149)*(measured[Date]=B149)*ISNUMBER(measured[Measured Value (kWh)]))=0,"",SUMIFS(measured[Measured Value (kWh)],measured[Site Name],A149,measured[Date],B149)),"")} -> 9850 | D149: {=IFERROR(IF(SUMPRODUCT((expected_production[Site Name]=A149)*(expected_production[Date]=B149)*ISNUMBER(expected_production[Expected Production (kWh)]))=0,"",SUMIFS(expected_production[Expected Production (kWh)],expected_production[Site Name],A149,expected_production[Date],B149)),"")} -> 14750.68 | E149: =IF(OR(C149="",D149="",D149=0),"",C149/D149) -> 0.66776584 | F149: =IF(E149="","",IF(E149>=0.9,"Expected",IF(E149>=0.7,"Moderate","Poor"))) -> Poor
A150: Bendstore Plaza Shops | B150: 45413 | C150: {=IFERROR(IF(SUMPRODUCT((measured[Site Name]=A150)*(measured[Date]=B150)*ISNUMBER(measured[Measured Value (kWh)]))=0,"",SUMIFS(measured[Measured Value (kWh)],measured[Site Name],A150,measured[Date],B150)),"")} -> 10329 | D150: {=IFERROR(IF(SUMPRODUCT((expected_production[Site Name]=A150)*(expected_production[Date]=B150)*ISNUMBER(expected_production[Expected Production (kWh)]))=0,"",SUMIFS(expected_production[Expected Production (kWh)],expected_production[Site Name],A150,expected_production[Date],B150)),"")} -> 14272.456 | E150: =IF(OR(C150="",D150="",D150=0),"",C150/D150) -> 0.72370166 | F150: =IF(E150="","",IF(E150>=0.9,"Expected",IF(E150>=0.7,"Moderate","Poor"))) -> Moderate
A151: Bendstore Plaza Shops | B151: 45444 | C151: {=IFERROR(IF(SUMPRODUCT((measured[Site Name]=A151)*(measured[Date]=B151)*ISNUMBER(measured[Measured Value (kWh)]))=0,"",SUMIFS(measured[Measured Value (kWh)],measured[Site Name],A151,measured[Date],B151)),"")} -> 9684 | D151: {=IFERROR(IF(SUMPRODUCT((expected_production[Site Name]=A151)*(expected_production[Date]=B151)*ISNUMBER(expected_production[Expected Production (kWh)]))=0,"",SUMIFS(expected_production[Expected Production (kWh)],expected_production[Site Name],A151,expected_production[Date],B151)),"")} -> 12916.214 | E151: =IF(OR(C151="",D151="",D151=0),"",C151/D151) -> 0.7497553 | F151: =IF(E151="","",IF(E151>=0.9,"Expected",IF(E151>=0.7,"Moderate","Poor"))) -> Moderate
A152: Bendstore Plaza Shops | B152: 45474 | C152: {=IFERROR(IF(SUMPRODUCT((measured[Site Name]=A152)*(measured[Date]=B152)*ISNUMBER(measured[Measured Value (kWh)]))=0,"",SUMIFS(measured[Measured Value (kWh)],measured[Site Name],A152,measured[Date],B152)),"")} -> 10193 | D152: {=IFERROR(IF(SUMPRODUCT((expected_production[Site Name]=A152)*(expected_production[Date]=B152)*ISNUMBER(expected_production[Expected Production (kWh)]))=0,"",SUMIFS(expected_production[Expected Production (kWh)],expected_production[Site Name],A152,expected_production[Date],B152)),"")} -> 13586.447 | E152: =IF(OR(C152="",D152="",D152=0),"",C152/D152) -> 0.75023295 | F152: =IF(E152="","",IF(E152>=0.9,"Expected",IF(E152>=0.7,"Moderate","Poor"))) -> Moderate
A153: Bendstore Plaza Shops | B153: 45505 | C153: {=IFERROR(IF(SUMPRODUCT((measured[Site Name]=A153)*(measured[Date]=B153)*ISNUMBER(measured[Measured Value (kWh)]))=0,"",SUMIFS(measured[Measured Value (kWh)],measured[Site Name],A153,measured[Date],B153)),"")} -> 9840 | D153: {=IFERROR(IF(SUMPRODUCT((expected_production[Site Name]=A153)*(expected_production[Date]=B153)*ISNUMBER(expected_production[Expected Production (kWh)]))=0,"",SUMIFS(expected_production[Expected Production (kWh)],expected_production[Site Name],A153,expected_production[Date],B153)),"")} -> 15174.912 | E153: =IF(OR(C153="",D153="",D153=0),"",C153/D153) -> 0.64843869 | F153: =IF(E153="","",IF(E153>=0.9,"Expected",IF(E153>=0.7,"Moderate","Poor"))) -> Poor
A154: Bendstore Plaza Shops | B154: 45536 | C154: {=IFERROR(IF(SUMPRODUCT((measured[Site Name]=A154)*(measured[Date]=B154)*ISNUMBER(measured[Measured Value (kWh)]))=0,"",SUMIFS(measured[Measured Value (kWh)],measured[Site Name],A154,measured[Date],B154)),"")} -> 3277 | D154: {=IFERROR(IF(SUMPRODUCT((expected_production[Site Name]=A154)*(expected_production[Date]=B154)*ISNUMBER(expected_production[Expected Production (kWh)]))=0,"",SUMIFS(expected_production[Expected Production (kWh)],expected_production[Site Name],A154,expected_production[Date],B154)),"")} -> 15246.488 | E154: =IF(OR(C154="",D154="",D154=0),"",C154/D154) -> 0.21493475 | F154: =IF(E154="","",IF(E154>=0.9,"Expected",IF(E154>=0.7,"Moderate","Poor"))) -> Poor
... A175: Bendstore Plaza Shops | B175: 46174 | C175: {=IFERROR(IF(SUMPRODUCT((measured[Site Name]=A175)*(measured[Date]=B175)*ISNUMBER(measured[Measured Value (kWh)]))=0,"",SUMIFS(measured[Measured Value (kWh)],measured[Site Name],A175,measured[Date],B175)),"")} -> 7968.17 | D175: {=IFERROR(IF(SUMPRODUCT((expected_production[Site Name]=A175)*(expected_production[Date]=B175)*ISNUMBER(expected_production[Expected Production (kWh)]))=0,"",SUMIFS(expected_production[Expected Production (kWh)],expected_production[Site Name],A175,expected_production[Date],B175)),"")} -> 12736.142 | E175: =IF(OR(C175="",D175="",D175=0),"",C175/D175) -> 0.62563449 | F175: =IF(E175="","",IF(E175>=0.9,"Expected",IF(E175>=0.7,"Moderate","Poor"))) -> Poor
A176: Bendstore Plaza Shops | B176: 46204 | C176: {=IFERROR(IF(SUMPRODUCT((measured[Site Name]=A176)*(measured[Date]=B176)*ISNUMBER(measured[Measured Value (kWh)]))=0,"",SUMIFS(measured[Measured Value (kWh)],measured[Site Name],A176,measured[Date],B176)),"")} -> 10351.41 | D176: {=IFERROR(IF(SUMPRODUCT((expected_production[Site Name]=A176)*(expected_production[Date]=B176)*ISNUMBER(expected_production[Expected Production (kWh)]))=0,"",SUMIFS(expected_production[Expected Production (kWh)],expected_production[Site Name],A176,expected_production[Date],B176)),"")} -> 13397.031 | E176: =IF(OR(C176="",D176="",D176=0),"",C176/D176) -> 0.77266448 | F176: =IF(E176="","",IF(E176>=0.9,"Expected",IF(E176>=0.7,"Moderate","Poor"))) -> Moderate | G176: NO
A177: Bendstore Plaza Shops | B177: 46235 | C177: {=IFERROR(IF(SUMPRODUCT((measured[Site Name]=A177)*(measured[Date]=B177)*ISNUMBER(measured[Measured Value (kWh)]))=0,"",SUMIFS(measured[Measured Value (kWh)],measured[Site Name],A177,measured[Date],B177)),"")} -> 11244.861 | D177: {=IFERROR(IF(SUMPRODUCT((expected_production[Site Name]=A177)*(expected_production[Date]=B177)*ISNUMBER(expected_production[Expected Production (kWh)]))=0,"",SUMIFS(expected_production[Expected Production (kWh)],expected_production[Site Name],A177,expected_production[Date],B177)),"")} -> 14963.351 | E177: =IF(OR(C177="",D177="",D177=0),"",C177/D177) -> 0.75149352 | F177: =IF(E177="","",IF(E177>=0.9,"Expected",IF(E177>=0.7,"Moderate","Poor"))) -> Moderate | G177: NO
A178: Bendstore Plaza Shops | B178: 46266 | C178: {=IFERROR(IF(SUMPRODUCT((measured[Site Name]=A178)*(measured[Date]=B178)*ISNUMBER(measured[Measured Value (kWh)]))=0,"",SUMIFS(measured[Measured Value (kWh)],measured[Site Name],A178,measured[Date],B178)),"")} -> 8314.17 | D178: {=IFERROR(IF(SUMPRODUCT((expected_production[Site Name]=A178)*(expected_production[Date]=B178)*ISNUMBER(expected_production[Expected Production (kWh)]))=0,"",SUMIFS(expected_production[Expected Production (kWh)],expected_production[Site Name],A178,expected_production[Date],B178)),"")} -> 15033.929 | E178: =IF(OR(C178="",D178="",D178=0),"",C178/D178) -> 0.55302711 | F178: =IF(E178="","",IF(E178>=0.9,"Expected",IF(E178>=0.7,"Moderate","Poor"))) -> Poor | G178: NO
A179: Bendstore Plaza Shops | B179: 46296 | C179: {=IFERROR(IF(SUMPRODUCT((measured[Site Name]=A179)*(measured[Date]=B179)*ISNUMBER(measured[Measured Value (kWh)]))=0,"",SUMIFS(measured[Measured Value (kWh)],measured[Site Name],A179,measured[Date],B179)),"")} | D179: {=IFERROR(IF(SUMPRODUCT((expected_production[Site Name]=A179)*(expected_production[Date]=B179)*ISNUMBER(expected_production[Expected Production (kWh)]))=0,"",SUMIFS(expected_production[Expected Production (kWh)],expected_production[Site Name],A179,expected_production[Date],B179)),"")} -> 14431.033 | E179: =IF(OR(C179="",D179="",D179=0),"",C179/D179) | F179: =IF(E179="","",IF(E179>=0.9,"Expected",IF(E179>=0.7,"Moderate","Poor")))
A180: Bendstore Plaza Shops | B180: 46327 | C180: {=IFERROR(IF(SUMPRODUCT((measured[Site Name]=A180)*(measured[Date]=B180)*ISNUMBER(measured[Measured Value (kWh)]))=0,"",SUMIFS(measured[Measured Value (kWh)],measured[Site Name],A180,measured[Date],B180)),"")} | D180: {=IFERROR(IF(SUMPRODUCT((expected_production[Site Name]=A180)*(expected_production[Date]=B180)*ISNUMBER(expected_production[Expected Production (kWh)]))=0,"",SUMIFS(expected_production[Expected Production (kWh)],expected_production[Site Name],A180,expected_production[Date],B180)),"")} -> 14300.018 | E180: =IF(OR(C180="",D180="",D180=0),"",C180/D180) | F180: =IF(E180="","",IF(E180>=0.9,"Expected",IF(E180>=0.7,"Moderate","Poor")))
A181: Bendstore Plaza Shops | B181: 46357 | C181: {=IFERROR(IF(SUMPRODUCT((measured[Site Name]=A181)*(measured[Date]=B181)*ISNUMBER(measured[Measured Value (kWh)]))=0,"",SUMIFS(measured[Measured Value (kWh)],measured[Site Name],A181,measured[Date],B181)),"")} | D181: {=IFERROR(IF(SUMPRODUCT((expected_production[Site Name]=A181)*(expected_production[Date]=B181)*ISNUMBER(expected_production[Expected Production (kWh)]))=0,"",SUMIFS(expected_production[Expected Production (kWh)],expected_production[Site Name],A181,expected_production[Date],B181)),"")} -> 15710.284 | E181: =IF(OR(C181="",D181="",D181=0),"",C181/D181) | F181: =IF(E181="","",IF(E181>=0.9,"Expected",IF(E181>=0.7,"Moderate","Poor")))
A182: Bendstore Spar | B182: 45292 | C182: {=IFERROR(IF(SUMPRODUCT((measured[Site Name]=A182)*(measured[Date]=B182)*ISNUMBER(measured[Measured Value (kWh)]))=0,"",SUMIFS(measured[Measured Value (kWh)],measured[Site Name],A182,measured[Date],B182)),"")} -> 55000 | D182: {=IFERROR(IF(SUMPRODUCT((expected_production[Site Name]=A182)*(expected_production[Date]=B182)*ISNUMBER(expected_production[Expected Production (kWh)]))=0,"",SUMIFS(expected_production[Expected Production (kWh)],expected_production[Site Name],A182,expected_production[Date],B182)),"")} -> 51295 | E182: =IF(OR(C182="",D182="",D182=0),"",C182/D182) -> 1.0722293 | F182: =IF(E182="","",IF(E182>=0.9,"Expected",IF(E182>=0.7,"Moderate","Poor"))) -> Expected
A183: Bendstore Spar | B183: 45323 | C183: {=IFERROR(IF(SUMPRODUCT((measured[Site Name]=A183)*(measured[Date]=B183)*ISNUMBER(measured[Measured Value (kWh)]))=0,"",SUMIFS(measured[Measured Value (kWh)],measured[Site Name],A183,measured[Date],B183)),"")} -> 46799 | D183: {=IFERROR(IF(SUMPRODUCT((expected_production[Site Name]=A183)*(expected_production[Date]=B183)*ISNUMBER(expected_production[Expected Production (kWh)]))=0,"",SUMIFS(expected_production[Expected Production (kWh)],expected_production[Site Name],A183,expected_production[Date],B183)),"")} -> 44060.053 | E183: =IF(OR(C183="",D183="",D183=0),"",C183/D183) -> 1.0621639 | F183: =IF(E183="","",IF(E183>=0.9,"Expected",IF(E183>=0.7,"Moderate","Poor"))) -> Expected
