Workbook
Name AfricaCountries: CountryList!$A$1:$A$54

Sheet site_tech_info
A1: Site Name | B1: PV Capacity (W) | C1: PV Inverter Size (kW) | D1: Battery Size (Wh) | E1: Battery Name | F1: Battery Inverter/Hybrid Size | G1: Generator Size | H1: Genset/Grid set point kit | I1: Country | J1: Province | K1: Location | L1: Meter | M1: Contract Type | N1: Business Type | O1: Operational Satus | P1: Sales Type | Q1: Investment Party | R1: Project Number | S1: Commisioned Date | T1: Installer Name | U1: Platform | V1: Offtake Guarantee | W1: Age | X1: Soiling Intensity | Y1: Shading
A2: Vaal Maseru Klerksdorp | B2: 40000 | D2: 0 | E2: Solar MD | F2: Sunsynk | G2: null | H2: null | I2: South Africa | J2: Free state | K2: Cnr of Mikro and Von Wielligh Streets, Klerksdorp | L2: null | M2: PPA | N2: Commercial | O2: Decommissioned | Q2: SSI | R2: P00044 | S2: null | T2: SA Energy | U2: null | V2: NO | W2: =IF(ISNUMBER(S2),(TODAY()-S2)/365.25,"") | X2: Unknown
A3: 21 Melrose | B3: 14000 | C3: 36 | D3: 35808 | E3: Sunsynk | F3: 3x12kW | G3: None | H3: None | I3: South Africa | J3: Gauteng | K3: 21 Melrose St Melrose | L3: N/A | M3: RTO | N3: Residential | O3: Reduced Demand | Q3: Anuva | R3: P00062 | S3: 45171 | T3: SA Energy | U3: Sunsynk | V3: NO | W3: =IF(ISNUMBER(S3),(TODAY()-S3)/365.25,"") -> 2.9596167 | X3: Low
A4: African Global Plastics | B4: 178000 | C4: =2*80 -> 160 | D4: 0 | E4: N/A | F4: N/A | G4: None | H4: None | I4: South Africa | J4: Gauteng | K4: 1st St & 11th road, Kew, Sandton, 2090 | L4: Alester Meter | M4: PPA | N4: Manufacture | O4: Producing | Q4: SSI | R4: P00008 | S4: null | T4: SA Energy | U4: mypower24 | V4: NO | W4: =IF(ISNUMBER(S4),(TODAY()-S4)/365.25,"") | X4: Medium
A5: Alpine Heath Residential | B5: 36000 | C5: =1*33 -> 33 | D5: 0 | E5: N/A | F5: N/A | G5: None | H5: None | I5: South Africa | J5: KZN | K5: Busingatha, South Africa | L5: Eastron Meter | M5: PPA | N5: Residential | O5: Reduced Demand | Q5: 12B Fund | R5: null | S5: 45658 | T5: SA Energy | U5: isolarCloud | V5: YES | W5: =IF(ISNUMBER(S5),(TODAY()-S5)/365.25,"") -> 1.6262834 | X5: Low
A6: Bendstore Plaza Shops | B6: 110000 | C6: =1*110 -> 110 | D6: 0 | E6: N/A | F6: N/A | G6: N/A | H6: N/A | I6: South Africa | J6: Limpopo | K6: Stand 87, Bendstore Plaza, Giyani Main Rd, Giyani-BA, Giyani, 0832 | L6: null | M6: PPA | N6: Retail | O6: Reduced Demand | Q6: Anuva | R6: P00072 | S6: null | T6: SA Energy | U6: null | V6: NO | W6: =IF(ISNUMBER(S6),(TODAY()-S6)/365.25,"") | X6: Low
A7: Bendstore Spar | B7: 400000 | C7: null | D7: 0 | E7: N/A | F7: N/A | G7: null | H7: null | I7: South Africa | J7: Limpopo | K7: null | L7: null | M7: PPA | N7: Retail | O7: Producing | Q7: Anuva | R7: null | S7: null | T7: SA Energy | U7: null | V7: NO | W7: =IF(ISNUMBER(S7),(TODAY()-S7)/365.25,"") | X7: Low
A8: Beyerskloof | B8: 78000 | C8: null | D8: 0 | E8: N/A | F8: N/A | G8: null | H8: null | I8: South Africa | J8: Western Cape | K8: Koelenhof Street, R304, Koelenhof, Stellenbosch, 7600 | L8: null | M8: PPA | N8: Manufacture | O8: Reduced Demand | Q8: SSI | R8: null | S8: null | T8: Solar Synergy | U8: null | V8: NO | W8: =IF(ISNUMBER(S8),(TODAY()-S8)/365.25,"") | X8: Low
A9: BP Parys | B9: 544000 | C9: 50 | D9: 0 | E9: N/A | F9: N/A | G9: N/A | H9: N/A | I9: South Africa | J9: Free state | K9: 63 Bree St, Parys, 9585 | L9: Eastron Meter | M9: RTO | N9: Retail | O9: Reduced Demand | Q9: SSI | R9: null | T9: SA Energy | U9: null | V9: NO | W9: =IF(ISNUMBER(S9),(TODAY()-S9)/365.25,"") | X9: Low
A10: Buffalo Rock | B10: 15000 | C10: N/A | E10: null | F10: 2x12kW | G10: N/A | H10: N/A | I10: South Africa | J10: Mpumalanga | K10: Hazyview Ehlanzeni District Municipality MP | L10: null | M10: RTO | N10: Residential | O10: Reduced Demand | Q10: SSI | R10: P00054 | S10: 45448 | T10: SA Energy | U10: Sunsynk | V10: NO | W10: =IF(ISNUMBER(S10),(TODAY()-S10)/365.25,"") -> 2.201232 | X10: Low
A11: Checkers De Aar | B11: 154000 | C11: 125 | D11: 0 | E11: N/A | F11: N/A | G11: N/A | H11: NuVo | I11: South Africa | J11: Northern Cape | K11: 21 Alexander St, De Aar, 7000, South Africa | M11: PPA | N11: Retail | O11: Producing | Q11: 12B Fund | R11: P00038 | S11: null | T11: SA Energy | U11: iSolarCloud & NuVo | V11: NO | W11: =IF(ISNUMBER(S11),(TODAY()-S11)/365.25,"") | X11: Low
A12: Checkers Silverlakes Gen | B12: 152000 | C12: 125 | D12: 0 | E12: N/A | F12: N/A | G12: 500 | H12: Nuvo | I12: South Africa | J12: Gauteng | K12: Chamberlain Shopping Cntr (Six Fountains Cnr Solomon Mahlangu Dr, Bendeman Blvd, &, Pretoria, 0081 | L12: Eastron Meter | M12: PPA | N12: Retail | O12: Producing | Q12: 12B Fund | R12: null | S12: 45841 | T12: SA Energy | U12: isolarCloud | V12: NO | W12: =IF(ISNUMBER(S12),(TODAY()-S12)/365.25,"") -> 1.1252567 | X12: Low
A13: Checkers Silverlakes No Gen | B13: 142000 | C13: 125 | D13: 0 | E13: N/A | F13: N/A | G13: N/A | H13: N/A | I13: South Africa | J13: Gauteng | K13: Chamberlain Shopping Cntr (Six Fountains Cnr Solomon Mahlangu Dr, Bendeman Blvd, &, Pretoria, 0081 | L13: Eastron Meter | M13: PPA | N13: Retail | O13: Producing | Q13: 12B Fund | R13: null | S13: 46206 | T13: SA Energy | U13: isolarCloud | V13: NO | W13: =IF(ISNUMBER(S13),(TODAY()-S13)/365.25,"") -> 0.12594114 | X13: Low
A14: Checkrite Inanda | B14: 70000 | C14: =2*33 -> 66 | D14: 0 | E14: N/A | F14: N/A | G14: N/A | H14: N/A | I14: South Africa | J14: Gauteng | K14: 6th Ave, Springs New, Springs, 1560 | L14: null | M14: PPA | N14: Retail | O14: Producing | Q14: 12B Fund | R14: P00056 | S14: 45318 | T14: SA Energy | U14: iSolarCloud | V14: YES | W14: =IF(ISNUMBER(S14),(TODAY()-S14)/365.25,"") -> 2.5571526 | X14: Low
A15: Club Houghton | B15: 60000 | C15: N/A | D15: 84000 | E15: N/A | F15: 6x12kW Sunsynk Inverters | G15: N/A | H15: null | I15: South Africa | J15: Gauteng | K15: Osborn Rd, Houghton Estate, Johannesburg, 2198, South Africa | L15: N/A | M15: PPA | N15: Residential | O15: Reduced Demand | Q15: Anuva | R15: P00067 | S15: null | T15: SA Energy | U15: Sunsysnk;SolarMd | V15: NO | W15: =IF(ISNUMBER(S15),(TODAY()-S15)/365.25,"") | X15: Low
A16: Coldstar International | B16: 41000 | C16: 36 | D16: 0 | E16: N/A | F16: N/A | G16: N/A | H16: N/A | I16: South Africa | J16: KZN | K16: Coldstar International, 3 Rana Rd, Isipingo Rail, Isipingo, 4110 | client miss use data | L16: N/A | M16: PPA | N16: Commercial | O16: Reduced Demand | Q16: Anuva | R16: P00051 | T16: SA Energy | U16: iSolarCloud | V16: NO | W16: =IF(ISNUMBER(S16),(TODAY()-S16)/365.25,"") | X16: Low
A17: Cultura Fresh | B17: 65000 | C17: null | D17: 0 | E17: N/A | F17: N/A | G17: N/A | H17: null | I17: South Africa | J17: Western Cape | K17: null | L17: null | M17: PPA | N17: Agricultural | O17: Reduced Demand | Q17: 12B Fund | R17: null | S17: null | T17: Solar Synergy | U17: null | V17: NO | W17: =IF(ISNUMBER(S17),(TODAY()-S17)/365.25,"") | X17: Low
A18: Demco | B18: 235000 | C18: =2*110 -> 220 | D18: 0 | E18: N/A | F18: N/A | G18: N/A | H18: N/A | I18: South Africa | J18: Gauteng | K18: Industries East, 12 -14 Moller Street, Germiston. 1401 | L18: Alester Meter | M18: PPA | N18: Manufacture | O18: Reduced Demand | Q18: 12B Fund | R18: P00035 | S18: 45047 | T18: SA Energy | U18: iSolarCloud | V18: YES | W18: =IF(ISNUMBER(S18),(TODAY()-S18)/365.25,"") -> 3.2991102 | X18: Low
A19: Giba Gorge Main | B19: 180000 | C19: 160 | D19: 0 | E19: N/A | F19: N/A | G19: N/A | H19: N/A | I19: South Africa | J19: KZN | K19: 5QCJ+XM2 Clifton Canyon, Pinetown Rural | L19: Alester Meter | M19: PPA | N19: Manufacture | O19: Reduced Demand | Q19: SSI | R19: P00069 | S19: null | T19: SA Energy | U19: soliscloud | V19: NO | W19: =IF(ISNUMBER(S19),(TODAY()-S19)/365.25,"") | X19: Low
A20: Giba Gorge Storage | B20: 106000 | C20: null | D20: 0 | E20: N/A | F20: N/A | G20: N/A | H20: null | I20: South Africa | J20: KZN | K20: 5QCJ+XM2 Clifton Canyon, Pinetown Rural | L20: Alester Meter | M20: PPA | N20: Commercial | O20: Reduced Demand | Q20: SSI | R20: null | S20: null | T20: SA Energy | U20: SolisCloud | V20: NO | W20: =IF(ISNUMBER(S20),(TODAY()-S20)/365.25,"") | X20: Low
A21: Golden Spot Resort | B21: 30000 | C21: 33 | D21: 0 | E21: N/A | F21: N/A | G21: N/A | H21: N/A | I21: South Africa | J21: Mpumalanga | K21: HR2M+GQ7 Alkmaar (-25.4487127, 30.8344204) | L21: null | M21: PPA | N21: Residential | O21: Reduced Demand | Q21: SSI | R21: P00071 | S21: 45072 | T21: SA Energy | U21: iSolarCloud | V21: YES | W21: =IF(ISNUMBER(S21),(TODAY()-S21)/365.25,"") -> 3.2306639 | X21: Low
A22: Golden Spot Shops | B22: 30000 | C22: 33 | D22: 0 | E22: N/A | F22: N/A | G22: N/A | H22: N/A | I22: South Africa | J22: Mpumalanga | K22: HR2M+GQ7 Alkmaar (-25.4487127, 30.8344204) | L22: null | M22: PPA | N22: Retail | O22: Producing | Q22: SSI | R22: P00060 | S22: 45072 | T22: SA Energy | U22: iSolarCloud | V22: YES | W22: =IF(ISNUMBER(S22),(TODAY()-S22)/365.25,"") -> 3.2306639 | X22: Low
A23: HB Dunn | B23: 24000 | C23: N/A | D23: 127400 | E23: N/A | F23: 1x50 kW | G23: N/A | H23: N/A | I23: South Africa | J23: Mpumalanga | K23: Kriel Nkangala District Municipality MP | L23: null | M23: RTO | N23: Residential | O23: Reduced Demand | Q23: SSI | R23: P00045 | T23: SA Energy | U23: Sunsynk | V23: NO | W23: =IF(ISNUMBER(S23),(TODAY()-S23)/365.25,"") | X23: Low
A24: Helderberg Collage | B24: 223000 | C24: null | D24: 0 | E24: N/A | F24: N/A | G24: N/A | H24: null | I24: South Africa | J24: Western Cape | K24: null | L24: null | M24: PPA | N24: Residential | O24: Producing | Q24: SSI | R24: null | S24: null | T24: SA Energy | U24: null | V24: NO | W24: =IF(ISNUMBER(S24),(TODAY()-S24)/365.25,"") | X24: Low
A25: Hilston Rotoflo | B25: 240000 | C25: 240 | D25: 0 | E25: N/A | F25: N/A | G25: N/A | H25: N/A | I25: South Africa | J25: Gauteng | K25: 28 Hilston Rd, Kya Sand, Randburg, 2163 | L25: null | M25: PPA | N25: Residential | O25: Producing | Q25: Anuva | R25: P00055 | S25: 45175 | T25: SA Energy | U25: isolarCloud | V25: YES | W25: =IF(ISNUMBER(S25),(TODAY()-S25)/365.25,"") -> 2.9486653 | X25: Low
A26: Huis Herfsblaar | B26: 215000 | C26: =2*110 -> 220 | D26: 0 | E26: N/A | F26: N/A | G26: N/A | H26: N/A | I26: South Africa | J26: Gauteng | K26: Edging Pretoria, 1244 Webb Rd, Queenswood, Pretoria, 0186, South Africa | L26: Eastron Meter | M26: PPA | N26: Commercial | O26: Producing | Q26: 12B Fund | R26: P00034 | S26: 45463 | T26: SA Energy | U26: iSolarCloud | V26: YES | W26: =IF(ISNUMBER(S26),(TODAY()-S26)/365.25,"") -> 2.1601643 | X26: Low
A27: Kool Village | B27: 79000 | C27: null | D27: 0 | E27: N/A | F27: N/A | G27: N/A | H27: null | I27: South Africa | J27: Northern Cape | K27: Kool Village, 89 Virginia Way, Virginia, 9430 | L27: null | M27: null | N27: Commercial | O27: Producing | Q27: Anuva | R27: null | S27: null | T27: SA Energy | U27: null | V27: NO | W27: =IF(ISNUMBER(S27),(TODAY()-S27)/365.25,"") | X27: Low
A28: Mambha Cash & Carry | B28: 184000 | C28: null | D28: 0 | E28: N/A | F28: N/A | G28: N/A | H28: null | I28: South Africa | J28: KZN | K28: null | L28: null | M28: PPA | N28: Retail | O28: Producing | Q28: Anuva | R28: P00015 | S28: null | T28: SA Energy | U28: mypower24 | V28: NO | W28: =IF(ISNUMBER(S28),(TODAY()-S28)/365.25,"") | X28: Medium
A29: Mathe Group Company | B29: 518000 | C29: =4*110 -> 440 | D29: 0 | E29: N/A | F29: N/A | G29: N/A | H29: N/A | I29: South Africa | J29: KZN | K29: 4/160 Buckman Blvd, Cato Ridge, 3699, South Africa | L29: null | M29: PPA | N29: Manufacture | O29: Producing | Q29: Anuva | R29: P00059 | S29: 44662 | T29: SA Energy | U29: iSolarCloud | W29: =IF(ISNUMBER(S29),(TODAY()-S29)/365.25,"") -> 4.3531828 | X29: Low
A30: Mdluli | B30: 114000 | C30: null | D30: 0 | E30: N/A | F30: N/A | G30: N/A | H30: null | I30: South Africa | J30: Mpumalanga | K30: Makoko, South Africa,1251 | L30: null | M30: PPA | N30: Residential | O30: Reduced Demand | Q30: 12B Fund | R30: P00083 | S30: 45352 | T30: SA Energy | U30: mypower24&IsolarCloud | V30: YES | W30: =IF(ISNUMBER(S30),(TODAY()-S30)/365.25,"") -> 2.4640657 | X30: Low
A31: Meredale Heights | B31: 33000 | C31: =1*33 -> 33 | D31: 0 | E31: N/A | F31: N/A | G31: N/A | H31: N/A | I31: South Africa | J31: Gauteng | K31: 40 thomas street | L31: null | M31: PPA | N31: Residential | O31: Producing | Q31: Anuva | R31: P00052 | S31: 44963 | T31: SA Energy | U31: iSolarCloud | V31: YES | W31: =IF(ISNUMBER(S31),(TODAY()-S31)/365.25,"") -> 3.5290897 | X31: Low
A32: Monument Park Checkers | B32: 281000 | C32: =2*125 -> 250 | D32: 0 | E32: N/A | F32: N/A | G32: N/A | H32: NuVo | I32: South Africa | J32: Gauteng | K32: 242 Voortrekker Rd, Monument, Krugersdorp, 1739, South Africa | L32: null | M32: PPA | N32: Retail | O32: Producing | Q32: Anuva | R32: P00037 | S32: null | T32: SA Energy | U32: isloarcloud &Nuvo | V32: NO | W32: =IF(ISNUMBER(S32),(TODAY()-S32)/365.25,"") | X32: Low
A33: Nkambeni Industrial | B33: 158400 | C33: 125 | D33: 0 | E33: Solar MD | F33: Atess PCS500 | G33: N/A | H33: null | I33: South Africa | J33: Mpumalanga | K33: 139 Numbi Rd Numbi Gate Kruger National Park, Hazyview, 1350 | L33: null | M33: RTO | N33: Residential | O33: Reduced Demand | Q33: SSI | R33: P00040 | S33: null | T33: SA Energy | U33: null | V33: NO | W33: =IF(ISNUMBER(S33),(TODAY()-S33)/365.25,"") | X33: Low
A34: Opal Students | B34: 35000 | C34: =1*33 -> 33 | D34: 0 | E34: N/A | F34: N/A | G34: N/A | H34: N/A | I34: South Africa | J34: Gauteng | K34: Opal students | L34: null | M34: RTO | N34: Retail | O34: Producing | Q34: Anuva | R34: P00057 | S34: 45174 | T34: SA Energy | U34: iSolarCloud | V34: YES | W34: =IF(ISNUMBER(S34),(TODAY()-S34)/365.25,"") -> 2.9514031 | X34: Low
A35: Orthochem Bethlehem | B35: 220000 | C35: null | D35: 0 | E35: N/A | F35: N/A | G35: N/A | H35: null | I35: South Africa | J35: Free state | K35: 6 Sauer Street Bethlehem Free State 9700 | L35: null | M35: PPA | N35: Manufacture | O35: Producing | Q35: SSI | R35: P00063 | S35: null | T35: SA Energy | U35: isolarcloud, & NuVO | V35: NO | W35: =IF(ISNUMBER(S35),(TODAY()-S35)/365.25,"") | X35: Low
A36: Plastiplate | B36: 66000 | C36: =2*33 -> 66 | D36: 0 | E36: N/A | F36: N/A | G36: N/A | H36: N/A | I36: South Africa | J36: Gauteng | K36: 6 adderley, Roodepoort, 1724, South Africa | L36: null | M36: PPA | N36: Manufacture | O36: Producing | Q36: Anuva | R36: P00061 | S36: 44688 | T36: SA Energy | U36: iSolarCloud | V36: YES | W36: =IF(ISNUMBER(S36),(TODAY()-S36)/365.25,"") -> 4.2819986 | X36: Low
A37: PNB Unlimited | B37: 95000 | C37: null | D37: 0 | E37: N/A | F37: N/A | G37: N/A | H37: null | I37: South Africa | J37: North West | K37: 8X4H+VXW Amaoti | L37: null | M37: PPA | N37: Commercial | O37: Producing | Q37: SSI | R37: null | S37: null | T37: SA Energy | U37: null | V37: NO | W37: =IF(ISNUMBER(S37),(TODAY()-S37)/365.25,"") | X37: Low
A38: Q-lity Meat | B38: 35000 | C38: 30 | D38: 0 | E38: N/A | F38: N/A | G38: N/A | H38: NuVo | I38: South Africa | J38: Gauteng | K38: null | L38: null | M38: PPA | N38: Retail | O38: Producing | Q38: SSI | R38: P00007 | S38: null | T38: SA Energy | U38: isloarcloud &Nuvo | V38: NO | W38: =IF(ISNUMBER(S38),(TODAY()-S38)/365.25,"") | X38: Low
A39: Quintondale | B39: 40000 | C39: 33 | D39: 0 | E39: N/A | F39: N/A | G39: N/A | H39: N/A | I39: South Africa | J39: Gauteng | K39: 43 Orchards Street, Johannesburg, Johannesburg, Gauteng 2192, South Africa | L39: null | M39: PPA | N39: Residential | O39: Reduced Demand | Q39: SSI | R39: P00065 | S39: null | T39: SA Energy | U39: null | V39: NO | W39: =IF(ISNUMBER(S39),(TODAY()-S39)/365.25,"") | X39: Low
A40: Riverside Lodge | B40: 110000 | C40: =2*50 -> 100 | D40: 0 | E40: N/A | F40: N/A | G40: N/A | H40: N/A | I40: South Africa | J40: North West | K40: Hartbeespoort, South Africa | L40: null | M40: PPA | N40: Residential | O40: Producing | Q40: Anuva | R40: P00053 | S40: 45265 | T40: SA Energy | U40: iSolarCloud | V40: YES | W40: =IF(ISNUMBER(S40),(TODAY()-S40)/365.25,"") -> 2.7022587 | X40: Low
A41: Sakhumnotho | B41: 38000 | C41: 30 | D41: 0 | E41: N/A | F41: N/A | G41: N/A | H41: N/A | I41: South Africa | J41: Gauteng | K41: R3W5+96X Johannesburg | L41: null | M41: PPA | N41: Commercial | O41: Decommissioned | Q41: SSI | R41: P00043 | S41: null | T41: SA Energy | U41: null | V41: NO | W41: =IF(ISNUMBER(S41),(TODAY()-S41)/365.25,"") | X41: Low
A42: SaveMore Alldays - Store | B42: 180000 | C42: 100 | D42: 0 | E42: N/A | F42: N/A | G42: N/A | H42: N/A | I42: South Africa | J42: Limpopo | K42: R572, Alldays, 0909 | L42: null | M42: PPA | N42: Retail | O42: Reduced Demand | Q42: SSI | R42: P00050 | S42: null | T42: SA Energy | U42: soliscloud | V42: NO | W42: =IF(ISNUMBER(S42),(TODAY()-S42)/365.25,"") | X42: Low
A43: Savemore Liquor Alldays | B43: 27300 | C43: 30 | D43: 0 | E43: N/A | F43: N/A | G43: N/A | H43: N/A | I43: South Africa | J43: Limpopo | K43: 84C3+PG2 Alldays | L43: null | M43: PPA | N43: Retail | O43: Reduced Demand | Q43: SSI | R43: null | S43: null | T43: SA Energy | U43: soliscloud | V43: NO | W43: =IF(ISNUMBER(S43),(TODAY()-S43)/365.25,"") | X43: Low
A44: Saverite Durban | B44: 95000 | C44: null | D44: 0 | E44: N/A | F44: N/A | G44: N/A | H44: null | I44: South Africa | J44: KZN | K44: null | L44: null | M44: PPA | N44: Retail | O44: Producing | Q44: Anuva | R44: null | S44: null | T44: SA Energy | U44: null | V44: NO | W44: =IF(ISNUMBER(S44),(TODAY()-S44)/365.25,"") | X44: Low
A45: Saverite PMB | B45: 96000 | C45: null | D45: 0 | E45: N/A | F45: N/A | G45: N/A | H45: null | I45: South Africa | J45: KZN | K45: 457 Langalibalele St, Pietermaritzburg, 3200 | L45: null | M45: PPA | N45: Retail | O45: Producing | Q45: SSI | R45: null | S45: null | T45: SA Energy | U45: null | V45: NO | W45: =IF(ISNUMBER(S45),(TODAY()-S45)/365.25,"") | X45: Low
A46: Secunda Plaza Choppies | B46: 121000 | C46: 110 | D46: 0 | E46: N/A | F46: N/A | G46: N/A | H46: N/A | I46: South Africa | J46: Mpumalanga | K46: 8337 Pichlerplien, Secunda, 2302, South Africa | L46: null | M46: PPA | N46: Retail | O46: Reduced Demand | Q46: SSI | R46: P00076 | T46: SA Energy | U46: iSolarCloud | V46: NO | W46: =IF(ISNUMBER(S46),(TODAY()-S46)/365.25,"") | X46: Low
A47: Secunda Plaza Shops | B47: 35000 | C47: 33 | D47: 0 | E47: N/A | F47: N/A | G47: N/A | H47: N/A | I47: South Africa | J47: Mpumalanga | K47: 8309 Louwrens Muller St, Secunda, 2302, South Africa | L47: null | M47: PPA | N47: Retail | O47: Reduced Demand | Q47: SSI | R47: P00075 | T47: SA Energy | U47: iSolarCloud | V47: NO | W47: =IF(ISNUMBER(S47),(TODAY()-S47)/365.25,"") | X47: Low
A48: Shoprite Dube | B48: 153000 | C48: 125 | D48: 0 | E48: N/A | F48: N/A | G48: N/A | H48: N/A | I48: South Africa | J48: Gauteng | K48: Shoprite Maponya Center, 1980 Mahalefele Rd, Dube, Soweto, 1801 | L48: Eastron Meter | M48: PPA | N48: Retail | O48: Producing | Q48: 12B Fund | R48: null | T48: SA Energy | U48: isolarCloud | V48: NO | W48: =IF(ISNUMBER(S48),(TODAY()-S48)/365.25,"") | X48: Low
A49: Shoprite Hillbrow | B49: 126000 | C49: null | D49: 0 | E49: N/A | F49: N/A | G49: 500kVa | H49: NuVo | I49: South Africa | J49: Gauteng | K49: null | L49: Eastron Meter | M49: PPA | N49: Retail | O49: Producing | Q49: 12B Fund | R49: null | S49: null | T49: SA Energy | U49: null | V49: NO | W49: =IF(ISNUMBER(S49),(TODAY()-S49)/365.25,"") | X49: Low | Y49: High
A50: Shoprite Ladybrand | B50: 250000 | C50: 110 | D50: 0 | E50: N/A | F50: N/A | G50: N/A | H50: N/A | I50: South Africa | J50: Free state | K50: 248 Voortrekkers Ave, CBD, Ladybrand, 9745, South Africa | L50: Eastron Meter | M50: PPA | N50: Retail | O50: Producing | Q50: 12B Fund | R50: null | T50: SA Energy | U50: null | V50: NO | W50: =IF(ISNUMBER(S50),(TODAY()-S50)/365.25,"") | X50: Low
A51: Shoprite Mini Ganyesa | B51: 240000 | C51: 110 | D51: 0 | E51: N/A | F51: N/A | G51: N/A | H51: NuVo | I51: South Africa | J51: North West | K51: Hartbeespoort, South Africa | L51: Eastron Meter | M51: PPA | N51: Retail | O51: Producing | Q51: 12B Fund | R51: P00078 | T51: SA Energy | U51: isloarcloud &Nuvo | V51: NO | W51: =IF(ISNUMBER(S51),(TODAY()-S51)/365.25,"") | X51: Low
A52: Shoprite Naledi | B52: 125000 | C52: 125 | D52: 0 | E52: N/A | F52: N/A | G52: 500 | H52: NuVo | I52: South Africa | J52: Gauteng | K52: PRVC+MPW Soweto | L52: Eastron Meter | M52: PPA | N52: Retail | O52: Producing | Q52: 12B Fund | R52: null | S52: null | T52: SA Energy | U52: Sunsynk | V52: NO | W52: =IF(ISNUMBER(S52),(TODAY()-S52)/365.25,"") | X52: Low
A53: Spring Glade | B53: 116000 | C53: 110 | D53: 0 | E53: N/A | F53: N/A | G53: N/A | H53: N/A | I53: South Africa | J53: Gauteng | K53: VR7R+269 Roodepoort | L53: Alester Meter | M53: PPA | N53: Residential | O53: Reduced Demand | Q53: SSI | R53: null | S53: null | T53: SA Energy | U53: SolisCloud | V53: NO | W53: =IF(ISNUMBER(S53),(TODAY()-S53)/365.25,"") | X53: Low
A54: Thakadu Industrial | B54: 61600 | C54: null | D54: 289000 | E54: N/A | F54: N/A | G54: N/A | H54: null | I54: South Africa | J54: North West | K54: D53 Thakadu Gate, Madikwe Game Reserve Molatedi, 2838 | L54: null | M54: PPA | N54: Residential | O54: Reduced Demand | Q54: SSI | R54: null | S54: null | T54: SA Energy | U54: null | V54: NO | W54: =IF(ISNUMBER(S54),(TODAY()-S54)/365.25,"") | X54: Low
A55: The Alec | B55: 55000 | C55: 50 | D55: 0 | E55: N/A | F55: N/A | G55: N/A | H55: NuVo | I55: South Africa | J55: Gauteng | K55: 48 Goldreich St, Hillbrow, Johannesburg, 2198, South Africa | L55: null | M55: PPA | N55: Residential | O55: Reduced Demand | Q55: Anuva | R55: null | S55: 45127 | T55: SA Energy | U55: isolarCloud | V55: YES | W55: =IF(ISNUMBER(S55),(TODAY()-S55)/365.25,"") -> 3.0800821 | X55: Low
A56: Three Peaks | B56: 40000 | C56: =1*33 -> 33 | D56: 0 | E56: N/A | F56: N/A | G56: N/A | H56: N/A | I56: South Africa | J56: KZN | K56: 22A Underwood Rd, Hatton Estate, Pinetown, 3610 | M56: PPA | N56: Residential | O56: Reduced Demand | Q56: Anuva | R56: P00064 | T56: SA Energy | U56: iSolarCloud | V56: NO | W56: =IF(ISNUMBER(S56),(TODAY()-S56)/365.25,"") | X56: Low
A57: TPF Foods | B57: 34000 | C57: 30 | D57: 0 | E57: N/A | F57: N/A | G57: N/A | H57: null | I57: South Africa | J57: Limpopo | K57: Q2R4+98G Johannesburg | L57: Alester Meter | M57: PPA | N57: Retail | O57: Reduced Demand | Q57: SSI | R57: null | S57: null | T57: SA Energy | U57: null | V57: NO | W57: =IF(ISNUMBER(S57),(TODAY()-S57)/365.25,"") | X57: Low
A58: Trouw Nutrition | B58: 103000 | C58: null | D58: 0 | E58: N/A | F58: N/A | G58: N/A | H58: null | I58: South Africa | J58: Gauteng | K58: null | L58: Alester Meter | M58: PPA | N58: Manufacture | O58: Producing | Q58: SSI | R58: null | S58: null | T58: SA Energy | U58: null | V58: NO | W58: =IF(ISNUMBER(S58),(TODAY()-S58)/365.25,"") | X58: Low
A59: Watt Place Rotoflo | B59: 230000 | C59: =2*110 -> 220 | D59: 0 | E59: N/A | F59: N/A | G59: N/A | H59: NuVo | I59: South Africa | J59: Gauteng | K59: 10 Watt Pl, Kya Sand, Randburg, 2163, South Africa | L59: null | M59: PPA | N59: Manufacture | O59: Producing | Q59: Anuva | R59: P00048 | S59: 45175 | T59: SA Energy | U59: isolarCloud & Nuvo | V59: YES | W59: =IF(ISNUMBER(S59),(TODAY()-S59)/365.25,"") -> 2.9486653 | X59: Low
A60: Zwartop Golf Course | B60: 27000 | C60: =1*33 -> 33 | D60: null | E60: N/A | F60: N/A | G60: N/A | H60: null | I60: South Africa | J60: Gauteng | K60: ZwartKop Golf and Country club, 108 Golf Avenue Club view Centurion 0157 | L60: null | M60: RTO | N60: Residential | O60: Reduced Demand | Q60: Anuva | R60: null | S60: null | T60: SA Energy | U60: null | V60: NO | W60: =IF(ISNUMBER(S60),(TODAY()-S60)/365.25,"") | X60: Low
A61: Shoprite Thokoza | B61: 115000 | C61: 125 | D61: 0 | E61: N/A | F61: N/A | G61: N/A | H61: N/A | I61: South Africa | J61: Gauteng | K61: 9102 Khumalo St, Thokoza, 1426 | L61: Eastron Meter | M61: PPA | N61: Retail | O61: Producing | Q61: 12B Fund | R61: null | S61: 45752 | T61: SA Energy | U61: IsolarCloud | V61: NO | W61: =IF(ISNUMBER(S61),(TODAY()-S61)/365.25,"") -> 1.3689254 | X61: Medium
A62: U Save Botrivier | B62: 33000 | C62: 30 | D62: 0 | E62: N/A | F62: N/A | G62: N/A | H62: N/A | I62: South Africa | J62: Western Cape | K62: 3 8th Ave, Bot River, 7185, South Africa | L62: Eastron Meter | M62: PPA | N62: Retail | O62: Reduced Demand | Q62: SSI | R62: null | T62: SA Energy | U62: IsolarCloud | V62: NO | W62: =IF(ISNUMBER(S62),(TODAY()-S62)/365.25,"") | X62: Low
A63: SR Morula TF 1 | B63: 57000 | C63: 50 | D63: 0 | E63: N/A | F63: N/A | G63: N/A | H63: N/A | I63: South Africa | J63: Gauteng | K63: 8408 Mangope Rd, Mabopane Unit M, Mabopane, 0190, South Africa | L63: Eastron Meter | M63: PPA | N63: Retail | O63: Producing | Q63: SSI | R63: P00091 | S63: 45159 | T63: SA Energy | U63: IsolarCloud | V63: YES | W63: =IF(ISNUMBER(S63),(TODAY()-S63)/365.25,"") -> 2.9924709 | X63: High
A64: SR Morula TF 1 - Shoprite | B64: 177000 | C64: 125 | D64: 0 | E64: N/A | F64: N/A | G64: N/A | H64: N/A | I64: South Africa | J64: Gauteng | K64: 8409 Mangope Rd, Mabopane Unit M, Mabopane, 0190, South Africa | L64: Eastron Meter | M64: PPA | N64: Retail | O64: Producing | Q64: 12B Fund | R64: P00091 | T64: SA Energy | U64: IsolarCloud | V64: NO | W64: =IF(ISNUMBER(S64),(TODAY()-S64)/365.25,"") | X64: High
A65: SR Morula TF 2 | B65: 57000 | C65: 50 | D65: 0 | E65: N/A | F65: N/A | G65: N/A | H65: N/A | I65: South Africa | J65: Gauteng | K65: 8410 Mangope Rd, Mabopane Unit M, Mabopane, 0190, South Africa | L65: Eastron Meter | M65: PPA | N65: Retail | O65: Producing | Q65: 12B Fund | R65: P00091 | S65: 45159 | T65: SA Energy | U65: IsolarCloud | V65: YES | W65: =IF(ISNUMBER(S65),(TODAY()-S65)/365.25,"") -> 2.9924709 | X65: High
A66: Olievenhoutbosch 1 | B66: 300000 | C66: null | D66: 0 | E66: N/A | F66: N/A | G66: N/A | H66: N/A | I66: South Africa | J66: Gauteng | K66: 33WW+C5W Centurion | L66: Eastron Meter | M66: PPA | N66: Retail | O66: Producing | Q66: SSI | R66: null | S66: 45924 | T66: SA Energy | U66: IsolarCloud | V66: YES | W66: =IF(ISNUMBER(S66),(TODAY()-S66)/365.25,"") -> 0.89801506 | X66: High
A67: Olievenhoutbosch 2 | B67: 70000 | C67: null | D67: 0 | E67: N/A | F67: N/A | G67: N/A | H67: N/A | I67: South Africa | J67: Gauteng | K67: 33WW+C5W Centurion | L67: Eastron Meter | M67: PPA | N67: Retail | O67: Producing | Q67: SSI | R67: null | S67: 45924 | T67: SA Energy | U67: IsolarCloud | V67: YES | W67: =IF(ISNUMBER(S67),(TODAY()-S67)/365.25,"") -> 0.89801506 | X67: High
A68: IPID - Floor 6 | B68: 47600 | C68: null | D68: 0 | E68: N/A | F68: N/A | G68: N/A | H68: N/A | I68: South Africa | J68: Gauteng | K68: 7633+M46 Pretoria | L68: Eastron Meter | M68: PPA | N68: Commercial | O68: Producing | Q68: SSI | R68: null | S68: 45934 | T68: SA Energy | U68: IsolarCloud | V68: YES | W68: =IF(ISNUMBER(S68),(TODAY()-S68)/365.25,"") -> 0.87063655 | X68: Low
A69: IPID - Floor 4 | B69: 54740 | C69: null | D69: 0 | E69: N/A | F69: N/A | G69: N/A | H69: N/A | I69: South Africa | J69: Gauteng | K69: 7633+M46 Pretoria | L69: Eastron Meter | M69: PPA | N69: Commercial | O69: Producing | Q69: SSI | R69: null | S69: 45934 | T69: SA Energy | U69: IsolarCloud | V69: YES | W69: =IF(ISNUMBER(S69),(TODAY()-S69)/365.25,"") -> 0.87063655 | X69: Low
A70: Shoprite Newlands | B70: 200000 | C70: null | D70: 0 | E70: N/A | F70: N/A | G70: N/A | H70: N/A | I70: South Africa | J70: KZN | K70: Newlands City Centre, 2 Marble Ray Drive, New Dawn Park, Durban, 4037 | L70: Eastron Meter | M70: PPA | N70: Residential | O70: Producing | Q70: SSI | R70: null | S70: null | T70: SA Energy | U70: null | V70: NO | W70: =IF(ISNUMBER(S70),(TODAY()-S70)/365.25,"") | X70: Low
A71: Grootpan | B71: 170000 | C71: =4*50 -> 200 | D71: 491520 | E71: Deye | F71: Daye | G71: N/A | H71: N/A | I71: South Africa | J71: North West | K71: 2G4H+RXQ Ga-Motlatla | L71: N/A | M71: RTO | N71: Agricultural | O71: Reduced Demand | Q71: SSI | R71: null | S71: null | T71: OTG 4 U | U71: Deye Cloud | V71: NO | W71: =IF(ISNUMBER(S71),(TODAY()-S71)/365.25,"") | X71: Low
A72: Medipost | B72: 330000 | C72: null | D72: 0 | E72: N/A | F72: N/A | G72: N/A | H72: N/A | I72: South Africa | J72: Western Cape | K72: 593 Nico Smith St, Gezina, Pretoria, 0084 | L72: Eastron Meter | M72: PPA | N72: Commercial | O72: Producing | Q72: 12B Fund | R72: null | S72: null | T72: SA Energy | U72: null | W72: =IF(ISNUMBER(S72),(TODAY()-S72)/365.25,"") | X72: Low
A73: Makalali | B73: 120000 | D73: 0 | E73: N/A | F73: N/A | G73: N/A | H73: N/A | I73: South Africa | J73: Limpopo | K73: Makalali game reserve Road D202 Harmony Block 33, Gravelotte | N73: Agriculural | O73: Reduced Demand | Q73: SSI | T73: SA Energy | W73: =IF(ISNUMBER(S73),(TODAY()-S73)/365.25,"") | X73: Low
A74: Engen Lotus Gardens | B74: 23010 | D74: 0 | E74: N/A | F74: N/A | G74: N/A | H74: N/A | I74: South Africa | J74: Gauteng | K74: 63WC+CQ4 Pretoria | L74: Eastron Meter | M74: PPA | N74: Retail | O74: Producing | Q74: SSI | S74: 45951 | T74: SA Energy | U74: IsolarCloud | V74: YES | W74: =IF(ISNUMBER(S74),(TODAY()-S74)/365.25,"") -> 0.82409309 | X74: Low
A75: Shoprite Ekhaya | B75: 175680 | C75: 150 | D75: 0 | E75: N/A | F75: N/A | G75: N/A | H75: N/A | I75: South Africa | J75: Mpumalanga | K75: Ekhaya Mall, R546, Evander, 2285 | L75: Eastron Meter | M75: PPA | N75: Retail | O75: Producing | Q75: SSI | S75: 46068 | T75: SA Energy | U75: IsolarCloud | V75: NO | W75: =IF(ISNUMBER(S75),(TODAY()-S75)/365.25,"") -> 0.50376454 | X75: Unknown
A76: Roan Foods | B76: 127440 | C76: 100 | D76: 246 | E76: Deye | F76: Deye | G76: N/A | H76: N/A | I76: Zambia | J76: Lusaka | K76: J8VC+WPJ, Lusaka, Zambia | L76: N/A | M76: RTO | N76: Retail | O76: Producing | S76: 46114 | T76: Dorman Energy | U76: Deye Cloud | V76: NO | W76: =IF(ISNUMBER(S76),(TODAY()-S76)/365.25,"") -> 0.37782341 | X76: Unknown
A77: Engen Kaalfontein | B77: 114070 | C77: 125 | D77: 0 | E77: N/A | F77: N/A | G77: N/A | H77: N/A | I77: South Africa | J77: Gauteng | K77: 3117 Angelfish St, Kaalfontein, Midrand, 1632 | L77: Eastron Meter | M77: PPA | N77: Retail | O77: Producing | S77: 46162 | T77: SA Energy | U77: IsolarCloud | V77: YES | W77: =IF(ISNUMBER(S77),(TODAY()-S77)/365.25,"") -> 0.24640657 | X77: High
A78: Alpine Heath Resort | B78: 217000 | C78: =2*110 -> 220 | D78: 0 | E78: N/A | F78: N/A | G78: N/A | H78: N/A | I78: South Africa | J78: KZN | K78: Busingatha, South Africa | L78: Eastron Meter | M78: PPA | N78: Residential | O78: Producing | Q78: 12B Fund | S78: 46140 | T78: SA Energy | U78: IsolarCloud | V78: YES | W78: =IF(ISNUMBER(S78),(TODAY()-S78)/365.25,"") -> 0.30663929 | X78: Low
A79: Checkers Lichtenburg | B79: 161000 | C79: 150 | D79: 0 | E79: N/A | F79: N/A | G79: N/A | H79: N/A | I79: South Africa | J79: North West | K79: 33 Nelson Mandela Dr, Lichtenburg, 2740 | L79: Eastron Meter | M79: PPA | N79: Retail | O79: Producing | Q79: SSI | T79: SA Energy | U79: IsolarCloud | V79: NO | W79: =IF(ISNUMBER(S79),(TODAY()-S79)/365.25,"") | X79: Unknown
A80: Shoprite SRH Bizana | B80: 148800 | C80: 150 | D80: 0 | E80: N/A | F80: N/A | G80: N/A | H80: N/A | I80: South Africa | J80: Eastern Cape | K80: 4VR3+G6F Mbizana | L80: Eastron Meter | M80: PPA | N80: Retail | O80: Producing | Q80: SSI | T80: SA Energy | U80: IsolarCloud | V80: NO | W80: =IF(ISNUMBER(S80),(TODAY()-S80)/365.25,"") | X80: Unknown
A81: Shoprite Mayfair | B81: 132680 | C81: 125 | D81: 0 | E81: N/A | F81: N/A | G81: N/A | H81: N/A | I81: South Africa | J81: Gauteng | K81: 1804 Albertina Sisulu Rd, Mayfair, Johannesburg, 2092 | L81: Eastron Meter | M81: PPA | N81: Retail | Q81: SSI | T81: SA Energy | U81: IsolarCloud | V81: NO | W81: =IF(ISNUMBER(S81),(TODAY()-S81)/365.25,"") | X81: Unknown
A82: Usave Naboomspruit | B82: 29760 | C82: 30 | D82: 0 | E82: N/A | F82: N/A | G82: N/A | H82: N/A | I82: South Africa | J82: Limpopo | K82: 76 Thabo Mbeki St, Mookgophong, 0560 | L82: Eastron Meter | M82: PPA | N82: Retail | Q82: SSI | S82: 46185 | T82: SA Energy | U82: IsolarCloud | V82: NO | W82: =IF(ISNUMBER(S82),(TODAY()-S82)/365.25,"") -> 0.183436 | X82: Unknown

Sheet Simulated Production
A1: Site Name | B1: Jan | C1: Feb | D1: Mar | E1: Apr | F1: May | G1: Jun | H1: Jul | I1: Aug | J1: Sep | K1: Oct | L1: Nov | M1: Dec
A2: 21 Melrose | B2: 2634 | C2: 2978 | D2: 2426 | E2: 2082 | F2: 2025 | G2: 1810 | H2: 2016 | I2: 2352 | J2: 2528 | K2: 2675 | L2: 2618 | M2: 2758
A3: African Global Plastics | B3: 26489.3 | C3: 23277.8 | D3: 23704 | E3: 19723.4 | F3: 18790.7 | G3: 16902.6 | H3: 18714.9 | I3: 21796.9 | J3: 24005.1 | K3: 26259.6 | L3: 26494.9 | M3: 27974.1
A4: Alpine Heath Residential | B4: 5335 | C4: 4782 | D4: 5051 | E4: 5133 | F4: 5545 | G4: 5291 | H4: 5201 | I4: 5833 | J4: 5216 | K4: 5258 | L4: 5358 | M4: 5339
A5: Bendstore Plaza Shops | B5: 19132 | C5: 16455 | D5: 18192 | E5: 17513 | F5: 16955 | G5: 15353 | H5: 16159 | I5: 18059 | J5: 18155 | K5: 17437 | L5: 17289 | M5: 19005
A6: Bendstore Spar | B6: 57016.372 | C6: 49003.656 | D6: 54154.745 | E6: 52055.443 | F6: 50303.593 | G6: 45493.302 | H6: 47903.114 | I6: 53629.448 | J6: 54003.213 | K6: 51943.234 | L6: 51542.757 | M6: 56267.013
A7: Beyerskloof | B7: 15319 | C7: 12622 | D7: 12090 | E7: 8698 | F7: 6615 | G7: 5740 | H7: 6183 | I7: 7734 | J7: 9940 | K7: 12572 | L7: 14126 | M7: 15421
A8: BP Parys | B8: 9057 | C8: 8039 | D8: 7862 | E8: 6394 | F8: 6027 | G8: 5319 | H8: 5956 | I8: 7070 | J8: 8021 | K8: 8710 | L8: =9102 -> 9102 | M8: 9142
A9: Buffalo Rock | B9: 2447 | C9: 2204 | D9: 2364 | E9: 1964 | F9: 1813 | G9: 1645 | H9: 1792 | I9: 1960 | J9: 2076 | K9: 2112 | L9: 2039 | M9: 2207
A10: Checkers De Aar | B10: 29655 | C10: 22972 | D10: 22328 | E10: 18096 | F10: 15021 | G10: 13183 | H10: 15099 | I10: 19010 | J10: 21674 | K10: 26757 | L10: 28766 | M10: 31103
A11: Checkers Silverlakes Gen | B11: 23450 | C11: 20245 | D11: 20409 | E11: 16782 | F11: 15700 | G11: 14022 | H11: 15558 | I11: 18491 | J11: 20696 | K11: 22782 | L11: 22890 | M11: 24472
A12: Checkers Silverlakes No Gen | B12: 23450 | C12: 20245 | D12: 20409 | E12: 16782 | F12: 15700 | G12: 14022 | H12: 15558 | I12: 18491 | J12: 20696 | K12: 22782 | L12: 22890 | M12: 24472
A13: Checkrite Inanda | B13: 9627 | C13: 9000 | D13: 8673 | E13: 7260 | F13: 6214 | G13: 5622 | H13: 5969 | I13: 7206 | J13: 7683 | K13: 8926 | L13: 8903 | M13: 9497
A14: Club Houghton | B14: 6408 | C14: 5365 | D14: 5459 | E14: 4611 | F14: 4375 | G14: 3848 | H14: 4305 | I14: 5067 | J14: 5593 | K14: 6237 | L14: 6347 | M14: 6697
A15: Coldstar International | B15: 5761.2 | C15: 5289.7 | D15: 5351.3 | E15: 4476.7 | F15: 4144.2 | G15: 3750.5 | H15: 4019 | I15: 4537.7 | J15: 4477.3 | K15: 4986.7 | L15: 5100.4 | M15: 5950.6
A16: Cultura Fresh | B16: 13109 | C16: 11411 | D16: 11746 | E16: 9262 | F16: 7471 | G16: 6511 | H16: 7170 | I16: 8324 | J16: 9849 | K16: 11513 | L16: 12192 | M16: 12923
A17: Demco | B17: 41895 | C17: 35971 | D17: 36483 | E17: 30848 | F17: 29226 | G17: 26233 | H17: 29069 | I17: 34133 | J17: 37890 | K17: 41280 | L17: 41518 | M17: 43833
A18: Engen Lotus Gardens | B18: 2735 | C18: 2556 | D18: 2535 | E18: 2442 | F18: 2474 | G18: 2756 | H18: 2611 | I18: 2800 | J18: 2707 | K18: 2695 | L18: 2618 | M18: 2708
A19: Giba Gorge Main | B19: 16980 | C19: 15556.6 | D19: 15927.6 | E19: 13677.3 | F19: 12351.6 | G19: 11543.6 | H19: 12195.1 | I19: 13528 | J19: 13644.6 | K19: 15166.4 | L19: 15407.487 | M19: 16842.372
A20: Giba Gorge Storage | B20: 15179.5 | C20: 13524.8 | D20: 13861.9 | E20: 11789.7 | F20: 10618.3 | G20: 9819.1 | H20: 10486.9 | I20: 11678.3 | J20: 11941.8 | K20: 13277 | L20: 13346.218 | M20: 14828.668
... A22: Golden Spot Shops | B22: 4020 | C22: 3616 | D22: 4009 | E22: 3292 | F22: 3026 | G22: 2735 | H22: 3002 | I22: 3304 | J22: 3497 | K22: 3533 | L22: 3348 | M22: 3560
A23: Grootpan
A24: HB Dunn | B24: 4706 | C24: 4110 | D24: 4209 | E24: 3538 | F24: 3392 | G24: 3058 | H24: 3366 | I24: 3941 | J24: 4346 | K24: 4559 | L24: 4578 | M24: 4864
A25: Helderberg Collage | B25: 44000.9 | C25: 36738.8 | D25: 35799.5 | E25: 26238.2 | F25: 19947.3 | G25: 16584 | H25: 18638.7 | I25: 23207.5 | J25: 29655.5 | K25: 36694.1 | L25: 41235.3 | M25: 44584.1
A26: Hilston Rotoflo | B26: 32657 | C26: 28530 | D26: 26894 | E26: 23945 | F26: 21446 | G26: 18974 | H26: 21123 | I26: 24633 | J26: 27402 | K26: 30501 | L26: 32028 | M26: 31475
A27: Huis Herfsblaar | B27: 33572 | C27: 29313 | D27: 30629 | E27: 26386 | F27: 25077 | G27: 22476 | H27: 24838 | I27: 29965 | J27: 32045 | K27: 33620 | L27: 32645 | M27: 34688
A28: IPID - Floor 4 | B28: 8415 | C28: 7237.5 | D28: 7601.5 | E28: 6870 | F28: 6583 | G28: 5884 | H28: 6428 | I28: 7317 | J28: 7798.5 | K28: 8310.5 | L28: 8392 | M28: 8239
A29: IPID - Floor 6 | B29: 8415 | C29: 7237.5 | D29: 7601.5 | E29: 6870 | F29: 6583 | G29: 5884 | H29: 6428 | I29: 7317 | J29: 7798.5 | K29: 8310.5 | L29: 8392 | M29: 8239
A30: Kool Village | B30: 13570 | C30: 11745 | D30: 11799 | E30: 10155 | F30: 9548 | G30: 8534 | H30: 9501 | I30: 11108 | J30: 11891 | K30: 13149 | L30: 13477 | M30: 14443
A31: Makalali
A32: Mambha Cash & Carry | B32: 24713 | C32: 21612 | D32: 21750 | E32: 17547 | F32: 14975 | G32: 13472 | H32: 14555 | I32: 17167 | J32: 18426 | K32: 21592 | L32: 22234 | M32: 24984
A33: Mathe Group Company | B33: 72121 | C33: 65458 | D33: 68264 | E33: 57584 | F33: 52130 | G33: 48157 | H33: 51738 | I33: 57201 | J33: 59213 | K33: 64977 | L33: 66569 | M33: 71854
A34: Mdluli | B34: 17634 | C34: 16473 | D34: 19238 | E34: 17065 | F34: 16886 | G34: 16099 | H34: 17101 | I34: 17348 | J34: 16879 | K34: 15944 | L34: 14731 | M34: 15377
A35: Medipost | B35: 59291 | C35: 48612 | D35: 45479 | E35: 32312 | F35: 23816 | G35: 19426 | H35: 21982 | I35: 28360 | J35: 37091 | K35: 47820 | L35: 55073 | M35: 60151
A36: Meredale Heights | B36: 5957 | C36: 5410 | D36: 5967 | E36: 5723 | F36: 6086 | G36: 5885 | H36: 6334 | I36: 6633 | J36: 6573 | K36: 6461 | L36: 6012 | M36: 6145
A37: Monument Park Checkers | B37: 44907 | C37: 37765 | D37: 39036 | E37: 33226 | F37: 31537 | G37: 28491 | H37: 31513 | I37: 36674 | J37: 40579 | K37: 44092 | L37: 44165 | M37: 47244
A38: Nkambeni Industrial | B38: 23544 | C38: 21677 | D38: 24212 | E38: 20861 | F38: 20012 | G38: 18485 | H38: 20016 | I38: 21052 | J38: 21403 | K38: 20962 | L38: 19856 | M38: 21184
A39: Olievenhoutbosch 1 | B39: 52080 | C39: 45544 | D39: 44433 | E39: 38648 | F39: 35710 | G39: 31508 | H39: 34699 | I39: 40906 | J39: 45309 | K39: 51347 | L39: 51837 | M39: 52952
A40: Olievenhoutbosch 2 | B40: 13744 | C40: 12002 | D40: 11708 | E40: 10193 | F40: 9448 | G40: 8384 | H40: 9230 | I40: 10801 | J40: 11951 | K40: 13545 | L40: 13626 | M40: 13933
A41: Opal Students | B41: 6317 | C41: 5312 | D41: 5484 | E41: 4844 | F41: 4660 | G41: 4243 | H41: 4686 | I41: 5383 | J41: 5889 | K41: 6297 | L41: 6249 | M41: 6662
A42: Orthochem Bethlehem | B42: 45787.2 | C42: 39973.5 | D42: 40622.2 | E42: 37337.9 | F42: 36620.7 | G42: 33353.579 | H42: 36066.455 | I42: 40562.362 | J42: 41523.189 | K42: 44647.762 | L42: 44811.707 | M42: 47334.92
A43: Plastiplate | B43: 11454.7 | C43: 9955.3 | D43: 10575.8 | E43: 9316.2 | F43: 9144.7 | G43: 8500.6 | H43: 9262.3 | I43: 10470.2 | J43: 11129.4 | K43: 11715.5 | L43: 11402.4 | M43: 12145.4
... A60: Shoprite Newlands | B60: 34135 | C60: 26981 | D60: 26829 | E60: 20433 | F60: 21068 | G60: 16978 | H60: 19291 | I60: 21448 | J60: 20157 | K60: 25054 | L60: 25471 | M60: 31547
A61: Shoprite Thokoza | B61: 20649 | C61: 17891 | D61: 17668 | E61: =15178 -> 15178 | F61: 14023 | G61: 12327 | H61: 13742 | I61: 16094 | J61: 17988 | K61: 20737 | L61: 20655 | M61: 21136
A62: Spring Glade | B62: 19574.9 | C62: 16723.6 | D62: 17808.6 | E62: 15502.2 | F62: 15075 | G62: 13622.2 | H62: 15167.7 | I62: 17455.2 | J62: 18819 | K62: 19760.2 | L62: 19368.5 | M62: 20469.3
A63: SR Morula TF 1 | B63: 10342 | C63: 8891 | D63: 8671 | E63: 7539 | F63: 6938 | G63: 6138 | H63: 6763 | I63: =(10/31)*7916 -> 2553.5484 | J63: 8738 | K63: 10008 | L63: 9999 | M63: 10268
A64: SR Morula TF 1 - Shoprite | B64: 31888.4 | C64: 27677 | D64: 27300 | E64: 23765 | F64: 21915 | G64: 19368 | H64: 21313 | I64: =(10/31)*24908 -> 8034.8387 | J64: 27534 | K64: 31253 | L64: 31179 | M64: 31893
A65: SR Morula TF 2 | B65: 10668.8 | C65: 9218.6 | D65: 9045 | E65: 7797 | F65: 7144.8 | G65: 6299.2 | H65: 6941.6 | I65: =(10/31)*8155.7 -> 2630.871 | J65: 9060 | K65: 10392 | L65: 10393 | M65: 10647
A66: Thakadu Industrial
A67: The Alec | B67: 8222 | C67: 6998 | D67: 7059 | E67: 5574 | F67: 5282 | G67: 4730 | H67: 5256 | I67: 6045 | J67: 7051 | K67: 8056 | L67: 8145 | M67: 8740
A68: Three Peaks | B68: 5698.8 | C68: 5080.8 | D68: 5209.7 | E68: 4357.5 | F68: 3906.6 | G68: 3553 | H68: 3801.5 | I68: 4316 | J68: 4437 | K68: 5034.3 | L68: 5106.1 | M68: 5754.2
A69: TPF Foods | B69: 5045.9 | C69: 4360.2 | D69: 4711.1 | E69: 4084.1 | F69: 4125.1 | G69: 3778.7 | H69: 4137.8 | I69: 4655.4 | J69: 4964.6 | K69: 5199.2 | L69: 4977 | M69: 5354.9
A70: Trouw Nutrition | B70: 15814.1 | C70: 14182.5 | D70: 15127.6 | E70: 13566.2 | F70: 13865.8 | G70: 12963.1 | H70: 14146.2 | I70: 15603.1 | J70: 15929.8 | K70: 16382.7 | L70: 15892.2 | M70: 16746.5
A71: U Save Botrivier | B71: 8111 | C71: 6915 | D71: 6721 | E71: 5701 | F71: 5135 | G71: 4368 | H71: 4517 | I71: 5248 | J71: 5835 | K71: 7211 | L71: 7571 | M71: 8107
A72: Watt Place Rotoflo | B72: 31142 | C72: 26504 | D72: 26827 | E72: 22270 | F72: 21135 | G72: 18949 | H72: 21000 | I72: 24518 | J72: 27252 | K72: 30285 | L72: 29971 | M72: 32254
A73: Zwartop Golf Course | B73: N/A | C73: N/A | D73: N/A | E73: N/A | F73: N/A | G73: N/A | H73: N/A | I73: N/A | J73: N/A | K73: N/A | L73: N/A | M73: N/A
A74: Shoprite Ekhaya | B74: 31534 | C74: 27088 | D74: 25946 | E74: 22097 | F74: 19717 | G74: 17225 | H74: 19287 | I74: 23158 | J74: 26490 | K74: 30317 | L74: 30935 | M74: 31977
A75: Grootpan | B75: 32305 | C75: 29685 | D75: 31046 | E75: 28456 | F75: 28669 | G75: 26032 | H75: 28480 | I75: 31722 | J75: 32846 | K75: 34908 | L75: 33468 | M75: 32717
A76: Roan Foods | B76: 20178 | C76: 17954 | D76: 19150 | E76: 18060 | F76: 18124 | G76: 15908 | H76: 16827 | I76: 19405 | J76: 19981 | K76: 22401 | L76: 20125 | M76: 20771
A77: Engen Kaalfontein | B77: 19301 | C77: 16753 | D77: 16260 | E77: 13800 | F77: 12669 | G77: 11099 | H77: 12207 | I77: 14565.3 | J77: 16481.3 | K77: 18948 | L77: 19155 | M77: 19406
A78: Checkers Lichtenburg | B78: 29390 | C78: 25795 | D78: 25594 | E78: 22145 | F78: 20838 | G78: 18631 | H78: 20290 | I78: 23679 | J78: 26288 | K78: 29851 | L78: 30171 | M78: 30447
A79: Alpine Heath Resort | B79: 32086 | C79: 28761 | D79: 30379 | E79: 30915 | F79: 33245 | G79: 31827 | H79: 31168 | I79: 35166 | J79: 31389 | K79: 31629 | L79: 32213 | M79: 32115
A80: Usave Naboomspruit | B80: 6637 | C80: 5857 | D80: 5923 | E80: 5363 | F80: 5166 | G80: 4726 | H80: 5161 | I80: 5838 | J80: 6186 | K80: 6701 | L80: 6553 | M80: 6655

Sheet OG
A1: Site Name | B1: Offtake Guarantee | C1: Expected Utilisation% | D1: Age | E1: As-Built kWh | F1: Guaranteed Generation (kWh) | G1: Unavailability kWh | H1: Correct kWh | I1: Actual Generation (kWh) | J1: Shortfall (kWh) | K1: Performance Rate | L1: Notes
A2: Alpine Heath Residential | B2: YES | C2: {=IFERROR(INDEX('Expected Production'!$B$2:$B$80,MATCH(TRIM($A2),INDEX(TRIM('Expected Production'!$A$2:$A$80),0),0)),"Not found")} -> 0.9 | D2: {=_xlfn.IFNA(_xlfn.XLOOKUP(TRIM(A2),TRIM(site_tech_info!$A$2:$A$79),site_tech_info!$W$2:$W$79),"")} -> 1.6262834 | E2: {=IFERROR(SUM(INDEX('Simulated Production'!$B$2:$M$80,MATCH(TRIM($A2),INDEX(TRIM('Simulated Production'!$A$2:$A$80),0),0),0)),"Not found")} -> 63342 | F2: =(Table2[[#This Row],[As-Built kWh]]*Table2[[#This Row],[Expected Utilisation%]])*(1-0.007)^(Table2[[#This Row],[Age]]) -> 56360.248 | G2: =(4681+4732*(9/31)+4546*(10/31)+4620*(3/30)+4991+4762)*(1-0.007)^(Table2[[#This Row],[Age]]) -> 17534.792 | H2: =F2-G2 -> 38825.456 | I2: {=SUMPRODUCT((TRIM(measured[Site Name])=TRIM($A2))*(measured[Date]>=DATE(2025,7,1))*(measured[Date]<=DATE(2026,6,30))*measured[Measured Value (kWh)])} -> 34917.2 | J2: =I2-H2 -> -3908.2562 | K2: =(Table2[[#This Row],[Actual Generation (kWh)]]/Table2[[#This Row],[Correct kWh]])*100 -> 89.933779 | L2: The system performed moderately. A few technical issues were experienced , the expected system production was corrected and system restored to normal production.
A3: Checkrite Inanda | B3: YES | C3: {=IFERROR(INDEX('Expected Production'!$B$2:$B$80,MATCH(TRIM($A3),INDEX(TRIM('Expected Production'!$A$2:$A$80),0),0)),"Not found")} -> 0.9 | D3: {=_xlfn.IFNA(_xlfn.XLOOKUP(TRIM(A3),TRIM(site_tech_info!$A$2:$A$79),site_tech_info!$W$2:$W$79),"")} -> 2.5571526 | E3: {=IFERROR(SUM(INDEX('Simulated Production'!$B$2:$M$80,MATCH(TRIM($A3),INDEX(TRIM('Simulated Production'!$A$2:$A$80),0),0),0)),"Not found")} -> 94580 | F3: =(Table2[[#This Row],[As-Built kWh]]*Table2[[#This Row],[Expected Utilisation%]])*(1-0.007)^(Table2[[#This Row],[Age]]) -> 83606.604 | G3: =(8100*(1/2)+7806*(1/2))*(1-0.007)^(Table2[[#This Row],[Age]]) -> 7811.4156 | H3: =F3-G3 -> 75795.188 | I3: {=SUMPRODUCT((TRIM(measured[Site Name])=TRIM($A3))*(measured[Date]>=DATE(2025,7,1))*(measured[Date]<=DATE(2026,6,30))*measured[Measured Value (kWh)])} -> 76046.756 | J3: =I3-H3 -> 251.56778 | K3: =(Table2[[#This Row],[Actual Generation (kWh)]]/Table2[[#This Row],[Correct kWh]])*100 -> 100.3319 | L3: The system performed as expected. A few technical issues were experienced during Feb 2026, the expected system production was corrected and system restored to normal production.
A4: Demco | B4: YES | C4: {=IFERROR(INDEX('Expected Production'!$B$2:$B$80,MATCH(TRIM($A4),INDEX(TRIM('Expected Production'!$A$2:$A$80),0),0)),"Not found")} -> 0.8 | D4: {=_xlfn.IFNA(_xlfn.XLOOKUP(TRIM(A4),TRIM(site_tech_info!$A$2:$A$79),site_tech_info!$W$2:$W$79),"")} -> 3.2991102 | E4: {=IFERROR(SUM(INDEX('Simulated Production'!$B$2:$M$80,MATCH(TRIM($A4),INDEX(TRIM('Simulated Production'!$A$2:$A$80),0),0),0)),"Not found")} -> 428379 | F4: =(Table2[[#This Row],[As-Built kWh]]*Table2[[#This Row],[Expected Utilisation%]])*(1-0.007)^(Table2[[#This Row],[Age]]) -> 334852.38 | G4: =(23255*(7/30)+35066*(2/30))*(1-0.007)^(Table2[[#This Row],[Age]]) -> 7586.0407 | H4: =F4-G4 -> 327266.34 | I4: {=SUMPRODUCT((TRIM(measured[Site Name])=TRIM($A4))*(measured[Date]>=DATE(2025,7,1))*(measured[Date]<=DATE(2026,6,30))*measured[Measured Value (kWh)])} -> 166060.42 | J4: =I4-H4 -> -161205.92 | K4: =(Table2[[#This Row],[Actual Generation (kWh)]]/Table2[[#This Row],[Correct kWh]])*100 -> 50.741674 | L4: The system performed as expected. As previously experienced, the site demand is low and the system was not fully utilized.
A5: Golden Spot Resort | B5: YES | C5: {=IFERROR(INDEX('Expected Production'!$B$2:$B$80,MATCH(TRIM($A5),INDEX(TRIM('Expected Production'!$A$2:$A$80),0),0)),"Not found")} -> 0.9 | D5: {=_xlfn.IFNA(_xlfn.XLOOKUP(TRIM(A5),TRIM(site_tech_info!$A$2:$A$79),site_tech_info!$W$2:$W$79),"")} -> 3.2306639 | E5: {=IFERROR(SUM(INDEX('Simulated Production'!$B$2:$M$80,MATCH(TRIM($A5),INDEX(TRIM('Simulated Production'!$A$2:$A$80),0),0),0)),"Not found")} -> 45617 | F5: =(Table2[[#This Row],[As-Built kWh]]*Table2[[#This Row],[Expected Utilisation%]])*(1-0.007)^(Table2[[#This Row],[Age]]) -> 40134.077 | G5: =(4681+3499*(9/31)+2081*(10/31)+4317*(3/30)+4991*(18/31))*(1-0.007)^(Table2[[#This Row],[Age]]) -> 9480.2234 | H5: =F5-G5 -> 30653.853 | I5: {=SUMPRODUCT((TRIM(measured[Site Name])=TRIM($A5))*(measured[Date]>=DATE(2025,7,1))*(measured[Date]<=DATE(2026,6,30))*measured[Measured Value (kWh)])} -> 24341.6 | J5: =I5-H5 -> -6312.2534 | K5: =(Table2[[#This Row],[Actual Generation (kWh)]]/Table2[[#This Row],[Correct kWh]])*100 -> 79.407961
A6: Golden Spot Shops | B6: YES | C6: {=IFERROR(INDEX('Expected Production'!$B$2:$B$80,MATCH(TRIM($A6),INDEX(TRIM('Expected Production'!$A$2:$A$80),0),0)),"Not found")} -> 0.9 | D6: {=_xlfn.IFNA(_xlfn.XLOOKUP(TRIM(A6),TRIM(site_tech_info!$A$2:$A$79),site_tech_info!$W$2:$W$79),"")} -> 3.2306639 | E6: {=IFERROR(SUM(INDEX('Simulated Production'!$B$2:$M$80,MATCH(TRIM($A6),INDEX(TRIM('Simulated Production'!$A$2:$A$80),0),0),0)),"Not found")} -> 40942 | F6: =(Table2[[#This Row],[As-Built kWh]]*Table2[[#This Row],[Expected Utilisation%]])*(1-0.007)^(Table2[[#This Row],[Age]]) -> 36020.987 | G6: =(2974*(24/31)+3147*(2/30))*(1-0.007)^(Table2[[#This Row],[Age]]) -> 2455.8802 | H6: =F6-G6 -> 33565.107 | I6: {=SUMPRODUCT((TRIM(measured[Site Name])=TRIM($A6))*(measured[Date]>=DATE(2025,7,1))*(measured[Date]<=DATE(2026,6,30))*measured[Measured Value (kWh)])} -> 32105.5 | J6: =I6-H6 -> -1459.6069 | K6: =(Table2[[#This Row],[Actual Generation (kWh)]]/Table2[[#This Row],[Correct kWh]])*100 -> 95.651416 | L6: Testing
A7: Hilston Rotoflo | B7: YES | C7: {=IFERROR(INDEX('Expected Production'!$B$2:$B$80,MATCH(TRIM($A7),INDEX(TRIM('Expected Production'!$A$2:$A$80),0),0)),"Not found")} -> 0.85 | D7: {=_xlfn.IFNA(_xlfn.XLOOKUP(TRIM(A7),TRIM(site_tech_info!$A$2:$A$79),site_tech_info!$W$2:$W$79),"")} -> 2.9486653 | E7: {=IFERROR(SUM(INDEX('Simulated Production'!$B$2:$M$80,MATCH(TRIM($A7),INDEX(TRIM('Simulated Production'!$A$2:$A$80),0),0),0)),"Not found")} -> 319608 | F7: =(Table2[[#This Row],[As-Built kWh]]*Table2[[#This Row],[Expected Utilisation%]])*(1-0.007)^(Table2[[#This Row],[Age]]) -> 266097.58 | G7: 0 | H7: =F7-G7 -> 266097.58 | I7: {=SUMPRODUCT((TRIM(measured[Site Name])=TRIM($A7))*(measured[Date]>=DATE(2025,7,1))*(measured[Date]<=DATE(2026,6,30))*measured[Measured Value (kWh)])} -> 254905.02 | J7: =I7-H7 -> -11192.558 | K7: =(Table2[[#This Row],[Actual Generation (kWh)]]/Table2[[#This Row],[Correct kWh]])*100 -> 95.793814 | L7: The system performed as expected. System produced 96% of expected production due to 20 days of closure during December-Jan.
A8: Huis Herfsblaar | B8: YES | C8: {=IFERROR(INDEX('Expected Production'!$B$2:$B$80,MATCH(TRIM($A8),INDEX(TRIM('Expected Production'!$A$2:$A$80),0),0)),"Not found")} -> 0.9 | D8: {=_xlfn.IFNA(_xlfn.XLOOKUP(TRIM(A8),TRIM(site_tech_info!$A$2:$A$79),site_tech_info!$W$2:$W$79),"")} -> 2.1601643 | E8: {=IFERROR(SUM(INDEX('Simulated Production'!$B$2:$M$80,MATCH(TRIM($A8),INDEX(TRIM('Simulated Production'!$A$2:$A$80),0),0),0)),"Not found")} -> 355254 | F8: =(Table2[[#This Row],[As-Built kWh]]*Table2[[#This Row],[Expected Utilisation%]])*(1-0.007)^(Table2[[#This Row],[Age]]) -> 314913.56 | G8: =((22354*(0.5)+26969*(7/31))*(1-0.007)^(Table2[[#This Row],[Age]]))*(1-0.007)^(Table2[[#This Row],[Age]]) -> 16750.623 | H8: =F8-G8 -> 298162.94 | I8: {=SUMPRODUCT((TRIM(measured[Site Name])=TRIM($A8))*(measured[Date]>=DATE(2025,7,1))*(measured[Date]<=DATE(2026,6,30))*measured[Measured Value (kWh)])} -> 271722.18 | J8: =I8-H8 -> -26440.758 | K8: =(Table2[[#This Row],[Actual Generation (kWh)]]/Table2[[#This Row],[Correct kWh]])*100 -> 91.132111 | L8: The system performed as expected. A few technical issues were experienced during July - Aug 2025, the expected system production was corrected and system restored to normal production.
A9: Mdluli | B9: YES | C9: {=IFERROR(INDEX('Expected Production'!$B$2:$B$80,MATCH(TRIM($A9),INDEX(TRIM('Expected Production'!$A$2:$A$80),0),0)),"Not found")} -> 0.8 | D9: {=_xlfn.IFNA(_xlfn.XLOOKUP(TRIM(A9),TRIM(site_tech_info!$A$2:$A$79),site_tech_info!$W$2:$W$79),"")} -> 2.4640657 | E9: {=IFERROR(SUM(INDEX('Simulated Production'!$B$2:$M$80,MATCH(TRIM($A9),INDEX(TRIM('Simulated Production'!$A$2:$A$80),0),0),0)),"Not found")} -> 200775 | F9: =(Table2[[#This Row],[As-Built kWh]]*Table2[[#This Row],[Expected Utilisation%]])*(1-0.007)^(Table2[[#This Row],[Age]]) -> 157863.73 | G9: =('Expected Production'!I34*0.5+'Expected Production'!C34*0.8)*(1-0.007)^(Table2[[#This Row],[Age]]) -> 17815.112 | H9: =F9-G9 -> 140048.62 | I9: {=SUMPRODUCT((TRIM(measured[Site Name])=TRIM($A9))*(measured[Date]>=DATE(2025,7,1))*(measured[Date]<=DATE(2026,6,30))*measured[Measured Value (kWh)])} -> 147166.31 | J9: =I9-H9 -> 7117.6886 | K9: =(Table2[[#This Row],[Actual Generation (kWh)]]/Table2[[#This Row],[Correct kWh]])*100 -> 105.0823 | L9: The system performed as expected. A few technical issues were experienced during July - Aug 2025 and Jan 2026 which limited inverter production during repairs, the expected system production was corrected and system restored to normal production.
A10: Meredale Heights | B10: YES | C10: {=IFERROR(INDEX('Expected Production'!$B$2:$B$80,MATCH(TRIM($A10),INDEX(TRIM('Expected Production'!$A$2:$A$80),0),0)),"Not found")} -> 0.9 | D10: {=_xlfn.IFNA(_xlfn.XLOOKUP(TRIM(A10),TRIM(site_tech_info!$A$2:$A$79),site_tech_info!$W$2:$W$79),"")} -> 3.5290897 | E10: {=IFERROR(SUM(INDEX('Simulated Production'!$B$2:$M$80,MATCH(TRIM($A10),INDEX(TRIM('Simulated Production'!$A$2:$A$80),0),0),0)),"Not found")} -> 73186 | F10: =(Table2[[#This Row],[As-Built kWh]]*Table2[[#This Row],[Expected Utilisation%]])*(1-0.007)^(Table2[[#This Row],[Age]]) -> 64254.588 | G10: 0 | H10: =F10-G10 -> 64254.588 | I10: {=SUMPRODUCT((TRIM(measured[Site Name])=TRIM($A10))*(measured[Date]>=DATE(2025,7,1))*(measured[Date]<=DATE(2026,6,30))*measured[Measured Value (kWh)])} -> 61467.39 | J10: =I10-H10 -> -2787.1983 | K10: =(Table2[[#This Row],[Actual Generation (kWh)]]/Table2[[#This Row],[Correct kWh]])*100 -> 95.662258 | L10: The system performed as expected. As previously experienced, the site demand is low and the system was not fully utilized.
A11: Opal Students | B11: YES | C11: {=IFERROR(INDEX('Expected Production'!$B$2:$B$80,MATCH(TRIM($A11),INDEX(TRIM('Expected Production'!$A$2:$A$80),0),0)),"Not found")} -> 0.9 | D11: {=_xlfn.IFNA(_xlfn.XLOOKUP(TRIM(A11),TRIM(site_tech_info!$A$2:$A$79),site_tech_info!$W$2:$W$79),"")} -> 2.9514031 | E11: {=IFERROR(SUM(INDEX('Simulated Production'!$B$2:$M$80,MATCH(TRIM($A11),INDEX(TRIM('Simulated Production'!$A$2:$A$80),0),0),0)),"Not found")} -> 66026 | F11: =(Table2[[#This Row],[As-Built kWh]]*Table2[[#This Row],[Expected Utilisation%]])*(1-0.007)^(Table2[[#This Row],[Age]]) -> 58204.089 | G11: 0 | H11: =F11-G11 -> 58204.089 | I11: {=SUMPRODUCT((TRIM(measured[Site Name])=TRIM($A11))*(measured[Date]>=DATE(2025,7,1))*(measured[Date]<=DATE(2026,6,30))*measured[Measured Value (kWh)])} -> 46668.7 | J11: =I11-H11 -> -11535.389 | K11: =(Table2[[#This Row],[Actual Generation (kWh)]]/Table2[[#This Row],[Correct kWh]])*100 -> 80.181136 | L11: Testing
A12: Plastiplate | B12: YES | C12: {=IFERROR(INDEX('Expected Production'!$B$2:$B$80,MATCH(TRIM($A12),INDEX(TRIM('Expected Production'!$A$2:$A$80),0),0)),"Not found")} -> 0.75 | D12: {=_xlfn.IFNA(_xlfn.XLOOKUP(TRIM(A12),TRIM(site_tech_info!$A$2:$A$79),site_tech_info!$W$2:$W$79),"")} -> 4.2819986 | E12: {=IFERROR(SUM(INDEX('Simulated Production'!$B$2:$M$80,MATCH(TRIM($A12),INDEX(TRIM('Simulated Production'!$A$2:$A$80),0),0),0)),"Not found")} -> 125072.5 | F12: =(Table2[[#This Row],[As-Built kWh]]*Table2[[#This Row],[Expected Utilisation%]])*(1-0.007)^(Table2[[#This Row],[Age]]) -> 91024.81 | G12: =(5691*0.3*(1-0.007)^(Table2[[#This Row],[Age]]))*(1-0.007)^(Table2[[#This Row],[Age]]) -> 1607.6193 | H12: =F12-G12 -> 89417.191 | I12: {=SUMPRODUCT((TRIM(measured[Site Name])=TRIM($A12))*(measured[Date]>=DATE(2025,7,1))*(measured[Date]<=DATE(2026,6,30))*measured[Measured Value (kWh)])} -> 72438 | J12: =I12-H12 -> -16979.191 | K12: =(Table2[[#This Row],[Actual Generation (kWh)]]/Table2[[#This Row],[Correct kWh]])*100 -> 81.011268 | L12: Testing
A13: Riverside Lodge | B13: YES | C13: {=IFERROR(INDEX('Expected Production'!$B$2:$B$80,MATCH(TRIM($A13),INDEX(TRIM('Expected Production'!$A$2:$A$80),0),0)),"Not found")} -> 0.85 | D13: {=_xlfn.IFNA(_xlfn.XLOOKUP(TRIM(A13),TRIM(site_tech_info!$A$2:$A$79),site_tech_info!$W$2:$W$79),"")} -> 2.7022587 | E13: {=IFERROR(SUM(INDEX('Simulated Production'!$B$2:$M$80,MATCH(TRIM($A13),INDEX(TRIM('Simulated Production'!$A$2:$A$80),0),0),0)),"Not found")} -> 225937 | F13: =(Table2[[#This Row],[As-Built kWh]]*Table2[[#This Row],[Expected Utilisation%]])*(1-0.007)^(Table2[[#This Row],[Age]]) -> 188435.34 | G13: 0 | H13: =F13-G13 -> 188435.34 | I13: {=SUMPRODUCT((TRIM(measured[Site Name])=TRIM($A13))*(measured[Date]>=DATE(2025,7,1))*(measured[Date]<=DATE(2026,6,30))*measured[Measured Value (kWh)])} -> 176720.45 | J13: =I13-H13 -> -11714.894 | K13: =(Table2[[#This Row],[Actual Generation (kWh)]]/Table2[[#This Row],[Correct kWh]])*100 -> 93.78307 | L13: Testing
A14: The Alec | B14: YES | C14: {=IFERROR(INDEX('Expected Production'!$B$2:$B$80,MATCH(TRIM($A14),INDEX(TRIM('Expected Production'!$A$2:$A$80),0),0)),"Not found")} -> 0.925 | D14: {=_xlfn.IFNA(_xlfn.XLOOKUP(TRIM(A14),TRIM(site_tech_info!$A$2:$A$79),site_tech_info!$W$2:$W$79),"")} -> 3.0800821 | E14: {=IFERROR(SUM(INDEX('Simulated Production'!$B$2:$M$80,MATCH(TRIM($A14),INDEX(TRIM('Simulated Production'!$A$2:$A$80),0),0),0)),"Not found")} -> 81158 | F14: =(Table2[[#This Row],[As-Built kWh]]*Table2[[#This Row],[Expected Utilisation%]])*(1-0.007)^(Table2[[#This Row],[Age]]) -> 73464.327 | G14: 0 | H14: =F14-G14 -> 73464.327 | I14: {=SUMPRODUCT((TRIM(measured[Site Name])=TRIM($A14))*(measured[Date]>=DATE(2025,7,1))*(measured[Date]<=DATE(2026,6,30))*measured[Measured Value (kWh)])} -> 56043.3 | J14: =I14-H14 -> -17421.027 | K14: =(Table2[[#This Row],[Actual Generation (kWh)]]/Table2[[#This Row],[Correct kWh]])*100 -> 76.286413 | L14: Testing
A15: Watt Place Rotoflo | B15: YES | C15: {=IFERROR(INDEX('Expected Production'!$B$2:$B$80,MATCH(TRIM($A15),INDEX(TRIM('Expected Production'!$A$2:$A$80),0),0)),"Not found")} -> 0.9 | D15: {=_xlfn.IFNA(_xlfn.XLOOKUP(TRIM(A15),TRIM(site_tech_info!$A$2:$A$79),site_tech_info!$W$2:$W$79),"")} -> 2.9486653 | E15: {=IFERROR(SUM(INDEX('Simulated Production'!$B$2:$M$80,MATCH(TRIM($A15),INDEX(TRIM('Simulated Production'!$A$2:$A$80),0),0),0)),"Not found")} -> 312107 | F15: =(Table2[[#This Row],[As-Built kWh]]*Table2[[#This Row],[Expected Utilisation%]])*(1-0.007)^(Table2[[#This Row],[Age]]) -> 275137.87 | G15: 0 | H15: =F15-G15 -> 275137.87 | I15: {=SUMPRODUCT((TRIM(measured[Site Name])=TRIM($A15))*(measured[Date]>=DATE(2025,7,1))*(measured[Date]<=DATE(2026,6,30))*measured[Measured Value (kWh)])} -> 237169.27 | J15: =I15-H15 -> -37968.602 | K15: =(Table2[[#This Row],[Actual Generation (kWh)]]/Table2[[#This Row],[Correct kWh]])*100 -> 86.200154 | L15: Testing
A16: SR Morula TF 1 | B16: YES | C16: {=IFERROR(INDEX('Expected Production'!$B$2:$B$80,MATCH(TRIM($A16),INDEX(TRIM('Expected Production'!$A$2:$A$80),0),0)),"Not found")} -> 0.9 | D16: {=_xlfn.IFNA(_xlfn.XLOOKUP(TRIM(A16),TRIM(site_tech_info!$A$2:$A$79),site_tech_info!$W$2:$W$79),"")} -> 2.9924709 | E16: {=IFERROR(SUM(INDEX('Simulated Production'!$B$2:$M$80,MATCH(TRIM($A16),INDEX(TRIM('Simulated Production'!$A$2:$A$80),0),0),0)),"Not found")} -> 96848.548 | F16: =(Table2[[#This Row],[As-Built kWh]]*Table2[[#This Row],[Expected Utilisation%]])*(1-0.007)^(Table2[[#This Row],[Age]]) -> 85350.553 | G16: =(6087*(1-0.007)^(Table2[[#This Row],[Age]]))*(1-0.007)^(Table2[[#This Row],[Age]]) -> 5836.3957 | H16: =F16-G16 -> 79514.157 | I16: {=SUMPRODUCT((TRIM(measured[Site Name])=TRIM($A16))*(measured[Date]>=DATE(2025,7,1))*(measured[Date]<=DATE(2026,6,30))*measured[Measured Value (kWh)])} -> 77775.48 | J16: =I16-H16 -> -1738.6774 | K16: =(Table2[[#This Row],[Actual Generation (kWh)]]/Table2[[#This Row],[Correct kWh]])*100 -> 97.813374 | L16: Testing
A17: SR Morula TF 2 | B17: YES | C17: {=IFERROR(INDEX('Expected Production'!$B$2:$B$80,MATCH(TRIM($A17),INDEX(TRIM('Expected Production'!$A$2:$A$80),0),0)),"Not found")} -> 0.9 | D17: {=_xlfn.IFNA(_xlfn.XLOOKUP(TRIM(A17),TRIM(site_tech_info!$A$2:$A$79),site_tech_info!$W$2:$W$79),"")} -> 2.9924709 | E17: {=IFERROR(SUM(INDEX('Simulated Production'!$B$2:$M$80,MATCH(TRIM($A17),INDEX(TRIM('Simulated Production'!$A$2:$A$80),0),0),0)),"Not found")} -> 100237.87 | F17: =(Table2[[#This Row],[As-Built kWh]]*Table2[[#This Row],[Expected Utilisation%]])*(1-0.007)^(Table2[[#This Row],[Age]]) -> 88337.491 | G17: =(6247*(1-0.007)^(Table2[[#This Row],[Age]]))*(1-0.007)^(Table2[[#This Row],[Age]]) -> 5989.8085 | H17: =F17-G17 -> 82347.682 | I17: {=SUMPRODUCT((TRIM(measured[Site Name])=TRIM($A17))*(measured[Date]>=DATE(2025,7,1))*(measured[Date]<=DATE(2026,6,30))*measured[Measured Value (kWh)])} -> 78264.64 | J17: =I17-H17 -> -4083.0421 | K17: =(Table2[[#This Row],[Actual Generation (kWh)]]/Table2[[#This Row],[Correct kWh]])*100 -> 95.041704 | L17: Testing
A18: Olievenhoutbosch 1 | B18: YES | C18: {=IFERROR(INDEX('Expected Production'!$B$2:$B$80,MATCH(TRIM($A18),INDEX(TRIM('Expected Production'!$A$2:$A$80),0),0)),"Not found")} -> 0.9 | D18: {=_xlfn.IFNA(_xlfn.XLOOKUP(TRIM(A18),TRIM(site_tech_info!$A$2:$A$79),site_tech_info!$W$2:$W$79),"")} -> 0.89801506 | E18: {=IFERROR(SUM(INDEX('Simulated Production'!$B$2:$M$80,MATCH(TRIM($A18),INDEX(TRIM('Simulated Production'!$A$2:$A$80),0),0),0)),"Not found")} -> 524973 | F18: =(Table2[[#This Row],[As-Built kWh]]*Table2[[#This Row],[Expected Utilisation%]])*(1-0.007)^(Table2[[#This Row],[Age]]) -> 469504.61 | G18: =(31229+36815+40778+47657*(5/30))*(1-0.007)^(Table2[[#This Row],[Age]]) -> 116030.57 | H18: =F18-G18 -> 353474.03 | I18: {=SUMPRODUCT((TRIM(measured[Site Name])=TRIM($A18))*(measured[Date]>=DATE(2025,7,1))*(measured[Date]<=DATE(2026,6,30))*measured[Measured Value (kWh)])} -> 300497.96 | J18: =I18-H18 -> -52976.075 | K18: =(Table2[[#This Row],[Actual Generation (kWh)]]/Table2[[#This Row],[Correct kWh]])*100 -> 85.012739 | L18: Testing
A19: Olievenhoutbosch 2 | B19: YES | C19: {=IFERROR(INDEX('Expected Production'!$B$2:$B$80,MATCH(TRIM($A19),INDEX(TRIM('Expected Production'!$A$2:$A$80),0),0)),"Not found")} -> 0.9 | D19: {=_xlfn.IFNA(_xlfn.XLOOKUP(TRIM(A19),TRIM(site_tech_info!$A$2:$A$79),site_tech_info!$W$2:$W$79),"")} -> 0.89801506 | E19: {=IFERROR(SUM(INDEX('Simulated Production'!$B$2:$M$80,MATCH(TRIM($A19),INDEX(TRIM('Simulated Production'!$A$2:$A$80),0),0),0)),"Not found")} -> 138565 | F19: =(Table2[[#This Row],[As-Built kWh]]*Table2[[#This Row],[Expected Utilisation%]])*(1-0.007)^(Table2[[#This Row],[Age]]) -> 123924.29 | G19: =(8307+9721+10756+12191*(5/30))*(1-0.007)^(Table2[[#This Row],[Age]]) -> 30622.052 | H19: =F19-G19 -> 93302.236 | I19: {=SUMPRODUCT((TRIM(measured[Site Name])=TRIM($A19))*(measured[Date]>=DATE(2025,7,1))*(measured[Date]<=DATE(2026,6,30))*measured[Measured Value (kWh)])} -> 81974.633 | J19: =I19-H19 -> -11327.603 | K19: =(Table2[[#This Row],[Actual Generation (kWh)]]/Table2[[#This Row],[Correct kWh]])*100 -> 87.859237 | L19: Testing
A20: IPID - Floor 6 | B20: YES | C20: {=IFERROR(INDEX('Expected Production'!$B$2:$B$80,MATCH(TRIM($A20),INDEX(TRIM('Expected Production'!$A$2:$A$80),0),0)),"Not found")} -> 0.9 | D20: {=_xlfn.IFNA(_xlfn.XLOOKUP(TRIM(A20),TRIM(site_tech_info!$A$2:$A$79),site_tech_info!$W$2:$W$79),"")} -> 0.87063655 | E20: {=IFERROR(SUM(INDEX('Simulated Production'!$B$2:$M$80,MATCH(TRIM($A20),INDEX(TRIM('Simulated Production'!$A$2:$A$80),0),0),0)),"Not found")} -> 89076 | F20: =(Table2[[#This Row],[As-Built kWh]]*Table2[[#This Row],[Expected Utilisation%]])*(1-0.007)^(Table2[[#This Row],[Age]]) -> 79679.595 | G20: =(5785+6585+7019+7479+7553+7553*(3/30))*(1-0.007)^(Table2[[#This Row],[Age]]) -> 34961.822 | H20: =F20-G20 -> 44717.773 | I20: {=SUMPRODUCT((TRIM(measured[Site Name])=TRIM($A20))*(measured[Date]>=DATE(2025,7,1))*(measured[Date]<=DATE(2026,6,30))*measured[Measured Value (kWh)])} -> 33061.7 | J20: =I20-H20 -> -11656.073 | K20: =(Table2[[#This Row],[Actual Generation (kWh)]]/Table2[[#This Row],[Correct kWh]])*100 -> 73.934138 | L20: Testing
A21: IPID - Floor 4 | B21: YES | C21: {=IFERROR(INDEX('Expected Production'!$B$2:$B$80,MATCH(TRIM($A21),INDEX(TRIM('Expected Production'!$A$2:$A$80),0),0)),"Not found")} -> 0.9 | D21: {=_xlfn.IFNA(_xlfn.XLOOKUP(TRIM(A21),TRIM(site_tech_info!$A$2:$A$79),site_tech_info!$W$2:$W$79),"")} -> 0.87063655 | E21: {=IFERROR(SUM(INDEX('Simulated Production'!$B$2:$M$80,MATCH(TRIM($A21),INDEX(TRIM('Simulated Production'!$A$2:$A$80),0),0),0)),"Not found")} -> 89076 | F21: =(Table2[[#This Row],[As-Built kWh]]*Table2[[#This Row],[Expected Utilisation%]])*(1-0.007)^(Table2[[#This Row],[Age]]) -> 79679.595 | G21: =(5785+6585+7019+7479+7553+7553*(3/30))*(1-0.007)^(Table2[[#This Row],[Age]]) -> 34961.822 | H21: =F21-G21 -> 44717.773 | I21: {=SUMPRODUCT((TRIM(measured[Site Name])=TRIM($A21))*(measured[Date]>=DATE(2025,7,1))*(measured[Date]<=DATE(2026,6,30))*measured[Measured Value (kWh)])} -> 47460.3 | J21: =I21-H21 -> 2742.5268 | K21: =(Table2[[#This Row],[Actual Generation (kWh)]]/Table2[[#This Row],[Correct kWh]])*100 -> 106.13297 | L21: Testing
A22: Engen Lotus Gardens | B22: YES | C22: {=IFERROR(INDEX('Expected Production'!$B$2:$B$80,MATCH(TRIM($A22),INDEX(TRIM('Expected Production'!$A$2:$A$80),0),0)),"Not found")} -> 0.9 | D22: {=_xlfn.IFNA(_xlfn.XLOOKUP(TRIM(A22),TRIM(site_tech_info!$A$2:$A$79),site_tech_info!$W$2:$W$79),"")} -> 0.82409309 | E22: {=IFERROR(SUM(INDEX('Simulated Production'!$B$2:$M$80,MATCH(TRIM($A22),INDEX(TRIM('Simulated Production'!$A$2:$A$80),0),0),0)),"Not found")} -> 31637 | F22: =(Table2[[#This Row],[As-Built kWh]]*Table2[[#This Row],[Expected Utilisation%]])*(1-0.007)^(Table2[[#This Row],[Age]]) -> 28308.946 | G22: =(2350+2520+2436+2426+2356+2437)*(1-0.007)^(Table2[[#This Row],[Age]]) -> 14441.159 | H22: =F22-G22 -> 13867.787 | I22: {=SUMPRODUCT((TRIM(measured[Site Name])=TRIM($A22))*(measured[Date]>=DATE(2025,7,1))*(measured[Date]<=DATE(2026,6,30))*measured[Measured Value (kWh)])} -> 17882.44 | J22: =I22-H22 -> 4014.6526 | K22: =(Table2[[#This Row],[Actual Generation (kWh)]]/Table2[[#This Row],[Correct kWh]])*100 -> 128.94948 | L22: Testing
A23: Engen Kaalfontein | B23: YES | C23: {=IFERROR(INDEX('Expected Production'!$B$2:$B$80,MATCH(TRIM($A23),INDEX(TRIM('Expected Production'!$A$2:$A$80),0),0)),"Not found")} -> 0.9 | D23: {=_xlfn.IFNA(_xlfn.XLOOKUP(TRIM(A23),TRIM(site_tech_info!$A$2:$A$79),site_tech_info!$W$2:$W$79),"")} -> 0.24640657 | E23: {=IFERROR(SUM(INDEX('Simulated Production'!$B$2:$M$80,MATCH(TRIM($A23),INDEX(TRIM('Simulated Production'!$A$2:$A$80),0),0),0)),"Not found")} -> 190644.6 | F23: =(Table2[[#This Row],[As-Built kWh]]*Table2[[#This Row],[Expected Utilisation%]])*(1-0.007)^(Table2[[#This Row],[Age]]) -> 171283.41 | G23: 171487.77 | H23: =F23-G23 -> -204.3611 | I23: {=SUMPRODUCT((TRIM(measured[Site Name])=TRIM($A23))*(measured[Date]>=DATE(2025,7,1))*(measured[Date]<=DATE(2026,6,30))*measured[Measured Value (kWh)])} -> 10169 | J23: =I23-H23 -> 10373.361 | K23: =(Table2[[#This Row],[Actual Generation (kWh)]]/Table2[[#This Row],[Correct kWh]])*100 -> -4975.9959 | L23: Testing
A24: Alpine Heath Resort | B24: YES | C24: {=IFERROR(INDEX('Expected Production'!$B$2:$B$80,MATCH(TRIM($A24),INDEX(TRIM('Expected Production'!$A$2:$A$80),0),0)),"Not found")} -> 0.9 | D24: {=_xlfn.IFNA(_xlfn.XLOOKUP(TRIM(A24),TRIM(site_tech_info!$A$2:$A$79),site_tech_info!$W$2:$W$79),"")} -> 0.30663929 | E24: {=IFERROR(SUM(INDEX('Simulated Production'!$B$2:$M$80,MATCH(TRIM($A24),INDEX(TRIM('Simulated Production'!$A$2:$A$80),0),0),0)),"Not found")} -> 380893 | F24: =(Table2[[#This Row],[As-Built kWh]]*Table2[[#This Row],[Expected Utilisation%]])*(1-0.007)^(Table2[[#This Row],[Age]]) -> 342066.09 | G24: =(28051+31649+28250+28466+28992+28904+28877+25885+27341+27824*(28/30))*(1-0.007)^(Table2[[#This Row],[Age]]) -> 281776.46 | H24: =F24-G24 -> 60289.628 | I24: {=SUMPRODUCT((TRIM(measured[Site Name])=TRIM($A24))*(measured[Date]>=DATE(2025,7,1))*(measured[Date]<=DATE(2026,6,30))*measured[Measured Value (kWh)])} -> 53212.2 | J24: =I24-H24 -> -7077.4281 | K24: =(Table2[[#This Row],[Actual Generation (kWh)]]/Table2[[#This Row],[Correct kWh]])*100 -> 88.260952 | L24: Testing

Sheet measured
A1: Site Name | B1: Date | C1: Measured Value (kWh)
A2: 21 Melrose | B2: 45292 | C2: 1815
A3: 21 Melrose | B3: 45323 | C3: 2295
A4: 21 Melrose | B4: 45352 | C4: 2474
A5: 21 Melrose | B5: 45383 | C5: 2136
A6: 21 Melrose | B6: 45413 | C6: 2212
A7: 21 Melrose | B7: 45444 | C7: 1863
A8: 21 Melrose | B8: 45474 | C8: 1943
A9: 21 Melrose | B9: 45505 | C9: 1710
A10: 21 Melrose | B10: 45536 | C10: 1579
A11: 21 Melrose | B11: 45566 | C11: 1593
A12: 21 Melrose | B12: 45597 | C12: 1794
A13: 21 Melrose | B13: 45627 | C13: 1794
... A32: 21 Melrose | B32: 46204 | C32: 1638
A33: 21 Melrose | B33: 46235
A34: 21 Melrose | B34: 46266
A35: 21 Melrose | B35: 46296
A36: 21 Melrose | B36: 46327
A37: 21 Melrose | B37: 46357
A38: African Global Plastics | B38: 45292 | C38: 23024
A39: African Global Plastics | B39: 45323 | C39: 23235
A40: African Global Plastics | B40: 45352 | C40: 23235
A41: African Global Plastics | B41: 45383 | C41: 19307
A42: African Global Plastics | B42: 45413 | C42: 18418
A43: African Global Plastics | B43: 45444 | C43: 15949
A44: African Global Plastics | B44: 45474 | C44: 17174
A45: African Global Plastics | B45: 45505 | C45: 13588
A46: African Global Plastics | B46: 45536 | C46: 20254
A47: African Global Plastics | B47: 45566 | C47: 27693
A48: African Global Plastics | B48: 45597 | C48: 24041
A49: African Global Plastics | B49: 45627 | C49: 25076
... A68: African Global Plastics | B68: 46204 | C68: 13136.53
A69: African Global Plastics | B69: 46235
A70: African Global Plastics | B70: 46266
A71: African Global Plastics | B71: 46296
A72: African Global Plastics | B72: 46327
A73: African Global Plastics | B73: 46357
A74: Alpine Heath Residential | B74: 45292
A75: Alpine Heath Residential | B75: 45323
A76: Alpine Heath Residential | B76: 45352
A77: Alpine Heath Residential | B77: 45383
A78: Alpine Heath Residential | B78: 45413
A79: Alpine Heath Residential | B79: 45444
A80: Alpine Heath Residential | B80: 45474
... A85: Alpine Heath Residential | B85: 45627
A86: Alpine Heath Residential | B86: 45658 | C86: 2400
A87: Alpine Heath Residential | B87: 45689 | C87: 3000
A88: Alpine Heath Residential | B88: 45717 | C88: 3144
A89: Alpine Heath Residential | B89: 45748 | C89: 2310
A90: Alpine Heath Residential | B90: 45778 | C90: 3866
A91: Alpine Heath Residential | B91: 45809 | C91: 3102
A92: Alpine Heath Residential | B92: 45839
A93: Alpine Heath Residential | B93: 45870 | C93: 4721
A94: Alpine Heath Residential | B94: 45901 | C94: 4200
A95: Alpine Heath Residential | B95: 45931 | C95: 3499
A96: Alpine Heath Residential | B96: 45962 | C96: 4045
A97: Alpine Heath Residential | B97: 45992 | C97: 4277
A98: Alpine Heath Residential | B98: 46023 | C98: 3071
A99: Alpine Heath Residential | B99: 46054 | C99: 3013
A100: Alpine Heath Residential | B100: 46082 | C100: 2340.8
A101: Alpine Heath Residential | B101: 46113 | C101: 1505.4
A102: Alpine Heath Residential | B102: 46143 | C102: 1467
A103: Alpine Heath Residential | B103: 46174 | C103: 2778
A104: Alpine Heath Residential | B104: 46204 | C104: 2644
A105: Alpine Heath Residential | B105: 46235
A106: Alpine Heath Residential | B106: 46266
A107: Alpine Heath Residential | B107: 46296
A108: Alpine Heath Residential | B108: 46327
A109: Alpine Heath Residential | B109: 46357
A110: BP Parys | B110: 45292
A111: BP Parys | B111: 45323
A112: BP Parys | B112: 45352
A113: BP Parys | B113: 45383
A114: BP Parys | B114: 45413
A115: BP Parys | B115: 45444
A116: BP Parys | B116: 45474
... A121: BP Parys | B121: 45627
A122: BP Parys | B122: 45658 | C122: 5900
A123: BP Parys | B123: 45689 | C123: 4277
A124: BP Parys | B124: 45717 | C124: 4770
A125: BP Parys | B125: 45748 | C125: 3375
A126: BP Parys | B126: 45778 | C126: 3507
A127: BP Parys | B127: 45809 | C127: 2400
A128: BP Parys | B128: 45839 | C128: 2169
A129: BP Parys | B129: 45870 | C129: 968.6
A130: BP Parys | B130: 45901 | C130: 2001.5
A131: BP Parys | B131: 45931 | C131: 3111
A132: BP Parys | B132: 45962 | C132: 1605
A133: BP Parys | B133: 45992
A134: BP Parys | B134: 46023
A135: BP Parys | B135: 46054 | C135: 6068
A136: BP Parys | B136: 46082 | C136: 4800
A137: BP Parys | B137: 46113 | C137: 4318
A138: BP Parys | B138: 46143 | C138: 3727.7
A139: BP Parys | B139: 46174 | C139: 3149
A140: Alpine Heath Resort | B140: 46204 | C140: 27942
A141: BP Parys | B141: 46235
A142: BP Parys | B142: 46266
A143: BP Parys | B143: 46296
A144: BP Parys | B144: 46327
...

Sheet Expected Production
A1: Site Name | B1: Expected Utilisation% | C1: Jan | D1: Feb | E1: Mar | F1: Apr | G1: May | H1: Jun | I1: Jul | J1: Aug | K1: Sep | L1: Oct | M1: Nov | N1: Dec
A2: 21 Melrose | B2: 0.9 | C2: =Table4[[#This Row],[Jan]]*$B2 -> 2370.6 | D2: =Table4[[#This Row],[Feb]]*$B2 -> 2680.2 | E2: =Table4[[#This Row],[Mar]]*$B2 -> 2183.4 | F2: =Table4[[#This Row],[Apr]]*$B2 -> 1873.8 | G2: =Table4[[#This Row],[May]]*$B2 -> 1822.5 | H2: =Table4[[#This Row],[Jun]]*$B2 -> 1629 | I2: =Table4[[#This Row],[Jul]]*$B2 -> 1814.4 | J2: =Table4[[#This Row],[Aug]]*$B2 -> 2116.8 | K2: =Table4[[#This Row],[Sep]]*$B2 -> 2275.2 | L2: =Table4[[#This Row],[Oct]]*$B2 -> 2407.5 | M2: =Table4[[#This Row],[Nov]]*$B2 -> 2356.2 | N2: =Table4[[#This Row],[Dec]]*$B2 -> 2482.2
A3: African Global Plastics | B3: 0.85 | C3: =Table4[[#This Row],[Jan]]*$B3 -> 22515.905 | D3: =Table4[[#This Row],[Feb]]*$B3 -> 19786.13 | E3: =Table4[[#This Row],[Mar]]*$B3 -> 20148.4 | F3: =Table4[[#This Row],[Apr]]*$B3 -> 16764.89 | G3: =Table4[[#This Row],[May]]*$B3 -> 15972.095 | H3: =Table4[[#This Row],[Jun]]*$B3 -> 14367.21 | I3: =Table4[[#This Row],[Jul]]*$B3 -> 15907.665 | J3: =Table4[[#This Row],[Aug]]*$B3 -> 18527.365 | K3: =Table4[[#This Row],[Sep]]*$B3 -> 20404.335 | L3: =Table4[[#This Row],[Oct]]*$B3 -> 22320.66 | M3: =Table4[[#This Row],[Nov]]*$B3 -> 22520.665 | N3: =Table4[[#This Row],[Dec]]*$B3 -> 23777.985
A4: Alpine Heath Residential | B4: 0.9 | C4: =Table4[[#This Row],[Jan]]*$B4 -> 4801.5 | D4: =Table4[[#This Row],[Feb]]*$B4 -> 4303.8 | E4: =Table4[[#This Row],[Mar]]*$B4 -> 4545.9 | F4: =Table4[[#This Row],[Apr]]*$B4 -> 4619.7 | G4: =Table4[[#This Row],[May]]*$B4 -> 4990.5 | H4: =Table4[[#This Row],[Jun]]*$B4 -> 4761.9 | I4: =Table4[[#This Row],[Jul]]*$B4 -> 4680.9 | J4: =Table4[[#This Row],[Aug]]*$B4 -> 5249.7 | K4: =Table4[[#This Row],[Sep]]*$B4 -> 4694.4 | L4: =Table4[[#This Row],[Oct]]*$B4 -> 4732.2 | M4: =Table4[[#This Row],[Nov]]*$B4 -> 4822.2 | N4: =Table4[[#This Row],[Dec]]*$B4 -> 4805.1
A5: Bendstore Plaza Shops | B5: 0.85 | C5: =Table4[[#This Row],[Jan]]*$B5 -> 16262.2 | D5: =Table4[[#This Row],[Feb]]*$B5 -> 13986.75 | E5: =Table4[[#This Row],[Mar]]*$B5 -> 15463.2 | F5: =Table4[[#This Row],[Apr]]*$B5 -> 14886.05 | G5: =Table4[[#This Row],[May]]*$B5 -> 14411.75 | H5: =Table4[[#This Row],[Jun]]*$B5 -> 13050.05 | I5: =Table4[[#This Row],[Jul]]*$B5 -> 13735.15 | J5: =Table4[[#This Row],[Aug]]*$B5 -> 15350.15 | K5: =Table4[[#This Row],[Sep]]*$B5 -> 15431.75 | L5: =Table4[[#This Row],[Oct]]*$B5 -> 14821.45 | M5: =Table4[[#This Row],[Nov]]*$B5 -> 14695.65 | N5: =Table4[[#This Row],[Dec]]*$B5 -> 16154.25
A6: Bendstore Spar | B6: 0.9 | C6: =Table4[[#This Row],[Jan]]*$B6 -> 51314.735 | D6: =Table4[[#This Row],[Feb]]*$B6 -> 44103.291 | E6: =Table4[[#This Row],[Mar]]*$B6 -> 48739.27 | F6: =Table4[[#This Row],[Apr]]*$B6 -> 46849.899 | G6: =Table4[[#This Row],[May]]*$B6 -> 45273.233 | H6: =Table4[[#This Row],[Jun]]*$B6 -> 40943.972 | I6: =Table4[[#This Row],[Jul]]*$B6 -> 43112.803 | J6: =Table4[[#This Row],[Aug]]*$B6 -> 48266.503 | K6: =Table4[[#This Row],[Sep]]*$B6 -> 48602.891 | L6: =Table4[[#This Row],[Oct]]*$B6 -> 46748.911 | M6: =Table4[[#This Row],[Nov]]*$B6 -> 46388.482 | N6: =Table4[[#This Row],[Dec]]*$B6 -> 50640.311
A7: Beyerskloof | B7: 0.9 | C7: =Table4[[#This Row],[Jan]]*$B7 -> 13787.1 | D7: =Table4[[#This Row],[Feb]]*$B7 -> 11359.8 | E7: =Table4[[#This Row],[Mar]]*$B7 -> 10881 | F7: =Table4[[#This Row],[Apr]]*$B7 -> 7828.2 | G7: =Table4[[#This Row],[May]]*$B7 -> 5953.5 | H7: =Table4[[#This Row],[Jun]]*$B7 -> 5166 | I7: =Table4[[#This Row],[Jul]]*$B7 -> 5564.7 | J7: =Table4[[#This Row],[Aug]]*$B7 -> 6960.6 | K7: =Table4[[#This Row],[Sep]]*$B7 -> 8946 | L7: =Table4[[#This Row],[Oct]]*$B7 -> 11314.8 | M7: =Table4[[#This Row],[Nov]]*$B7 -> 12713.4 | N7: =Table4[[#This Row],[Dec]]*$B7 -> 13878.9
A8: BP Parys | B8: 0.9 | C8: =Table4[[#This Row],[Jan]]*$B8 -> 8151.3 | D8: =Table4[[#This Row],[Feb]]*$B8 -> 7235.1 | E8: =Table4[[#This Row],[Mar]]*$B8 -> 7075.8 | F8: =Table4[[#This Row],[Apr]]*$B8 -> 5754.6 | G8: =Table4[[#This Row],[May]]*$B8 -> 5424.3 | H8: =Table4[[#This Row],[Jun]]*$B8 -> 4787.1 | I8: =Table4[[#This Row],[Jul]]*$B8 -> 5360.4 | J8: =Table4[[#This Row],[Aug]]*$B8 -> 6363 | K8: =Table4[[#This Row],[Sep]]*$B8 -> 7218.9 | L8: =Table4[[#This Row],[Oct]]*$B8 -> 7839 | M8: =Table4[[#This Row],[Nov]]*$B8 -> 8191.8 | N8: =Table4[[#This Row],[Dec]]*$B8 -> 8227.8
A9: Buffalo Rock | B9: 0.9 | C9: =Table4[[#This Row],[Jan]]*$B9 -> 2202.3 | D9: =Table4[[#This Row],[Feb]]*$B9 -> 1983.6 | E9: =Table4[[#This Row],[Mar]]*$B9 -> 2127.6 | F9: =Table4[[#This Row],[Apr]]*$B9 -> 1767.6 | G9: =Table4[[#This Row],[May]]*$B9 -> 1631.7 | H9: =Table4[[#This Row],[Jun]]*$B9 -> 1480.5 | I9: =Table4[[#This Row],[Jul]]*$B9 -> 1612.8 | J9: =Table4[[#This Row],[Aug]]*$B9 -> 1764 | K9: =Table4[[#This Row],[Sep]]*$B9 -> 1868.4 | L9: =Table4[[#This Row],[Oct]]*$B9 -> 1900.8 | M9: =Table4[[#This Row],[Nov]]*$B9 -> 1835.1 | N9: =Table4[[#This Row],[Dec]]*$B9 -> 1986.3
A10: Checkers De Aar | B10: 0.9 | C10: =Table4[[#This Row],[Jan]]*$B10 -> 26689.5 | D10: =Table4[[#This Row],[Feb]]*$B10 -> 20674.8 | E10: =Table4[[#This Row],[Mar]]*$B10 -> 20095.2 | F10: =Table4[[#This Row],[Apr]]*$B10 -> 16286.4 | G10: =Table4[[#This Row],[May]]*$B10 -> 13518.9 | H10: =Table4[[#This Row],[Jun]]*$B10 -> 11864.7 | I10: =Table4[[#This Row],[Jul]]*$B10 -> 13589.1 | J10: =Table4[[#This Row],[Aug]]*$B10 -> 17109 | K10: =Table4[[#This Row],[Sep]]*$B10 -> 19506.6 | L10: =Table4[[#This Row],[Oct]]*$B10 -> 24081.3 | M10: =Table4[[#This Row],[Nov]]*$B10 -> 25889.4 | N10: =Table4[[#This Row],[Dec]]*$B10 -> 27992.7
A11: Checkers Silverlakes Gen | B11: 0.9 | C11: =Table4[[#This Row],[Jan]]*$B11 -> 21105 | D11: =Table4[[#This Row],[Feb]]*$B11 -> 18220.5 | E11: =Table4[[#This Row],[Mar]]*$B11 -> 18368.1 | F11: =Table4[[#This Row],[Apr]]*$B11 -> 15103.8 | G11: =Table4[[#This Row],[May]]*$B11 -> 14130 | H11: =Table4[[#This Row],[Jun]]*$B11 -> 12619.8 | I11: =Table4[[#This Row],[Jul]]*$B11 -> 14002.2 | J11: =Table4[[#This Row],[Aug]]*$B11 -> 16641.9 | K11: =Table4[[#This Row],[Sep]]*$B11 -> 18626.4 | L11: =Table4[[#This Row],[Oct]]*$B11 -> 20503.8 | M11: =Table4[[#This Row],[Nov]]*$B11 -> 20601 | N11: =Table4[[#This Row],[Dec]]*$B11 -> 22024.8
A12: Checkers Silverlakes No Gen | B12: 0.9 | C12: =Table4[[#This Row],[Jan]]*$B12 -> 21105 | D12: =Table4[[#This Row],[Feb]]*$B12 -> 18220.5 | E12: =Table4[[#This Row],[Mar]]*$B12 -> 18368.1 | F12: =Table4[[#This Row],[Apr]]*$B12 -> 15103.8 | G12: =Table4[[#This Row],[May]]*$B12 -> 14130 | H12: =Table4[[#This Row],[Jun]]*$B12 -> 12619.8 | I12: =Table4[[#This Row],[Jul]]*$B12 -> 14002.2 | J12: =Table4[[#This Row],[Aug]]*$B12 -> 16641.9 | K12: =Table4[[#This Row],[Sep]]*$B12 -> 18626.4 | L12: =Table4[[#This Row],[Oct]]*$B12 -> 20503.8 | M12: =Table4[[#This Row],[Nov]]*$B12 -> 20601 | N12: =Table4[[#This Row],[Dec]]*$B12 -> 22024.8
A13: Checkrite Inanda | B13: 0.9 | C13: =Table4[[#This Row],[Jan]]*$B13 -> 8664.3 | D13: =Table4[[#This Row],[Feb]]*$B13 -> 8100 | E13: =Table4[[#This Row],[Mar]]*$B13 -> 7805.7 | F13: =Table4[[#This Row],[Apr]]*$B13 -> 6534 | G13: =Table4[[#This Row],[May]]*$B13 -> 5592.6 | H13: =Table4[[#This Row],[Jun]]*$B13 -> 5059.8 | I13: =Table4[[#This Row],[Jul]]*$B13 -> 5372.1 | J13: =Table4[[#This Row],[Aug]]*$B13 -> 6485.4 | K13: =Table4[[#This Row],[Sep]]*$B13 -> 6914.7 | L13: =Table4[[#This Row],[Oct]]*$B13 -> 8033.4 | M13: =Table4[[#This Row],[Nov]]*$B13 -> 8012.7 | N13: =Table4[[#This Row],[Dec]]*$B13 -> 8547.3
... A30: Kool Village | B30: 0.9 | C30: =Table4[[#This Row],[Jan]]*$B30 -> 12213 | D30: =Table4[[#This Row],[Feb]]*$B30 -> 10570.5 | E30: =Table4[[#This Row],[Mar]]*$B30 -> 10619.1 | F30: =Table4[[#This Row],[Apr]]*$B30 -> 9139.5 | G30: =Table4[[#This Row],[May]]*$B30 -> 8593.2 | H30: =Table4[[#This Row],[Jun]]*$B30 -> 7680.6 | I30: =Table4[[#This Row],[Jul]]*$B30 -> 8550.9 | J30: =Table4[[#This Row],[Aug]]*$B30 -> 9997.2 | K30: =Table4[[#This Row],[Sep]]*$B30 -> 10701.9 | L30: =Table4[[#This Row],[Oct]]*$B30 -> 11834.1 | M30: =Table4[[#This Row],[Nov]]*$B30 -> 12129.3 | N30: =Table4[[#This Row],[Dec]]*$B30 -> 12998.7
A31: Makalali | C31: =Table4[[#This Row],[Jan]]*$B31 -> 0 | D31: =Table4[[#This Row],[Feb]]*$B31 -> 0 | E31: =Table4[[#This Row],[Mar]]*$B31 -> 0 | F31: =Table4[[#This Row],[Apr]]*$B31 -> 0 | G31: =Table4[[#This Row],[May]]*$B31 -> 0 | H31: =Table4[[#This Row],[Jun]]*$B31 -> 0 | I31: =Table4[[#This Row],[Jul]]*$B31 -> 0 | J31: =Table4[[#This Row],[Aug]]*$B31 -> 0 | K31: =Table4[[#This Row],[Sep]]*$B31 -> 0 | L31: =Table4[[#This Row],[Oct]]*$B31 -> 0 | M31: =Table4[[#This Row],[Nov]]*$B31 -> 0 | N31: =Table4[[#This Row],[Dec]]*$B31 -> 0
A32: Mambha Cash & Carry | B32: 0.9 | C32: =Table4[[#This Row],[Jan]]*$B32 -> 22241.7 | D32: =Table4[[#This Row],[Feb]]*$B32 -> 19450.8 | E32: =Table4[[#This Row],[Mar]]*$B32 -> 19575 | F32: =Table4[[#This Row],[Apr]]*$B32 -> 15792.3 | G32: =Table4[[#This Row],[May]]*$B32 -> 13477.5 | H32: =Table4[[#This Row],[Jun]]*$B32 -> 12124.8 | I32: =Table4[[#This Row],[Jul]]*$B32 -> 13099.5 | J32: =Table4[[#This Row],[Aug]]*$B32 -> 15450.3 | K32: =Table4[[#This Row],[Sep]]*$B32 -> 16583.4 | L32: =Table4[[#This Row],[Oct]]*$B32 -> 19432.8 | M32: =Table4[[#This Row],[Nov]]*$B32 -> 20010.6 | N32: =Table4[[#This Row],[Dec]]*$B32 -> 22485.6
A33: Mathe Group Company | B33: 0.85 | C33: =Table4[[#This Row],[Jan]]*$B33 -> 61302.85 | D33: =Table4[[#This Row],[Feb]]*$B33 -> 55639.3 | E33: =Table4[[#This Row],[Mar]]*$B33 -> 58024.4 | F33: =Table4[[#This Row],[Apr]]*$B33 -> 48946.4 | G33: =Table4[[#This Row],[May]]*$B33 -> 44310.5 | H33: =Table4[[#This Row],[Jun]]*$B33 -> 40933.45 | I33: =Table4[[#This Row],[Jul]]*$B33 -> 43977.3 | J33: =Table4[[#This Row],[Aug]]*$B33 -> 48620.85 | K33: =Table4[[#This Row],[Sep]]*$B33 -> 50331.05 | L33: =Table4[[#This Row],[Oct]]*$B33 -> 55230.45 | M33: =Table4[[#This Row],[Nov]]*$B33 -> 56583.65 | N33: =Table4[[#This Row],[Dec]]*$B33 -> 61075.9
A34: Mdluli | B34: 0.8 | C34: =Table4[[#This Row],[Jan]]*$B34 -> 14107.2 | D34: =Table4[[#This Row],[Feb]]*$B34 -> 13178.4 | E34: =Table4[[#This Row],[Mar]]*$B34 -> 15390.4 | F34: =Table4[[#This Row],[Apr]]*$B34 -> 13652 | G34: =Table4[[#This Row],[May]]*$B34 -> 13508.8 | H34: =Table4[[#This Row],[Jun]]*$B34 -> 12879.2 | I34: =Table4[[#This Row],[Jul]]*$B34 -> 13680.8 | J34: =Table4[[#This Row],[Aug]]*$B34 -> 13878.4 | K34: =Table4[[#This Row],[Sep]]*$B34 -> 13503.2 | L34: =Table4[[#This Row],[Oct]]*$B34 -> 12755.2 | M34: =Table4[[#This Row],[Nov]]*$B34 -> 11784.8 | N34: =Table4[[#This Row],[Dec]]*$B34 -> 12301.6
A35: Medipost | B35: 0.9 | C35: =Table4[[#This Row],[Jan]]*$B35 -> 53361.9 | D35: =Table4[[#This Row],[Feb]]*$B35 -> 43750.8 | E35: =Table4[[#This Row],[Mar]]*$B35 -> 40931.1 | F35: =Table4[[#This Row],[Apr]]*$B35 -> 29080.8 | G35: =Table4[[#This Row],[May]]*$B35 -> 21434.4 | H35: =Table4[[#This Row],[Jun]]*$B35 -> 17483.4 | I35: =Table4[[#This Row],[Jul]]*$B35 -> 19783.8 | J35: =Table4[[#This Row],[Aug]]*$B35 -> 25524 | K35: =Table4[[#This Row],[Sep]]*$B35 -> 33381.9 | L35: =Table4[[#This Row],[Oct]]*$B35 -> 43038 | M35: =Table4[[#This Row],[Nov]]*$B35 -> 49565.7 | N35: =Table4[[#This Row],[Dec]]*$B35 -> 54135.9
A36: Meredale Heights | B36: 0.9 | C36: =Table4[[#This Row],[Jan]]*$B36 -> 5361.3 | D36: =Table4[[#This Row],[Feb]]*$B36 -> 4869 | E36: =Table4[[#This Row],[Mar]]*$B36 -> 5370.3 | F36: =Table4[[#This Row],[Apr]]*$B36 -> 5150.7 | G36: =Table4[[#This Row],[May]]*$B36 -> 5477.4 | H36: =Table4[[#This Row],[Jun]]*$B36 -> 5296.5 | I36: =Table4[[#This Row],[Jul]]*$B36 -> 5700.6 | J36: =Table4[[#This Row],[Aug]]*$B36 -> 5969.7 | K36: =Table4[[#This Row],[Sep]]*$B36 -> 5915.7 | L36: =Table4[[#This Row],[Oct]]*$B36 -> 5814.9 | M36: =Table4[[#This Row],[Nov]]*$B36 -> 5410.8 | N36: =Table4[[#This Row],[Dec]]*$B36 -> 5530.5
A37: Monument Park Checkers | B37: 0.9 | C37: =Table4[[#This Row],[Jan]]*$B37 -> 40416.3 | D37: =Table4[[#This Row],[Feb]]*$B37 -> 33988.5 | E37: =Table4[[#This Row],[Mar]]*$B37 -> 35132.4 | F37: =Table4[[#This Row],[Apr]]*$B37 -> 29903.4 | G37: =Table4[[#This Row],[May]]*$B37 -> 28383.3 | H37: =Table4[[#This Row],[Jun]]*$B37 -> 25641.9 | I37: =Table4[[#This Row],[Jul]]*$B37 -> 28361.7 | J37: =Table4[[#This Row],[Aug]]*$B37 -> 33006.6 | K37: =Table4[[#This Row],[Sep]]*$B37 -> 36521.1 | L37: =Table4[[#This Row],[Oct]]*$B37 -> 39682.8 | M37: =Table4[[#This Row],[Nov]]*$B37 -> 39748.5 | N37: =Table4[[#This Row],[Dec]]*$B37 -> 42519.6
A38: Nkambeni Industrial | B38: 1 | C38: =Table4[[#This Row],[Jan]]*$B38 -> 23544 | D38: =Table4[[#This Row],[Feb]]*$B38 -> 21677 | E38: =Table4[[#This Row],[Mar]]*$B38 -> 24212 | F38: =Table4[[#This Row],[Apr]]*$B38 -> 20861 | G38: =Table4[[#This Row],[May]]*$B38 -> 20012 | H38: =Table4[[#This Row],[Jun]]*$B38 -> 18485 | I38: =Table4[[#This Row],[Jul]]*$B38 -> 20016 | J38: =Table4[[#This Row],[Aug]]*$B38 -> 21052 | K38: =Table4[[#This Row],[Sep]]*$B38 -> 21403 | L38: =Table4[[#This Row],[Oct]]*$B38 -> 20962 | M38: =Table4[[#This Row],[Nov]]*$B38 -> 19856 | N38: =Table4[[#This Row],[Dec]]*$B38 -> 21184
A39: Olievenhoutbosch 1 | B39: 0.9 | C39: =Table4[[#This Row],[Jan]]*$B39 -> 46872 | D39: =Table4[[#This Row],[Feb]]*$B39 -> 40989.6 | E39: =Table4[[#This Row],[Mar]]*$B39 -> 39989.7 | F39: =Table4[[#This Row],[Apr]]*$B39 -> 34783.2 | G39: =Table4[[#This Row],[May]]*$B39 -> 32139 | H39: =Table4[[#This Row],[Jun]]*$B39 -> 28357.2 | I39: =Table4[[#This Row],[Jul]]*$B39 -> 31229.1 | J39: =Table4[[#This Row],[Aug]]*$B39 -> 36815.4 | K39: =Table4[[#This Row],[Sep]]*$B39 -> 40778.1 | L39: =Table4[[#This Row],[Oct]]*$B39 -> 46212.3 | M39: =Table4[[#This Row],[Nov]]*$B39 -> 46653.3 | N39: =Table4[[#This Row],[Dec]]*$B39 -> 47656.8
A40: Olievenhoutbosch 2 | B40: 0.9 | C40: =Table4[[#This Row],[Jan]]*$B40 -> 12369.6 | D40: =Table4[[#This Row],[Feb]]*$B40 -> 10801.8 | E40: =Table4[[#This Row],[Mar]]*$B40 -> 10537.2 | F40: =Table4[[#This Row],[Apr]]*$B40 -> 9173.7 | G40: =Table4[[#This Row],[May]]*$B40 -> 8503.2 | H40: =Table4[[#This Row],[Jun]]*$B40 -> 7545.6 | I40: =Table4[[#This Row],[Jul]]*$B40 -> 8307 | J40: =Table4[[#This Row],[Aug]]*$B40 -> 9720.9 | K40: =Table4[[#This Row],[Sep]]*$B40 -> 10755.9 | L40: =Table4[[#This Row],[Oct]]*$B40 -> 12190.5 | M40: =Table4[[#This Row],[Nov]]*$B40 -> 12263.4 | N40: =Table4[[#This Row],[Dec]]*$B40 -> 12539.7
A41: Opal Students | B41: 0.9 | C41: =Table4[[#This Row],[Jan]]*$B41 -> 5685.3 | D41: =Table4[[#This Row],[Feb]]*$B41 -> 4780.8 | E41: =Table4[[#This Row],[Mar]]*$B41 -> 4935.6 | F41: =Table4[[#This Row],[Apr]]*$B41 -> 4359.6 | G41: =Table4[[#This Row],[May]]*$B41 -> 4194 | H41: =Table4[[#This Row],[Jun]]*$B41 -> 3818.7 | I41: =Table4[[#This Row],[Jul]]*$B41 -> 4217.4 | J41: =Table4[[#This Row],[Aug]]*$B41 -> 4844.7 | K41: =Table4[[#This Row],[Sep]]*$B41 -> 5300.1 | L41: =Table4[[#This Row],[Oct]]*$B41 -> 5667.3 | M41: =Table4[[#This Row],[Nov]]*$B41 -> 5624.1 | N41: =Table4[[#This Row],[Dec]]*$B41 -> 5995.8
A42: Orthochem Bethlehem | B42: 0.9 | C42: =Table4[[#This Row],[Jan]]*$B42 -> 41208.48 | D42: =Table4[[#This Row],[Feb]]*$B42 -> 35976.15 | E42: =Table4[[#This Row],[Mar]]*$B42 -> 36559.98 | F42: =Table4[[#This Row],[Apr]]*$B42 -> 33604.11 | G42: =Table4[[#This Row],[May]]*$B42 -> 32958.63 | H42: =Table4[[#This Row],[Jun]]*$B42 -> 30018.221 | I42: =Table4[[#This Row],[Jul]]*$B42 -> 32459.81 | J42: =Table4[[#This Row],[Aug]]*$B42 -> 36506.126 | K42: =Table4[[#This Row],[Sep]]*$B42 -> 37370.87 | L42: =Table4[[#This Row],[Oct]]*$B42 -> 40182.986 | M42: =Table4[[#This Row],[Nov]]*$B42 -> 40330.536 | N42: =Table4[[#This Row],[Dec]]*$B42 -> 42601.428
A43: Plastiplate | B43: 0.75 | C43: =Table4[[#This Row],[Jan]]*$B43 -> 8591.025 | D43: =Table4[[#This Row],[Feb]]*$B43 -> 7466.475 | E43: =Table4[[#This Row],[Mar]]*$B43 -> 7931.85 | F43: =Table4[[#This Row],[Apr]]*$B43 -> 6987.15 | G43: =Table4[[#This Row],[May]]*$B43 -> 6858.525 | H43: =Table4[[#This Row],[Jun]]*$B43 -> 6375.45 | I43: =Table4[[#This Row],[Jul]]*$B43 -> 6946.725 | J43: =Table4[[#This Row],[Aug]]*$B43 -> 7852.65 | K43: =Table4[[#This Row],[Sep]]*$B43 -> 8347.05 | L43: =Table4[[#This Row],[Oct]]*$B43 -> 8786.625 | M43: =Table4[[#This Row],[Nov]]*$B43 -> 8551.8 | N43: =Table4[[#This Row],[Dec]]*$B43 -> 9109.05
... A65: SR Morula TF 2 | B65: 0.9 | C65: =Table4[[#This Row],[Jan]]*$B65 -> 9601.92 | D65: =Table4[[#This Row],[Feb]]*$B65 -> 8296.74 | E65: =Table4[[#This Row],[Mar]]*$B65 -> 8140.5 | F65: =Table4[[#This Row],[Apr]]*$B65 -> 7017.3 | G65: =Table4[[#This Row],[May]]*$B65 -> 6430.32 | H65: =Table4[[#This Row],[Jun]]*$B65 -> 5669.28 | I65: =Table4[[#This Row],[Jul]]*$B65 -> 6247.44 | J65: =Table4[[#This Row],[Aug]]*$B65 -> 2367.7839 | K65: =Table4[[#This Row],[Sep]]*$B65 -> 8154 | L65: =Table4[[#This Row],[Oct]]*$B65 -> 9352.8 | M65: =Table4[[#This Row],[Nov]]*$B65 -> 9353.7 | N65: =Table4[[#This Row],[Dec]]*$B65 -> 9582.3
A66: Thakadu Industrial | C66: =Table4[[#This Row],[Jan]]*$B66 -> 0 | D66: =Table4[[#This Row],[Feb]]*$B66 -> 0 | E66: =Table4[[#This Row],[Mar]]*$B66 -> 0 | F66: =Table4[[#This Row],[Apr]]*$B66 -> 0 | G66: =Table4[[#This Row],[May]]*$B66 -> 0 | H66: =Table4[[#This Row],[Jun]]*$B66 -> 0 | I66: =Table4[[#This Row],[Jul]]*$B66 -> 0 | J66: =Table4[[#This Row],[Aug]]*$B66 -> 0 | K66: =Table4[[#This Row],[Sep]]*$B66 -> 0 | L66: =Table4[[#This Row],[Oct]]*$B66 -> 0 | M66: =Table4[[#This Row],[Nov]]*$B66 -> 0 | N66: =Table4[[#This Row],[Dec]]*$B66 -> 0
A67: The Alec | B67: 0.925 | C67: =Table4[[#This Row],[Jan]]*$B67 -> 7605.35 | D67: =Table4[[#This Row],[Feb]]*$B67 -> 6473.15 | E67: =Table4[[#This Row],[Mar]]*$B67 -> 6529.575 | F67: =Table4[[#This Row],[Apr]]*$B67 -> 5155.95 | G67: =Table4[[#This Row],[May]]*$B67 -> 4885.85 | H67: =Table4[[#This Row],[Jun]]*$B67 -> 4375.25 | I67: =Table4[[#This Row],[Jul]]*$B67 -> 4861.8 | J67: =Table4[[#This Row],[Aug]]*$B67 -> 5591.625 | K67: =Table4[[#This Row],[Sep]]*$B67 -> 6522.175 | L67: =Table4[[#This Row],[Oct]]*$B67 -> 7451.8 | M67: =Table4[[#This Row],[Nov]]*$B67 -> 7534.125 | N67: =Table4[[#This Row],[Dec]]*$B67 -> 8084.5
A68: Three Peaks | B68: 0.75 | C68: =Table4[[#This Row],[Jan]]*$B68 -> 4274.1 | D68: =Table4[[#This Row],[Feb]]*$B68 -> 3810.6 | E68: =Table4[[#This Row],[Mar]]*$B68 -> 3907.275 | F68: =Table4[[#This Row],[Apr]]*$B68 -> 3268.125 | G68: =Table4[[#This Row],[May]]*$B68 -> 2929.95 | H68: =Table4[[#This Row],[Jun]]*$B68 -> 2664.75 | I68: =Table4[[#This Row],[Jul]]*$B68 -> 2851.125 | J68: =Table4[[#This Row],[Aug]]*$B68 -> 3237 | K68: =Table4[[#This Row],[Sep]]*$B68 -> 3327.75 | L68: =Table4[[#This Row],[Oct]]*$B68 -> 3775.725 | M68: =Table4[[#This Row],[Nov]]*$B68 -> 3829.575 | N68: =Table4[[#This Row],[Dec]]*$B68 -> 4315.65
A69: TPF Foods | B69: 0.75 | C69: =Table4[[#This Row],[Jan]]*$B69 -> 3784.425 | D69: =Table4[[#This Row],[Feb]]*$B69 -> 3270.15 | E69: =Table4[[#This Row],[Mar]]*$B69 -> 3533.325 | F69: =Table4[[#This Row],[Apr]]*$B69 -> 3063.075 | G69: =Table4[[#This Row],[May]]*$B69 -> 3093.825 | H69: =Table4[[#This Row],[Jun]]*$B69 -> 2834.025 | I69: =Table4[[#This Row],[Jul]]*$B69 -> 3103.35 | J69: =Table4[[#This Row],[Aug]]*$B69 -> 3491.55 | K69: =Table4[[#This Row],[Sep]]*$B69 -> 3723.45 | L69: =Table4[[#This Row],[Oct]]*$B69 -> 3899.4 | M69: =Table4[[#This Row],[Nov]]*$B69 -> 3732.75 | N69: =Table4[[#This Row],[Dec]]*$B69 -> 4016.175
A70: Trouw Nutrition | B70: 0.85 | C70: =Table4[[#This Row],[Jan]]*$B70 -> 13441.985 | D70: =Table4[[#This Row],[Feb]]*$B70 -> 12055.125 | E70: =Table4[[#This Row],[Mar]]*$B70 -> 12858.46 | F70: =Table4[[#This Row],[Apr]]*$B70 -> 11531.27 | G70: =Table4[[#This Row],[May]]*$B70 -> 11785.93 | H70: =Table4[[#This Row],[Jun]]*$B70 -> 11018.635 | I70: =Table4[[#This Row],[Jul]]*$B70 -> 12024.27 | J70: =Table4[[#This Row],[Aug]]*$B70 -> 13262.635 | K70: =Table4[[#This Row],[Sep]]*$B70 -> 13540.33 | L70: =Table4[[#This Row],[Oct]]*$B70 -> 13925.295 | M70: =Table4[[#This Row],[Nov]]*$B70 -> 13508.37 | N70: =Table4[[#This Row],[Dec]]*$B70 -> 14234.525
A71: U Save Botrivier | B71: 0.9 | C71: =Table4[[#This Row],[Jan]]*$B71 -> 7299.9 | D71: =Table4[[#This Row],[Feb]]*$B71 -> 6223.5 | E71: =Table4[[#This Row],[Mar]]*$B71 -> 6048.9 | F71: =Table4[[#This Row],[Apr]]*$B71 -> 5130.9 | G71: =Table4[[#This Row],[May]]*$B71 -> 4621.5 | H71: =Table4[[#This Row],[Jun]]*$B71 -> 3931.2 | I71: =Table4[[#This Row],[Jul]]*$B71 -> 4065.3 | J71: =Table4[[#This Row],[Aug]]*$B71 -> 4723.2 | K71: =Table4[[#This Row],[Sep]]*$B71 -> 5251.5 | L71: =Table4[[#This Row],[Oct]]*$B71 -> 6489.9 | M71: =Table4[[#This Row],[Nov]]*$B71 -> 6813.9 | N71: =Table4[[#This Row],[Dec]]*$B71 -> 7296.3
A72: Watt Place Rotoflo | B72: 0.9 | C72: =Table4[[#This Row],[Jan]]*$B72 -> 28027.8 | D72: =Table4[[#This Row],[Feb]]*$B72 -> 23853.6 | E72: =Table4[[#This Row],[Mar]]*$B72 -> 24144.3 | F72: =Table4[[#This Row],[Apr]]*$B72 -> 20043 | G72: =Table4[[#This Row],[May]]*$B72 -> 19021.5 | H72: =Table4[[#This Row],[Jun]]*$B72 -> 17054.1 | I72: =Table4[[#This Row],[Jul]]*$B72 -> 18900 | J72: =Table4[[#This Row],[Aug]]*$B72 -> 22066.2 | K72: =Table4[[#This Row],[Sep]]*$B72 -> 24526.8 | L72: =Table4[[#This Row],[Oct]]*$B72 -> 27256.5 | M72: =Table4[[#This Row],[Nov]]*$B72 -> 26973.9 | N72: =Table4[[#This Row],[Dec]]*$B72 -> 29028.6
A73: Zwartop Golf Course | B73: 0.9 | C73: =Table4[[#This Row],[Jan]]*$B73 -> #VALUE! | D73: =Table4[[#This Row],[Feb]]*$B73 -> #VALUE! | E73: =Table4[[#This Row],[Mar]]*$B73 -> #VALUE! | F73: =Table4[[#This Row],[Apr]]*$B73 -> #VALUE! | G73: =Table4[[#This Row],[May]]*$B73 -> #VALUE! | H73: =Table4[[#This Row],[Jun]]*$B73 -> #VALUE! | I73: =Table4[[#This Row],[Jul]]*$B73 -> #VALUE! | J73: =Table4[[#This Row],[Aug]]*$B73 -> #VALUE! | K73: =Table4[[#This Row],[Sep]]*$B73 -> #VALUE! | L73: =Table4[[#This Row],[Oct]]*$B73 -> #VALUE! | M73: =Table4[[#This Row],[Nov]]*$B73 -> #VALUE! | N73: =Table4[[#This Row],[Dec]]*$B73 -> #VALUE!
A74: Shoprite Ekhaya | B74: 0.9 | C74: =Table4[[#This Row],[Jan]]*$B74 -> 28380.6 | D74: =Table4[[#This Row],[Feb]]*$B74 -> 24379.2 | E74: =Table4[[#This Row],[Mar]]*$B74 -> 23351.4 | F74: =Table4[[#This Row],[Apr]]*$B74 -> 19887.3 | G74: =Table4[[#This Row],[May]]*$B74 -> 17745.3 | H74: =Table4[[#This Row],[Jun]]*$B74 -> 15502.5 | I74: =Table4[[#This Row],[Jul]]*$B74 -> 17358.3 | J74: =Table4[[#This Row],[Aug]]*$B74 -> 20842.2 | K74: =Table4[[#This Row],[Sep]]*$B74 -> 23841 | L74: =Table4[[#This Row],[Oct]]*$B74 -> 27285.3 | M74: =Table4[[#This Row],[Nov]]*$B74 -> 27841.5 | N74: =Table4[[#This Row],[Dec]]*$B74 -> 28779.3
A75: Grootpan | B75: 0.9 | C75: =Table4[[#This Row],[Jan]]*$B75 -> 29074.5 | D75: =Table4[[#This Row],[Feb]]*$B75 -> 26716.5 | E75: =Table4[[#This Row],[Mar]]*$B75 -> 27941.4 | F75: =Table4[[#This Row],[Apr]]*$B75 -> 25610.4 | G75: =Table4[[#This Row],[May]]*$B75 -> 25802.1 | H75: =Table4[[#This Row],[Jun]]*$B75 -> 23428.8 | I75: =Table4[[#This Row],[Jul]]*$B75 -> 25632 | J75: =Table4[[#This Row],[Aug]]*$B75 -> 28549.8 | K75: =Table4[[#This Row],[Sep]]*$B75 -> 29561.4 | L75: =Table4[[#This Row],[Oct]]*$B75 -> 31417.2 | M75: =Table4[[#This Row],[Nov]]*$B75 -> 30121.2 | N75: =Table4[[#This Row],[Dec]]*$B75 -> 29445.3
A76: Roan Foods | B76: 1 | C76: =Table4[[#This Row],[Jan]]*$B76 -> 20178 | D76: =Table4[[#This Row],[Feb]]*$B76 -> 17954 | E76: =Table4[[#This Row],[Mar]]*$B76 -> 19150 | F76: =Table4[[#This Row],[Apr]]*$B76 -> 18060 | G76: =Table4[[#This Row],[May]]*$B76 -> 18124 | H76: =Table4[[#This Row],[Jun]]*$B76 -> 15908 | I76: =Table4[[#This Row],[Jul]]*$B76 -> 16827 | J76: =Table4[[#This Row],[Aug]]*$B76 -> 19405 | K76: =Table4[[#This Row],[Sep]]*$B76 -> 19981 | L76: =Table4[[#This Row],[Oct]]*$B76 -> 22401 | M76: =Table4[[#This Row],[Nov]]*$B76 -> 20125 | N76: =Table4[[#This Row],[Dec]]*$B76 -> 20771
A77: Engen Kaalfontein | B77: 0.9 | C77: =Table4[[#This Row],[Jan]]*$B77 -> 17370.9 | D77: =Table4[[#This Row],[Feb]]*$B77 -> 15077.7 | E77: =Table4[[#This Row],[Mar]]*$B77 -> 14634 | F77: =Table4[[#This Row],[Apr]]*$B77 -> 12420 | G77: =Table4[[#This Row],[May]]*$B77 -> 11402.1 | H77: =Table4[[#This Row],[Jun]]*$B77 -> 9989.1 | I77: =Table4[[#This Row],[Jul]]*$B77 -> 10986.3 | J77: =Table4[[#This Row],[Aug]]*$B77 -> 13108.77 | K77: =Table4[[#This Row],[Sep]]*$B77 -> 14833.17 | L77: =Table4[[#This Row],[Oct]]*$B77 -> 17053.2 | M77: =Table4[[#This Row],[Nov]]*$B77 -> 17239.5 | N77: =Table4[[#This Row],[Dec]]*$B77 -> 17465.4
A78: Checkers Lichtenburg | B78: 0.9 | C78: =Table4[[#This Row],[Jan]]*$B78 -> 26451 | D78: =Table4[[#This Row],[Feb]]*$B78 -> 23215.5 | E78: =Table4[[#This Row],[Mar]]*$B78 -> 23034.6 | F78: =Table4[[#This Row],[Apr]]*$B78 -> 19930.5 | G78: =Table4[[#This Row],[May]]*$B78 -> 18754.2 | H78: =Table4[[#This Row],[Jun]]*$B78 -> 16767.9 | I78: =Table4[[#This Row],[Jul]]*$B78 -> 18261 | J78: =Table4[[#This Row],[Aug]]*$B78 -> 21311.1 | K78: =Table4[[#This Row],[Sep]]*$B78 -> 23659.2 | L78: =Table4[[#This Row],[Oct]]*$B78 -> 26865.9 | M78: =Table4[[#This Row],[Nov]]*$B78 -> 27153.9 | N78: =Table4[[#This Row],[Dec]]*$B78 -> 27402.3
... A80: Usave Naboomspruit | B80: 0.9 | C80: =Table4[[#This Row],[Jan]]*$B80 -> 5973.3 | D80: =Table4[[#This Row],[Feb]]*$B80 -> 5271.3 | E80: =Table4[[#This Row],[Mar]]*$B80 -> 5330.7 | F80: =Table4[[#This Row],[Apr]]*$B80 -> 4826.7 | G80: =Table4[[#This Row],[May]]*$B80 -> 4649.4 | H80: =Table4[[#This Row],[Jun]]*$B80 -> 4253.4 | I80: =Table4[[#This Row],[Jul]]*$B80 -> 4644.9 | J80: =Table4[[#This Row],[Aug]]*$B80 -> 5254.2 | K80: =Table4[[#This Row],[Sep]]*$B80 -> 5567.4 | L80: =Table4[[#This Row],[Oct]]*$B80 -> 6030.9 | M80: =Table4[[#This Row],[Nov]]*$B80 -> 5897.7 | N80: =Table4[[#This Row],[Dec]]*$B80 -> 5989.5

Sheet expected_production
A1: Site Name | B1: Date | C1: Expected Production (kWh)
A2: 21 Melrose | B2: 45292 | C2: 2370.6
A3: 21 Melrose | B3: 45323 | C3: 2680.2
A4: 21 Melrose | B4: 45352 | C4: 2183.4
A5: 21 Melrose | B5: 45383 | C5: 1873.8
A6: 21 Melrose | B6: 45413 | C6: 1822.5
A7: 21 Melrose | B7: 45444 | C7: 1629
A8: 21 Melrose | B8: 45474 | C8: 1814.4
A9: 21 Melrose | B9: 45505 | C9: 2116.8
A10: 21 Melrose | B10: 45536 | C10: 2275.2
A11: 21 Melrose | B11: 45566 | C11: 2407.5
A12: 21 Melrose | B12: 45597 | C12: 2356.2
A13: 21 Melrose | B13: 45627 | C13: 2482.2
... A2665: Watt Place Rotoflo | B2665: 46357 | C2665: 29028.6
A2666: Zwartop Golf Course | B2666: 45292
A2667: Zwartop Golf Course | B2667: 45323
A2668: Zwartop Golf Course | B2668: 45352
A2669: Zwartop Golf Course | B2669: 45383
A2670: Zwartop Golf Course | B2670: 45413
A2671: Zwartop Golf Course | B2671: 45444
A2672: Zwartop Golf Course | B2672: 45474
A2673: Zwartop Golf Course | B2673: 45505
A2674: Zwartop Golf Course | B2674: 45536
A2675: Zwartop Golf Course | B2675: 45566
A2676: Zwartop Golf Course | B2676: 45597
A2677: Zwartop Golf Course | B2677: 45627
... A2701: Zwartop Golf Course | B2701: 46357
A2702: Engen Kaalfontein | B2702: 45292 | C2702: {=IFERROR(INDEX('Expected Production'!$C$2:$N$200,MATCH(A2702,'Expected Production'!$A$2:$A$200,0),MONTH(B2702)),"")} -> 17370.9
A2703: Engen Kaalfontein | B2703: 45323 | C2703: {=IFERROR(INDEX('Expected Production'!$C$2:$N$200,MATCH(A2703,'Expected Production'!$A$2:$A$200,0),MONTH(B2703)),"")} -> 15077.7
A2704: Engen Kaalfontein | B2704: 45352 | C2704: {=IFERROR(INDEX('Expected Production'!$C$2:$N$200,MATCH(A2704,'Expected Production'!$A$2:$A$200,0),MONTH(B2704)),"")} -> 14634
A2705: Engen Kaalfontein | B2705: 45383 | C2705: {=IFERROR(INDEX('Expected Production'!$C$2:$N$200,MATCH(A2705,'Expected Production'!$A$2:$A$200,0),MONTH(B2705)),"")} -> 12420
A2706: Engen Kaalfontein | B2706: 45413 | C2706: {=IFERROR(INDEX('Expected Production'!$C$2:$N$200,MATCH(A2706,'Expected Production'!$A$2:$A$200,0),MONTH(B2706)),"")} -> 11402.1
A2707: Engen Kaalfontein | B2707: 45444 | C2707: {=IFERROR(INDEX('Expected Production'!$C$2:$N$200,MATCH(A2707,'Expected Production'!$A$2:$A$200,0),MONTH(B2707)),"")} -> 9989.1
A2708: Engen Kaalfontein | B2708: 45474 | C2708: {=IFERROR(INDEX('Expected Production'!$C$2:$N$200,MATCH(A2708,'Expected Production'!$A$2:$A$200,0),MONTH(B2708)),"")} -> 10986.3
A2709: Engen Kaalfontein | B2709: 45505 | C2709: {=IFERROR(INDEX('Expected Production'!$C$2:$N$200,MATCH(A2709,'Expected Production'!$A$2:$A$200,0),MONTH(B2709)),"")} -> 13108.77
A2710: Engen Kaalfontein | B2710: 45536 | C2710: {=IFERROR(INDEX('Expected Production'!$C$2:$N$200,MATCH(A2710,'Expected Production'!$A$2:$A$200,0),MONTH(B2710)),"")} -> 14833.17
A2711: Engen Kaalfontein | B2711: 45566 | C2711: {=IFERROR(INDEX('Expected Production'!$C$2:$N$200,MATCH(A2711,'Expected Production'!$A$2:$A$200,0),MONTH(B2711)),"")} -> 17053.2
A2712: Engen Kaalfontein | B2712: 45597 | C2712: {=IFERROR(INDEX('Expected Production'!$C$2:$N$200,MATCH(A2712,'Expected Production'!$A$2:$A$200,0),MONTH(B2712)),"")} -> 17239.5
A2713: Engen Kaalfontein | B2713: 45627 | C2713: {=IFERROR(INDEX('Expected Production'!$C$2:$N$200,MATCH(A2713,'Expected Production'!$A$2:$A$200,0),MONTH(B2713)),"")} -> 17465.4
... A2815: Usave Naboomspruit | B2815: 46357 | C2815: {=IFERROR(INDEX('Expected Production'!$C$2:$N$200,MATCH(A2815,'Expected Production'!$A$2:$A$200,0),MONTH(B2815)),"")} -> 5989.5

Sheet Comments
A1: Site Name | B1: Date | C1: Availability | D1: Downtime (days) | E1: Cause of downtime | F1: Technical Events | G1: Energy Impact | H1: Other Comments
A2: 21 Melrose | B2: 45536
A3: 21 Melrose | B3: 45566
A4: 21 Melrose | B4: 45597
A5: 21 Melrose | B5: 45627
A6: 21 Melrose | B6: 45658
A7: 21 Melrose | B7: 45689 | C7: Underperforming Low demand Excessive rain and cloudy weather for approx. 2 weeks -50% less production compared to Feb 2024 Avg load: Feb 2024: 200kW; Feb 2025 150-160kW
A8: 21 Melrose | B8: 45717 | C8: Underperforming due to Low demand System performance is >65% expected production System Performance improved by 9% compared to last month System Performance decreased by 55% compared to march 2024 System Performance affected by rain on some days
A9: 21 Melrose | B9: 45748 | C9: 1. Underperformance due to low demand 2. Production is 63% of expected 3. Production is 45% Compared to April 2024 4. Production is the same compared to last month
A10: 21 Melrose | B10: 45778 | C10: 1. Production is 102% of the expected energy. 2. Production is 16% less compared to May 2024. 3. Production is 39% more compared to last month. 4. There is no downtime on the solar, Eskom, and communication.
A11: 21 Melrose | B11: 45809 | C11: 1. Production is 108% of the expected energy. 2. Production is 6% less compared to June 2024. 3. Production is 6% more compared to last month. 4. There is no downtime on the solar, Eskom, and communication.
A12: 21 Melrose | B12: 45839 | C12: 1. Production is 96% of the expected energy. 2. Production is 10% less compared to Jul 2024. 3. Production is 12% less compared to last month. 4. There is no downtime on the solar, Eskom, and communication.
A13: 21 Melrose | B13: 45870 | C13: 1. Production is 76% of the expected energy. 2. Production is 6% less compared to Aug 2024. 3. Production is 20% less compared to last month. 4. System performed moderately, client loads are slightly low.
A14: 21 Melrose | B14: 45901 | C14: 1. Production is 60% of the expected energy. 2. Production is 146% less compared to Sep 2024. 3. Production is 16% less compared to last month. 4. System performed moderately; client load demand is low.
A15: 21 Melrose | B15: 45931 | C15: 1. Production is 67% of the expected energy. 2. Production is 1% more compared to Oct 2024. 3. Production is 7% more compared to last month. 4. System performed poorly; client load demand is low.
A16: 21 Melrose | B16: 45962 | C16: 1. Production is 61% of the expected energy. 2. Production is 20% less compared to Nov 2024. 3. Production is 3% less compared to last month. 4. System performed poorly; client load demand is low.
A17: 21 Melrose | B17: 45992 | C17: System performed poorly; client load demand is low.
A18: 21 Melrose | B18: 46023 | C18: System performed poorly; client load demand is low.
... A22: 21 Melrose | B22: 46143 | C22: Performend poorly due to load demand
A23: 21 Melrose | B23: 46174
A24: 21 Melrose | B24: 46204 | C24: 31 | D24: 0 | E24: None | F24: None | G24: The System performed as expected | H24: N/A
A25: 21 Melrose | B25: 46235
A26: African Global Plastics | B26: 45536
A27: African Global Plastics | B27: 45566
A28: African Global Plastics | B28: 45597
A29: African Global Plastics | B29: 45627
A30: African Global Plastics | B30: 45658
A31: African Global Plastics | B31: 45689 | C31: Performance decreased by 25% due to rainy weather -36% lower production, compared to Feb 2024 Intermittent comms, IOT sim required
A32: African Global Plastics | B32: 45717 | C32: Fix Comms - Install IoT simcard
A33: African Global Plastics | B33: 45748 | C33: Fix Comms - Install IoT simcard
A34: African Global Plastics | B34: 45778 | C34: 1. Production is 96% of the expected energy. 2. Production is 17% less compared to May 2024. 3. Production is 14% more compared to last month. 4. The system is performing well, monitoring platform was offline for 31 day, to install IoT sim to improve internet stability
A35: African Global Plastics | B35: 45809 | C35: 1. Production is 82% of the expected energy. 2. Production is 27% less compared to Jun 2024. 3. Production is 14% less compared to last month. 4. The system is performing moderate, monitoring platform was offline for 30 days, to install IoT sim to improve internet stability
A36: African Global Plastics | B36: 45839 | C36: 1. Production is 20% of the expected energy. 2. Production is 81% less compared to Jul 2024. 3. Production is 62% less compared to last month. 4. The system is performing poor. The reading are incorrect from monitoring. Billing meter is offline.
A37: African Global Plastics | B37: 45870 | C37: 1. Production is 60% of the expected energy. 2. Production is 18% less compared to Aug 2024. 3. Production is 40% more compared to last month. 4. The system is performing poorly. The reading are incorrect on the billing meter.
A38: African Global Plastics | B38: 45901 | C38: 1. Production is 56% of the expected energy. 2. Production is 43% less compared to Sep 2024. 3. Production is 4% less compared to last month. 4. The system is performing poorly. The system is offline, and the system needs site attendance
A39: African Global Plastics | B39: 45931 | C39: 1. Production is 58% of the expected energy. 2. Production is 54% less compared to Oct 2024. 3. Production is 2% more compared to last month. 4. The system is performing poorly. The system is offline, The system was under performing due to faulty controls logger; issue was resoved. System performance should increase next month
A40: African Global Plastics | B40: 45962 | C40: 1. Production is 51% of the expected energy. 2. Production is 52% less compared to Nov 2024. 3. Production is 7% less compared to last month. 4. System performed poorly. controls system has faulty software. Logger to be replaced
A41: African Global Plastics | B41: 45992 | C41: System performed poorly. controls system has faulty software. Logger to be replaced
A42: African Global Plastics | B42: 46023 | C42: Performed poorly due to controls malfunction
... A46: African Global Plastics | B46: 46143 | C46: Performing poorly due to slightly reduced load demand
A47: African Global Plastics | B47: 46174 | C47: 31 days | D47: 0 | E47: None
A48: African Global Plastics | B48: 46204 | C48: 31 | D48: 0 | E48: None | F48: None | G48: Energy production was limited by reduced load demand | H48: N/A
A49: African Global Plastics | B49: 46235
A50: Alpine Heath Residential | B50: 45536
A51: Alpine Heath Residential | B51: 45566
A52: Alpine Heath Residential | B52: 45597
A53: Alpine Heath Residential | B53: 45627
A54: Alpine Heath Residential | B54: 45658 | C54: 31 days | D54: None | E54: None | F54: Internet connectivity issues | G54: Energy production was limited by reduced load demand
A55: Alpine Heath Residential | B55: 45689 | C55: 28 days | D55: None | E55: None | F55: Internet connectivity issues | G55: Energy production was limited by reduced load demand
A56: Alpine Heath Residential | B56: 45717 | C56: 31 days | D56: None | E56: None | F56: Internet connectivity issues | G56: Energy production was limited by reduced load demand
A57: Alpine Heath Residential | B57: 45748 | C57: 30 days | F57: Internet connectivity issues | G57: Energy production was limited by reduced load demand
A58: Alpine Heath Residential | B58: 45778 | C58: 0 | D58: 30 | F58: Internet connectivity issues | G58: Energy production was limited by reduced load demand
A59: Alpine Heath Residential | B59: 45809 | C59: 26 days | D59: 4 | E59: Inverter was offline | F59: Internet connectivity issues | G59: Energy production was limited by reduced load demand
A60: Alpine Heath Residential | B60: 45839 | C60: 0 days | D60: 31 days | E60: System shutdown | F60: Technical Fault. Inverter offline due to repairs | G60: No solar production due to technical fault
A61: Alpine Heath Residential | B61: 45870 | C61: 31 days | D61: 0 | F61: None | G61: Energy production was limited by reduced load demand
A62: Alpine Heath Residential | B62: 45901 | C62: 31 days | D62: 0 | F62: None | G62: produced as expected
A63: Alpine Heath Residential | B63: 45931 | C63: 22 days | D63: 19-27, 9 days | E63: PV Breaker tripped | F63: Faulty AC breakers | G63: Energy production was limited by reduced load demand & technical event
A64: Alpine Heath Residential | B64: 45962 | C64: 30 days | D64: 0 | F64: None | G64: Energy production was limited by reduced load demand
A65: Alpine Heath Residential | B65: 45992 | C65: 31 days | D65: 0 | E65: None | F65: Internet connectivity issues | G65: Energy production was limited by reduced load demand
A66: Alpine Heath Residential | B66: 46023 | C66: 31 days | D66: 0 | F66: None | G66: Low energy demand reduced production
A67: Alpine Heath Residential | B67: 46054 | C67: 28 days | D67: 0 | F67: None | G67: Energy production was limited by reduced load demand
A68: Alpine Heath Residential | B68: 46082 | C68: 21 days | D68: 21-31, 10 days | E68: PV Breaker tripped | F68: Faulty DC breakers | G68: Energy production was limited by reduced load demand & technical event
A69: Alpine Heath Residential | B69: 46113 | C69: 30 days | D69: 28-30, 3 days | E69: PV Breaker tripped | F69: Faulty DC breakers | G69: Energy production was limited by technical event
A70: Alpine Heath Residential | B70: 46143 | C70: 31 days | D70: 01-18, 18 days | E70: System isolated for maintenance | F70: Faulty DC breakers | G70: Energy production was limited by reduced load demand & technical event
A71: Alpine Heath Residential | B71: 46174 | C71: 30 days | D71: 0 | E71: None | F71: None | G71: Energy production was limited by reduced load demand | H71: N/A
A72: Alpine Heath Residential | B72: 46204 | C72: 30 | D72: 1 day, 14th | E72: Power outage | F72: None | G72: Energy production was limited by reduced load demand and weather | H72: N/A
A73: Alpine Heath Residential | B73: 46235
A74: BP Parys | B74: 45536
A75: BP Parys | B75: 45566
A76: BP Parys | B76: 45597
A77: BP Parys | B77: 45627
A78: BP Parys | B78: 45658
A79: BP Parys | B79: 45689 | C79: Low load demand, 15-20kW avg System performing as expected due to low loads
A80: BP Parys | B80: 45717 | C80: Rain Load Demand Low
A81: BP Parys | B81: 45748 | C81: Load Demand Low
A82: BP Parys | B82: 45778 | C82: 1. Production is 65% of the expected energy. 2. Production is 6% more compared to last month. 3. There was a power outage for 1 day, client load is lower than the system installed
A83: BP Parys | B83: 45809 | C83: 1. Production is 50% of the expected energy. 2. Production is 15% less compared to last month. 4. The system comms went ofline for 8 days, client load demand is lower than the system installed.
A84: BP Parys | B84: 45839 | C84: 1. Production is 40% of the expected energy. 2. Production is 10% less compared to last month. 4. The system is performing poorly due to low load demand
A85: BP Parys | B85: 45870 | C85: 1. Production is 15% of the expected energy. 2. Production is 25% less compared to last month. 4. Inverter reading has 10 days (10/08/25-31/08/25) of missing data (actual reading should be higher), the system has been operational regardless of comms being offline on the monitoring, and the comms are online again.
A86: BP Parys | B86: 45901 | C86: 1. Production is 28% of the expected energy. 2. Production is 13% more compared to last month. 4. The system produced poorly due to reduced load demand
A87: BP Parys | B87: 45931 | C87: 1. Production is 40% of the expected energy. 2. Production is 12% more compared to last month. 4. The system produced poorly due to reduced load demand
A88: BP Parys | B88: 45962 | C88: 1. Production is 20% of the expected energy. 2. Production is 20% less compared to last month. 4. The system produced poorly due to reduced load demand
A89: BP Parys | B89: 45992 | C89: The system produced poorly due to business closure
A90: BP Parys | B90: 46023 | C90: The system produced poorly due to business closure
... A94: BP Parys | B94: 46143 | C94: Performend poorly due to load demand
A95: Alpine Heath Resort | B95: 46204 | C95: 31 | D95: 0 | E95: None | F95: None | G95: The system performed as expected | H95: N/A
A96: Alpine Heath Resort | B96: 46174 | C96: 30 days | D96: 0 | E96: None | F96: None | G96: The energy production was limited by load demand & bad weather | H96: N/A
A97: BP Parys | B97: 46235
A98: Bendstore Plaza Shops | B98: 45536 | C98: Client Load Demand went Lower than Installed Capacity
A99: Bendstore Plaza Shops | B99: 45566
A100: Bendstore Plaza Shops | B100: 45597
A101: Bendstore Plaza Shops | B101: 45627
A102: Bendstore Plaza Shops | B102: 45658
A103: Bendstore Plaza Shops | B103: 45689 | C103: Fluctuating loads Load demand lower as of Jan 2024 Production lower than expected simulated production but improved from prior year by 10-15%. Due to increased ramp rate settings. Rainy weather affected Feb performance
A104: Bendstore Plaza Shops | B104: 45717 | C104: Fluctuating loads Load demand lower as of Jan 2024 System performance is >80% expected production Performance improved by 1% compared to last month Performance Improved by 4,2% compared to march 2024 Performance affected by rain on some days
A105: Bendstore Plaza Shops | B105: 45748 | C105: 1. Fuctuating load & Reduced 2. Production is 62% of expected energy 3. Production is 7% less Compared to April 2024 4. Production is 20% less compared to last month 5. Loadscheding for three days
A106: Bendstore Plaza Shops | B106: 45778 | C106: 1. Production is 67% of the expected energy. 2. Production is 7% less compared to May 2024. 3. Production is 5% more compared to last month. 4. Production is in line with historical production, High fluctuating loads and Reduced. There was 3 times comms loss and 1-time grid loss.
A107: Bendstore Plaza Shops | B107: 45809 | C107: 1. Production is 70% of the expected energy. 2. Production is 6% less compared to Jun 2024. 3. Production is 3% more compared to last month. 4. The system is performing moderate, monitoring platform was offline for 2 days.
A108: Bendstore Plaza Shops | B108: 45839 | C108: 1. Production is 69% of the expected energy. 2. Production is 7% less compared to Jul 2024. 3. Production is 1% less compared to last month. 4. The system is performing poorly, monitoring platform was offline for 5 days. Days: 8th ,9th ,10th, 30th, 31th
A109: Bendstore Plaza Shops | B109: 45870 | C109: 1. Production is 70% of the expected energy. 2. Production is 9% more compared to Aug 2024. 3. Production is 1% more compared to last month. 4. The system is performing modaretly. Load demand is modarate.
...

Sheet performance
A1: Site Name | B1: Date | C1: Measured (kWh) | D1: Expected (kWh) | E1: Performance | F1: PF Band | G1: Discussion
A2: 21 Melrose | B2: 45292 | C2: {=IFERROR(IF(SUMPRODUCT((measured[Site Name]=A2)*(measured[Date]=B2)*ISNUMBER(measured[Measured Value (kWh)]))=0,"",SUMIFS(measured[Measured Value (kWh)],measured[Site Name],A2,measured[Date],B2)),"")} -> 1815 | D2: {=IFERROR(IF(SUMPRODUCT((expected_production[Site Name]=A2)*(expected_production[Date]=B2)*ISNUMBER(expected_production[Expected Production (kWh)]))=0,"",SUMIFS(expected_production[Expected Production (kWh)],expected_production[Site Name],A2,expected_production[Date],B2)),"")} -> 2370.6 | E2: =IF(OR(C2="",D2="",D2=0),"",C2/D2) -> 0.76562895 | F2: =IF(E2="","",IF(E2>=0.9,"Expected",IF(E2>=0.7,"Moderate","Poor"))) -> Moderate
A3: 21 Melrose | B3: 45323 | C3: {=IFERROR(IF(SUMPRODUCT((measured[Site Name]=A3)*(measured[Date]=B3)*ISNUMBER(measured[Measured Value (kWh)]))=0,"",SUMIFS(measured[Measured Value (kWh)],measured[Site Name],A3,measured[Date],B3)),"")} -> 2295 | D3: {=IFERROR(IF(SUMPRODUCT((expected_production[Site Name]=A3)*(expected_production[Date]=B3)*ISNUMBER(expected_production[Expected Production (kWh)]))=0,"",SUMIFS(expected_production[Expected Production (kWh)],expected_production[Site Name],A3,expected_production[Date],B3)),"")} -> 2680.2 | E3: =IF(OR(C3="",D3="",D3=0),"",C3/D3) -> 0.85627938 | F3: =IF(E3="","",IF(E3>=0.9,"Expected",IF(E3>=0.7,"Moderate","Poor"))) -> Moderate
A4: 21 Melrose | B4: 45352 | C4: {=IFERROR(IF(SUMPRODUCT((measured[Site Name]=A4)*(measured[Date]=B4)*ISNUMBER(measured[Measured Value (kWh)]))=0,"",SUMIFS(measured[Measured Value (kWh)],measured[Site Name],A4,measured[Date],B4)),"")} -> 2474 | D4: {=IFERROR(IF(SUMPRODUCT((expected_production[Site Name]=A4)*(expected_production[Date]=B4)*ISNUMBER(expected_production[Expected Production (kWh)]))=0,"",SUMIFS(expected_production[Expected Production (kWh)],expected_production[Site Name],A4,expected_production[Date],B4)),"")} -> 2183.4 | E4: =IF(OR(C4="",D4="",D4=0),"",C4/D4) -> 1.1330952 | F4: =IF(E4="","",IF(E4>=0.9,"Expected",IF(E4>=0.7,"Moderate","Poor"))) -> Expected
A5: 21 Melrose | B5: 45383 | C5: {=IFERROR(IF(SUMPRODUCT((measured[Site Name]=A5)*(measured[Date]=B5)*ISNUMBER(measured[Measured Value (kWh)]))=0,"",SUMIFS(measured[Measured Value (kWh)],measured[Site Name],A5,measured[Date],B5)),"")} -> 2136 | D5: {=IFERROR(IF(SUMPRODUCT((expected_production[Site Name]=A5)*(expected_production[Date]=B5)*ISNUMBER(expected_production[Expected Production (kWh)]))=0,"",SUMIFS(expected_production[Expected Production (kWh)],expected_production[Site Name],A5,expected_production[Date],B5)),"")} -> 1873.8 | E5: =IF(OR(C5="",D5="",D5=0),"",C5/D5) -> 1.1399296 | F5: =IF(E5="","",IF(E5>=0.9,"Expected",IF(E5>=0.7,"Moderate","Poor"))) -> Expected
A6: 21 Melrose | B6: 45413 | C6: {=IFERROR(IF(SUMPRODUCT((measured[Site Name]=A6)*(measured[Date]=B6)*ISNUMBER(measured[Measured Value (kWh)]))=0,"",SUMIFS(measured[Measured Value (kWh)],measured[Site Name],A6,measured[Date],B6)),"")} -> 2212 | D6: {=IFERROR(IF(SUMPRODUCT((expected_production[Site Name]=A6)*(expected_production[Date]=B6)*ISNUMBER(expected_production[Expected Production (kWh)]))=0,"",SUMIFS(expected_production[Expected Production (kWh)],expected_production[Site Name],A6,expected_production[Date],B6)),"")} -> 1822.5 | E6: =IF(OR(C6="",D6="",D6=0),"",C6/D6) -> 1.2137174 | F6: =IF(E6="","",IF(E6>=0.9,"Expected",IF(E6>=0.7,"Moderate","Poor"))) -> Expected
A7: 21 Melrose | B7: 45444 | C7: {=IFERROR(IF(SUMPRODUCT((measured[Site Name]=A7)*(measured[Date]=B7)*ISNUMBER(measured[Measured Value (kWh)]))=0,"",SUMIFS(measured[Measured Value (kWh)],measured[Site Name],A7,measured[Date],B7)),"")} -> 1863 | D7: {=IFERROR(IF(SUMPRODUCT((expected_production[Site Name]=A7)*(expected_production[Date]=B7)*ISNUMBER(expected_production[Expected Production (kWh)]))=0,"",SUMIFS(expected_production[Expected Production (kWh)],expected_production[Site Name],A7,expected_production[Date],B7)),"")} -> 1629 | E7: =IF(OR(C7="",D7="",D7=0),"",C7/D7) -> 1.1436464 | F7: =IF(E7="","",IF(E7>=0.9,"Expected",IF(E7>=0.7,"Moderate","Poor"))) -> Expected
A8: 21 Melrose | B8: 45474 | C8: {=IFERROR(IF(SUMPRODUCT((measured[Site Name]=A8)*(measured[Date]=B8)*ISNUMBER(measured[Measured Value (kWh)]))=0,"",SUMIFS(measured[Measured Value (kWh)],measured[Site Name],A8,measured[Date],B8)),"")} -> 1943 | D8: {=IFERROR(IF(SUMPRODUCT((expected_production[Site Name]=A8)*(expected_production[Date]=B8)*ISNUMBER(expected_production[Expected Production (kWh)]))=0,"",SUMIFS(expected_production[Expected Production (kWh)],expected_production[Site Name],A8,expected_production[Date],B8)),"")} -> 1814.4 | E8: =IF(OR(C8="",D8="",D8=0),"",C8/D8) -> 1.0708774 | F8: =IF(E8="","",IF(E8>=0.9,"Expected",IF(E8>=0.7,"Moderate","Poor"))) -> Expected
A9: 21 Melrose | B9: 45505 | C9: {=IFERROR(IF(SUMPRODUCT((measured[Site Name]=A9)*(measured[Date]=B9)*ISNUMBER(measured[Measured Value (kWh)]))=0,"",SUMIFS(measured[Measured Value (kWh)],measured[Site Name],A9,measured[Date],B9)),"")} -> 1710 | D9: {=IFERROR(IF(SUMPRODUCT((expected_production[Site Name]=A9)*(expected_production[Date]=B9)*ISNUMBER(expected_production[Expected Production (kWh)]))=0,"",SUMIFS(expected_production[Expected Production (kWh)],expected_production[Site Name],A9,expected_production[Date],B9)),"")} -> 2116.8 | E9: =IF(OR(C9="",D9="",D9=0),"",C9/D9) -> 0.80782313 | F9: =IF(E9="","",IF(E9>=0.9,"Expected",IF(E9>=0.7,"Moderate","Poor"))) -> Moderate
A10: 21 Melrose | B10: 45536 | C10: {=IFERROR(IF(SUMPRODUCT((measured[Site Name]=A10)*(measured[Date]=B10)*ISNUMBER(measured[Measured Value (kWh)]))=0,"",SUMIFS(measured[Measured Value (kWh)],measured[Site Name],A10,measured[Date],B10)),"")} -> 1579 | D10: {=IFERROR(IF(SUMPRODUCT((expected_production[Site Name]=A10)*(expected_production[Date]=B10)*ISNUMBER(expected_production[Expected Production (kWh)]))=0,"",SUMIFS(expected_production[Expected Production (kWh)],expected_production[Site Name],A10,expected_production[Date],B10)),"")} -> 2275.2 | E10: =IF(OR(C10="",D10="",D10=0),"",C10/D10) -> 0.69400492 | F10: =IF(E10="","",IF(E10>=0.9,"Expected",IF(E10>=0.7,"Moderate","Poor"))) -> Poor
A11: 21 Melrose | B11: 45566 | C11: {=IFERROR(IF(SUMPRODUCT((measured[Site Name]=A11)*(measured[Date]=B11)*ISNUMBER(measured[Measured Value (kWh)]))=0,"",SUMIFS(measured[Measured Value (kWh)],measured[Site Name],A11,measured[Date],B11)),"")} -> 1593 | D11: {=IFERROR(IF(SUMPRODUCT((expected_production[Site Name]=A11)*(expected_production[Date]=B11)*ISNUMBER(expected_production[Expected Production (kWh)]))=0,"",SUMIFS(expected_production[Expected Production (kWh)],expected_production[Site Name],A11,expected_production[Date],B11)),"")} -> 2407.5 | E11: =IF(OR(C11="",D11="",D11=0),"",C11/D11) -> 0.66168224 | F11: =IF(E11="","",IF(E11>=0.9,"Expected",IF(E11>=0.7,"Moderate","Poor"))) -> Poor
A12: 21 Melrose | B12: 45597 | C12: {=IFERROR(IF(SUMPRODUCT((measured[Site Name]=A12)*(measured[Date]=B12)*ISNUMBER(measured[Measured Value (kWh)]))=0,"",SUMIFS(measured[Measured Value (kWh)],measured[Site Name],A12,measured[Date],B12)),"")} -> 1794 | D12: {=IFERROR(IF(SUMPRODUCT((expected_production[Site Name]=A12)*(expected_production[Date]=B12)*ISNUMBER(expected_production[Expected Production (kWh)]))=0,"",SUMIFS(expected_production[Expected Production (kWh)],expected_production[Site Name],A12,expected_production[Date],B12)),"")} -> 2356.2 | E12: =IF(OR(C12="",D12="",D12=0),"",C12/D12) -> 0.76139547 | F12: =IF(E12="","",IF(E12>=0.9,"Expected",IF(E12>=0.7,"Moderate","Poor"))) -> Moderate
A13: 21 Melrose | B13: 45627 | C13: {=IFERROR(IF(SUMPRODUCT((measured[Site Name]=A13)*(measured[Date]=B13)*ISNUMBER(measured[Measured Value (kWh)]))=0,"",SUMIFS(measured[Measured Value (kWh)],measured[Site Name],A13,measured[Date],B13)),"")} -> 1794 | D13: {=IFERROR(IF(SUMPRODUCT((expected_production[Site Name]=A13)*(expected_production[Date]=B13)*ISNUMBER(expected_production[Expected Production (kWh)]))=0,"",SUMIFS(expected_production[Expected Production (kWh)],expected_production[Site Name],A13,expected_production[Date],B13)),"")} -> 2482.2 | E13: =IF(OR(C13="",D13="",D13=0),"",C13/D13) -> 0.72274595 | F13: =IF(E13="","",IF(E13>=0.9,"Expected",IF(E13>=0.7,"Moderate","Poor"))) -> Moderate
... A31: 21 Melrose | B31: 46174 | C31: {=IFERROR(IF(SUMPRODUCT((measured[Site Name]=A31)*(measured[Date]=B31)*ISNUMBER(measured[Measured Value (kWh)]))=0,"",SUMIFS(measured[Measured Value (kWh)],measured[Site Name],A31,measured[Date],B31)),"")} -> 1287 | D31: {=IFERROR(IF(SUMPRODUCT((expected_production[Site Name]=A31)*(expected_production[Date]=B31)*ISNUMBER(expected_production[Expected Production (kWh)]))=0,"",SUMIFS(expected_production[Expected Production (kWh)],expected_production[Site Name],A31,expected_production[Date],B31)),"")} -> 1629 | E31: =IF(OR(C31="",D31="",D31=0),"",C31/D31) -> 0.79005525 | F31: =IF(E31="","",IF(E31>=0.9,"Expected",IF(E31>=0.7,"Moderate","Poor"))) -> Moderate
A32: 21 Melrose | B32: 46204 | C32: {=IFERROR(IF(SUMPRODUCT((measured[Site Name]=A32)*(measured[Date]=B32)*ISNUMBER(measured[Measured Value (kWh)]))=0,"",SUMIFS(measured[Measured Value (kWh)],measured[Site Name],A32,measured[Date],B32)),"")} -> 1638 | D32: {=IFERROR(IF(SUMPRODUCT((expected_production[Site Name]=A32)*(expected_production[Date]=B32)*ISNUMBER(expected_production[Expected Production (kWh)]))=0,"",SUMIFS(expected_production[Expected Production (kWh)],expected_production[Site Name],A32,expected_production[Date],B32)),"")} -> 1814.4 | E32: =IF(OR(C32="",D32="",D32=0),"",C32/D32) -> 0.90277778 | F32: =IF(E32="","",IF(E32>=0.9,"Expected",IF(E32>=0.7,"Moderate","Poor"))) -> Expected | G32: NO
A33: 21 Melrose | B33: 46235 | C33: {=IFERROR(IF(SUMPRODUCT((measured[Site Name]=A33)*(measured[Date]=B33)*ISNUMBER(measured[Measured Value (kWh)]))=0,"",SUMIFS(measured[Measured Value (kWh)],measured[Site Name],A33,measured[Date],B33)),"")} | D33: {=IFERROR(IF(SUMPRODUCT((expected_production[Site Name]=A33)*(expected_production[Date]=B33)*ISNUMBER(expected_production[Expected Production (kWh)]))=0,"",SUMIFS(expected_production[Expected Production (kWh)],expected_production[Site Name],A33,expected_production[Date],B33)),"")} -> 2116.8 | E33: =IF(OR(C33="",D33="",D33=0),"",C33/D33) | F33: =IF(E33="","",IF(E33>=0.9,"Expected",IF(E33>=0.7,"Moderate","Poor")))
A34: 21 Melrose | B34: 46266 | C34: {=IFERROR(IF(SUMPRODUCT((measured[Site Name]=A34)*(measured[Date]=B34)*ISNUMBER(measured[Measured Value (kWh)]))=0,"",SUMIFS(measured[Measured Value (kWh)],measured[Site Name],A34,measured[Date],B34)),"")} | D34: {=IFERROR(IF(SUMPRODUCT((expected_production[Site Name]=A34)*(expected_production[Date]=B34)*ISNUMBER(expected_production[Expected Production (kWh)]))=0,"",SUMIFS(expected_production[Expected Production (kWh)],expected_production[Site Name],A34,expected_production[Date],B34)),"")} -> 2275.2 | E34: =IF(OR(C34="",D34="",D34=0),"",C34/D34) | F34: =IF(E34="","",IF(E34>=0.9,"Expected",IF(E34>=0.7,"Moderate","Poor")))
A35: 21 Melrose | B35: 46296 | C35: {=IFERROR(IF(SUMPRODUCT((measured[Site Name]=A35)*(measured[Date]=B35)*ISNUMBER(measured[Measured Value (kWh)]))=0,"",SUMIFS(measured[Measured Value (kWh)],measured[Site Name],A35,measured[Date],B35)),"")} | D35: {=IFERROR(IF(SUMPRODUCT((expected_production[Site Name]=A35)*(expected_production[Date]=B35)*ISNUMBER(expected_production[Expected Production (kWh)]))=0,"",SUMIFS(expected_production[Expected Production (kWh)],expected_production[Site Name],A35,expected_production[Date],B35)),"")} -> 2407.5 | E35: =IF(OR(C35="",D35="",D35=0),"",C35/D35) | F35: =IF(E35="","",IF(E35>=0.9,"Expected",IF(E35>=0.7,"Moderate","Poor")))
A36: 21 Melrose | B36: 46327 | C36: {=IFERROR(IF(SUMPRODUCT((measured[Site Name]=A36)*(measured[Date]=B36)*ISNUMBER(measured[Measured Value (kWh)]))=0,"",SUMIFS(measured[Measured Value (kWh)],measured[Site Name],A36,measured[Date],B36)),"")} | D36: {=IFERROR(IF(SUMPRODUCT((expected_production[Site Name]=A36)*(expected_production[Date]=B36)*ISNUMBER(expected_production[Expected Production (kWh)]))=0,"",SUMIFS(expected_production[Expected Production (kWh)],expected_production[Site Name],A36,expected_production[Date],B36)),"")} -> 2356.2 | E36: =IF(OR(C36="",D36="",D36=0),"",C36/D36) | F36: =IF(E36="","",IF(E36>=0.9,"Expected",IF(E36>=0.7,"Moderate","Poor")))
A37: 21 Melrose | B37: 46357 | C37: {=IFERROR(IF(SUMPRODUCT((measured[Site Name]=A37)*(measured[Date]=B37)*ISNUMBER(measured[Measured Value (kWh)]))=0,"",SUMIFS(measured[Measured Value (kWh)],measured[Site Name],A37,measured[Date],B37)),"")} | D37: {=IFERROR(IF(SUMPRODUCT((expected_production[Site Name]=A37)*(expected_production[Date]=B37)*ISNUMBER(expected_production[Expected Production (kWh)]))=0,"",SUMIFS(expected_production[Expected Production (kWh)],expected_production[Site Name],A37,expected_production[Date],B37)),"")} -> 2482.2 | E37: =IF(OR(C37="",D37="",D37=0),"",C37/D37) | F37: =IF(E37="","",IF(E37>=0.9,"Expected",IF(E37>=0.7,"Moderate","Poor")))
A38: African Global Plastics | B38: 45292 | C38: {=IFERROR(IF(SUMPRODUCT((measured[Site Name]=A38)*(measured[Date]=B38)*ISNUMBER(measured[Measured Value (kWh)]))=0,"",SUMIFS(measured[Measured Value (kWh)],measured[Site Name],A38,measured[Date],B38)),"")} -> 23024 | D38: {=IFERROR(IF(SUMPRODUCT((expected_production[Site Name]=A38)*(expected_production[Date]=B38)*ISNUMBER(expected_production[Expected Production (kWh)]))=0,"",SUMIFS(expected_production[Expected Production (kWh)],expected_production[Site Name],A38,expected_production[Date],B38)),"")} -> 22515.905 | E38: =IF(OR(C38="",D38="",D38=0),"",C38/D38) -> 1.022566 | F38: =IF(E38="","",IF(E38>=0.9,"Expected",IF(E38>=0.7,"Moderate","Poor"))) -> Expected
A39: African Global Plastics | B39: 45323 | C39: {=IFERROR(IF(SUMPRODUCT((measured[Site Name]=A39)*(measured[Date]=B39)*ISNUMBER(measured[Measured Value (kWh)]))=0,"",SUMIFS(measured[Measured Value (kWh)],measured[Site Name],A39,measured[Date],B39)),"")} -> 23235 | D39: {=IFERROR(IF(SUMPRODUCT((expected_production[Site Name]=A39)*(expected_production[Date]=B39)*ISNUMBER(expected_production[Expected Production (kWh)]))=0,"",SUMIFS(expected_production[Expected Production (kWh)],expected_production[Site Name],A39,expected_production[Date],B39)),"")} -> 19786.13 | E39: =IF(OR(C39="",D39="",D39=0),"",C39/D39) -> 1.1743075 | F39: =IF(E39="","",IF(E39>=0.9,"Expected",IF(E39>=0.7,"Moderate","Poor"))) -> Expected
A40: African Global Plastics | B40: 45352 | C40: {=IFERROR(IF(SUMPRODUCT((measured[Site Name]=A40)*(measured[Date]=B40)*ISNUMBER(measured[Measured Value (kWh)]))=0,"",SUMIFS(measured[Measured Value (kWh)],measured[Site Name],A40,measured[Date],B40)),"")} -> 23235 | D40: {=IFERROR(IF(SUMPRODUCT((expected_production[Site Name]=A40)*(expected_production[Date]=B40)*ISNUMBER(expected_production[Expected Production (kWh)]))=0,"",SUMIFS(expected_production[Expected Production (kWh)],expected_production[Site Name],A40,expected_production[Date],B40)),"")} -> 20148.4 | E40: =IF(OR(C40="",D40="",D40=0),"",C40/D40) -> 1.1531933 | F40: =IF(E40="","",IF(E40>=0.9,"Expected",IF(E40>=0.7,"Moderate","Poor"))) -> Expected
A41: African Global Plastics | B41: 45383 | C41: {=IFERROR(IF(SUMPRODUCT((measured[Site Name]=A41)*(measured[Date]=B41)*ISNUMBER(measured[Measured Value (kWh)]))=0,"",SUMIFS(measured[Measured Value (kWh)],measured[Site Name],A41,measured[Date],B41)),"")} -> 19307 | D41: {=IFERROR(IF(SUMPRODUCT((expected_production[Site Name]=A41)*(expected_production[Date]=B41)*ISNUMBER(expected_production[Expected Production (kWh)]))=0,"",SUMIFS(expected_production[Expected Production (kWh)],expected_production[Site Name],A41,expected_production[Date],B41)),"")} -> 16764.89 | E41: =IF(OR(C41="",D41="",D41=0),"",C41/D41) -> 1.151633 | F41: =IF(E41="","",IF(E41>=0.9,"Expected",IF(E41>=0.7,"Moderate","Poor"))) -> Expected
A42: African Global Plastics | B42: 45413 | C42: {=IFERROR(IF(SUMPRODUCT((measured[Site Name]=A42)*(measured[Date]=B42)*ISNUMBER(measured[Measured Value (kWh)]))=0,"",SUMIFS(measured[Measured Value (kWh)],measured[Site Name],A42,measured[Date],B42)),"")} -> 18418 | D42: {=IFERROR(IF(SUMPRODUCT((expected_production[Site Name]=A42)*(expected_production[Date]=B42)*ISNUMBER(expected_production[Expected Production (kWh)]))=0,"",SUMIFS(expected_production[Expected Production (kWh)],expected_production[Site Name],A42,expected_production[Date],B42)),"")} -> 15972.095 | E42: =IF(OR(C42="",D42="",D42=0),"",C42/D42) -> 1.1531361 | F42: =IF(E42="","",IF(E42>=0.9,"Expected",IF(E42>=0.7,"Moderate","Poor"))) -> Expected
A43: African Global Plastics | B43: 45444 | C43: {=IFERROR(IF(SUMPRODUCT((measured[Site Name]=A43)*(measured[Date]=B43)*ISNUMBER(measured[Measured Value (kWh)]))=0,"",SUMIFS(measured[Measured Value (kWh)],measured[Site Name],A43,measured[Date],B43)),"")} -> 15949 | D43: {=IFERROR(IF(SUMPRODUCT((expected_production[Site Name]=A43)*(expected_production[Date]=B43)*ISNUMBER(expected_production[Expected Production (kWh)]))=0,"",SUMIFS(expected_production[Expected Production (kWh)],expected_production[Site Name],A43,expected_production[Date],B43)),"")} -> 14367.21 | E43: =IF(OR(C43="",D43="",D43=0),"",C43/D43) -> 1.1100972 | F43: =IF(E43="","",IF(E43>=0.9,"Expected",IF(E43>=0.7,"Moderate","Poor"))) -> Expected
A44: African Global Plastics | B44: 45474 | C44: {=IFERROR(IF(SUMPRODUCT((measured[Site Name]=A44)*(measured[Date]=B44)*ISNUMBER(measured[Measured Value (kWh)]))=0,"",SUMIFS(measured[Measured Value (kWh)],measured[Site Name],A44,measured[Date],B44)),"")} -> 17174 | D44: {=IFERROR(IF(SUMPRODUCT((expected_production[Site Name]=A44)*(expected_production[Date]=B44)*ISNUMBER(expected_production[Expected Production (kWh)]))=0,"",SUMIFS(expected_production[Expected Production (kWh)],expected_production[Site Name],A44,expected_production[Date],B44)),"")} -> 15907.665 | E44: =IF(OR(C44="",D44="",D44=0),"",C44/D44) -> 1.0796053 | F44: =IF(E44="","",IF(E44>=0.9,"Expected",IF(E44>=0.7,"Moderate","Poor"))) -> Expected
... A67: African Global Plastics | B67: 46174 | C67: {=IFERROR(IF(SUMPRODUCT((measured[Site Name]=A67)*(measured[Date]=B67)*ISNUMBER(measured[Measured Value (kWh)]))=0,"",SUMIFS(measured[Measured Value (kWh)],measured[Site Name],A67,measured[Date],B67)),"")} -> 10184.42 | D67: {=IFERROR(IF(SUMPRODUCT((expected_production[Site Name]=A67)*(expected_production[Date]=B67)*ISNUMBER(expected_production[Expected Production (kWh)]))=0,"",SUMIFS(expected_production[Expected Production (kWh)],expected_production[Site Name],A67,expected_production[Date],B67)),"")} -> 14367.21 | E67: =IF(OR(C67="",D67="",D67=0),"",C67/D67) -> 0.70886553 | F67: =IF(E67="","",IF(E67>=0.9,"Expected",IF(E67>=0.7,"Moderate","Poor"))) -> Moderate
A68: African Global Plastics | B68: 46204 | C68: {=IFERROR(IF(SUMPRODUCT((measured[Site Name]=A68)*(measured[Date]=B68)*ISNUMBER(measured[Measured Value (kWh)]))=0,"",SUMIFS(measured[Measured Value (kWh)],measured[Site Name],A68,measured[Date],B68)),"")} -> 13136.53 | D68: {=IFERROR(IF(SUMPRODUCT((expected_production[Site Name]=A68)*(expected_production[Date]=B68)*ISNUMBER(expected_production[Expected Production (kWh)]))=0,"",SUMIFS(expected_production[Expected Production (kWh)],expected_production[Site Name],A68,expected_production[Date],B68)),"")} -> 15907.665 | E68: =IF(OR(C68="",D68="",D68=0),"",C68/D68) -> 0.82579878 | F68: =IF(E68="","",IF(E68>=0.9,"Expected",IF(E68>=0.7,"Moderate","Poor"))) -> Moderate | G68: NO
A69: African Global Plastics | B69: 46235 | C69: {=IFERROR(IF(SUMPRODUCT((measured[Site Name]=A69)*(measured[Date]=B69)*ISNUMBER(measured[Measured Value (kWh)]))=0,"",SUMIFS(measured[Measured Value (kWh)],measured[Site Name],A69,measured[Date],B69)),"")} | D69: {=IFERROR(IF(SUMPRODUCT((expected_production[Site Name]=A69)*(expected_production[Date]=B69)*ISNUMBER(expected_production[Expected Production (kWh)]))=0,"",SUMIFS(expected_production[Expected Production (kWh)],expected_production[Site Name],A69,expected_production[Date],B69)),"")} -> 18527.365 | E69: =IF(OR(C69="",D69="",D69=0),"",C69/D69) | F69: =IF(E69="","",IF(E69>=0.9,"Expected",IF(E69>=0.7,"Moderate","Poor")))
A70: African Global Plastics | B70: 46266 | C70: {=IFERROR(IF(SUMPRODUCT((measured[Site Name]=A70)*(measured[Date]=B70)*ISNUMBER(measured[Measured Value (kWh)]))=0,"",SUMIFS(measured[Measured Value (kWh)],measured[Site Name],A70,measured[Date],B70)),"")} | D70: {=IFERROR(IF(SUMPRODUCT((expected_production[Site Name]=A70)*(expected_production[Date]=B70)*ISNUMBER(expected_production[Expected Production (kWh)]))=0,"",SUMIFS(expected_production[Expected Production (kWh)],expected_production[Site Name],A70,expected_production[Date],B70)),"")} -> 20404.335 | E70: =IF(OR(C70="",D70="",D70=0),"",C70/D70) | F70: =IF(E70="","",IF(E70>=0.9,"Expected",IF(E70>=0.7,"Moderate","Poor")))
A71: African Global Plastics | B71: 46296 | C71: {=IFERROR(IF(SUMPRODUCT((measured[Site Name]=A71)*(measured[Date]=B71)*ISNUMBER(measured[Measured Value (kWh)]))=0,"",SUMIFS(measured[Measured Value (kWh)],measured[Site Name],A71,measured[Date],B71)),"")} | D71: {=IFERROR(IF(SUMPRODUCT((expected_production[Site Name]=A71)*(expected_production[Date]=B71)*ISNUMBER(expected_production[Expected Production (kWh)]))=0,"",SUMIFS(expected_production[Expected Production (kWh)],expected_production[Site Name],A71,expected_production[Date],B71)),"")} -> 22320.66 | E71: =IF(OR(C71="",D71="",D71=0),"",C71/D71) | F71: =IF(E71="","",IF(E71>=0.9,"Expected",IF(E71>=0.7,"Moderate","Poor")))
A72: African Global Plastics | B72: 46327 | C72: {=IFERROR(IF(SUMPRODUCT((measured[Site Name]=A72)*(measured[Date]=B72)*ISNUMBER(measured[Measured Value (kWh)]))=0,"",SUMIFS(measured[Measured Value (kWh)],measured[Site Name],A72,measured[Date],B72)),"")} | D72: {=IFERROR(IF(SUMPRODUCT((expected_production[Site Name]=A72)*(expected_production[Date]=B72)*ISNUMBER(expected_production[Expected Production (kWh)]))=0,"",SUMIFS(expected_production[Expected Production (kWh)],expected_production[Site Name],A72,expected_production[Date],B72)),"")} -> 22520.665 | E72: =IF(OR(C72="",D72="",D72=0),"",C72/D72) | F72: =IF(E72="","",IF(E72>=0.9,"Expected",IF(E72>=0.7,"Moderate","Poor")))
A73: African Global Plastics | B73: 46357 | C73: {=IFERROR(IF(SUMPRODUCT((measured[Site Name]=A73)*(measured[Date]=B73)*ISNUMBER(measured[Measured Value (kWh)]))=0,"",SUMIFS(measured[Measured Value (kWh)],measured[Site Name],A73,measured[Date],B73)),"")} | D73: {=IFERROR(IF(SUMPRODUCT((expected_production[Site Name]=A73)*(expected_production[Date]=B73)*ISNUMBER(expected_production[Expected Production (kWh)]))=0,"",SUMIFS(expected_production[Expected Production (kWh)],expected_production[Site Name],A73,expected_production[Date],B73)),"")} -> 23777.985 | E73: =IF(OR(C73="",D73="",D73=0),"",C73/D73) | F73: =IF(E73="","",IF(E73>=0.9,"Expected",IF(E73>=0.7,"Moderate","Poor")))
A74: Alpine Heath Residential | B74: 45292 | C74: {=IFERROR(IF(SUMPRODUCT((measured[Site Name]=A74)*(measured[Date]=B74)*ISNUMBER(measured[Measured Value (kWh)]))=0,"",SUMIFS(measured[Measured Value (kWh)],measured[Site Name],A74,measured[Date],B74)),"")} | D74: {=IFERROR(IF(SUMPRODUCT((expected_production[Site Name]=A74)*(expected_production[Date]=B74)*ISNUMBER(expected_production[Expected Production (kWh)]))=0,"",SUMIFS(expected_production[Expected Production (kWh)],expected_production[Site Name],A74,expected_production[Date],B74)),"")} -> 4801.5 | E74: =IF(OR(C74="",D74="",D74=0),"",C74/D74) | F74: =IF(E74="","",IF(E74>=0.9,"Expected",IF(E74>=0.7,"Moderate","Poor")))
A75: Alpine Heath Residential | B75: 45323 | C75: {=IFERROR(IF(SUMPRODUCT((measured[Site Name]=A75)*(measured[Date]=B75)*ISNUMBER(measured[Measured Value (kWh)]))=0,"",SUMIFS(measured[Measured Value (kWh)],measured[Site Name],A75,measured[Date],B75)),"")} | D75: {=IFERROR(IF(SUMPRODUCT((expected_production[Site Name]=A75)*(expected_production[Date]=B75)*ISNUMBER(expected_production[Expected Production (kWh)]))=0,"",SUMIFS(expected_production[Expected Production (kWh)],expected_production[Site Name],A75,expected_production[Date],B75)),"")} -> 4303.8 | E75: =IF(OR(C75="",D75="",D75=0),"",C75/D75) | F75: =IF(E75="","",IF(E75>=0.9,"Expected",IF(E75>=0.7,"Moderate","Poor")))
A76: Alpine Heath Residential | B76: 45352 | C76: {=IFERROR(IF(SUMPRODUCT((measured[Site Name]=A76)*(measured[Date]=B76)*ISNUMBER(measured[Measured Value (kWh)]))=0,"",SUMIFS(measured[Measured Value (kWh)],measured[Site Name],A76,measured[Date],B76)),"")} | D76: {=IFERROR(IF(SUMPRODUCT((expected_production[Site Name]=A76)*(expected_production[Date]=B76)*ISNUMBER(expected_production[Expected Production (kWh)]))=0,"",SUMIFS(expected_production[Expected Production (kWh)],expected_production[Site Name],A76,expected_production[Date],B76)),"")} -> 4545.9 | E76: =IF(OR(C76="",D76="",D76=0),"",C76/D76) | F76: =IF(E76="","",IF(E76>=0.9,"Expected",IF(E76>=0.7,"Moderate","Poor")))
A77: Alpine Heath Residential | B77: 45383 | C77: {=IFERROR(IF(SUMPRODUCT((measured[Site Name]=A77)*(measured[Date]=B77)*ISNUMBER(measured[Measured Value (kWh)]))=0,"",SUMIFS(measured[Measured Value (kWh)],measured[Site Name],A77,measured[Date],B77)),"")} | D77: {=IFERROR(IF(SUMPRODUCT((expected_production[Site Name]=A77)*(expected_production[Date]=B77)*ISNUMBER(expected_production[Expected Production (kWh)]))=0,"",SUMIFS(expected_production[Expected Production (kWh)],expected_production[Site Name],A77,expected_production[Date],B77)),"")} -> 4619.7 | E77: =IF(OR(C77="",D77="",D77=0),"",C77/D77) | F77: =IF(E77="","",IF(E77>=0.9,"Expected",IF(E77>=0.7,"Moderate","Poor")))
A78: Alpine Heath Residential | B78: 45413 | C78: {=IFERROR(IF(SUMPRODUCT((measured[Site Name]=A78)*(measured[Date]=B78)*ISNUMBER(measured[Measured Value (kWh)]))=0,"",SUMIFS(measured[Measured Value (kWh)],measured[Site Name],A78,measured[Date],B78)),"")} | D78: {=IFERROR(IF(SUMPRODUCT((expected_production[Site Name]=A78)*(expected_production[Date]=B78)*ISNUMBER(expected_production[Expected Production (kWh)]))=0,"",SUMIFS(expected_production[Expected Production (kWh)],expected_production[Site Name],A78,expected_production[Date],B78)),"")} -> 4990.5 | E78: =IF(OR(C78="",D78="",D78=0),"",C78/D78) | F78: =IF(E78="","",IF(E78>=0.9,"Expected",IF(E78>=0.7,"Moderate","Poor")))
A79: Alpine Heath Residential | B79: 45444 | C79: {=IFERROR(IF(SUMPRODUCT((measured[Site Name]=A79)*(measured[Date]=B79)*ISNUMBER(measured[Measured Value (kWh)]))=0,"",SUMIFS(measured[Measured Value (kWh)],measured[Site Name],A79,measured[Date],B79)),"")} | D79: {=IFERROR(IF(SUMPRODUCT((expected_production[Site Name]=A79)*(expected_production[Date]=B79)*ISNUMBER(expected_production[Expected Production (kWh)]))=0,"",SUMIFS(expected_production[Expected Production (kWh)],expected_production[Site Name],A79,expected_production[Date],B79)),"")} -> 4761.9 | E79: =IF(OR(C79="",D79="",D79=0),"",C79/D79) | F79: =IF(E79="","",IF(E79>=0.9,"Expected",IF(E79>=0.7,"Moderate","Poor")))
A80: Alpine Heath Residential | B80: 45474 | C80: {=IFERROR(IF(SUMPRODUCT((measured[Site Name]=A80)*(measured[Date]=B80)*ISNUMBER(measured[Measured Value (kWh)]))=0,"",SUMIFS(measured[Measured Value (kWh)],measured[Site Name],A80,measured[Date],B80)),"")} | D80: {=IFERROR(IF(SUMPRODUCT((expected_production[Site Name]=A80)*(expected_production[Date]=B80)*ISNUMBER(expected_production[Expected Production (kWh)]))=0,"",SUMIFS(expected_production[Expected Production (kWh)],expected_production[Site Name],A80,expected_production[Date],B80)),"")} -> 4680.9 | E80: =IF(OR(C80="",D80="",D80=0),"",C80/D80) | F80: =IF(E80="","",IF(E80>=0.9,"Expected",IF(E80>=0.7,"Moderate","Poor")))
... A103: Alpine Heath Residential | B103: 46174 | C103: {=IFERROR(IF(SUMPRODUCT((measured[Site Name]=A103)*(measured[Date]=B103)*ISNUMBER(measured[Measured Value (kWh)]))=0,"",SUMIFS(measured[Measured Value (kWh)],measured[Site Name],A103,measured[Date],B103)),"")} -> 2778 | D103: {=IFERROR(IF(SUMPRODUCT((expected_production[Site Name]=A103)*(expected_production[Date]=B103)*ISNUMBER(expected_production[Expected Production (kWh)]))=0,"",SUMIFS(expected_production[Expected Production (kWh)],expected_production[Site Name],A103,expected_production[Date],B103)),"")} -> 4761.9 | E103: =IF(OR(C103="",D103="",D103=0),"",C103/D103) -> 0.58338058 | F103: =IF(E103="","",IF(E103>=0.9,"Expected",IF(E103>=0.7,"Moderate","Poor"))) -> Poor
A104: Alpine Heath Residential | B104: 46204 | C104: {=IFERROR(IF(SUMPRODUCT((measured[Site Name]=A104)*(measured[Date]=B104)*ISNUMBER(measured[Measured Value (kWh)]))=0,"",SUMIFS(measured[Measured Value (kWh)],measured[Site Name],A104,measured[Date],B104)),"")} -> 2644 | D104: {=IFERROR(IF(SUMPRODUCT((expected_production[Site Name]=A104)*(expected_production[Date]=B104)*ISNUMBER(expected_production[Expected Production (kWh)]))=0,"",SUMIFS(expected_production[Expected Production (kWh)],expected_production[Site Name],A104,expected_production[Date],B104)),"")} -> 4680.9 | E104: =IF(OR(C104="",D104="",D104=0),"",C104/D104) -> 0.56484864 | F104: =IF(E104="","",IF(E104>=0.9,"Expected",IF(E104>=0.7,"Moderate","Poor"))) -> Poor | G104: NO
A105: Alpine Heath Residential | B105: 46235 | C105: {=IFERROR(IF(SUMPRODUCT((measured[Site Name]=A105)*(measured[Date]=B105)*ISNUMBER(measured[Measured Value (kWh)]))=0,"",SUMIFS(measured[Measured Value (kWh)],measured[Site Name],A105,measured[Date],B105)),"")} | D105: {=IFERROR(IF(SUMPRODUCT((expected_production[Site Name]=A105)*(expected_production[Date]=B105)*ISNUMBER(expected_production[Expected Production (kWh)]))=0,"",SUMIFS(expected_production[Expected Production (kWh)],expected_production[Site Name],A105,expected_production[Date],B105)),"")} -> 5249.7 | E105: =IF(OR(C105="",D105="",D105=0),"",C105/D105) | F105: =IF(E105="","",IF(E105>=0.9,"Expected",IF(E105>=0.7,"Moderate","Poor")))
A106: Alpine Heath Residential | B106: 46266 | C106: {=IFERROR(IF(SUMPRODUCT((measured[Site Name]=A106)*(measured[Date]=B106)*ISNUMBER(measured[Measured Value (kWh)]))=0,"",SUMIFS(measured[Measured Value (kWh)],measured[Site Name],A106,measured[Date],B106)),"")} | D106: {=IFERROR(IF(SUMPRODUCT((expected_production[Site Name]=A106)*(expected_production[Date]=B106)*ISNUMBER(expected_production[Expected Production (kWh)]))=0,"",SUMIFS(expected_production[Expected Production (kWh)],expected_production[Site Name],A106,expected_production[Date],B106)),"")} -> 4694.4 | E106: =IF(OR(C106="",D106="",D106=0),"",C106/D106) | F106: =IF(E106="","",IF(E106>=0.9,"Expected",IF(E106>=0.7,"Moderate","Poor")))
A107: Alpine Heath Residential | B107: 46296 | C107: {=IFERROR(IF(SUMPRODUCT((measured[Site Name]=A107)*(measured[Date]=B107)*ISNUMBER(measured[Measured Value (kWh)]))=0,"",SUMIFS(measured[Measured Value (kWh)],measured[Site Name],A107,measured[Date],B107)),"")} | D107: {=IFERROR(IF(SUMPRODUCT((expected_production[Site Name]=A107)*(expected_production[Date]=B107)*ISNUMBER(expected_production[Expected Production (kWh)]))=0,"",SUMIFS(expected_production[Expected Production (kWh)],expected_production[Site Name],A107,expected_production[Date],B107)),"")} -> 4732.2 | E107: =IF(OR(C107="",D107="",D107=0),"",C107/D107) | F107: =IF(E107="","",IF(E107>=0.9,"Expected",IF(E107>=0.7,"Moderate","Poor")))
A108: Alpine Heath Residential | B108: 46327 | C108: {=IFERROR(IF(SUMPRODUCT((measured[Site Name]=A108)*(measured[Date]=B108)*ISNUMBER(measured[Measured Value (kWh)]))=0,"",SUMIFS(measured[Measured Value (kWh)],measured[Site Name],A108,measured[Date],B108)),"")} | D108: {=IFERROR(IF(SUMPRODUCT((expected_production[Site Name]=A108)*(expected_production[Date]=B108)*ISNUMBER(expected_production[Expected Production (kWh)]))=0,"",SUMIFS(expected_production[Expected Production (kWh)],expected_production[Site Name],A108,expected_production[Date],B108)),"")} -> 4822.2 | E108: =IF(OR(C108="",D108="",D108=0),"",C108/D108) | F108: =IF(E108="","",IF(E108>=0.9,"Expected",IF(E108>=0.7,"Moderate","Poor")))
A109: Alpine Heath Residential | B109: 46357 | C109: {=IFERROR(IF(SUMPRODUCT((measured[Site Name]=A109)*(measured[Date]=B109)*ISNUMBER(measured[Measured Value (kWh)]))=0,"",SUMIFS(measured[Measured Value (kWh)],measured[Site Name],A109,measured[Date],B109)),"")} | D109: {=IFERROR(IF(SUMPRODUCT((expected_production[Site Name]=A109)*(expected_production[Date]=B109)*ISNUMBER(expected_production[Expected Production (kWh)]))=0,"",SUMIFS(expected_production[Expected Production (kWh)],expected_production[Site Name],A109,expected_production[Date],B109)),"")} -> 4805.1 | E109: =IF(OR(C109="",D109="",D109=0),"",C109/D109) | F109: =IF(E109="","",IF(E109>=0.9,"Expected",IF(E109>=0.7,"Moderate","Poor")))
A110: BP Parys | B110: 45292 | C110: {=IFERROR(IF(SUMPRODUCT((measured[Site Name]=A110)*(measured[Date]=B110)*ISNUMBER(measured[Measured Value (kWh)]))=0,"",SUMIFS(measured[Measured Value (kWh)],measured[Site Name],A110,measured[Date],B110)),"")} | D110: {=IFERROR(IF(SUMPRODUCT((expected_production[Site Name]=A110)*(expected_production[Date]=B110)*ISNUMBER(expected_production[Expected Production (kWh)]))=0,"",SUMIFS(expected_production[Expected Production (kWh)],expected_production[Site Name],A110,expected_production[Date],B110)),"")} -> 8151.3 | E110: =IF(OR(C110="",D110="",D110=0),"",C110/D110) | F110: =IF(E110="","",IF(E110>=0.9,"Expected",IF(E110>=0.7,"Moderate","Poor")))
A111: BP Parys | B111: 45323 | C111: {=IFERROR(IF(SUMPRODUCT((measured[Site Name]=A111)*(measured[Date]=B111)*ISNUMBER(measured[Measured Value (kWh)]))=0,"",SUMIFS(measured[Measured Value (kWh)],measured[Site Name],A111,measured[Date],B111)),"")} | D111: {=IFERROR(IF(SUMPRODUCT((expected_production[Site Name]=A111)*(expected_production[Date]=B111)*ISNUMBER(expected_production[Expected Production (kWh)]))=0,"",SUMIFS(expected_production[Expected Production (kWh)],expected_production[Site Name],A111,expected_production[Date],B111)),"")} -> 7235.1 | E111: =IF(OR(C111="",D111="",D111=0),"",C111/D111) | F111: =IF(E111="","",IF(E111>=0.9,"Expected",IF(E111>=0.7,"Moderate","Poor")))
A112: BP Parys | B112: 45352 | C112: {=IFERROR(IF(SUMPRODUCT((measured[Site Name]=A112)*(measured[Date]=B112)*ISNUMBER(measured[Measured Value (kWh)]))=0,"",SUMIFS(measured[Measured Value (kWh)],measured[Site Name],A112,measured[Date],B112)),"")} | D112: {=IFERROR(IF(SUMPRODUCT((expected_production[Site Name]=A112)*(expected_production[Date]=B112)*ISNUMBER(expected_production[Expected Production (kWh)]))=0,"",SUMIFS(expected_production[Expected Production (kWh)],expected_production[Site Name],A112,expected_production[Date],B112)),"")} -> 7075.8 | E112: =IF(OR(C112="",D112="",D112=0),"",C112/D112) | F112: =IF(E112="","",IF(E112>=0.9,"Expected",IF(E112>=0.7,"Moderate","Poor")))
A113: BP Parys | B113: 45383 | C113: {=IFERROR(IF(SUMPRODUCT((measured[Site Name]=A113)*(measured[Date]=B113)*ISNUMBER(measured[Measured Value (kWh)]))=0,"",SUMIFS(measured[Measured Value (kWh)],measured[Site Name],A113,measured[Date],B113)),"")} | D113: {=IFERROR(IF(SUMPRODUCT((expected_production[Site Name]=A113)*(expected_production[Date]=B113)*ISNUMBER(expected_production[Expected Production (kWh)]))=0,"",SUMIFS(expected_production[Expected Production (kWh)],expected_production[Site Name],A113,expected_production[Date],B113)),"")} -> 5754.6 | E113: =IF(OR(C113="",D113="",D113=0),"",C113/D113) | F113: =IF(E113="","",IF(E113>=0.9,"Expected",IF(E113>=0.7,"Moderate","Poor")))
A114: BP Parys | B114: 45413 | C114: {=IFERROR(IF(SUMPRODUCT((measured[Site Name]=A114)*(measured[Date]=B114)*ISNUMBER(measured[Measured Value (kWh)]))=0,"",SUMIFS(measured[Measured Value (kWh)],measured[Site Name],A114,measured[Date],B114)),"")} | D114: {=IFERROR(IF(SUMPRODUCT((expected_production[Site Name]=A114)*(expected_production[Date]=B114)*ISNUMBER(expected_production[Expected Production (kWh)]))=0,"",SUMIFS(expected_production[Expected Production (kWh)],expected_production[Site Name],A114,expected_production[Date],B114)),"")} -> 5424.3 | E114: =IF(OR(C114="",D114="",D114=0),"",C114/D114) | F114: =IF(E114="","",IF(E114>=0.9,"Expected",IF(E114>=0.7,"Moderate","Poor")))
A115: BP Parys | B115: 45444 | C115: {=IFERROR(IF(SUMPRODUCT((measured[Site Name]=A115)*(measured[Date]=B115)*ISNUMBER(measured[Measured Value (kWh)]))=0,"",SUMIFS(measured[Measured Value (kWh)],measured[Site Name],A115,measured[Date],B115)),"")} | D115: {=IFERROR(IF(SUMPRODUCT((expected_production[Site Name]=A115)*(expected_production[Date]=B115)*ISNUMBER(expected_production[Expected Production (kWh)]))=0,"",SUMIFS(expected_production[Expected Production (kWh)],expected_production[Site Name],A115,expected_production[Date],B115)),"")} -> 4787.1 | E115: =IF(OR(C115="",D115="",D115=0),"",C115/D115) | F115: =IF(E115="","",IF(E115>=0.9,"Expected",IF(E115>=0.7,"Moderate","Poor")))
A116: BP Parys | B116: 45474 | C116: {=IFERROR(IF(SUMPRODUCT((measured[Site Name]=A116)*(measured[Date]=B116)*ISNUMBER(measured[Measured Value (kWh)]))=0,"",SUMIFS(measured[Measured Value (kWh)],measured[Site Name],A116,measured[Date],B116)),"")} | D116: {=IFERROR(IF(SUMPRODUCT((expected_production[Site Name]=A116)*(expected_production[Date]=B116)*ISNUMBER(expected_production[Expected Production (kWh)]))=0,"",SUMIFS(expected_production[Expected Production (kWh)],expected_production[Site Name],A116,expected_production[Date],B116)),"")} -> 5360.4 | E116: =IF(OR(C116="",D116="",D116=0),"",C116/D116) | F116: =IF(E116="","",IF(E116>=0.9,"Expected",IF(E116>=0.7,"Moderate","Poor")))
... A139: BP Parys | B139: 46174 | C139: {=IFERROR(IF(SUMPRODUCT((measured[Site Name]=A139)*(measured[Date]=B139)*ISNUMBER(measured[Measured Value (kWh)]))=0,"",SUMIFS(measured[Measured Value (kWh)],measured[Site Name],A139,measured[Date],B139)),"")} -> 3149 | D139: {=IFERROR(IF(SUMPRODUCT((expected_production[Site Name]=A139)*(expected_production[Date]=B139)*ISNUMBER(expected_production[Expected Production (kWh)]))=0,"",SUMIFS(expected_production[Expected Production (kWh)],expected_production[Site Name],A139,expected_production[Date],B139)),"")} -> 4787.1 | E139: =IF(OR(C139="",D139="",D139=0),"",C139/D139) -> 0.65780953 | F139: =IF(E139="","",IF(E139>=0.9,"Expected",IF(E139>=0.7,"Moderate","Poor"))) -> Poor
A140: Alpine Heath Resort | B140: 46204 | C140: {=IFERROR(IF(SUMPRODUCT((measured[Site Name]=A140)*(measured[Date]=B140)*ISNUMBER(measured[Measured Value (kWh)]))=0,"",SUMIFS(measured[Measured Value (kWh)],measured[Site Name],A140,measured[Date],B140)),"")} -> 27942 | D140: {=IFERROR(IF(SUMPRODUCT((expected_production[Site Name]=A140)*(expected_production[Date]=B140)*ISNUMBER(expected_production[Expected Production (kWh)]))=0,"",SUMIFS(expected_production[Expected Production (kWh)],expected_production[Site Name],A140,expected_production[Date],B140)),"")} -> 28051.2 | E140: =IF(OR(C140="",D140="",D140=0),"",C140/D140) -> 0.99610712 | F140: =IF(E140="","",IF(E140>=0.9,"Expected",IF(E140>=0.7,"Moderate","Poor"))) -> Expected | G140: NO
A141: BP Parys | B141: 46235 | C141: {=IFERROR(IF(SUMPRODUCT((measured[Site Name]=A141)*(measured[Date]=B141)*ISNUMBER(measured[Measured Value (kWh)]))=0,"",SUMIFS(measured[Measured Value (kWh)],measured[Site Name],A141,measured[Date],B141)),"")} | D141: {=IFERROR(IF(SUMPRODUCT((expected_production[Site Name]=A141)*(expected_production[Date]=B141)*ISNUMBER(expected_production[Expected Production (kWh)]))=0,"",SUMIFS(expected_production[Expected Production (kWh)],expected_production[Site Name],A141,expected_production[Date],B141)),"")} -> 6363 | E141: =IF(OR(C141="",D141="",D141=0),"",C141/D141) | F141: =IF(E141="","",IF(E141>=0.9,"Expected",IF(E141>=0.7,"Moderate","Poor")))
A142: BP Parys | B142: 46266 | C142: {=IFERROR(IF(SUMPRODUCT((measured[Site Name]=A142)*(measured[Date]=B142)*ISNUMBER(measured[Measured Value (kWh)]))=0,"",SUMIFS(measured[Measured Value (kWh)],measured[Site Name],A142,measured[Date],B142)),"")} | D142: {=IFERROR(IF(SUMPRODUCT((expected_production[Site Name]=A142)*(expected_production[Date]=B142)*ISNUMBER(expected_production[Expected Production (kWh)]))=0,"",SUMIFS(expected_production[Expected Production (kWh)],expected_production[Site Name],A142,expected_production[Date],B142)),"")} -> 7218.9 | E142: =IF(OR(C142="",D142="",D142=0),"",C142/D142) | F142: =IF(E142="","",IF(E142>=0.9,"Expected",IF(E142>=0.7,"Moderate","Poor")))
A143: BP Parys | B143: 46296 | C143: {=IFERROR(IF(SUMPRODUCT((measured[Site Name]=A143)*(measured[Date]=B143)*ISNUMBER(measured[Measured Value (kWh)]))=0,"",SUMIFS(measured[Measured Value (kWh)],measured[Site Name],A143,measured[Date],B143)),"")} | D143: {=IFERROR(IF(SUMPRODUCT((expected_production[Site Name]=A143)*(expected_production[Date]=B143)*ISNUMBER(expected_production[Expected Production (kWh)]))=0,"",SUMIFS(expected_production[Expected Production (kWh)],expected_production[Site Name],A143,expected_production[Date],B143)),"")} -> 7839 | E143: =IF(OR(C143="",D143="",D143=0),"",C143/D143) | F143: =IF(E143="","",IF(E143>=0.9,"Expected",IF(E143>=0.7,"Moderate","Poor")))
A144: BP Parys | B144: 46327 | C144: {=IFERROR(IF(SUMPRODUCT((measured[Site Name]=A144)*(measured[Date]=B144)*ISNUMBER(measured[Measured Value (kWh)]))=0,"",SUMIFS(measured[Measured Value (kWh)],measured[Site Name],A144,measured[Date],B144)),"")} | D144: {=IFERROR(IF(SUMPRODUCT((expected_production[Site Name]=A144)*(expected_production[Date]=B144)*ISNUMBER(expected_production[Expected Production (kWh)]))=0,"",SUMIFS(expected_production[Expected Production (kWh)],expected_production[Site Name],A144,expected_production[Date],B144)),"")} -> 8191.8 | E144: =IF(OR(C144="",D144="",D144=0),"",C144/D144) | F144: =IF(E144="","",IF(E144>=0.9,"Expected",IF(E144>=0.7,"Moderate","Poor")))
A145: BP Parys | B145: 46357 | C145: {=IFERROR(IF(SUMPRODUCT((measured[Site Name]=A145)*(measured[Date]=B145)*ISNUMBER(measured[Measured Value (kWh)]))=0,"",SUMIFS(measured[Measured Value (kWh)],measured[Site Name],A145,measured[Date],B145)),"")} | D145: {=IFERROR(IF(SUMPRODUCT((expected_production[Site Name]=A145)*(expected_production[Date]=B145)*ISNUMBER(expected_production[Expected Production (kWh)]))=0,"",SUMIFS(expected_production[Expected Production (kWh)],expected_production[Site Name],A145,expected_production[Date],B145)),"")} -> 8227.8 | E145: =IF(OR(C145="",D145="",D145=0),"",C145/D145) | F145: =IF(E145="","",IF(E145>=0.9,"Expected",IF(E145>=0.7,"Moderate","Poor")))
A146: Bendstore Plaza Shops | B146: 45292 | C146: {=IFERROR(IF(SUMPRODUCT((measured[Site Name]=A146)*(measured[Date]=B146)*ISNUMBER(measured[Measured Value (kWh)]))=0,"",SUMIFS(measured[Measured Value (kWh)],measured[Site Name],A146,measured[Date],B146)),"")} -> 7453 | D146: {=IFERROR(IF(SUMPRODUCT((expected_production[Site Name]=A146)*(expected_production[Date]=B146)*ISNUMBER(expected_production[Expected Production (kWh)]))=0,"",SUMIFS(expected_production[Expected Production (kWh)],expected_production[Site Name],A146,expected_production[Date],B146)),"")} -> 16262.2 | E146: =IF(OR(C146="",D146="",D146=0),"",C146/D146) -> 0.45830207 | F146: =IF(E146="","",IF(E146>=0.9,"Expected",IF(E146>=0.7,"Moderate","Poor"))) -> Poor
A147: Bendstore Plaza Shops | B147: 45323 | C147: {=IFERROR(IF(SUMPRODUCT((measured[Site Name]=A147)*(measured[Date]=B147)*ISNUMBER(measured[Measured Value (kWh)]))=0,"",SUMIFS(measured[Measured Value (kWh)],measured[Site Name],A147,measured[Date],B147)),"")} -> 10174 | D147: {=IFERROR(IF(SUMPRODUCT((expected_production[Site Name]=A147)*(expected_production[Date]=B147)*ISNUMBER(expected_production[Expected Production (kWh)]))=0,"",SUMIFS(expected_production[Expected Production (kWh)],expected_production[Site Name],A147,expected_production[Date],B147)),"")} -> 13986.75 | E147: =IF(OR(C147="",D147="",D147=0),"",C147/D147) -> 0.72740272 | F147: =IF(E147="","",IF(E147>=0.9,"Expected",IF(E147>=0.7,"Moderate","Poor"))) -> Moderate
A148: Bendstore Plaza Shops | B148: 45352 | C148: {=IFERROR(IF(SUMPRODUCT((measured[Site Name]=A148)*(measured[Date]=B148)*ISNUMBER(measured[Measured Value (kWh)]))=0,"",SUMIFS(measured[Measured Value (kWh)],measured[Site Name],A148,measured[Date],B148)),"")} -> 12197 | D148: {=IFERROR(IF(SUMPRODUCT((expected_production[Site Name]=A148)*(expected_production[Date]=B148)*ISNUMBER(expected_production[Expected Production (kWh)]))=0,"",SUMIFS(expected_production[Expected Production (kWh)],expected_production[Site Name],A148,expected_production[Date],B148)),"")} -> 15463.2 | E148: =IF(OR(C148="",D148="",D148=0),"",C148/D148) -> 0.78877593 | F148: =IF(E148="","",IF(E148>=0.9,"Expected",IF(E148>=0.7,"Moderate","Poor"))) -> Moderate
A149: Bendstore Plaza Shops | B149: 45383 | C149: {=IFERROR(IF(SUMPRODUCT((measured[Site Name]=A149)*(measured[Date]=B149)*ISNUMBER(measured[Measured Value (kWh)]))=0,"",SUMIFS(measured[Measured Value (kWh)],measured[Site Name],A149,measured[Date],B149)),"")} -> 9850 | D149: {=IFERROR(IF(SUMPRODUCT((expected_production[Site Name]=A149)*(expected_production[Date]=B149)*ISNUMBER(expected_production[Expected Production (kWh)]))=0,"",SUMIFS(expected_production[Expected Production (kWh)],expected_production[Site Name],A149,expected_production[Date],B149)),"")} -> 14886.05 | E149: =IF(OR(C149="",D149="",D149=0),"",C149/D149) -> 0.66169333 | F149: =IF(E149="","",IF(E149>=0.9,"Expected",IF(E149>=0.7,"Moderate","Poor"))) -> Poor
A150: Bendstore Plaza Shops | B150: 45413 | C150: {=IFERROR(IF(SUMPRODUCT((measured[Site Name]=A150)*(measured[Date]=B150)*ISNUMBER(measured[Measured Value (kWh)]))=0,"",SUMIFS(measured[Measured Value (kWh)],measured[Site Name],A150,measured[Date],B150)),"")} -> 10329 | D150: {=IFERROR(IF(SUMPRODUCT((expected_production[Site Name]=A150)*(expected_production[Date]=B150)*ISNUMBER(expected_production[Expected Production (kWh)]))=0,"",SUMIFS(expected_production[Expected Production (kWh)],expected_production[Site Name],A150,expected_production[Date],B150)),"")} -> 14411.75 | E150: =IF(OR(C150="",D150="",D150=0),"",C150/D150) -> 0.71670685 | F150: =IF(E150="","",IF(E150>=0.9,"Expected",IF(E150>=0.7,"Moderate","Poor"))) -> Moderate
A151: Bendstore Plaza Shops | B151: 45444 | C151: {=IFERROR(IF(SUMPRODUCT((measured[Site Name]=A151)*(measured[Date]=B151)*ISNUMBER(measured[Measured Value (kWh)]))=0,"",SUMIFS(measured[Measured Value (kWh)],measured[Site Name],A151,measured[Date],B151)),"")} -> 9684 | D151: {=IFERROR(IF(SUMPRODUCT((expected_production[Site Name]=A151)*(expected_production[Date]=B151)*ISNUMBER(expected_production[Expected Production (kWh)]))=0,"",SUMIFS(expected_production[Expected Production (kWh)],expected_production[Site Name],A151,expected_production[Date],B151)),"")} -> 13050.05 | E151: =IF(OR(C151="",D151="",D151=0),"",C151/D151) -> 0.74206612 | F151: =IF(E151="","",IF(E151>=0.9,"Expected",IF(E151>=0.7,"Moderate","Poor"))) -> Moderate
A152: Bendstore Plaza Shops | B152: 45474 | C152: {=IFERROR(IF(SUMPRODUCT((measured[Site Name]=A152)*(measured[Date]=B152)*ISNUMBER(measured[Measured Value (kWh)]))=0,"",SUMIFS(measured[Measured Value (kWh)],measured[Site Name],A152,measured[Date],B152)),"")} -> 10193 | D152: {=IFERROR(IF(SUMPRODUCT((expected_production[Site Name]=A152)*(expected_production[Date]=B152)*ISNUMBER(expected_production[Expected Production (kWh)]))=0,"",SUMIFS(expected_production[Expected Production (kWh)],expected_production[Site Name],A152,expected_production[Date],B152)),"")} -> 13735.15 | E152: =IF(OR(C152="",D152="",D152=0),"",C152/D152) -> 0.74211057 | F152: =IF(E152="","",IF(E152>=0.9,"Expected",IF(E152>=0.7,"Moderate","Poor"))) -> Moderate
... A175: Bendstore Plaza Shops | B175: 46174 | C175: {=IFERROR(IF(SUMPRODUCT((measured[Site Name]=A175)*(measured[Date]=B175)*ISNUMBER(measured[Measured Value (kWh)]))=0,"",SUMIFS(measured[Measured Value (kWh)],measured[Site Name],A175,measured[Date],B175)),"")} -> 7968.17 | D175: {=IFERROR(IF(SUMPRODUCT((expected_production[Site Name]=A175)*(expected_production[Date]=B175)*ISNUMBER(expected_production[Expected Production (kWh)]))=0,"",SUMIFS(expected_production[Expected Production (kWh)],expected_production[Site Name],A175,expected_production[Date],B175)),"")} -> 13050.05 | E175: =IF(OR(C175="",D175="",D175=0),"",C175/D175) -> 0.6105854 | F175: =IF(E175="","",IF(E175>=0.9,"Expected",IF(E175>=0.7,"Moderate","Poor"))) -> Poor
A176: Bendstore Plaza Shops | B176: 46204 | C176: {=IFERROR(IF(SUMPRODUCT((measured[Site Name]=A176)*(measured[Date]=B176)*ISNUMBER(measured[Measured Value (kWh)]))=0,"",SUMIFS(measured[Measured Value (kWh)],measured[Site Name],A176,measured[Date],B176)),"")} -> 10351.41 | D176: {=IFERROR(IF(SUMPRODUCT((expected_production[Site Name]=A176)*(expected_production[Date]=B176)*ISNUMBER(expected_production[Expected Production (kWh)]))=0,"",SUMIFS(expected_production[Expected Production (kWh)],expected_production[Site Name],A176,expected_production[Date],B176)),"")} -> 13735.15 | E176: =IF(OR(C176="",D176="",D176=0),"",C176/D176) -> 0.75364375 | F176: =IF(E176="","",IF(E176>=0.9,"Expected",IF(E176>=0.7,"Moderate","Poor"))) -> Moderate | G176: NO
A177: Bendstore Plaza Shops | B177: 46235 | C177: {=IFERROR(IF(SUMPRODUCT((measured[Site Name]=A177)*(measured[Date]=B177)*ISNUMBER(measured[Measured Value (kWh)]))=0,"",SUMIFS(measured[Measured Value (kWh)],measured[Site Name],A177,measured[Date],B177)),"")} | D177: {=IFERROR(IF(SUMPRODUCT((expected_production[Site Name]=A177)*(expected_production[Date]=B177)*ISNUMBER(expected_production[Expected Production (kWh)]))=0,"",SUMIFS(expected_production[Expected Production (kWh)],expected_production[Site Name],A177,expected_production[Date],B177)),"")} -> 15350.15 | E177: =IF(OR(C177="",D177="",D177=0),"",C177/D177) | F177: =IF(E177="","",IF(E177>=0.9,"Expected",IF(E177>=0.7,"Moderate","Poor")))
A178: Bendstore Plaza Shops | B178: 46266 | C178: {=IFERROR(IF(SUMPRODUCT((measured[Site Name]=A178)*(measured[Date]=B178)*ISNUMBER(measured[Measured Value (kWh)]))=0,"",SUMIFS(measured[Measured Value (kWh)],measured[Site Name],A178,measured[Date],B178)),"")} | D178: {=IFERROR(IF(SUMPRODUCT((expected_production[Site Name]=A178)*(expected_production[Date]=B178)*ISNUMBER(expected_production[Expected Production (kWh)]))=0,"",SUMIFS(expected_production[Expected Production (kWh)],expected_production[Site Name],A178,expected_production[Date],B178)),"")} -> 15431.75 | E178: =IF(OR(C178="",D178="",D178=0),"",C178/D178) | F178: =IF(E178="","",IF(E178>=0.9,"Expected",IF(E178>=0.7,"Moderate","Poor")))
A179: Bendstore Plaza Shops | B179: 46296 | C179: {=IFERROR(IF(SUMPRODUCT((measured[Site Name]=A179)*(measured[Date]=B179)*ISNUMBER(measured[Measured Value (kWh)]))=0,"",SUMIFS(measured[Measured Value (kWh)],measured[Site Name],A179,measured[Date],B179)),"")} | D179: {=IFERROR(IF(SUMPRODUCT((expected_production[Site Name]=A179)*(expected_production[Date]=B179)*ISNUMBER(expected_production[Expected Production (kWh)]))=0,"",SUMIFS(expected_production[Expected Production (kWh)],expected_production[Site Name],A179,expected_production[Date],B179)),"")} -> 14821.45 | E179: =IF(OR(C179="",D179="",D179=0),"",C179/D179) | F179: =IF(E179="","",IF(E179>=0.9,"Expected",IF(E179>=0.7,"Moderate","Poor")))
A180: Bendstore Plaza Shops | B180: 46327 | C180: {=IFERROR(IF(SUMPRODUCT((measured[Site Name]=A180)*(measured[Date]=B180)*ISNUMBER(measured[Measured Value (kWh)]))=0,"",SUMIFS(measured[Measured Value (kWh)],measured[Site Name],A180,measured[Date],B180)),"")} | D180: {=IFERROR(IF(SUMPRODUCT((expected_production[Site Name]=A180)*(expected_production[Date]=B180)*ISNUMBER(expected_production[Expected Production (kWh)]))=0,"",SUMIFS(expected_production[Expected Production (kWh)],expected_production[Site Name],A180,expected_production[Date],B180)),"")} -> 14695.65 | E180: =IF(OR(C180="",D180="",D180=0),"",C180/D180) | F180: =IF(E180="","",IF(E180>=0.9,"Expected",IF(E180>=0.7,"Moderate","Poor")))
A181: Bendstore Plaza Shops | B181: 46357 | C181: {=IFERROR(IF(SUMPRODUCT((measured[Site Name]=A181)*(measured[Date]=B181)*ISNUMBER(measured[Measured Value (kWh)]))=0,"",SUMIFS(measured[Measured Value (kWh)],measured[Site Name],A181,measured[Date],B181)),"")} | D181: {=IFERROR(IF(SUMPRODUCT((expected_production[Site Name]=A181)*(expected_production[Date]=B181)*ISNUMBER(expected_production[Expected Production (kWh)]))=0,"",SUMIFS(expected_production[Expected Production (kWh)],expected_production[Site Name],A181,expected_production[Date],B181)),"")} -> 16154.25 | E181: =IF(OR(C181="",D181="",D181=0),"",C181/D181) | F181: =IF(E181="","",IF(E181>=0.9,"Expected",IF(E181>=0.7,"Moderate","Poor")))
A182: Bendstore Spar | B182: 45292 | C182: {=IFERROR(IF(SUMPRODUCT((measured[Site Name]=A182)*(measured[Date]=B182)*ISNUMBER(measured[Measured Value (kWh)]))=0,"",SUMIFS(measured[Measured Value (kWh)],measured[Site Name],A182,measured[Date],B182)),"")} -> 55000 | D182: {=IFERROR(IF(SUMPRODUCT((expected_production[Site Name]=A182)*(expected_production[Date]=B182)*ISNUMBER(expected_production[Expected Production (kWh)]))=0,"",SUMIFS(expected_production[Expected Production (kWh)],expected_production[Site Name],A182,expected_production[Date],B182)),"")} -> 51314.735 | E182: =IF(OR(C182="",D182="",D182=0),"",C182/D182) -> 1.0718169 | F182: =IF(E182="","",IF(E182>=0.9,"Expected",IF(E182>=0.7,"Moderate","Poor"))) -> Expected
A183: Bendstore Spar | B183: 45323 | C183: {=IFERROR(IF(SUMPRODUCT((measured[Site Name]=A183)*(measured[Date]=B183)*ISNUMBER(measured[Measured Value (kWh)]))=0,"",SUMIFS(measured[Measured Value (kWh)],measured[Site Name],A183,measured[Date],B183)),"")} -> 46799 | D183: {=IFERROR(IF(SUMPRODUCT((expected_production[Site Name]=A183)*(expected_production[Date]=B183)*ISNUMBER(expected_production[Expected Production (kWh)]))=0,"",SUMIFS(expected_production[Expected Production (kWh)],expected_production[Site Name],A183,expected_production[Date],B183)),"")} -> 44103.291 | E183: =IF(OR(C183="",D183="",D183=0),"",C183/D183) -> 1.0611226 | F183: =IF(E183="","",IF(E183>=0.9,"Expected",IF(E183>=0.7,"Moderate","Poor"))) -> Expected
A184: Bendstore Spar | B184: 45352 | C184: {=IFERROR(IF(SUMPRODUCT((measured[Site Name]=A184)*(measured[Date]=B184)*ISNUMBER(measured[Measured Value (kWh)]))=0,"",SUMIFS(measured[Measured Value (kWh)],measured[Site Name],A184,measured[Date],B184)),"")} -> 40582 | D184: {=IFERROR(IF(SUMPRODUCT((expected_production[Site Name]=A184)*(expected_production[Date]=B184)*ISNUMBER(expected_production[Expected Production (kWh)]))=0,"",SUMIFS(expected_production[Expected Production (kWh)],expected_production[Site Name],A184,expected_production[Date],B184)),"")} -> 48739.27 | E184: =IF(OR(C184="",D184="",D184=0),"",C184/D184) -> 0.83263455 | F184: =IF(E184="","",IF(E184>=0.9,"Expected",IF(E184>=0.7,"Moderate","Poor"))) -> Moderate
A185: Bendstore Spar | B185: 45383 | C185: {=IFERROR(IF(SUMPRODUCT((measured[Site Name]=A185)*(measured[Date]=B185)*ISNUMBER(measured[Measured Value (kWh)]))=0,"",SUMIFS(measured[Measured Value (kWh)],measured[Site Name],A185,measured[Date],B185)),"")} -> 39615 | D185: {=IFERROR(IF(SUMPRODUCT((expected_production[Site Name]=A185)*(expected_production[Date]=B185)*ISNUMBER(expected_production[Expected Production (kWh)]))=0,"",SUMIFS(expected_production[Expected Production (kWh)],expected_production[Site Name],A185,expected_production[Date],B185)),"")} -> 46849.899 | E185: =IF(OR(C185="",D185="",D185=0),"",C185/D185) -> 0.8455728 | F185: =IF(E185="","",IF(E185>=0.9,"Expected",IF(E185>=0.7,"Moderate","Poor"))) -> Moderate
A186: Bendstore Spar | B186: 45413 | C186: {=IFERROR(IF(SUMPRODUCT((measured[Site Name]=A186)*(measured[Date]=B186)*ISNUMBER(measured[Measured Value (kWh)]))=0,"",SUMIFS(measured[Measured Value (kWh)],measured[Site Name],A186,measured[Date],B186)),"")} -> 39494 | D186: {=IFERROR(IF(SUMPRODUCT((expected_production[Site Name]=A186)*(expected_production[Date]=B186)*ISNUMBER(expected_production[Expected Production (kWh)]))=0,"",SUMIFS(expected_production[Expected Production (kWh)],expected_production[Site Name],A186,expected_production[Date],B186)),"")} -> 45273.233 | E186: =IF(OR(C186="",D186="",D186=0),"",C186/D186) -> 0.87234768 | F186: =IF(E186="","",IF(E186>=0.9,"Expected",IF(E186>=0.7,"Moderate","Poor"))) -> Moderate
A187: Bendstore Spar | B187: 45444 | C187: {=IFERROR(IF(SUMPRODUCT((measured[Site Name]=A187)*(measured[Date]=B187)*ISNUMBER(measured[Measured Value (kWh)]))=0,"",SUMIFS(measured[Measured Value (kWh)],measured[Site Name],A187,measured[Date],B187)),"")} -> 35378 | D187: {=IFERROR(IF(SUMPRODUCT((expected_production[Site Name]=A187)*(expected_production[Date]=B187)*ISNUMBER(expected_production[Expected Production (kWh)]))=0,"",SUMIFS(expected_production[Expected Production (kWh)],expected_production[Site Name],A187,expected_production[Date],B187)),"")} -> 40943.972 | E187: =IF(OR(C187="",D187="",D187=0),"",C187/D187) -> 0.86405882 | F187: =IF(E187="","",IF(E187>=0.9,"Expected",IF(E187>=0.7,"Moderate","Poor"))) -> Moderate
A188: Bendstore Spar | B188: 45474 | C188: {=IFERROR(IF(SUMPRODUCT((measured[Site Name]=A188)*(measured[Date]=B188)*ISNUMBER(measured[Measured Value (kWh)]))=0,"",SUMIFS(measured[Measured Value (kWh)],measured[Site Name],A188,measured[Date],B188)),"")} -> 38293 | D188: {=IFERROR(IF(SUMPRODUCT((expected_production[Site Name]=A188)*(expected_production[Date]=B188)*ISNUMBER(expected_production[Expected Production (kWh)]))=0,"",SUMIFS(expected_production[Expected Production (kWh)],expected_production[Site Name],A188,expected_production[Date],B188)),"")} -> 43112.803 | E188: =IF(OR(C188="",D188="",D188=0),"",C188/D188) -> 0.88820483 | F188: =IF(E188="","",IF(E188>=0.9,"Expected",IF(E188>=0.7,"Moderate","Poor"))) -> Moderate
... A211: Bendstore Spar | B211: 46174 | C211: {=IFERROR(IF(SUMPRODUCT((measured[Site Name]=A211)*(measured[Date]=B211)*ISNUMBER(measured[Measured Value (kWh)]))=0,"",SUMIFS(measured[Measured Value (kWh)],measured[Site Name],A211,measured[Date],B211)),"")} -> 31578.49 | D211: {=IFERROR(IF(SUMPRODUCT((expected_production[Site Name]=A211)*(expected_production[Date]=B211)*ISNUMBER(expected_production[Expected Production (kWh)]))=0,"",SUMIFS(expected_production[Expected Production (kWh)],expected_production[Site Name],A211,expected_production[Date],B211)),"")} -> 40943.972 | E211: =IF(OR(C211="",D211="",D211=0),"",C211/D211) -> 0.77126103 | F211: =IF(E211="","",IF(E211>=0.9,"Expected",IF(E211>=0.7,"Moderate","Poor"))) -> Moderate
A212: Bendstore Spar | B212: 46204 | C212: {=IFERROR(IF(SUMPRODUCT((measured[Site Name]=A212)*(measured[Date]=B212)*ISNUMBER(measured[Measured Value (kWh)]))=0,"",SUMIFS(measured[Measured Value (kWh)],measured[Site Name],A212,measured[Date],B212)),"")} -> 39160 | D212: {=IFERROR(IF(SUMPRODUCT((expected_production[Site Name]=A212)*(expected_production[Date]=B212)*ISNUMBER(expected_production[Expected Production (kWh)]))=0,"",SUMIFS(expected_production[Expected Production (kWh)],expected_production[Site Name],A212,expected_production[Date],B212)),"")} -> 43112.803 | E212: =IF(OR(C212="",D212="",D212=0),"",C212/D212) -> 0.90831487 | F212: =IF(E212="","",IF(E212>=0.9,"Expected",IF(E212>=0.7,"Moderate","Poor"))) -> Expected | G212: NO
A213: Bendstore Spar | B213: 46235 | C213: {=IFERROR(IF(SUMPRODUCT((measured[Site Name]=A213)*(measured[Date]=B213)*ISNUMBER(measured[Measured Value (kWh)]))=0,"",SUMIFS(measured[Measured Value (kWh)],measured[Site Name],A213,measured[Date],B213)),"")} | D213: {=IFERROR(IF(SUMPRODUCT((expected_production[Site Name]=A213)*(expected_production[Date]=B213)*ISNUMBER(expected_production[Expected Production (kWh)]))=0,"",SUMIFS(expected_production[Expected Production (kWh)],expected_production[Site Name],A213,expected_production[Date],B213)),"")} -> 48266.503 | E213: =IF(OR(C213="",D213="",D213=0),"",C213/D213) | F213: =IF(E213="","",IF(E213>=0.9,"Expected",IF(E213>=0.7,"Moderate","Poor")))
A214: Bendstore Spar | B214: 46266 | C214: {=IFERROR(IF(SUMPRODUCT((measured[Site Name]=A214)*(measured[Date]=B214)*ISNUMBER(measured[Measured Value (kWh)]))=0,"",SUMIFS(measured[Measured Value (kWh)],measured[Site Name],A214,measured[Date],B214)),"")} | D214: {=IFERROR(IF(SUMPRODUCT((expected_production[Site Name]=A214)*(expected_production[Date]=B214)*ISNUMBER(expected_production[Expected Production (kWh)]))=0,"",SUMIFS(expected_production[Expected Production (kWh)],expected_production[Site Name],A214,expected_production[Date],B214)),"")} -> 48602.891 | E214: =IF(OR(C214="",D214="",D214=0),"",C214/D214) | F214: =IF(E214="","",IF(E214>=0.9,"Expected",IF(E214>=0.7,"Moderate","Poor")))
A215: Bendstore Spar | B215: 46296 | C215: {=IFERROR(IF(SUMPRODUCT((measured[Site Name]=A215)*(measured[Date]=B215)*ISNUMBER(measured[Measured Value (kWh)]))=0,"",SUMIFS(measured[Measured Value (kWh)],measured[Site Name],A215,measured[Date],B215)),"")} | D215: {=IFERROR(IF(SUMPRODUCT((expected_production[Site Name]=A215)*(expected_production[Date]=B215)*ISNUMBER(expected_production[Expected Production (kWh)]))=0,"",SUMIFS(expected_production[Expected Production (kWh)],expected_production[Site Name],A215,expected_production[Date],B215)),"")} -> 46748.911 | E215: =IF(OR(C215="",D215="",D215=0),"",C215/D215) | F215: =IF(E215="","",IF(E215>=0.9,"Expected",IF(E215>=0.7,"Moderate","Poor")))
A216: Bendstore Spar | B216: 46327 | C216: {=IFERROR(IF(SUMPRODUCT((measured[Site Name]=A216)*(measured[Date]=B216)*ISNUMBER(measured[Measured Value (kWh)]))=0,"",SUMIFS(measured[Measured Value (kWh)],measured[Site Name],A216,measured[Date],B216)),"")} | D216: {=IFERROR(IF(SUMPRODUCT((expected_production[Site Name]=A216)*(expected_production[Date]=B216)*ISNUMBER(expected_production[Expected Production (kWh)]))=0,"",SUMIFS(expected_production[Expected Production (kWh)],expected_production[Site Name],A216,expected_production[Date],B216)),"")} -> 46388.482 | E216: =IF(OR(C216="",D216="",D216=0),"",C216/D216) | F216: =IF(E216="","",IF(E216>=0.9,"Expected",IF(E216>=0.7,"Moderate","Poor")))
A217: Bendstore Spar | B217: 46357 | C217: {=IFERROR(IF(SUMPRODUCT((measured[Site Name]=A217)*(measured[Date]=B217)*ISNUMBER(measured[Measured Value (kWh)]))=0,"",SUMIFS(measured[Measured Value (kWh)],measured[Site Name],A217,measured[Date],B217)),"")} | D217: {=IFERROR(IF(SUMPRODUCT((expected_production[Site Name]=A217)*(expected_production[Date]=B217)*ISNUMBER(expected_production[Expected Production (kWh)]))=0,"",SUMIFS(expected_production[Expected Production (kWh)],expected_production[Site Name],A217,expected_production[Date],B217)),"")} -> 50640.311 | E217: =IF(OR(C217="",D217="",D217=0),"",C217/D217) | F217: =IF(E217="","",IF(E217>=0.9,"Expected",IF(E217>=0.7,"Moderate","Poor")))
A218: Beyerskloof | B218: 45292 | C218: {=IFERROR(IF(SUMPRODUCT((measured[Site Name]=A218)*(measured[Date]=B218)*ISNUMBER(measured[Measured Value (kWh)]))=0,"",SUMIFS(measured[Measured Value (kWh)],measured[Site Name],A218,measured[Date],B218)),"")} -> 8244 | D218: {=IFERROR(IF(SUMPRODUCT((expected_production[Site Name]=A218)*(expected_production[Date]=B218)*ISNUMBER(expected_production[Expected Production (kWh)]))=0,"",SUMIFS(expected_production[Expected Production (kWh)],expected_production[Site Name],A218,expected_production[Date],B218)),"")} -> 13787.1 | E218: =IF(OR(C218="",D218="",D218=0),"",C218/D218) -> 0.59795026 | F218: =IF(E218="","",IF(E218>=0.9,"Expected",IF(E218>=0.7,"Moderate","Poor"))) -> Poor
A219: Beyerskloof | B219: 45323 | C219: {=IFERROR(IF(SUMPRODUCT((measured[Site Name]=A219)*(measured[Date]=B219)*ISNUMBER(measured[Measured Value (kWh)]))=0,"",SUMIFS(measured[Measured Value (kWh)],measured[Site Name],A219,measured[Date],B219)),"")} -> 7277 | D219: {=IFERROR(IF(SUMPRODUCT((expected_production[Site Name]=A219)*(expected_production[Date]=B219)*ISNUMBER(expected_production[Expected Production (kWh)]))=0,"",SUMIFS(expected_production[Expected Production (kWh)],expected_production[Site Name],A219,expected_production[Date],B219)),"")} -> 11359.8 | E219: =IF(OR(C219="",D219="",D219=0),"",C219/D219) -> 0.64059226 | F219: =IF(E219="","",IF(E219>=0.9,"Expected",IF(E219>=0.7,"Moderate","Poor"))) -> Poor
A220: Beyerskloof | B220: 45352 | C220: {=IFERROR(IF(SUMPRODUCT((measured[Site Name]=A220)*(measured[Date]=B220)*ISNUMBER(measured[Measured Value (kWh)]))=0,"",SUMIFS(measured[Measured Value (kWh)],measured[Site Name],A220,measured[Date],B220)),"")} -> 6614 | D220: {=IFERROR(IF(SUMPRODUCT((expected_production[Site Name]=A220)*(expected_production[Date]=B220)*ISNUMBER(expected_production[Expected Production (kWh)]))=0,"",SUMIFS(expected_production[Expected Production (kWh)],expected_production[Site Name],A220,expected_production[Date],B220)),"")} -> 10881 | E220: =IF(OR(C220="",D220="",D220=0),"",C220/D220) -> 0.60784854 | F220: =IF(E220="","",IF(E220>=0.9,"Expected",IF(E220>=0.7,"Moderate","Poor"))) -> Poor
A221: Beyerskloof | B221: 45383 | C221: {=IFERROR(IF(SUMPRODUCT((measured[Site Name]=A221)*(measured[Date]=B221)*ISNUMBER(measured[Measured Value (kWh)]))=0,"",SUMIFS(measured[Measured Value (kWh)],measured[Site Name],A221,measured[Date],B221)),"")} -> 4053 | D221: {=IFERROR(IF(SUMPRODUCT((expected_production[Site Name]=A221)*(expected_production[Date]=B221)*ISNUMBER(expected_production[Expected Production (kWh)]))=0,"",SUMIFS(expected_production[Expected Production (kWh)],expected_production[Site Name],A221,expected_production[Date],B221)),"")} -> 7828.2 | E221: =IF(OR(C221="",D221="",D221=0),"",C221/D221) -> 0.51774354 | F221: =IF(E221="","",IF(E221>=0.9,"Expected",IF(E221>=0.7,"Moderate","Poor"))) -> Poor
A222: Beyerskloof | B222: 45413 | C222: {=IFERROR(IF(SUMPRODUCT((measured[Site Name]=A222)*(measured[Date]=B222)*ISNUMBER(measured[Measured Value (kWh)]))=0,"",SUMIFS(measured[Measured Value (kWh)],measured[Site Name],A222,measured[Date],B222)),"")} -> 3743 | D222: {=IFERROR(IF(SUMPRODUCT((expected_production[Site Name]=A222)*(expected_production[Date]=B222)*ISNUMBER(expected_production[Expected Production (kWh)]))=0,"",SUMIFS(expected_production[Expected Production (kWh)],expected_production[Site Name],A222,expected_production[Date],B222)),"")} -> 5953.5 | E222: =IF(OR(C222="",D222="",D222=0),"",C222/D222) -> 0.6287058 | F222: =IF(E222="","",IF(E222>=0.9,"Expected",IF(E222>=0.7,"Moderate","Poor"))) -> Poor
A223: Beyerskloof | B223: 45444 | C223: {=IFERROR(IF(SUMPRODUCT((measured[Site Name]=A223)*(measured[Date]=B223)*ISNUMBER(measured[Measured Value (kWh)]))=0,"",SUMIFS(measured[Measured Value (kWh)],measured[Site Name],A223,measured[Date],B223)),"")} -> 3473 | D223: {=IFERROR(IF(SUMPRODUCT((expected_production[Site Name]=A223)*(expected_production[Date]=B223)*ISNUMBER(expected_production[Expected Production (kWh)]))=0,"",SUMIFS(expected_production[Expected Production (kWh)],expected_production[Site Name],A223,expected_production[Date],B223)),"")} -> 5166 | E223: =IF(OR(C223="",D223="",D223=0),"",C223/D223) -> 0.67228029 | F223: =IF(E223="","",IF(E223>=0.9,"Expected",IF(E223>=0.7,"Moderate","Poor"))) -> Poor
A224: Beyerskloof | B224: 45474 | C224: {=IFERROR(IF(SUMPRODUCT((measured[Site Name]=A224)*(measured[Date]=B224)*ISNUMBER(measured[Measured Value (kWh)]))=0,"",SUMIFS(measured[Measured Value (kWh)],measured[Site Name],A224,measured[Date],B224)),"")} -> 4260 | D224: {=IFERROR(IF(SUMPRODUCT((expected_production[Site Name]=A224)*(expected_production[Date]=B224)*ISNUMBER(expected_production[Expected Production (kWh)]))=0,"",SUMIFS(expected_production[Expected Production (kWh)],expected_production[Site Name],A224,expected_production[Date],B224)),"")} -> 5564.7 | E224: =IF(OR(C224="",D224="",D224=0),"",C224/D224) -> 0.76553992 | F224: =IF(E224="","",IF(E224>=0.9,"Expected",IF(E224>=0.7,"Moderate","Poor"))) -> Moderate
... A247: Beyerskloof | B247: 46174 | C247: {=IFERROR(IF(SUMPRODUCT((measured[Site Name]=A247)*(measured[Date]=B247)*ISNUMBER(measured[Measured Value (kWh)]))=0,"",SUMIFS(measured[Measured Value (kWh)],measured[Site Name],A247,measured[Date],B247)),"")} -> 5030.25 | D247: {=IFERROR(IF(SUMPRODUCT((expected_production[Site Name]=A247)*(expected_production[Date]=B247)*ISNUMBER(expected_production[Expected Production (kWh)]))=0,"",SUMIFS(expected_production[Expected Production (kWh)],expected_production[Site Name],A247,expected_production[Date],B247)),"")} -> 5166 | E247: =IF(OR(C247="",D247="",D247=0),"",C247/D247) -> 0.97372242 | F247: =IF(E247="","",IF(E247>=0.9,"Expected",IF(E247>=0.7,"Moderate","Poor"))) -> Expected
A248: Beyerskloof | B248: 46204 | C248: {=IFERROR(IF(SUMPRODUCT((measured[Site Name]=A248)*(measured[Date]=B248)*ISNUMBER(measured[Measured Value (kWh)]))=0,"",SUMIFS(measured[Measured Value (kWh)],measured[Site Name],A248,measured[Date],B248)),"")} -> 5251.38 | D248: {=IFERROR(IF(SUMPRODUCT((expected_production[Site Name]=A248)*(expected_production[Date]=B248)*ISNUMBER(expected_production[Expected Production (kWh)]))=0,"",SUMIFS(expected_production[Expected Production (kWh)],expected_production[Site Name],A248,expected_production[Date],B248)),"")} -> 5564.7 | E248: =IF(OR(C248="",D248="",D248=0),"",C248/D248) -> 0.94369508 | F248: =IF(E248="","",IF(E248>=0.9,"Expected",IF(E248>=0.7,"Moderate","Poor"))) -> Expected | G248: NO
A249: Beyerskloof | B249: 46235 | C249: {=IFERROR(IF(SUMPRODUCT((measured[Site Name]=A249)*(measured[Date]=B249)*ISNUMBER(measured[Measured Value (kWh)]))=0,"",SUMIFS(measured[Measured Value (kWh)],measured[Site Name],A249,measured[Date],B249)),"")} | D249: {=IFERROR(IF(SUMPRODUCT((expected_production[Site Name]=A249)*(expected_production[Date]=B249)*ISNUMBER(expected_production[Expected Production (kWh)]))=0,"",SUMIFS(expected_production[Expected Production (kWh)],expected_production[Site Name],A249,expected_production[Date],B249)),"")} -> 6960.6 | E249: =IF(OR(C249="",D249="",D249=0),"",C249/D249) | F249: =IF(E249="","",IF(E249>=0.9,"Expected",IF(E249>=0.7,"Moderate","Poor")))
...

Sheet CountryList
A1: Algeria
A2: Angola
A3: Benin
A4: Botswana
A5: Burkina Faso
A6: Burundi
A7: Cabo Verde
A8: Cameroon
A9: Central African Republic
A10: Chad
A11: Comoros
A12: Democratic Republic of the Congo
... A54: Zimbabwe
